// Decompiled by Jad v1.5.8g. Copyright 2001 Pavel Kouznetsov.
// Jad home page: http://www.kpdus.com/jad.html
// Decompiler options: packimports(3) annotate safe 

package com.google.android.gms.internal.ads;

import android.os.SystemClock;
import android.text.TextUtils;
import java.io.*;
import java.util.*;

// Referenced classes of package com.google.android.gms.internal.ads:
//			zzb, zzaf, zzan, zzao, 
//			zzl, zzc

public final class zzam
	implements zzb
{

	public zzam(File file)
	{
		this(file, 0x500000);
	//    0    0:aload_0         
	//    1    1:aload_1         
	//    2    2:ldc1            #18  <Int 0x500000>
	//    3    4:invokespecial   #21  <Method void zzam(File, int)>
	//    4    7:return          
	}

	private zzam(File file, int i)
	{
	//    0    0:aload_0         
	//    1    1:invokespecial   #25  <Method void Object()>
		zzbw = ((Map) (new LinkedHashMap(16, 0.75F, true)));
	//    2    4:aload_0         
	//    3    5:new             #27  <Class LinkedHashMap>
	//    4    8:dup             
	//    5    9:bipush          16
	//    6   11:ldc1            #28  <Float 0.75F>
	//    7   13:iconst_1        
	//    8   14:invokespecial   #31  <Method void LinkedHashMap(int, float, boolean)>
	//    9   17:putfield        #33  <Field Map zzbw>
		zzbx = 0L;
	//   10   20:aload_0         
	//   11   21:lconst_0        
	//   12   22:putfield        #35  <Field long zzbx>
		zzby = file;
	//   13   25:aload_0         
	//   14   26:aload_1         
	//   15   27:putfield        #37  <Field File zzby>
		zzbz = 0x500000;
	//   16   30:aload_0         
	//   17   31:ldc1            #18  <Int 0x500000>
	//   18   33:putfield        #39  <Field int zzbz>
	//   19   36:return          
	}

	private final void remove(String s)
	{
		this;
	//    0    0:aload_0         
		JVM INSTR monitorenter ;
	//    1    1:monitorenter    
		boolean flag;
		flag = zze(s).delete();
	//    2    2:aload_0         
	//    3    3:aload_1         
	//    4    4:invokespecial   #45  <Method File zze(String)>
	//    5    7:invokevirtual   #51  <Method boolean File.delete()>
	//    6   10:istore_2        
		removeEntry(s);
	//    7   11:aload_0         
	//    8   12:aload_1         
	//    9   13:invokespecial   #54  <Method void removeEntry(String)>
		if(flag)
			break MISSING_BLOCK_LABEL_40;
	//   10   16:iload_2         
	//   11   17:ifne            40
		zzaf.d("Could not delete cache entry for key=%s, filename=%s", new Object[] {
			s, zzd(s)
		});
	//   12   20:ldc1            #56  <String "Could not delete cache entry for key=%s, filename=%s">
	//   13   22:iconst_2        
	//   14   23:anewarray       Object[]
	//   15   26:dup             
	//   16   27:iconst_0        
	//   17   28:aload_1         
	//   18   29:aastore         
	//   19   30:dup             
	//   20   31:iconst_1        
	//   21   32:aload_1         
	//   22   33:invokestatic    #60  <Method String zzd(String)>
	//   23   36:aastore         
	//   24   37:invokestatic    #66  <Method void zzaf.d(String, Object[])>
		this;
	//   25   40:aload_0         
		JVM INSTR monitorexit ;
	//   26   41:monitorexit     
		return;
	//   27   42:return          
		s;
	//   28   43:astore_1        
	//*  29   44:aload_0         
		throw s;
	//   30   45:monitorexit     
	//   31   46:aload_1         
	//   32   47:athrow          
	}

	private final void removeEntry(String s)
	{
		s = ((String) ((zzan)zzbw.remove(((Object) (s)))));
	//    0    0:aload_0         
	//    1    1:getfield        #33  <Field Map zzbw>
	//    2    4:aload_1         
	//    3    5:invokeinterface #71  <Method Object Map.remove(Object)>
	//    4   10:checkcast       #73  <Class zzan>
	//    5   13:astore_1        
		if(s != null)
	//*   6   14:aload_1         
	//*   7   15:ifnull          31
			zzbx = zzbx - ((zzan) (s)).zzca;
	//    8   18:aload_0         
	//    9   19:aload_0         
	//   10   20:getfield        #35  <Field long zzbx>
	//   11   23:aload_1         
	//   12   24:getfield        #76  <Field long zzan.zzca>
	//   13   27:lsub            
	//   14   28:putfield        #35  <Field long zzbx>
	//   15   31:return          
	}

	private static int zza(InputStream inputstream)
		throws IOException
	{
		int i = inputstream.read();
	//    0    0:aload_0         
	//    1    1:invokevirtual   #86  <Method int InputStream.read()>
	//    2    4:istore_1        
		if(i == -1)
	//*   3    5:iload_1         
	//*   4    6:iconst_m1       
	//*   5    7:icmpne          18
			throw new EOFException();
	//    6   10:new             #88  <Class EOFException>
	//    7   13:dup             
	//    8   14:invokespecial   #89  <Method void EOFException()>
	//    9   17:athrow          
		else
			return i;
	//   10   18:iload_1         
	//   11   19:ireturn         
	}

	private static InputStream zza(File file)
		throws FileNotFoundException
	{
		return ((InputStream) (new FileInputStream(file)));
	//    0    0:new             #95  <Class FileInputStream>
	//    1    3:dup             
	//    2    4:aload_0         
	//    3    5:invokespecial   #97  <Method void FileInputStream(File)>
	//    4    8:areturn         
	}

	static String zza(zzao zzao1)
		throws IOException
	{
		return new String(zza(zzao1, zzc(((InputStream) (zzao1)))), "UTF-8");
	//    0    0:new             #100 <Class String>
	//    1    3:dup             
	//    2    4:aload_0         
	//    3    5:aload_0         
	//    4    6:invokestatic    #104 <Method long zzc(InputStream)>
	//    5    9:invokestatic    #107 <Method byte[] zza(zzao, long)>
	//    6   12:ldc1            #109 <String "UTF-8">
	//    7   14:invokespecial   #112 <Method void String(byte[], String)>
	//    8   17:areturn         
	}

	static void zza(OutputStream outputstream, int i)
		throws IOException
	{
		outputstream.write(i & 0xff);
	//    0    0:aload_0         
	//    1    1:iload_1         
	//    2    2:sipush          255
	//    3    5:iand            
	//    4    6:invokevirtual   #119 <Method void OutputStream.write(int)>
		outputstream.write(i >> 8 & 0xff);
	//    5    9:aload_0         
	//    6   10:iload_1         
	//    7   11:bipush          8
	//    8   13:ishr            
	//    9   14:sipush          255
	//   10   17:iand            
	//   11   18:invokevirtual   #119 <Method void OutputStream.write(int)>
		outputstream.write(i >> 16 & 0xff);
	//   12   21:aload_0         
	//   13   22:iload_1         
	//   14   23:bipush          16
	//   15   25:ishr            
	//   16   26:sipush          255
	//   17   29:iand            
	//   18   30:invokevirtual   #119 <Method void OutputStream.write(int)>
		outputstream.write(i >>> 24);
	//   19   33:aload_0         
	//   20   34:iload_1         
	//   21   35:bipush          24
	//   22   37:iushr           
	//   23   38:invokevirtual   #119 <Method void OutputStream.write(int)>
	//   24   41:return          
	}

	static void zza(OutputStream outputstream, long l)
		throws IOException
	{
		outputstream.write(((int) ((byte)(int)l)));
	//    0    0:aload_0         
	//    1    1:lload_1         
	//    2    2:l2i             
	//    3    3:int2byte        
	//    4    4:invokevirtual   #119 <Method void OutputStream.write(int)>
		outputstream.write(((int) ((byte)(int)(l >>> 8))));
	//    5    7:aload_0         
	//    6    8:lload_1         
	//    7    9:bipush          8
	//    8   11:lushr           
	//    9   12:l2i             
	//   10   13:int2byte        
	//   11   14:invokevirtual   #119 <Method void OutputStream.write(int)>
		outputstream.write(((int) ((byte)(int)(l >>> 16))));
	//   12   17:aload_0         
	//   13   18:lload_1         
	//   14   19:bipush          16
	//   15   21:lushr           
	//   16   22:l2i             
	//   17   23:int2byte        
	//   18   24:invokevirtual   #119 <Method void OutputStream.write(int)>
		outputstream.write(((int) ((byte)(int)(l >>> 24))));
	//   19   27:aload_0         
	//   20   28:lload_1         
	//   21   29:bipush          24
	//   22   31:lushr           
	//   23   32:l2i             
	//   24   33:int2byte        
	//   25   34:invokevirtual   #119 <Method void OutputStream.write(int)>
		outputstream.write(((int) ((byte)(int)(l >>> 32))));
	//   26   37:aload_0         
	//   27   38:lload_1         
	//   28   39:bipush          32
	//   29   41:lushr           
	//   30   42:l2i             
	//   31   43:int2byte        
	//   32   44:invokevirtual   #119 <Method void OutputStream.write(int)>
		outputstream.write(((int) ((byte)(int)(l >>> 40))));
	//   33   47:aload_0         
	//   34   48:lload_1         
	//   35   49:bipush          40
	//   36   51:lushr           
	//   37   52:l2i             
	//   38   53:int2byte        
	//   39   54:invokevirtual   #119 <Method void OutputStream.write(int)>
		outputstream.write(((int) ((byte)(int)(l >>> 48))));
	//   40   57:aload_0         
	//   41   58:lload_1         
	//   42   59:bipush          48
	//   43   61:lushr           
	//   44   62:l2i             
	//   45   63:int2byte        
	//   46   64:invokevirtual   #119 <Method void OutputStream.write(int)>
		outputstream.write(((int) ((byte)(int)(l >>> 56))));
	//   47   67:aload_0         
	//   48   68:lload_1         
	//   49   69:bipush          56
	//   50   71:lushr           
	//   51   72:l2i             
	//   52   73:int2byte        
	//   53   74:invokevirtual   #119 <Method void OutputStream.write(int)>
	//   54   77:return          
	}

	static void zza(OutputStream outputstream, String s)
		throws IOException
	{
		s = ((String) (s.getBytes("UTF-8")));
	//    0    0:aload_1         
	//    1    1:ldc1            #109 <String "UTF-8">
	//    2    3:invokevirtual   #125 <Method byte[] String.getBytes(String)>
	//    3    6:astore_1        
		zza(outputstream, s.length);
	//    4    7:aload_0         
	//    5    8:aload_1         
	//    6    9:arraylength     
	//    7   10:i2l             
	//    8   11:invokestatic    #127 <Method void zza(OutputStream, long)>
		outputstream.write(((byte []) (s)), 0, s.length);
	//    9   14:aload_0         
	//   10   15:aload_1         
	//   11   16:iconst_0        
	//   12   17:aload_1         
	//   13   18:arraylength     
	//   14   19:invokevirtual   #130 <Method void OutputStream.write(byte[], int, int)>
	//   15   22:return          
	}

	private final void zza(String s, zzan zzan1)
	{
		if(!zzbw.containsKey(((Object) (s))))
	//*   0    0:aload_0         
	//*   1    1:getfield        #33  <Field Map zzbw>
	//*   2    4:aload_1         
	//*   3    5:invokeinterface #135 <Method boolean Map.containsKey(Object)>
	//*   4   10:ifne            29
		{
			zzbx = zzbx + zzan1.zzca;
	//    5   13:aload_0         
	//    6   14:aload_0         
	//    7   15:getfield        #35  <Field long zzbx>
	//    8   18:aload_2         
	//    9   19:getfield        #76  <Field long zzan.zzca>
	//   10   22:ladd            
	//   11   23:putfield        #35  <Field long zzbx>
		} else
	//*  12   26:goto            61
		{
			zzan zzan2 = (zzan)zzbw.get(((Object) (s)));
	//   13   29:aload_0         
	//   14   30:getfield        #33  <Field Map zzbw>
	//   15   33:aload_1         
	//   16   34:invokeinterface #138 <Method Object Map.get(Object)>
	//   17   39:checkcast       #73  <Class zzan>
	//   18   42:astore_3        
			zzbx = zzbx + (zzan1.zzca - zzan2.zzca);
	//   19   43:aload_0         
	//   20   44:aload_0         
	//   21   45:getfield        #35  <Field long zzbx>
	//   22   48:aload_2         
	//   23   49:getfield        #76  <Field long zzan.zzca>
	//   24   52:aload_3         
	//   25   53:getfield        #76  <Field long zzan.zzca>
	//   26   56:lsub            
	//   27   57:ladd            
	//   28   58:putfield        #35  <Field long zzbx>
		}
		zzbw.put(((Object) (s)), ((Object) (zzan1)));
	//   29   61:aload_0         
	//   30   62:getfield        #33  <Field Map zzbw>
	//   31   65:aload_1         
	//   32   66:aload_2         
	//   33   67:invokeinterface #142 <Method Object Map.put(Object, Object)>
	//   34   72:pop             
	//   35   73:return          
	}

	private static byte[] zza(zzao zzao1, long l)
		throws IOException
	{
		long l1 = zzao1.zzo();
	//    0    0:aload_0         
	//    1    1:invokevirtual   #148 <Method long zzao.zzo()>
	//    2    4:lstore          4
		if(l >= 0L && l <= l1)
	//*   3    6:lload_1         
	//*   4    7:lconst_0        
	//*   5    8:lcmp            
	//*   6    9:iflt            53
	//*   7   12:lload_1         
	//*   8   13:lload           4
	//*   9   15:lcmp            
	//*  10   16:ifgt            53
		{
			int i = (int)l;
	//   11   19:lload_1         
	//   12   20:l2i             
	//   13   21:istore_3        
			if((long)i == l)
	//*  14   22:iload_3         
	//*  15   23:i2l             
	//*  16   24:lload_1         
	//*  17   25:lcmp            
	//*  18   26:ifeq            32
	//*  19   29:goto            53
			{
				byte abyte0[] = new byte[i];
	//   20   32:iload_3         
	//   21   33:newarray        byte[]
	//   22   35:astore          6
				(new DataInputStream(((InputStream) (zzao1)))).readFully(abyte0);
	//   23   37:new             #150 <Class DataInputStream>
	//   24   40:dup             
	//   25   41:aload_0         
	//   26   42:invokespecial   #153 <Method void DataInputStream(InputStream)>
	//   27   45:aload           6
	//   28   47:invokevirtual   #157 <Method void DataInputStream.readFully(byte[])>
				return abyte0;
	//   29   50:aload           6
	//   30   52:areturn         
			}
		}
		zzao1 = ((zzao) (new StringBuilder(73)));
	//   31   53:new             #159 <Class StringBuilder>
	//   32   56:dup             
	//   33   57:bipush          73
	//   34   59:invokespecial   #161 <Method void StringBuilder(int)>
	//   35   62:astore_0        
		((StringBuilder) (zzao1)).append("streamToBytes length=");
	//   36   63:aload_0         
	//   37   64:ldc1            #163 <String "streamToBytes length=">
	//   38   66:invokevirtual   #167 <Method StringBuilder StringBuilder.append(String)>
	//   39   69:pop             
		((StringBuilder) (zzao1)).append(l);
	//   40   70:aload_0         
	//   41   71:lload_1         
	//   42   72:invokevirtual   #170 <Method StringBuilder StringBuilder.append(long)>
	//   43   75:pop             
		((StringBuilder) (zzao1)).append(", maxLength=");
	//   44   76:aload_0         
	//   45   77:ldc1            #172 <String ", maxLength=">
	//   46   79:invokevirtual   #167 <Method StringBuilder StringBuilder.append(String)>
	//   47   82:pop             
		((StringBuilder) (zzao1)).append(l1);
	//   48   83:aload_0         
	//   49   84:lload           4
	//   50   86:invokevirtual   #170 <Method StringBuilder StringBuilder.append(long)>
	//   51   89:pop             
		throw new IOException(((StringBuilder) (zzao1)).toString());
	//   52   90:new             #80  <Class IOException>
	//   53   93:dup             
	//   54   94:aload_0         
	//   55   95:invokevirtual   #176 <Method String StringBuilder.toString()>
	//   56   98:invokespecial   #178 <Method void IOException(String)>
	//   57  101:athrow          
	}

	static int zzb(InputStream inputstream)
		throws IOException
	{
		int i = zza(inputstream);
	//    0    0:aload_0         
	//    1    1:invokestatic    #181 <Method int zza(InputStream)>
	//    2    4:istore_1        
		int j = zza(inputstream);
	//    3    5:aload_0         
	//    4    6:invokestatic    #181 <Method int zza(InputStream)>
	//    5    9:istore_2        
		int k = zza(inputstream);
	//    6   10:aload_0         
	//    7   11:invokestatic    #181 <Method int zza(InputStream)>
	//    8   14:istore_3        
		return zza(inputstream) << 24 | (i | 0 | j << 8 | k << 16);
	//    9   15:aload_0         
	//   10   16:invokestatic    #181 <Method int zza(InputStream)>
	//   11   19:bipush          24
	//   12   21:ishl            
	//   13   22:iload_1         
	//   14   23:iconst_0        
	//   15   24:ior             
	//   16   25:iload_2         
	//   17   26:bipush          8
	//   18   28:ishl            
	//   19   29:ior             
	//   20   30:iload_3         
	//   21   31:bipush          16
	//   22   33:ishl            
	//   23   34:ior             
	//   24   35:ior             
	//   25   36:ireturn         
	}

	static List zzb(zzao zzao1)
		throws IOException
	{
		int j = zzb(((InputStream) (zzao1)));
	//    0    0:aload_0         
	//    1    1:invokestatic    #184 <Method int zzb(InputStream)>
	//    2    4:istore_2        
		Object obj;
		if(j == 0)
	//*   3    5:iload_2         
	//*   4    6:ifne            16
			obj = ((Object) (Collections.emptyList()));
	//    5    9:invokestatic    #190 <Method List Collections.emptyList()>
	//    6   12:astore_3        
		else
	//*   7   13:goto            25
			obj = ((Object) (new ArrayList(j)));
	//    8   16:new             #192 <Class ArrayList>
	//    9   19:dup             
	//   10   20:iload_2         
	//   11   21:invokespecial   #193 <Method void ArrayList(int)>
	//   12   24:astore_3        
		for(int i = 0; i < j; i++)
	//*  13   25:iconst_0        
	//*  14   26:istore_1        
	//*  15   27:iload_1         
	//*  16   28:iload_2         
	//*  17   29:icmpge          67
			((List) (obj)).add(((Object) (new zzl(zza(zzao1).intern(), zza(zzao1).intern()))));
	//   18   32:aload_3         
	//   19   33:new             #195 <Class zzl>
	//   20   36:dup             
	//   21   37:aload_0         
	//   22   38:invokestatic    #197 <Method String zza(zzao)>
	//   23   41:invokevirtual   #200 <Method String String.intern()>
	//   24   44:aload_0         
	//   25   45:invokestatic    #197 <Method String zza(zzao)>
	//   26   48:invokevirtual   #200 <Method String String.intern()>
	//   27   51:invokespecial   #203 <Method void zzl(String, String)>
	//   28   54:invokeinterface #208 <Method boolean List.add(Object)>
	//   29   59:pop             

	//   30   60:iload_1         
	//   31   61:iconst_1        
	//   32   62:iadd            
	//   33   63:istore_1        
	//*  34   64:goto            27
		return ((List) (obj));
	//   35   67:aload_3         
	//   36   68:areturn         
	}

	static long zzc(InputStream inputstream)
		throws IOException
	{
		return 0L | (long)zza(inputstream) & 255L | ((long)zza(inputstream) & 255L) << 8 | ((long)zza(inputstream) & 255L) << 16 | ((long)zza(inputstream) & 255L) << 24 | ((long)zza(inputstream) & 255L) << 32 | ((long)zza(inputstream) & 255L) << 40 | ((long)zza(inputstream) & 255L) << 48 | ((long)zza(inputstream) & 255L) << 56;
	//    0    0:lconst_0        
	//    1    1:aload_0         
	//    2    2:invokestatic    #181 <Method int zza(InputStream)>
	//    3    5:i2l             
	//    4    6:ldc2w           #211 <Long 255L>
	//    5    9:land            
	//    6   10:lor             
	//    7   11:aload_0         
	//    8   12:invokestatic    #181 <Method int zza(InputStream)>
	//    9   15:i2l             
	//   10   16:ldc2w           #211 <Long 255L>
	//   11   19:land            
	//   12   20:bipush          8
	//   13   22:lshl            
	//   14   23:lor             
	//   15   24:aload_0         
	//   16   25:invokestatic    #181 <Method int zza(InputStream)>
	//   17   28:i2l             
	//   18   29:ldc2w           #211 <Long 255L>
	//   19   32:land            
	//   20   33:bipush          16
	//   21   35:lshl            
	//   22   36:lor             
	//   23   37:aload_0         
	//   24   38:invokestatic    #181 <Method int zza(InputStream)>
	//   25   41:i2l             
	//   26   42:ldc2w           #211 <Long 255L>
	//   27   45:land            
	//   28   46:bipush          24
	//   29   48:lshl            
	//   30   49:lor             
	//   31   50:aload_0         
	//   32   51:invokestatic    #181 <Method int zza(InputStream)>
	//   33   54:i2l             
	//   34   55:ldc2w           #211 <Long 255L>
	//   35   58:land            
	//   36   59:bipush          32
	//   37   61:lshl            
	//   38   62:lor             
	//   39   63:aload_0         
	//   40   64:invokestatic    #181 <Method int zza(InputStream)>
	//   41   67:i2l             
	//   42   68:ldc2w           #211 <Long 255L>
	//   43   71:land            
	//   44   72:bipush          40
	//   45   74:lshl            
	//   46   75:lor             
	//   47   76:aload_0         
	//   48   77:invokestatic    #181 <Method int zza(InputStream)>
	//   49   80:i2l             
	//   50   81:ldc2w           #211 <Long 255L>
	//   51   84:land            
	//   52   85:bipush          48
	//   53   87:lshl            
	//   54   88:lor             
	//   55   89:aload_0         
	//   56   90:invokestatic    #181 <Method int zza(InputStream)>
	//   57   93:i2l             
	//   58   94:ldc2w           #211 <Long 255L>
	//   59   97:land            
	//   60   98:bipush          56
	//   61  100:lshl            
	//   62  101:lor             
	//   63  102:lreturn         
	}

	private static String zzd(String s)
	{
		int i = s.length() / 2;
	//    0    0:aload_0         
	//    1    1:invokevirtual   #215 <Method int String.length()>
	//    2    4:iconst_2        
	//    3    5:idiv            
	//    4    6:istore_1        
		String s1 = String.valueOf(((Object) (String.valueOf(s.substring(0, i).hashCode()))));
	//    5    7:aload_0         
	//    6    8:iconst_0        
	//    7    9:iload_1         
	//    8   10:invokevirtual   #219 <Method String String.substring(int, int)>
	//    9   13:invokevirtual   #222 <Method int String.hashCode()>
	//   10   16:invokestatic    #226 <Method String String.valueOf(int)>
	//   11   19:invokestatic    #229 <Method String String.valueOf(Object)>
	//   12   22:astore_2        
		s = String.valueOf(((Object) (String.valueOf(s.substring(i).hashCode()))));
	//   13   23:aload_0         
	//   14   24:iload_1         
	//   15   25:invokevirtual   #231 <Method String String.substring(int)>
	//   16   28:invokevirtual   #222 <Method int String.hashCode()>
	//   17   31:invokestatic    #226 <Method String String.valueOf(int)>
	//   18   34:invokestatic    #229 <Method String String.valueOf(Object)>
	//   19   37:astore_0        
		if(s.length() != 0)
	//*  20   38:aload_0         
	//*  21   39:invokevirtual   #215 <Method int String.length()>
	//*  22   42:ifeq            51
			return s1.concat(s);
	//   23   45:aload_2         
	//   24   46:aload_0         
	//   25   47:invokevirtual   #234 <Method String String.concat(String)>
	//   26   50:areturn         
		else
			return new String(s1);
	//   27   51:new             #100 <Class String>
	//   28   54:dup             
	//   29   55:aload_2         
	//   30   56:invokespecial   #235 <Method void String(String)>
	//   31   59:areturn         
	}

	private final File zze(String s)
	{
		return new File(zzby, zzd(s));
	//    0    0:new             #47  <Class File>
	//    1    3:dup             
	//    2    4:aload_0         
	//    3    5:getfield        #37  <Field File zzby>
	//    4    8:aload_1         
	//    5    9:invokestatic    #60  <Method String zzd(String)>
	//    6   12:invokespecial   #238 <Method void File(File, String)>
	//    7   15:areturn         
	}

	public final zzc zza(String s)
	{
		this;
	//    0    0:aload_0         
		JVM INSTR monitorenter ;
	//    1    1:monitorenter    
		zzan zzan1 = (zzan)zzbw.get(((Object) (s)));
	//    2    2:aload_0         
	//    3    3:getfield        #33  <Field Map zzbw>
	//    4    6:aload_1         
	//    5    7:invokeinterface #138 <Method Object Map.get(Object)>
	//    6   12:checkcast       #73  <Class zzan>
	//    7   15:astore          4
		if(zzan1 != null)
			break MISSING_BLOCK_LABEL_26;
	//    8   17:aload           4
	//    9   19:ifnonnull       26
		this;
	//   10   22:aload_0         
		JVM INSTR monitorexit ;
	//   11   23:monitorexit     
		return null;
	//   12   24:aconst_null     
	//   13   25:areturn         
		File file = zze(s);
	//   14   26:aload_0         
	//   15   27:aload_1         
	//   16   28:invokespecial   #45  <Method File zze(String)>
	//   17   31:astore_2        
		zzao zzao1 = new zzao(((InputStream) (new BufferedInputStream(zza(file)))), file.length());
	//   18   32:new             #144 <Class zzao>
	//   19   35:dup             
	//   20   36:new             #241 <Class BufferedInputStream>
	//   21   39:dup             
	//   22   40:aload_2         
	//   23   41:invokestatic    #243 <Method InputStream zza(File)>
	//   24   44:invokespecial   #244 <Method void BufferedInputStream(InputStream)>
	//   25   47:aload_2         
	//   26   48:invokevirtual   #246 <Method long File.length()>
	//   27   51:invokespecial   #249 <Method void zzao(InputStream, long)>
	//   28   54:astore_3        
		zzan zzan2 = zzan.zzc(zzao1);
	//   29   55:aload_3         
	//   30   56:invokestatic    #252 <Method zzan zzan.zzc(zzao)>
	//   31   59:astore          5
		if(TextUtils.equals(((CharSequence) (s)), ((CharSequence) (zzan2.zzcb))))
			break MISSING_BLOCK_LABEL_115;
	//   32   61:aload_1         
	//   33   62:aload           5
	//   34   64:getfield        #256 <Field String zzan.zzcb>
	//   35   67:invokestatic    #262 <Method boolean TextUtils.equals(CharSequence, CharSequence)>
	//   36   70:ifne            115
		zzaf.d("%s: key=%s, found=%s", new Object[] {
			file.getAbsolutePath(), s, zzan2.zzcb
		});
	//   37   73:ldc2            #264 <String "%s: key=%s, found=%s">
	//   38   76:iconst_3        
	//   39   77:anewarray       Object[]
	//   40   80:dup             
	//   41   81:iconst_0        
	//   42   82:aload_2         
	//   43   83:invokevirtual   #267 <Method String File.getAbsolutePath()>
	//   44   86:aastore         
	//   45   87:dup             
	//   46   88:iconst_1        
	//   47   89:aload_1         
	//   48   90:aastore         
	//   49   91:dup             
	//   50   92:iconst_2        
	//   51   93:aload           5
	//   52   95:getfield        #256 <Field String zzan.zzcb>
	//   53   98:aastore         
	//   54   99:invokestatic    #66  <Method void zzaf.d(String, Object[])>
		removeEntry(s);
	//   55  102:aload_0         
	//   56  103:aload_1         
	//   57  104:invokespecial   #54  <Method void removeEntry(String)>
		zzao1.close();
	//   58  107:aload_3         
	//   59  108:invokevirtual   #270 <Method void zzao.close()>
		this;
	//   60  111:aload_0         
		JVM INSTR monitorexit ;
	//   61  112:monitorexit     
		return null;
	//   62  113:aconst_null     
	//   63  114:areturn         
		zzc zzc1;
		TreeMap treemap;
		byte abyte0[] = zza(zzao1, zzao1.zzo());
	//   64  115:aload_3         
	//   65  116:aload_3         
	//   66  117:invokevirtual   #148 <Method long zzao.zzo()>
	//   67  120:invokestatic    #107 <Method byte[] zza(zzao, long)>
	//   68  123:astore          6
		zzc1 = new zzc();
	//   69  125:new             #272 <Class zzc>
	//   70  128:dup             
	//   71  129:invokespecial   #273 <Method void zzc()>
	//   72  132:astore          5
		zzc1.data = abyte0;
	//   73  134:aload           5
	//   74  136:aload           6
	//   75  138:putfield        #277 <Field byte[] zzc.data>
		zzc1.zza = zzan1.zza;
	//   76  141:aload           5
	//   77  143:aload           4
	//   78  145:getfield        #279 <Field String zzan.zza>
	//   79  148:putfield        #280 <Field String zzc.zza>
		zzc1.zzb = zzan1.zzb;
	//   80  151:aload           5
	//   81  153:aload           4
	//   82  155:getfield        #282 <Field long zzan.zzb>
	//   83  158:putfield        #283 <Field long zzc.zzb>
		zzc1.zzc = zzan1.zzc;
	//   84  161:aload           5
	//   85  163:aload           4
	//   86  165:getfield        #285 <Field long zzan.zzc>
	//   87  168:putfield        #286 <Field long zzc.zzc>
		zzc1.zzd = zzan1.zzd;
	//   88  171:aload           5
	//   89  173:aload           4
	//   90  175:getfield        #288 <Field long zzan.zzd>
	//   91  178:putfield        #289 <Field long zzc.zzd>
		zzc1.zze = zzan1.zze;
	//   92  181:aload           5
	//   93  183:aload           4
	//   94  185:getfield        #291 <Field long zzan.zze>
	//   95  188:putfield        #292 <Field long zzc.zze>
		Object obj = ((Object) (zzan1.zzg));
	//   96  191:aload           4
	//   97  193:getfield        #296 <Field List zzan.zzg>
	//   98  196:astore          7
		treemap = new TreeMap(String.CASE_INSENSITIVE_ORDER);
	//   99  198:new             #298 <Class TreeMap>
	//  100  201:dup             
	//  101  202:getstatic       #302 <Field java.util.Comparator String.CASE_INSENSITIVE_ORDER>
	//  102  205:invokespecial   #305 <Method void TreeMap(java.util.Comparator)>
	//  103  208:astore          6
		zzl zzl1;
		for(obj = ((Object) (((List) (obj)).iterator())); ((Iterator) (obj)).hasNext(); ((Map) (treemap)).put(((Object) (zzl1.getName())), ((Object) (zzl1.getValue()))))
	//* 104  210:aload           7
	//* 105  212:invokeinterface #309 <Method Iterator List.iterator()>
	//* 106  217:astore          7
	//* 107  219:aload           7
	//* 108  221:invokeinterface #314 <Method boolean Iterator.hasNext()>
	//* 109  226:ifeq            262
			zzl1 = (zzl)((Iterator) (obj)).next();
	//  110  229:aload           7
	//  111  231:invokeinterface #318 <Method Object Iterator.next()>
	//  112  236:checkcast       #195 <Class zzl>
	//  113  239:astore          8

	//  114  241:aload           6
	//  115  243:aload           8
	//  116  245:invokevirtual   #321 <Method String zzl.getName()>
	//  117  248:aload           8
	//  118  250:invokevirtual   #324 <Method String zzl.getValue()>
	//  119  253:invokeinterface #142 <Method Object Map.put(Object, Object)>
	//  120  258:pop             
	//* 121  259:goto            219
		zzc1.zzf = ((Map) (treemap));
	//  122  262:aload           5
	//  123  264:aload           6
	//  124  266:putfield        #327 <Field Map zzc.zzf>
		zzc1.zzg = Collections.unmodifiableList(zzan1.zzg);
	//  125  269:aload           5
	//  126  271:aload           4
	//  127  273:getfield        #296 <Field List zzan.zzg>
	//  128  276:invokestatic    #331 <Method List Collections.unmodifiableList(List)>
	//  129  279:putfield        #332 <Field List zzc.zzg>
		zzao1.close();
	//  130  282:aload_3         
	//  131  283:invokevirtual   #270 <Method void zzao.close()>
		this;
	//  132  286:aload_0         
		JVM INSTR monitorexit ;
	//  133  287:monitorexit     
		return zzc1;
	//  134  288:aload           5
	//  135  290:areturn         
		Exception exception;
		exception;
	//  136  291:astore          4
		zzao1.close();
	//  137  293:aload_3         
	//  138  294:invokevirtual   #270 <Method void zzao.close()>
		throw exception;
	//  139  297:aload           4
	//  140  299:athrow          
		IOException ioexception;
		ioexception;
	//  141  300:astore_3        
		zzaf.d("%s: %s", new Object[] {
			file.getAbsolutePath(), ioexception.toString()
		});
	//  142  301:ldc2            #334 <String "%s: %s">
	//  143  304:iconst_2        
	//  144  305:anewarray       Object[]
	//  145  308:dup             
	//  146  309:iconst_0        
	//  147  310:aload_2         
	//  148  311:invokevirtual   #267 <Method String File.getAbsolutePath()>
	//  149  314:aastore         
	//  150  315:dup             
	//  151  316:iconst_1        
	//  152  317:aload_3         
	//  153  318:invokevirtual   #335 <Method String IOException.toString()>
	//  154  321:aastore         
	//  155  322:invokestatic    #66  <Method void zzaf.d(String, Object[])>
		remove(s);
	//  156  325:aload_0         
	//  157  326:aload_1         
	//  158  327:invokespecial   #337 <Method void remove(String)>
		this;
	//  159  330:aload_0         
		JVM INSTR monitorexit ;
	//  160  331:monitorexit     
		return null;
	//  161  332:aconst_null     
	//  162  333:areturn         
		s;
	//  163  334:astore_1        
	//* 164  335:aload_0         
		throw s;
	//  165  336:monitorexit     
	//  166  337:aload_1         
	//  167  338:athrow          
	}

	public final void zza()
	{
		this;
	//    0    0:aload_0         
		JVM INSTR monitorenter ;
	//    1    1:monitorenter    
		boolean flag = zzby.exists();
	//    2    2:aload_0         
	//    3    3:getfield        #37  <Field File zzby>
	//    4    6:invokevirtual   #340 <Method boolean File.exists()>
	//    5    9:istore_3        
		int i;
		i = 0;
	//    6   10:iconst_0        
	//    7   11:istore_1        
		if(flag)
			break MISSING_BLOCK_LABEL_49;
	//    8   12:iload_3         
	//    9   13:ifne            49
		if(!zzby.mkdirs())
	//*  10   16:aload_0         
	//*  11   17:getfield        #37  <Field File zzby>
	//*  12   20:invokevirtual   #343 <Method boolean File.mkdirs()>
	//*  13   23:ifne            46
			zzaf.e("Unable to create cache dir %s", new Object[] {
				zzby.getAbsolutePath()
			});
	//   14   26:ldc2            #345 <String "Unable to create cache dir %s">
	//   15   29:iconst_1        
	//   16   30:anewarray       Object[]
	//   17   33:dup             
	//   18   34:iconst_0        
	//   19   35:aload_0         
	//   20   36:getfield        #37  <Field File zzby>
	//   21   39:invokevirtual   #267 <Method String File.getAbsolutePath()>
	//   22   42:aastore         
	//   23   43:invokestatic    #348 <Method void zzaf.e(String, Object[])>
		this;
	//   24   46:aload_0         
		JVM INSTR monitorexit ;
	//   25   47:monitorexit     
		return;
	//   26   48:return          
		File afile[] = zzby.listFiles();
	//   27   49:aload_0         
	//   28   50:getfield        #37  <Field File zzby>
	//   29   53:invokevirtual   #352 <Method File[] File.listFiles()>
	//   30   56:astore          6
		if(afile != null)
			break MISSING_BLOCK_LABEL_66;
	//   31   58:aload           6
	//   32   60:ifnonnull       66
		this;
	//   33   63:aload_0         
		JVM INSTR monitorexit ;
	//   34   64:monitorexit     
		return;
	//   35   65:return          
		int j = afile.length;
	//   36   66:aload           6
	//   37   68:arraylength     
	//   38   69:istore_2        
_L3:
		if(i >= j) goto _L2; else goto _L1
	//   39   70:iload_1         
	//   40   71:iload_2         
	//   41   72:icmpge          167
_L1:
		File file = afile[i];
	//   42   75:aload           6
	//   43   77:iload_1         
	//   44   78:aaload          
	//   45   79:astore          7
		long l;
		zzao zzao1;
		l = file.length();
	//   46   81:aload           7
	//   47   83:invokevirtual   #246 <Method long File.length()>
	//   48   86:lstore          4
		zzao1 = new zzao(((InputStream) (new BufferedInputStream(zza(file)))), l);
	//   49   88:new             #144 <Class zzao>
	//   50   91:dup             
	//   51   92:new             #241 <Class BufferedInputStream>
	//   52   95:dup             
	//   53   96:aload           7
	//   54   98:invokestatic    #243 <Method InputStream zza(File)>
	//   55  101:invokespecial   #244 <Method void BufferedInputStream(InputStream)>
	//   56  104:lload           4
	//   57  106:invokespecial   #249 <Method void zzao(InputStream, long)>
	//   58  109:astore          8
		zzan zzan1 = zzan.zzc(zzao1);
	//   59  111:aload           8
	//   60  113:invokestatic    #252 <Method zzan zzan.zzc(zzao)>
	//   61  116:astore          9
		zzan1.zzca = l;
	//   62  118:aload           9
	//   63  120:lload           4
	//   64  122:putfield        #76  <Field long zzan.zzca>
		zza(zzan1.zzcb, zzan1);
	//   65  125:aload_0         
	//   66  126:aload           9
	//   67  128:getfield        #256 <Field String zzan.zzcb>
	//   68  131:aload           9
	//   69  133:invokespecial   #354 <Method void zza(String, zzan)>
		Exception exception1;
		try
		{
			zzao1.close();
	//   70  136:aload           8
	//   71  138:invokevirtual   #270 <Method void zzao.close()>
		}
	//*  72  141:goto            160
	//*  73  144:astore          9
	//*  74  146:aload           8
	//*  75  148:invokevirtual   #270 <Method void zzao.close()>
	//*  76  151:aload           9
	//*  77  153:athrow          
	//*  78  154:aload           7
	//*  79  156:invokevirtual   #51  <Method boolean File.delete()>
	//*  80  159:pop             
	//*  81  160:iload_1         
	//*  82  161:iconst_1        
	//*  83  162:iadd            
	//*  84  163:istore_1        
	//*  85  164:goto            70
	//*  86  167:aload_0         
	//*  87  168:monitorexit     
	//*  88  169:return          
	//*  89  170:astore          6
	//*  90  172:aload_0         
	//*  91  173:monitorexit     
	//*  92  174:aload           6
	//*  93  176:athrow          
		// Misplaced declaration of an exception variable
		catch(IOException ioexception)
		{
			file.delete();
		}
		continue; /* Loop/switch isn't completed */
		exception1;
		zzao1.close();
		throw exception1;
		  goto _L3
_L2:
		this;
		JVM INSTR monitorexit ;
		return;
		Exception exception;
		exception;
		IOException ioexception;
		throw exception;
	//*  94  177:astore          8
	//*  95  179:goto            154
	}

	public final void zza(String s, zzc zzc1)
	{
		this;
	//    0    0:aload_0         
		JVM INSTR monitorenter ;
	//    1    1:monitorenter    
		int i;
		long l;
		i = zzc1.data.length;
	//    2    2:aload_2         
	//    3    3:getfield        #277 <Field byte[] zzc.data>
	//    4    6:arraylength     
	//    5    7:istore_3        
		l = zzbx;
	//    6    8:aload_0         
	//    7    9:getfield        #35  <Field long zzbx>
	//    8   12:lstore          4
		long l1 = i;
	//    9   14:iload_3         
	//   10   15:i2l             
	//   11   16:lstore          6
		long l2;
		Object obj;
		if(l + l1 < (long)zzbz)
			break MISSING_BLOCK_LABEL_253;
	//   12   18:lload           4
	//   13   20:lload           6
	//   14   22:ladd            
	//   15   23:aload_0         
	//   16   24:getfield        #39  <Field int zzbz>
	//   17   27:i2l             
	//   18   28:lcmp            
	//   19   29:iflt            253
		if(zzaf.DEBUG)
	//*  20   32:getstatic       #359 <Field boolean zzaf.DEBUG>
	//*  21   35:ifeq            48
			zzaf.v("Pruning old cache entries.", new Object[0]);
	//   22   38:ldc2            #361 <String "Pruning old cache entries.">
	//   23   41:iconst_0        
	//   24   42:anewarray       Object[]
	//   25   45:invokestatic    #364 <Method void zzaf.v(String, Object[])>
		l2 = zzbx;
	//   26   48:aload_0         
	//   27   49:getfield        #35  <Field long zzbx>
	//   28   52:lstore          8
		l = SystemClock.elapsedRealtime();
	//   29   54:invokestatic    #369 <Method long SystemClock.elapsedRealtime()>
	//   30   57:lstore          4
		obj = ((Object) (zzbw.entrySet().iterator()));
	//   31   59:aload_0         
	//   32   60:getfield        #33  <Field Map zzbw>
	//   33   63:invokeinterface #373 <Method Set Map.entrySet()>
	//   34   68:invokeinterface #376 <Method Iterator Set.iterator()>
	//   35   73:astore          10
		i = 0;
	//   36   75:iconst_0        
	//   37   76:istore_3        
_L2:
		zzan zzan1;
		if(!((Iterator) (obj)).hasNext())
			break; /* Loop/switch isn't completed */
	//   38   77:aload           10
	//   39   79:invokeinterface #314 <Method boolean Iterator.hasNext()>
	//   40   84:ifeq            398
		zzan1 = (zzan)((java.util.Map.Entry)((Iterator) (obj)).next()).getValue();
	//   41   87:aload           10
	//   42   89:invokeinterface #318 <Method Object Iterator.next()>
	//   43   94:checkcast       #378 <Class java.util.Map$Entry>
	//   44   97:invokeinterface #380 <Method Object java.util.Map$Entry.getValue()>
	//   45  102:checkcast       #73  <Class zzan>
	//   46  105:astore          11
		if(zze(zzan1.zzcb).delete())
	//*  47  107:aload_0         
	//*  48  108:aload           11
	//*  49  110:getfield        #256 <Field String zzan.zzcb>
	//*  50  113:invokespecial   #45  <Method File zze(String)>
	//*  51  116:invokevirtual   #51  <Method boolean File.delete()>
	//*  52  119:ifeq            139
		{
			zzbx = zzbx - zzan1.zzca;
	//   53  122:aload_0         
	//   54  123:aload_0         
	//   55  124:getfield        #35  <Field long zzbx>
	//   56  127:aload           11
	//   57  129:getfield        #76  <Field long zzan.zzca>
	//   58  132:lsub            
	//   59  133:putfield        #35  <Field long zzbx>
			break MISSING_BLOCK_LABEL_170;
	//   60  136:goto            392
		}
		zzaf.d("Could not delete cache entry for key=%s, filename=%s", new Object[] {
			zzan1.zzcb, zzd(zzan1.zzcb)
		});
	//   61  139:ldc1            #56  <String "Could not delete cache entry for key=%s, filename=%s">
	//   62  141:iconst_2        
	//   63  142:anewarray       Object[]
	//   64  145:dup             
	//   65  146:iconst_0        
	//   66  147:aload           11
	//   67  149:getfield        #256 <Field String zzan.zzcb>
	//   68  152:aastore         
	//   69  153:dup             
	//   70  154:iconst_1        
	//   71  155:aload           11
	//   72  157:getfield        #256 <Field String zzan.zzcb>
	//   73  160:invokestatic    #60  <Method String zzd(String)>
	//   74  163:aastore         
	//   75  164:invokestatic    #66  <Method void zzaf.d(String, Object[])>
	//*  76  167:goto            392
		((Iterator) (obj)).remove();
	//   77  170:aload           10
	//   78  172:invokeinterface #382 <Method void Iterator.remove()>
		i++;
	//   79  177:iload_3         
	//   80  178:iconst_1        
	//   81  179:iadd            
	//   82  180:istore_3        
		if((float)(zzbx + l1) >= (float)zzbz * 0.9F) goto _L2; else goto _L1
	//   83  181:aload_0         
	//   84  182:getfield        #35  <Field long zzbx>
	//   85  185:lload           6
	//   86  187:ladd            
	//   87  188:l2f             
	//   88  189:aload_0         
	//   89  190:getfield        #39  <Field int zzbz>
	//   90  193:i2f             
	//   91  194:ldc2            #383 <Float 0.9F>
	//   92  197:fmul            
	//   93  198:fcmpg           
	//   94  199:ifge            395
	//*  95  202:goto            205
_L1:
		if(zzaf.DEBUG)
	//*  96  205:getstatic       #359 <Field boolean zzaf.DEBUG>
	//*  97  208:ifeq            253
			zzaf.v("pruned %d files, %d bytes, %d ms", new Object[] {
				Integer.valueOf(i), Long.valueOf(zzbx - l2), Long.valueOf(SystemClock.elapsedRealtime() - l)
			});
	//   98  211:ldc2            #385 <String "pruned %d files, %d bytes, %d ms">
	//   99  214:iconst_3        
	//  100  215:anewarray       Object[]
	//  101  218:dup             
	//  102  219:iconst_0        
	//  103  220:iload_3         
	//  104  221:invokestatic    #390 <Method Integer Integer.valueOf(int)>
	//  105  224:aastore         
	//  106  225:dup             
	//  107  226:iconst_1        
	//  108  227:aload_0         
	//  109  228:getfield        #35  <Field long zzbx>
	//  110  231:lload           8
	//  111  233:lsub            
	//  112  234:invokestatic    #395 <Method Long Long.valueOf(long)>
	//  113  237:aastore         
	//  114  238:dup             
	//  115  239:iconst_2        
	//  116  240:invokestatic    #369 <Method long SystemClock.elapsedRealtime()>
	//  117  243:lload           4
	//  118  245:lsub            
	//  119  246:invokestatic    #395 <Method Long Long.valueOf(long)>
	//  120  249:aastore         
	//  121  250:invokestatic    #364 <Method void zzaf.v(String, Object[])>
		obj = ((Object) (zze(s)));
	//  122  253:aload_0         
	//  123  254:aload_1         
	//  124  255:invokespecial   #45  <Method File zze(String)>
	//  125  258:astore          10
		BufferedOutputStream bufferedoutputstream = new BufferedOutputStream(((OutputStream) (new FileOutputStream(((File) (obj))))));
	//  126  260:new             #397 <Class BufferedOutputStream>
	//  127  263:dup             
	//  128  264:new             #399 <Class FileOutputStream>
	//  129  267:dup             
	//  130  268:aload           10
	//  131  270:invokespecial   #400 <Method void FileOutputStream(File)>
	//  132  273:invokespecial   #403 <Method void BufferedOutputStream(OutputStream)>
	//  133  276:astore          11
		zzan zzan2 = new zzan(s, zzc1);
	//  134  278:new             #73  <Class zzan>
	//  135  281:dup             
	//  136  282:aload_1         
	//  137  283:aload_2         
	//  138  284:invokespecial   #405 <Method void zzan(String, zzc)>
	//  139  287:astore          12
		if(!zzan2.zza(((OutputStream) (bufferedoutputstream))))
	//* 140  289:aload           12
	//* 141  291:aload           11
	//* 142  293:invokevirtual   #408 <Method boolean zzan.zza(OutputStream)>
	//* 143  296:ifne            330
		{
			bufferedoutputstream.close();
	//  144  299:aload           11
	//  145  301:invokevirtual   #409 <Method void BufferedOutputStream.close()>
			zzaf.d("Failed to write header for %s", new Object[] {
				((File) (obj)).getAbsolutePath()
			});
	//  146  304:ldc2            #411 <String "Failed to write header for %s">
	//  147  307:iconst_1        
	//  148  308:anewarray       Object[]
	//  149  311:dup             
	//  150  312:iconst_0        
	//  151  313:aload           10
	//  152  315:invokevirtual   #267 <Method String File.getAbsolutePath()>
	//  153  318:aastore         
	//  154  319:invokestatic    #66  <Method void zzaf.d(String, Object[])>
			throw new IOException();
	//  155  322:new             #80  <Class IOException>
	//  156  325:dup             
	//  157  326:invokespecial   #412 <Method void IOException()>
	//  158  329:athrow          
		}
		bufferedoutputstream.write(zzc1.data);
	//  159  330:aload           11
	//  160  332:aload_2         
	//  161  333:getfield        #277 <Field byte[] zzc.data>
	//  162  336:invokevirtual   #414 <Method void BufferedOutputStream.write(byte[])>
		bufferedoutputstream.close();
	//  163  339:aload           11
	//  164  341:invokevirtual   #409 <Method void BufferedOutputStream.close()>
		zza(s, zzan2);
	//  165  344:aload_0         
	//  166  345:aload_1         
	//  167  346:aload           12
	//  168  348:invokespecial   #354 <Method void zza(String, zzan)>
		this;
	//  169  351:aload_0         
		JVM INSTR monitorexit ;
	//  170  352:monitorexit     
		return;
	//  171  353:return          
_L4:
		if(!((File) (obj)).delete())
	//* 172  354:aload           10
	//* 173  356:invokevirtual   #51  <Method boolean File.delete()>
	//* 174  359:ifne            380
			zzaf.d("Could not clean up file %s", new Object[] {
				((File) (obj)).getAbsolutePath()
			});
	//  175  362:ldc2            #416 <String "Could not clean up file %s">
	//  176  365:iconst_1        
	//  177  366:anewarray       Object[]
	//  178  369:dup             
	//  179  370:iconst_0        
	//  180  371:aload           10
	//  181  373:invokevirtual   #267 <Method String File.getAbsolutePath()>
	//  182  376:aastore         
	//  183  377:invokestatic    #66  <Method void zzaf.d(String, Object[])>
		this;
	//  184  380:aload_0         
		JVM INSTR monitorexit ;
	//  185  381:monitorexit     
		return;
	//  186  382:return          
		s;
	//  187  383:astore_1        
	//* 188  384:aload_0         
		throw s;
	//  189  385:monitorexit     
	//  190  386:aload_1         
	//  191  387:athrow          
		s;
	//  192  388:astore_1        
		if(true) goto _L4; else goto _L3
_L3:
	//* 193  389:goto            354
	//* 194  392:goto            170
	//* 195  395:goto            77
	//* 196  398:goto            205
	}

	private final Map zzbw;
	private long zzbx;
	private final File zzby;
	private final int zzbz;
}
