// Decompiled by Jad v1.5.8g. Copyright 2001 Pavel Kouznetsov.
// Jad home page: http://www.kpdus.com/jad.html
// Decompiler options: packimports(3) annotate safe 

package com.google.android.gms.internal.ads;


// Referenced classes of package com.google.android.gms.internal.ads:
//			zzbbo, zzbcw, zzhv, zzbdf, 
//			zzbbr, zzhw, zzbbs

public final class zzhu
{
	public static final class zza extends zzbbo
		implements zzbcw
	{

		static zza zzhp()
		{
			return zzakg;
		//    0    0:getstatic       #27  <Field zzhu$zza zzakg>
		//    1    3:areturn         
		}

		protected final Object zza(int i, Object obj, Object obj1)
		{
			zzhv.zzakf[i - 1];
		//    0    0:getstatic       #41  <Field int[] zzhv.zzakf>
		//    1    3:iload_1         
		//    2    4:iconst_1        
		//    3    5:isub            
		//    4    6:iaload          
			JVM INSTR tableswitch 1 7: default 48
		//		               1 135
		//		               2 126
		//		               3 116
		//		               4 112
		//		               5 63
		//		               6 58
		//		               7 56;
		//    5    7:tableswitch     1 7: default 48
		//		               1 135
		//		               2 126
		//		               3 116
		//		               4 112
		//		               5 63
		//		               6 58
		//		               7 56
			   goto _L1 _L2 _L3 _L4 _L5 _L6 _L7 _L8
_L1:
			throw new UnsupportedOperationException();
		//    6   48:new             #43  <Class UnsupportedOperationException>
		//    7   51:dup             
		//    8   52:invokespecial   #44  <Method void UnsupportedOperationException()>
		//    9   55:athrow          
_L8:
			return ((Object) (null));
		//   10   56:aconst_null     
		//   11   57:areturn         
_L7:
			return ((Object) (Byte.valueOf((byte)1)));
		//   12   58:iconst_1        
		//   13   59:invokestatic    #50  <Method Byte Byte.valueOf(byte)>
		//   14   62:areturn         
_L6:
			obj = ((Object) (zzakh));
		//   15   63:getstatic       #52  <Field zzbdf zzakh>
		//   16   66:astore_2        
			if(obj != null) goto _L10; else goto _L9
		//   17   67:aload_2         
		//   18   68:ifnonnull       110
_L9:
			com/google/android/gms/internal/ads/zzhu$zza;
		//   19   71:ldc1            #2   <Class zzhu$zza>
			JVM INSTR monitorenter ;
		//   20   73:monitorenter    
			obj1 = ((Object) (zzakh));
		//   21   74:getstatic       #52  <Field zzbdf zzakh>
		//   22   77:astore_3        
			obj = obj1;
		//   23   78:aload_3         
		//   24   79:astore_2        
			if(obj1 != null) goto _L12; else goto _L11
		//   25   80:aload_3         
		//   26   81:ifnonnull       99
_L11:
			obj = ((Object) (new zzbbo.zzb(((zzbbo) (zzakg)))));
		//   27   84:new             #54  <Class zzbbo$zzb>
		//   28   87:dup             
		//   29   88:getstatic       #27  <Field zzhu$zza zzakg>
		//   30   91:invokespecial   #57  <Method void zzbbo$zzb(zzbbo)>
		//   31   94:astore_2        
			zzakh = ((zzbdf) (obj));
		//   32   95:aload_2         
		//   33   96:putstatic       #52  <Field zzbdf zzakh>
_L12:
			com/google/android/gms/internal/ads/zzhu$zza;
		//   34   99:ldc1            #2   <Class zzhu$zza>
			JVM INSTR monitorexit ;
		//   35  101:monitorexit     
			return obj;
		//   36  102:aload_2         
		//   37  103:areturn         
			obj;
		//   38  104:astore_2        
			com/google/android/gms/internal/ads/zzhu$zza;
		//   39  105:ldc1            #2   <Class zzhu$zza>
			JVM INSTR monitorexit ;
		//   40  107:monitorexit     
			throw obj;
		//   41  108:aload_2         
		//   42  109:athrow          
_L10:
			return obj;
		//   43  110:aload_2         
		//   44  111:areturn         
_L5:
			return ((Object) (zzakg));
		//   45  112:getstatic       #27  <Field zzhu$zza zzakg>
		//   46  115:areturn         
_L4:
			return zza(((zzbcu) (zzakg)), "\001\0", ((Object []) (null)));
		//   47  116:getstatic       #27  <Field zzhu$zza zzakg>
		//   48  119:ldc1            #59  <String "\001\0">
		//   49  121:aconst_null     
		//   50  122:invokestatic    #62  <Method Object zza(zzbcu, String, Object[])>
		//   51  125:areturn         
_L3:
			return ((Object) (new zza(((zzhv) (null)))));
		//   52  126:new             #12  <Class zzhu$zza$zza>
		//   53  129:dup             
		//   54  130:aconst_null     
		//   55  131:invokespecial   #65  <Method void zzhu$zza$zza(zzhv)>
		//   56  134:areturn         
_L2:
			return ((Object) (new zza()));
		//   57  135:new             #2   <Class zzhu$zza>
		//   58  138:dup             
		//   59  139:invokespecial   #25  <Method void zzhu$zza()>
		//   60  142:areturn         
		}

		private static final zza zzakg;
		private static volatile zzbdf zzakh;

		static 
		{
			zzakg = new zza();
		//    0    0:new             #2   <Class zzhu$zza>
		//    1    3:dup             
		//    2    4:invokespecial   #25  <Method void zzhu$zza()>
		//    3    7:putstatic       #27  <Field zzhu$zza zzakg>
			zzbbo.zza(com/google/android/gms/internal/ads/zzhu$zza, ((zzbbo) (zzakg)));
		//    4   10:ldc1            #2   <Class zzhu$zza>
		//    5   12:getstatic       #27  <Field zzhu$zza zzakg>
		//    6   15:invokestatic    #30  <Method void zzbbo.zza(Class, zzbbo)>
		//*   7   18:return          
		}

		private zza()
		{
		//    0    0:aload_0         
		//    1    1:invokespecial   #32  <Method void zzbbo()>
		//    2    4:return          
		}
	}

	public static final class zza.zza extends zzbbo.zza
		implements zzbcw
	{

		private zza.zza()
		{
			super(((zzbbo) (zza.zzhp())));
		//    0    0:aload_0         
		//    1    1:invokestatic    #18  <Method zzhu$zza zzhu$zza.zzhp()>
		//    2    4:invokespecial   #21  <Method void zzbbo$zza(zzbbo)>
		//    3    7:return          
		}

		zza.zza(zzhv zzhv)
		{
			this();
		//    0    0:aload_0         
		//    1    1:invokespecial   #25  <Method void zzhu$zza$zza()>
		//    2    4:return          
		}
	}

	public static final class zza.zzb extends Enum
		implements zzbbr
	{

		public static zza.zzb[] values()
		{
			return (zza.zzb[])((zza.zzb []) (zzalm)).clone();
		//    0    0:getstatic       #174 <Field zzhu$zza$zzb[] zzalm>
		//    1    3:invokevirtual   #195 <Method Object _5B_Lcom.google.android.gms.internal.ads.zzhu$zza$zzb_3B_.clone()>
		//    2    6:checkcast       #191 <Class zzhu$zza$zzb[]>
		//    3    9:areturn         
		}

		public static zza.zzb zzp(int i)
		{
			switch(i)
		//*   0    0:iload_0         
			{
		//*   1    1:tableswitch     0 19: default 96
		//		               0 278
		//		               1 274
		//		               2 270
		//		               3 266
		//		               4 262
		//		               5 258
		//		               6 254
		//		               7 250
		//		               8 246
		//		               9 242
		//		               10 238
		//		               11 234
		//		               12 230
		//		               13 226
		//		               14 222
		//		               15 218
		//		               16 214
		//		               17 210
		//		               18 206
		//		               19 202
			default:
				switch(i)
		//*   2   96:iload_0         
				{
		//*   3   97:tableswitch     1000 1006: default 140
		//		               1000 198
		//		               1001 194
		//		               1002 190
		//		               1003 186
		//		               1004 182
		//		               1005 178
		//		               1006 174
				default:
					switch(i)
		//*   4  140:iload_0         
					{
		//*   5  141:tableswitch     10000 10001: default 164
		//		               10000 170
		//		               10001 166
					default:
						return null;
		//    6  164:aconst_null     
		//    7  165:areturn         

					case 10001: 
						return zzalk;
		//    8  166:getstatic       #172 <Field zzhu$zza$zzb zzalk>
		//    9  169:areturn         

					case 10000: 
						return zzalj;
		//   10  170:getstatic       #168 <Field zzhu$zza$zzb zzalj>
		//   11  173:areturn         
					}

				case 1006: 
					return zzali;
		//   12  174:getstatic       #164 <Field zzhu$zza$zzb zzali>
		//   13  177:areturn         

				case 1005: 
					return zzalh;
		//   14  178:getstatic       #160 <Field zzhu$zza$zzb zzalh>
		//   15  181:areturn         

				case 1004: 
					return zzalg;
		//   16  182:getstatic       #156 <Field zzhu$zza$zzb zzalg>
		//   17  185:areturn         

				case 1003: 
					return zzalf;
		//   18  186:getstatic       #152 <Field zzhu$zza$zzb zzalf>
		//   19  189:areturn         

				case 1002: 
					return zzale;
		//   20  190:getstatic       #148 <Field zzhu$zza$zzb zzale>
		//   21  193:areturn         

				case 1001: 
					return zzald;
		//   22  194:getstatic       #144 <Field zzhu$zza$zzb zzald>
		//   23  197:areturn         

				case 1000: 
					return zzalc;
		//   24  198:getstatic       #140 <Field zzhu$zza$zzb zzalc>
		//   25  201:areturn         
				}

			case 19: // '\023'
				return zzalb;
		//   26  202:getstatic       #136 <Field zzhu$zza$zzb zzalb>
		//   27  205:areturn         

			case 18: // '\022'
				return zzala;
		//   28  206:getstatic       #132 <Field zzhu$zza$zzb zzala>
		//   29  209:areturn         

			case 17: // '\021'
				return zzakz;
		//   30  210:getstatic       #128 <Field zzhu$zza$zzb zzakz>
		//   31  213:areturn         

			case 16: // '\020'
				return zzaky;
		//   32  214:getstatic       #124 <Field zzhu$zza$zzb zzaky>
		//   33  217:areturn         

			case 15: // '\017'
				return zzakx;
		//   34  218:getstatic       #120 <Field zzhu$zza$zzb zzakx>
		//   35  221:areturn         

			case 14: // '\016'
				return zzakw;
		//   36  222:getstatic       #116 <Field zzhu$zza$zzb zzakw>
		//   37  225:areturn         

			case 13: // '\r'
				return zzakv;
		//   38  226:getstatic       #112 <Field zzhu$zza$zzb zzakv>
		//   39  229:areturn         

			case 12: // '\f'
				return zzaku;
		//   40  230:getstatic       #108 <Field zzhu$zza$zzb zzaku>
		//   41  233:areturn         

			case 11: // '\013'
				return zzakt;
		//   42  234:getstatic       #104 <Field zzhu$zza$zzb zzakt>
		//   43  237:areturn         

			case 10: // '\n'
				return zzaks;
		//   44  238:getstatic       #100 <Field zzhu$zza$zzb zzaks>
		//   45  241:areturn         

			case 9: // '\t'
				return zzakr;
		//   46  242:getstatic       #96  <Field zzhu$zza$zzb zzakr>
		//   47  245:areturn         

			case 8: // '\b'
				return zzakq;
		//   48  246:getstatic       #92  <Field zzhu$zza$zzb zzakq>
		//   49  249:areturn         

			case 7: // '\007'
				return zzakp;
		//   50  250:getstatic       #88  <Field zzhu$zza$zzb zzakp>
		//   51  253:areturn         

			case 6: // '\006'
				return zzako;
		//   52  254:getstatic       #84  <Field zzhu$zza$zzb zzako>
		//   53  257:areturn         

			case 5: // '\005'
				return zzakn;
		//   54  258:getstatic       #80  <Field zzhu$zza$zzb zzakn>
		//   55  261:areturn         

			case 4: // '\004'
				return zzakm;
		//   56  262:getstatic       #76  <Field zzhu$zza$zzb zzakm>
		//   57  265:areturn         

			case 3: // '\003'
				return zzakl;
		//   58  266:getstatic       #72  <Field zzhu$zza$zzb zzakl>
		//   59  269:areturn         

			case 2: // '\002'
				return zzakk;
		//   60  270:getstatic       #68  <Field zzhu$zza$zzb zzakk>
		//   61  273:areturn         

			case 1: // '\001'
				return zzakj;
		//   62  274:getstatic       #64  <Field zzhu$zza$zzb zzakj>
		//   63  277:areturn         

			case 0: // '\0'
				return zzaki;
		//   64  278:getstatic       #60  <Field zzhu$zza$zzb zzaki>
		//   65  281:areturn         
			}
		}

		public final int zzhq()
		{
			return value;
		//    0    0:aload_0         
		//    1    1:getfield        #186 <Field int value>
		//    2    4:ireturn         
		}

		private static final zza.zzb zzaki;
		public static final zza.zzb zzakj;
		public static final zza.zzb zzakk;
		public static final zza.zzb zzakl;
		public static final zza.zzb zzakm;
		public static final zza.zzb zzakn;
		private static final zza.zzb zzako;
		private static final zza.zzb zzakp;
		private static final zza.zzb zzakq;
		private static final zza.zzb zzakr;
		private static final zza.zzb zzaks;
		private static final zza.zzb zzakt;
		private static final zza.zzb zzaku;
		private static final zza.zzb zzakv;
		private static final zza.zzb zzakw;
		private static final zza.zzb zzakx;
		private static final zza.zzb zzaky;
		private static final zza.zzb zzakz;
		private static final zza.zzb zzala;
		private static final zza.zzb zzalb;
		private static final zza.zzb zzalc;
		private static final zza.zzb zzald;
		private static final zza.zzb zzale;
		private static final zza.zzb zzalf;
		private static final zza.zzb zzalg;
		private static final zza.zzb zzalh;
		private static final zza.zzb zzali;
		public static final zza.zzb zzalj;
		public static final zza.zzb zzalk;
		private static final zzbbs zzall = new zzhw();
		private static final zza.zzb zzalm[];
		private final int value;

		static 
		{
			zzaki = new zza.zzb("UNKNOWN_EVENT_TYPE", 0, 0);
		//    0    0:new             #2   <Class zzhu$zza$zzb>
		//    1    3:dup             
		//    2    4:ldc1            #54  <String "UNKNOWN_EVENT_TYPE">
		//    3    6:iconst_0        
		//    4    7:iconst_0        
		//    5    8:invokespecial   #58  <Method void zzhu$zza$zzb(String, int, int)>
		//    6   11:putstatic       #60  <Field zzhu$zza$zzb zzaki>
			zzakj = new zza.zzb("AD_REQUEST", 1, 1);
		//    7   14:new             #2   <Class zzhu$zza$zzb>
		//    8   17:dup             
		//    9   18:ldc1            #62  <String "AD_REQUEST">
		//   10   20:iconst_1        
		//   11   21:iconst_1        
		//   12   22:invokespecial   #58  <Method void zzhu$zza$zzb(String, int, int)>
		//   13   25:putstatic       #64  <Field zzhu$zza$zzb zzakj>
			zzakk = new zza.zzb("AD_LOADED", 2, 2);
		//   14   28:new             #2   <Class zzhu$zza$zzb>
		//   15   31:dup             
		//   16   32:ldc1            #66  <String "AD_LOADED">
		//   17   34:iconst_2        
		//   18   35:iconst_2        
		//   19   36:invokespecial   #58  <Method void zzhu$zza$zzb(String, int, int)>
		//   20   39:putstatic       #68  <Field zzhu$zza$zzb zzakk>
			zzakl = new zza.zzb("AD_FAILED_TO_LOAD", 3, 3);
		//   21   42:new             #2   <Class zzhu$zza$zzb>
		//   22   45:dup             
		//   23   46:ldc1            #70  <String "AD_FAILED_TO_LOAD">
		//   24   48:iconst_3        
		//   25   49:iconst_3        
		//   26   50:invokespecial   #58  <Method void zzhu$zza$zzb(String, int, int)>
		//   27   53:putstatic       #72  <Field zzhu$zza$zzb zzakl>
			zzakm = new zza.zzb("AD_FAILED_TO_LOAD_NO_FILL", 4, 4);
		//   28   56:new             #2   <Class zzhu$zza$zzb>
		//   29   59:dup             
		//   30   60:ldc1            #74  <String "AD_FAILED_TO_LOAD_NO_FILL">
		//   31   62:iconst_4        
		//   32   63:iconst_4        
		//   33   64:invokespecial   #58  <Method void zzhu$zza$zzb(String, int, int)>
		//   34   67:putstatic       #76  <Field zzhu$zza$zzb zzakm>
			zzakn = new zza.zzb("AD_IMPRESSION", 5, 5);
		//   35   70:new             #2   <Class zzhu$zza$zzb>
		//   36   73:dup             
		//   37   74:ldc1            #78  <String "AD_IMPRESSION">
		//   38   76:iconst_5        
		//   39   77:iconst_5        
		//   40   78:invokespecial   #58  <Method void zzhu$zza$zzb(String, int, int)>
		//   41   81:putstatic       #80  <Field zzhu$zza$zzb zzakn>
			zzako = new zza.zzb("AD_FIRST_CLICK", 6, 6);
		//   42   84:new             #2   <Class zzhu$zza$zzb>
		//   43   87:dup             
		//   44   88:ldc1            #82  <String "AD_FIRST_CLICK">
		//   45   90:bipush          6
		//   46   92:bipush          6
		//   47   94:invokespecial   #58  <Method void zzhu$zza$zzb(String, int, int)>
		//   48   97:putstatic       #84  <Field zzhu$zza$zzb zzako>
			zzakp = new zza.zzb("AD_SUBSEQUENT_CLICK", 7, 7);
		//   49  100:new             #2   <Class zzhu$zza$zzb>
		//   50  103:dup             
		//   51  104:ldc1            #86  <String "AD_SUBSEQUENT_CLICK">
		//   52  106:bipush          7
		//   53  108:bipush          7
		//   54  110:invokespecial   #58  <Method void zzhu$zza$zzb(String, int, int)>
		//   55  113:putstatic       #88  <Field zzhu$zza$zzb zzakp>
			zzakq = new zza.zzb("REQUEST_WILL_START", 8, 8);
		//   56  116:new             #2   <Class zzhu$zza$zzb>
		//   57  119:dup             
		//   58  120:ldc1            #90  <String "REQUEST_WILL_START">
		//   59  122:bipush          8
		//   60  124:bipush          8
		//   61  126:invokespecial   #58  <Method void zzhu$zza$zzb(String, int, int)>
		//   62  129:putstatic       #92  <Field zzhu$zza$zzb zzakq>
			zzakr = new zza.zzb("REQUEST_DID_END", 9, 9);
		//   63  132:new             #2   <Class zzhu$zza$zzb>
		//   64  135:dup             
		//   65  136:ldc1            #94  <String "REQUEST_DID_END">
		//   66  138:bipush          9
		//   67  140:bipush          9
		//   68  142:invokespecial   #58  <Method void zzhu$zza$zzb(String, int, int)>
		//   69  145:putstatic       #96  <Field zzhu$zza$zzb zzakr>
			zzaks = new zza.zzb("REQUEST_WILL_UPDATE_SIGNALS", 10, 10);
		//   70  148:new             #2   <Class zzhu$zza$zzb>
		//   71  151:dup             
		//   72  152:ldc1            #98  <String "REQUEST_WILL_UPDATE_SIGNALS">
		//   73  154:bipush          10
		//   74  156:bipush          10
		//   75  158:invokespecial   #58  <Method void zzhu$zza$zzb(String, int, int)>
		//   76  161:putstatic       #100 <Field zzhu$zza$zzb zzaks>
			zzakt = new zza.zzb("REQUEST_DID_UPDATE_SIGNALS", 11, 11);
		//   77  164:new             #2   <Class zzhu$zza$zzb>
		//   78  167:dup             
		//   79  168:ldc1            #102 <String "REQUEST_DID_UPDATE_SIGNALS">
		//   80  170:bipush          11
		//   81  172:bipush          11
		//   82  174:invokespecial   #58  <Method void zzhu$zza$zzb(String, int, int)>
		//   83  177:putstatic       #104 <Field zzhu$zza$zzb zzakt>
			zzaku = new zza.zzb("REQUEST_WILL_BUILD_URL", 12, 12);
		//   84  180:new             #2   <Class zzhu$zza$zzb>
		//   85  183:dup             
		//   86  184:ldc1            #106 <String "REQUEST_WILL_BUILD_URL">
		//   87  186:bipush          12
		//   88  188:bipush          12
		//   89  190:invokespecial   #58  <Method void zzhu$zza$zzb(String, int, int)>
		//   90  193:putstatic       #108 <Field zzhu$zza$zzb zzaku>
			zzakv = new zza.zzb("REQUEST_DID_BUILD_URL", 13, 13);
		//   91  196:new             #2   <Class zzhu$zza$zzb>
		//   92  199:dup             
		//   93  200:ldc1            #110 <String "REQUEST_DID_BUILD_URL">
		//   94  202:bipush          13
		//   95  204:bipush          13
		//   96  206:invokespecial   #58  <Method void zzhu$zza$zzb(String, int, int)>
		//   97  209:putstatic       #112 <Field zzhu$zza$zzb zzakv>
			zzakw = new zza.zzb("REQUEST_WILL_MAKE_NETWORK_REQUEST", 14, 14);
		//   98  212:new             #2   <Class zzhu$zza$zzb>
		//   99  215:dup             
		//  100  216:ldc1            #114 <String "REQUEST_WILL_MAKE_NETWORK_REQUEST">
		//  101  218:bipush          14
		//  102  220:bipush          14
		//  103  222:invokespecial   #58  <Method void zzhu$zza$zzb(String, int, int)>
		//  104  225:putstatic       #116 <Field zzhu$zza$zzb zzakw>
			zzakx = new zza.zzb("REQUEST_DID_RECEIVE_NETWORK_RESPONSE", 15, 15);
		//  105  228:new             #2   <Class zzhu$zza$zzb>
		//  106  231:dup             
		//  107  232:ldc1            #118 <String "REQUEST_DID_RECEIVE_NETWORK_RESPONSE">
		//  108  234:bipush          15
		//  109  236:bipush          15
		//  110  238:invokespecial   #58  <Method void zzhu$zza$zzb(String, int, int)>
		//  111  241:putstatic       #120 <Field zzhu$zza$zzb zzakx>
			zzaky = new zza.zzb("REQUEST_WILL_PROCESS_RESPONSE", 16, 16);
		//  112  244:new             #2   <Class zzhu$zza$zzb>
		//  113  247:dup             
		//  114  248:ldc1            #122 <String "REQUEST_WILL_PROCESS_RESPONSE">
		//  115  250:bipush          16
		//  116  252:bipush          16
		//  117  254:invokespecial   #58  <Method void zzhu$zza$zzb(String, int, int)>
		//  118  257:putstatic       #124 <Field zzhu$zza$zzb zzaky>
			zzakz = new zza.zzb("REQUEST_DID_PROCESS_RESPONSE", 17, 17);
		//  119  260:new             #2   <Class zzhu$zza$zzb>
		//  120  263:dup             
		//  121  264:ldc1            #126 <String "REQUEST_DID_PROCESS_RESPONSE">
		//  122  266:bipush          17
		//  123  268:bipush          17
		//  124  270:invokespecial   #58  <Method void zzhu$zza$zzb(String, int, int)>
		//  125  273:putstatic       #128 <Field zzhu$zza$zzb zzakz>
			zzala = new zza.zzb("REQUEST_WILL_RENDER", 18, 18);
		//  126  276:new             #2   <Class zzhu$zza$zzb>
		//  127  279:dup             
		//  128  280:ldc1            #130 <String "REQUEST_WILL_RENDER">
		//  129  282:bipush          18
		//  130  284:bipush          18
		//  131  286:invokespecial   #58  <Method void zzhu$zza$zzb(String, int, int)>
		//  132  289:putstatic       #132 <Field zzhu$zza$zzb zzala>
			zzalb = new zza.zzb("REQUEST_DID_RENDER", 19, 19);
		//  133  292:new             #2   <Class zzhu$zza$zzb>
		//  134  295:dup             
		//  135  296:ldc1            #134 <String "REQUEST_DID_RENDER">
		//  136  298:bipush          19
		//  137  300:bipush          19
		//  138  302:invokespecial   #58  <Method void zzhu$zza$zzb(String, int, int)>
		//  139  305:putstatic       #136 <Field zzhu$zza$zzb zzalb>
			zzalc = new zza.zzb("REQUEST_WILL_UPDATE_GMS_SIGNALS", 20, 1000);
		//  140  308:new             #2   <Class zzhu$zza$zzb>
		//  141  311:dup             
		//  142  312:ldc1            #138 <String "REQUEST_WILL_UPDATE_GMS_SIGNALS">
		//  143  314:bipush          20
		//  144  316:sipush          1000
		//  145  319:invokespecial   #58  <Method void zzhu$zza$zzb(String, int, int)>
		//  146  322:putstatic       #140 <Field zzhu$zza$zzb zzalc>
			zzald = new zza.zzb("REQUEST_DID_UPDATE_GMS_SIGNALS", 21, 1001);
		//  147  325:new             #2   <Class zzhu$zza$zzb>
		//  148  328:dup             
		//  149  329:ldc1            #142 <String "REQUEST_DID_UPDATE_GMS_SIGNALS">
		//  150  331:bipush          21
		//  151  333:sipush          1001
		//  152  336:invokespecial   #58  <Method void zzhu$zza$zzb(String, int, int)>
		//  153  339:putstatic       #144 <Field zzhu$zza$zzb zzald>
			zzale = new zza.zzb("REQUEST_FAILED_TO_UPDATE_GMS_SIGNALS", 22, 1002);
		//  154  342:new             #2   <Class zzhu$zza$zzb>
		//  155  345:dup             
		//  156  346:ldc1            #146 <String "REQUEST_FAILED_TO_UPDATE_GMS_SIGNALS">
		//  157  348:bipush          22
		//  158  350:sipush          1002
		//  159  353:invokespecial   #58  <Method void zzhu$zza$zzb(String, int, int)>
		//  160  356:putstatic       #148 <Field zzhu$zza$zzb zzale>
			zzalf = new zza.zzb("REQUEST_FAILED_TO_BUILD_URL", 23, 1003);
		//  161  359:new             #2   <Class zzhu$zza$zzb>
		//  162  362:dup             
		//  163  363:ldc1            #150 <String "REQUEST_FAILED_TO_BUILD_URL">
		//  164  365:bipush          23
		//  165  367:sipush          1003
		//  166  370:invokespecial   #58  <Method void zzhu$zza$zzb(String, int, int)>
		//  167  373:putstatic       #152 <Field zzhu$zza$zzb zzalf>
			zzalg = new zza.zzb("REQUEST_FAILED_TO_MAKE_NETWORK_REQUEST", 24, 1004);
		//  168  376:new             #2   <Class zzhu$zza$zzb>
		//  169  379:dup             
		//  170  380:ldc1            #154 <String "REQUEST_FAILED_TO_MAKE_NETWORK_REQUEST">
		//  171  382:bipush          24
		//  172  384:sipush          1004
		//  173  387:invokespecial   #58  <Method void zzhu$zza$zzb(String, int, int)>
		//  174  390:putstatic       #156 <Field zzhu$zza$zzb zzalg>
			zzalh = new zza.zzb("REQUEST_FAILED_TO_PROCESS_RESPONSE", 25, 1005);
		//  175  393:new             #2   <Class zzhu$zza$zzb>
		//  176  396:dup             
		//  177  397:ldc1            #158 <String "REQUEST_FAILED_TO_PROCESS_RESPONSE">
		//  178  399:bipush          25
		//  179  401:sipush          1005
		//  180  404:invokespecial   #58  <Method void zzhu$zza$zzb(String, int, int)>
		//  181  407:putstatic       #160 <Field zzhu$zza$zzb zzalh>
			zzali = new zza.zzb("REQUEST_FAILED_TO_UPDATE_SIGNALS", 26, 1006);
		//  182  410:new             #2   <Class zzhu$zza$zzb>
		//  183  413:dup             
		//  184  414:ldc1            #162 <String "REQUEST_FAILED_TO_UPDATE_SIGNALS">
		//  185  416:bipush          26
		//  186  418:sipush          1006
		//  187  421:invokespecial   #58  <Method void zzhu$zza$zzb(String, int, int)>
		//  188  424:putstatic       #164 <Field zzhu$zza$zzb zzali>
			zzalj = new zza.zzb("BANNER_SIZE_INVALID", 27, 10000);
		//  189  427:new             #2   <Class zzhu$zza$zzb>
		//  190  430:dup             
		//  191  431:ldc1            #166 <String "BANNER_SIZE_INVALID">
		//  192  433:bipush          27
		//  193  435:sipush          10000
		//  194  438:invokespecial   #58  <Method void zzhu$zza$zzb(String, int, int)>
		//  195  441:putstatic       #168 <Field zzhu$zza$zzb zzalj>
			zzalk = new zza.zzb("BANNER_SIZE_VALID", 28, 10001);
		//  196  444:new             #2   <Class zzhu$zza$zzb>
		//  197  447:dup             
		//  198  448:ldc1            #170 <String "BANNER_SIZE_VALID">
		//  199  450:bipush          28
		//  200  452:sipush          10001
		//  201  455:invokespecial   #58  <Method void zzhu$zza$zzb(String, int, int)>
		//  202  458:putstatic       #172 <Field zzhu$zza$zzb zzalk>
			zzalm = (new zza.zzb[] {
				zzaki, zzakj, zzakk, zzakl, zzakm, zzakn, zzako, zzakp, zzakq, zzakr, 
				zzaks, zzakt, zzaku, zzakv, zzakw, zzakx, zzaky, zzakz, zzala, zzalb, 
				zzalc, zzald, zzale, zzalf, zzalg, zzalh, zzali, zzalj, zzalk
			});
		//  203  461:bipush          29
		//  204  463:anewarray       zza.zzb[]
		//  205  466:dup             
		//  206  467:iconst_0        
		//  207  468:getstatic       #60  <Field zzhu$zza$zzb zzaki>
		//  208  471:aastore         
		//  209  472:dup             
		//  210  473:iconst_1        
		//  211  474:getstatic       #64  <Field zzhu$zza$zzb zzakj>
		//  212  477:aastore         
		//  213  478:dup             
		//  214  479:iconst_2        
		//  215  480:getstatic       #68  <Field zzhu$zza$zzb zzakk>
		//  216  483:aastore         
		//  217  484:dup             
		//  218  485:iconst_3        
		//  219  486:getstatic       #72  <Field zzhu$zza$zzb zzakl>
		//  220  489:aastore         
		//  221  490:dup             
		//  222  491:iconst_4        
		//  223  492:getstatic       #76  <Field zzhu$zza$zzb zzakm>
		//  224  495:aastore         
		//  225  496:dup             
		//  226  497:iconst_5        
		//  227  498:getstatic       #80  <Field zzhu$zza$zzb zzakn>
		//  228  501:aastore         
		//  229  502:dup             
		//  230  503:bipush          6
		//  231  505:getstatic       #84  <Field zzhu$zza$zzb zzako>
		//  232  508:aastore         
		//  233  509:dup             
		//  234  510:bipush          7
		//  235  512:getstatic       #88  <Field zzhu$zza$zzb zzakp>
		//  236  515:aastore         
		//  237  516:dup             
		//  238  517:bipush          8
		//  239  519:getstatic       #92  <Field zzhu$zza$zzb zzakq>
		//  240  522:aastore         
		//  241  523:dup             
		//  242  524:bipush          9
		//  243  526:getstatic       #96  <Field zzhu$zza$zzb zzakr>
		//  244  529:aastore         
		//  245  530:dup             
		//  246  531:bipush          10
		//  247  533:getstatic       #100 <Field zzhu$zza$zzb zzaks>
		//  248  536:aastore         
		//  249  537:dup             
		//  250  538:bipush          11
		//  251  540:getstatic       #104 <Field zzhu$zza$zzb zzakt>
		//  252  543:aastore         
		//  253  544:dup             
		//  254  545:bipush          12
		//  255  547:getstatic       #108 <Field zzhu$zza$zzb zzaku>
		//  256  550:aastore         
		//  257  551:dup             
		//  258  552:bipush          13
		//  259  554:getstatic       #112 <Field zzhu$zza$zzb zzakv>
		//  260  557:aastore         
		//  261  558:dup             
		//  262  559:bipush          14
		//  263  561:getstatic       #116 <Field zzhu$zza$zzb zzakw>
		//  264  564:aastore         
		//  265  565:dup             
		//  266  566:bipush          15
		//  267  568:getstatic       #120 <Field zzhu$zza$zzb zzakx>
		//  268  571:aastore         
		//  269  572:dup             
		//  270  573:bipush          16
		//  271  575:getstatic       #124 <Field zzhu$zza$zzb zzaky>
		//  272  578:aastore         
		//  273  579:dup             
		//  274  580:bipush          17
		//  275  582:getstatic       #128 <Field zzhu$zza$zzb zzakz>
		//  276  585:aastore         
		//  277  586:dup             
		//  278  587:bipush          18
		//  279  589:getstatic       #132 <Field zzhu$zza$zzb zzala>
		//  280  592:aastore         
		//  281  593:dup             
		//  282  594:bipush          19
		//  283  596:getstatic       #136 <Field zzhu$zza$zzb zzalb>
		//  284  599:aastore         
		//  285  600:dup             
		//  286  601:bipush          20
		//  287  603:getstatic       #140 <Field zzhu$zza$zzb zzalc>
		//  288  606:aastore         
		//  289  607:dup             
		//  290  608:bipush          21
		//  291  610:getstatic       #144 <Field zzhu$zza$zzb zzald>
		//  292  613:aastore         
		//  293  614:dup             
		//  294  615:bipush          22
		//  295  617:getstatic       #148 <Field zzhu$zza$zzb zzale>
		//  296  620:aastore         
		//  297  621:dup             
		//  298  622:bipush          23
		//  299  624:getstatic       #152 <Field zzhu$zza$zzb zzalf>
		//  300  627:aastore         
		//  301  628:dup             
		//  302  629:bipush          24
		//  303  631:getstatic       #156 <Field zzhu$zza$zzb zzalg>
		//  304  634:aastore         
		//  305  635:dup             
		//  306  636:bipush          25
		//  307  638:getstatic       #160 <Field zzhu$zza$zzb zzalh>
		//  308  641:aastore         
		//  309  642:dup             
		//  310  643:bipush          26
		//  311  645:getstatic       #164 <Field zzhu$zza$zzb zzali>
		//  312  648:aastore         
		//  313  649:dup             
		//  314  650:bipush          27
		//  315  652:getstatic       #168 <Field zzhu$zza$zzb zzalj>
		//  316  655:aastore         
		//  317  656:dup             
		//  318  657:bipush          28
		//  319  659:getstatic       #172 <Field zzhu$zza$zzb zzalk>
		//  320  662:aastore         
		//  321  663:putstatic       #174 <Field zzhu$zza$zzb[] zzalm>
		//  322  666:new             #176 <Class zzhw>
		//  323  669:dup             
		//  324  670:invokespecial   #178 <Method void zzhw()>
		//  325  673:putstatic       #180 <Field zzbbs zzall>
		//* 326  676:return          
		}

		private zza.zzb(String s, int i, int j)
		{
			super(s, i);
		//    0    0:aload_0         
		//    1    1:aload_1         
		//    2    2:iload_2         
		//    3    3:invokespecial   #184 <Method void Enum(String, int)>
			value = j;
		//    4    6:aload_0         
		//    5    7:iload_3         
		//    6    8:putfield        #186 <Field int value>
		//    7   11:return          
		}
	}

}
