// Decompiled by Jad v1.5.8g. Copyright 2001 Pavel Kouznetsov.
// Jad home page: http://www.kpdus.com/jad.html
// Decompiler options: packimports(3) annotate safe 

package com.google.android.gms.internal.ads;

import android.content.Context;
import android.os.*;
import android.text.TextUtils;
import com.google.ads.mediation.AdUrlAdapter;
import com.google.ads.mediation.admob.AdMobAdapter;
import com.google.android.gms.ads.formats.NativeAdOptions;
import com.google.android.gms.ads.internal.zzbv;
import com.google.android.gms.ads.mediation.MediationAdapter;
import com.google.android.gms.common.util.Clock;
import com.google.android.gms.dynamic.ObjectWrapper;
import java.util.*;
import org.json.JSONException;
import org.json.JSONObject;

// Referenced classes of package com.google.android.gms.internal.ads:
//			zzxf, zzwx, zzwy, zzyk, 
//			zzang, zzjn, zzxq, zzpl, 
//			zzakb, zzxn, zzxw, zzxd, 
//			zznk, zzkb, zzni, zzzv, 
//			zzxa, zzakk, zzxc, zzxe, 
//			zzjj

public final class zzxb
	implements zzxf
{

	public zzxb(Context context, String s, zzxn zzxn1, zzwy zzwy1, zzwx zzwx1, zzjj zzjj, zzjn zzjn1, 
			zzang zzang1, boolean flag, boolean flag1, zzpl zzpl1, List list, List list1, List list2, 
			boolean flag2)
	{
	//    0    0:aload_0         
	//    1    1:invokespecial   #51  <Method void Object()>
	//    2    4:aload_0         
	//    3    5:new             #4   <Class Object>
	//    4    8:dup             
	//    5    9:invokespecial   #51  <Method void Object()>
	//    6   12:putfield        #53  <Field Object mLock>
		zzbtq = -2;
	//    7   15:aload_0         
	//    8   16:bipush          -2
	//    9   18:putfield        #55  <Field int zzbtq>
		mContext = context;
	//   10   21:aload_0         
	//   11   22:aload_1         
	//   12   23:putfield        #57  <Field Context mContext>
		zzwh = zzxn1;
	//   13   26:aload_0         
	//   14   27:aload_3         
	//   15   28:putfield        #59  <Field zzxn zzwh>
		zzbtk = zzwx1;
	//   16   31:aload_0         
	//   17   32:aload           5
	//   18   34:putfield        #61  <Field zzwx zzbtk>
		context = ((Context) (s));
	//   19   37:aload_2         
	//   20   38:astore_1        
		if("com.google.ads.mediation.customevent.CustomEventAdapter".equals(((Object) (s))))
	//*  21   39:ldc1            #63  <String "com.google.ads.mediation.customevent.CustomEventAdapter">
	//*  22   41:aload_2         
	//*  23   42:invokevirtual   #69  <Method boolean String.equals(Object)>
	//*  24   45:ifeq            53
			context = ((Context) (zzmh()));
	//   25   48:aload_0         
	//   26   49:invokespecial   #73  <Method String zzmh()>
	//   27   52:astore_1        
		zzbth = ((String) (context));
	//   28   53:aload_0         
	//   29   54:aload_1         
	//   30   55:putfield        #75  <Field String zzbth>
		zzbtj = zzwy1;
	//   31   58:aload_0         
	//   32   59:aload           4
	//   33   61:putfield        #77  <Field zzwy zzbtj>
		long l;
		if(zzwx1.zzbsl != -1L)
	//*  34   64:aload           5
	//*  35   66:getfield        #82  <Field long zzwx.zzbsl>
	//*  36   69:ldc2w           #83  <Long -1L>
	//*  37   72:lcmp            
	//*  38   73:ifeq            92
			l = zzwx1.zzbsl;
	//   39   76:aload           5
	//   40   78:getfield        #82  <Field long zzwx.zzbsl>
	//   41   81:lstore          16
		else
	//*  42   83:aload_0         
	//*  43   84:lload           16
	//*  44   86:putfield        #86  <Field long zzbti>
	//*  45   89:goto            122
		if(zzwy1.zzbsl != -1L)
	//*  46   92:aload           4
	//*  47   94:getfield        #89  <Field long zzwy.zzbsl>
	//*  48   97:ldc2w           #83  <Long -1L>
	//*  49  100:lcmp            
	//*  50  101:ifeq            114
			l = zzwy1.zzbsl;
	//   51  104:aload           4
	//   52  106:getfield        #89  <Field long zzwy.zzbsl>
	//   53  109:lstore          16
		else
	//*  54  111:goto            83
			l = 10000L;
	//   55  114:ldc2w           #90  <Long 10000L>
	//   56  117:lstore          16
		zzbti = l;
	//*  57  119:goto            83
		zzaao = zzjj;
	//   58  122:aload_0         
	//   59  123:aload           6
	//   60  125:putfield        #93  <Field zzjj zzaao>
		zzaau = zzjn1;
	//   61  128:aload_0         
	//   62  129:aload           7
	//   63  131:putfield        #95  <Field zzjn zzaau>
		zzyf = zzang1;
	//   64  134:aload_0         
	//   65  135:aload           8
	//   66  137:putfield        #97  <Field zzang zzyf>
		zzael = flag;
	//   67  140:aload_0         
	//   68  141:iload           9
	//   69  143:putfield        #99  <Field boolean zzael>
		zzbtn = flag1;
	//   70  146:aload_0         
	//   71  147:iload           10
	//   72  149:putfield        #101 <Field boolean zzbtn>
		zzyb = zzpl1;
	//   73  152:aload_0         
	//   74  153:aload           11
	//   75  155:putfield        #103 <Field zzpl zzyb>
		zzyc = list;
	//   76  158:aload_0         
	//   77  159:aload           12
	//   78  161:putfield        #105 <Field List zzyc>
		zzbtl = list1;
	//   79  164:aload_0         
	//   80  165:aload           13
	//   81  167:putfield        #107 <Field List zzbtl>
		zzbtm = list2;
	//   82  170:aload_0         
	//   83  171:aload           14
	//   84  173:putfield        #109 <Field List zzbtm>
		zzbto = flag2;
	//   85  176:aload_0         
	//   86  177:iload           15
	//   87  179:putfield        #111 <Field boolean zzbto>
	//   88  182:return          
	}

	private static zzxq zza(MediationAdapter mediationadapter)
	{
		return ((zzxq) (new zzyk(mediationadapter)));
	//    0    0:new             #119 <Class zzyk>
	//    1    3:dup             
	//    2    4:aload_0         
	//    3    5:invokespecial   #122 <Method void zzyk(MediationAdapter)>
	//    4    8:areturn         
	}

	static zzxq zza(zzxb zzxb1, zzxq zzxq1)
	{
		zzxb1.zzbtp = zzxq1;
	//    0    0:aload_0         
	//    1    1:aload_1         
	//    2    2:putfield        #126 <Field zzxq zzbtp>
		return zzxq1;
	//    3    5:aload_1         
	//    4    6:areturn         
	}

	static Object zza(zzxb zzxb1)
	{
		return zzxb1.mLock;
	//    0    0:aload_0         
	//    1    1:getfield        #53  <Field Object mLock>
	//    2    4:areturn         
	}

	private final void zza(zzxa zzxa1)
	{
		String s1 = zzbk(zzbtk.zzbsb);
	//    0    0:aload_0         
	//    1    1:aload_0         
	//    2    2:getfield        #61  <Field zzwx zzbtk>
	//    3    5:getfield        #133 <Field String zzwx.zzbsb>
	//    4    8:invokespecial   #137 <Method String zzbk(String)>
	//    5   11:astore          4
		if(zzyf.zzcvf >= 0x3e8fa0)
			break MISSING_BLOCK_LABEL_87;
	//    6   13:aload_0         
	//    7   14:getfield        #97  <Field zzang zzyf>
	//    8   17:getfield        #142 <Field int zzang.zzcvf>
	//    9   20:ldc1            #143 <Int 0x3e8fa0>
	//   10   22:icmpge          87
		if(zzaau.zzarc)
	//*  11   25:aload_0         
	//*  12   26:getfield        #95  <Field zzjn zzaau>
	//*  13   29:getfield        #148 <Field boolean zzjn.zzarc>
	//*  14   32:ifeq            59
		{
			zzbtp.zza(ObjectWrapper.wrap(((Object) (mContext))), zzaao, s1, ((zzxt) (zzxa1)));
	//   15   35:aload_0         
	//   16   36:getfield        #126 <Field zzxq zzbtp>
	//   17   39:aload_0         
	//   18   40:getfield        #57  <Field Context mContext>
	//   19   43:invokestatic    #154 <Method com.google.android.gms.dynamic.IObjectWrapper ObjectWrapper.wrap(Object)>
	//   20   46:aload_0         
	//   21   47:getfield        #93  <Field zzjj zzaao>
	//   22   50:aload           4
	//   23   52:aload_1         
	//   24   53:invokeinterface #159 <Method void zzxq.zza(com.google.android.gms.dynamic.IObjectWrapper, zzjj, String, zzxt)>
			return;
	//   25   58:return          
		}
		String s;
		Object obj;
		ArrayList arraylist;
		Iterator iterator;
		String s2;
		try
		{
			zzbtp.zza(ObjectWrapper.wrap(((Object) (mContext))), zzaau, zzaao, s1, ((zzxt) (zzxa1)));
	//   26   59:aload_0         
	//   27   60:getfield        #126 <Field zzxq zzbtp>
	//   28   63:aload_0         
	//   29   64:getfield        #57  <Field Context mContext>
	//   30   67:invokestatic    #154 <Method com.google.android.gms.dynamic.IObjectWrapper ObjectWrapper.wrap(Object)>
	//   31   70:aload_0         
	//   32   71:getfield        #95  <Field zzjn zzaau>
	//   33   74:aload_0         
	//   34   75:getfield        #93  <Field zzjj zzaao>
	//   35   78:aload           4
	//   36   80:aload_1         
	//   37   81:invokeinterface #162 <Method void zzxq.zza(com.google.android.gms.dynamic.IObjectWrapper, zzjn, zzjj, String, zzxt)>
			return;
	//   38   86:return          
		}
	//*  39   87:aload_0         
	//*  40   88:getfield        #99  <Field boolean zzael>
	//*  41   91:ifne            290
	//*  42   94:aload_0         
	//*  43   95:getfield        #61  <Field zzwx zzbtk>
	//*  44   98:invokevirtual   #166 <Method boolean zzwx.zzmg()>
	//*  45  101:ifeq            107
	//*  46  104:goto            290
	//*  47  107:aload_0         
	//*  48  108:getfield        #95  <Field zzjn zzaau>
	//*  49  111:getfield        #148 <Field boolean zzjn.zzarc>
	//*  50  114:ifeq            148
	//*  51  117:aload_0         
	//*  52  118:getfield        #126 <Field zzxq zzbtp>
	//*  53  121:aload_0         
	//*  54  122:getfield        #57  <Field Context mContext>
	//*  55  125:invokestatic    #154 <Method com.google.android.gms.dynamic.IObjectWrapper ObjectWrapper.wrap(Object)>
	//*  56  128:aload_0         
	//*  57  129:getfield        #93  <Field zzjj zzaao>
	//*  58  132:aload           4
	//*  59  134:aload_0         
	//*  60  135:getfield        #61  <Field zzwx zzbtk>
	//*  61  138:getfield        #169 <Field String zzwx.zzbrr>
	//*  62  141:aload_1         
	//*  63  142:invokeinterface #172 <Method void zzxq.zza(com.google.android.gms.dynamic.IObjectWrapper, zzjj, String, String, zzxt)>
	//*  64  147:return          
	//*  65  148:aload_0         
	//*  66  149:getfield        #101 <Field boolean zzbtn>
	//*  67  152:ifeq            255
	//*  68  155:aload_0         
	//*  69  156:getfield        #61  <Field zzwx zzbtk>
	//*  70  159:getfield        #175 <Field String zzwx.zzbsf>
	//*  71  162:ifnull          220
	//*  72  165:aload_0         
	//*  73  166:getfield        #126 <Field zzxq zzbtp>
	//*  74  169:aload_0         
	//*  75  170:getfield        #57  <Field Context mContext>
	//*  76  173:invokestatic    #154 <Method com.google.android.gms.dynamic.IObjectWrapper ObjectWrapper.wrap(Object)>
	//*  77  176:aload_0         
	//*  78  177:getfield        #93  <Field zzjj zzaao>
	//*  79  180:aload           4
	//*  80  182:aload_0         
	//*  81  183:getfield        #61  <Field zzwx zzbtk>
	//*  82  186:getfield        #169 <Field String zzwx.zzbrr>
	//*  83  189:aload_1         
	//*  84  190:new             #177 <Class zzpl>
	//*  85  193:dup             
	//*  86  194:aload_0         
	//*  87  195:getfield        #61  <Field zzwx zzbtk>
	//*  88  198:getfield        #180 <Field String zzwx.zzbsj>
	//*  89  201:invokestatic    #184 <Method NativeAdOptions zzbl(String)>
	//*  90  204:invokespecial   #187 <Method void zzpl(NativeAdOptions)>
	//*  91  207:aload_0         
	//*  92  208:getfield        #61  <Field zzwx zzbtk>
	//*  93  211:getfield        #190 <Field List zzwx.zzbsi>
	//*  94  214:invokeinterface #193 <Method void zzxq.zza(com.google.android.gms.dynamic.IObjectWrapper, zzjj, String, String, zzxt, zzpl, List)>
	//*  95  219:return          
	//*  96  220:aload_0         
	//*  97  221:getfield        #126 <Field zzxq zzbtp>
	//*  98  224:aload_0         
	//*  99  225:getfield        #57  <Field Context mContext>
	//* 100  228:invokestatic    #154 <Method com.google.android.gms.dynamic.IObjectWrapper ObjectWrapper.wrap(Object)>
	//* 101  231:aload_0         
	//* 102  232:getfield        #95  <Field zzjn zzaau>
	//* 103  235:aload_0         
	//* 104  236:getfield        #93  <Field zzjj zzaao>
	//* 105  239:aload           4
	//* 106  241:aload_0         
	//* 107  242:getfield        #61  <Field zzwx zzbtk>
	//* 108  245:getfield        #169 <Field String zzwx.zzbrr>
	//* 109  248:aload_1         
	//* 110  249:invokeinterface #196 <Method void zzxq.zza(com.google.android.gms.dynamic.IObjectWrapper, zzjn, zzjj, String, String, zzxt)>
	//* 111  254:return          
	//* 112  255:aload_0         
	//* 113  256:getfield        #126 <Field zzxq zzbtp>
	//* 114  259:aload_0         
	//* 115  260:getfield        #57  <Field Context mContext>
	//* 116  263:invokestatic    #154 <Method com.google.android.gms.dynamic.IObjectWrapper ObjectWrapper.wrap(Object)>
	//* 117  266:aload_0         
	//* 118  267:getfield        #95  <Field zzjn zzaau>
	//* 119  270:aload_0         
	//* 120  271:getfield        #93  <Field zzjj zzaao>
	//* 121  274:aload           4
	//* 122  276:aload_0         
	//* 123  277:getfield        #61  <Field zzwx zzbtk>
	//* 124  280:getfield        #169 <Field String zzwx.zzbrr>
	//* 125  283:aload_1         
	//* 126  284:invokeinterface #196 <Method void zzxq.zza(com.google.android.gms.dynamic.IObjectWrapper, zzjn, zzjj, String, String, zzxt)>
	//* 127  289:return          
	//* 128  290:new             #198 <Class ArrayList>
	//* 129  293:dup             
	//* 130  294:aload_0         
	//* 131  295:getfield        #105 <Field List zzyc>
	//* 132  298:invokespecial   #201 <Method void ArrayList(java.util.Collection)>
	//* 133  301:astore          5
	//* 134  303:aload_0         
	//* 135  304:getfield        #107 <Field List zzbtl>
	//* 136  307:ifnull          436
	//* 137  310:aload_0         
	//* 138  311:getfield        #107 <Field List zzbtl>
	//* 139  314:invokeinterface #207 <Method Iterator List.iterator()>
	//* 140  319:astore          6
	//* 141  321:aload           6
	//* 142  323:invokeinterface #212 <Method boolean Iterator.hasNext()>
	//* 143  328:ifeq            436
	//* 144  331:aload           6
	//* 145  333:invokeinterface #216 <Method Object Iterator.next()>
	//* 146  338:checkcast       #65  <Class String>
	//* 147  341:astore          7
	//* 148  343:ldc1            #218 <String ":false">
	//* 149  345:astore_3        
	//* 150  346:aload_3         
	//* 151  347:astore_2        
	//* 152  348:aload_0         
	//* 153  349:getfield        #109 <Field List zzbtm>
	//* 154  352:ifnull          374
	//* 155  355:aload_3         
	//* 156  356:astore_2        
	//* 157  357:aload_0         
	//* 158  358:getfield        #109 <Field List zzbtm>
	//* 159  361:aload           7
	//* 160  363:invokeinterface #221 <Method boolean List.contains(Object)>
	//* 161  368:ifeq            374
	//* 162  371:ldc1            #223 <String ":true">
	//* 163  373:astore_2        
	//* 164  374:new             #225 <Class StringBuilder>
	//* 165  377:dup             
	//* 166  378:bipush          7
	//* 167  380:aload           7
	//* 168  382:invokestatic    #229 <Method String String.valueOf(Object)>
	//* 169  385:invokevirtual   #233 <Method int String.length()>
	//* 170  388:iadd            
	//* 171  389:aload_2         
	//* 172  390:invokestatic    #229 <Method String String.valueOf(Object)>
	//* 173  393:invokevirtual   #233 <Method int String.length()>
	//* 174  396:iadd            
	//* 175  397:invokespecial   #236 <Method void StringBuilder(int)>
	//* 176  400:astore_3        
	//* 177  401:aload_3         
	//* 178  402:ldc1            #238 <String "custom:">
	//* 179  404:invokevirtual   #242 <Method StringBuilder StringBuilder.append(String)>
	//* 180  407:pop             
	//* 181  408:aload_3         
	//* 182  409:aload           7
	//* 183  411:invokevirtual   #242 <Method StringBuilder StringBuilder.append(String)>
	//* 184  414:pop             
	//* 185  415:aload_3         
	//* 186  416:aload_2         
	//* 187  417:invokevirtual   #242 <Method StringBuilder StringBuilder.append(String)>
	//* 188  420:pop             
	//* 189  421:aload           5
	//* 190  423:aload_3         
	//* 191  424:invokevirtual   #245 <Method String StringBuilder.toString()>
	//* 192  427:invokeinterface #248 <Method boolean List.add(Object)>
	//* 193  432:pop             
	//* 194  433:goto            321
	//* 195  436:aload_0         
	//* 196  437:getfield        #126 <Field zzxq zzbtp>
	//* 197  440:aload_0         
	//* 198  441:getfield        #57  <Field Context mContext>
	//* 199  444:invokestatic    #154 <Method com.google.android.gms.dynamic.IObjectWrapper ObjectWrapper.wrap(Object)>
	//* 200  447:aload_0         
	//* 201  448:getfield        #93  <Field zzjj zzaao>
	//* 202  451:aload           4
	//* 203  453:aload_0         
	//* 204  454:getfield        #61  <Field zzwx zzbtk>
	//* 205  457:getfield        #169 <Field String zzwx.zzbrr>
	//* 206  460:aload_1         
	//* 207  461:aload_0         
	//* 208  462:getfield        #103 <Field zzpl zzyb>
	//* 209  465:aload           5
	//* 210  467:invokeinterface #193 <Method void zzxq.zza(com.google.android.gms.dynamic.IObjectWrapper, zzjj, String, String, zzxt, zzpl, List)>
	//* 211  472:return          
		// Misplaced declaration of an exception variable
		catch(zzxa zzxa1)
	//* 212  473:astore_1        
		{
			zzakb.zzc("Could not request ad from mediation adapter.", ((Throwable) (zzxa1)));
	//  213  474:ldc1            #250 <String "Could not request ad from mediation adapter.">
	//  214  476:aload_1         
	//  215  477:invokestatic    #256 <Method void zzakb.zzc(String, Throwable)>
		}
		break MISSING_BLOCK_LABEL_480;
		if(zzael || zzbtk.zzmg())
			break MISSING_BLOCK_LABEL_290;
		if(zzaau.zzarc)
		{
			zzbtp.zza(ObjectWrapper.wrap(((Object) (mContext))), zzaao, s1, zzbtk.zzbrr, ((zzxt) (zzxa1)));
			return;
		}
		if(!zzbtn)
			break MISSING_BLOCK_LABEL_255;
		if(zzbtk.zzbsf != null)
		{
			zzbtp.zza(ObjectWrapper.wrap(((Object) (mContext))), zzaao, s1, zzbtk.zzbrr, ((zzxt) (zzxa1)), new zzpl(zzbl(zzbtk.zzbsj)), zzbtk.zzbsi);
			return;
		}
		zzbtp.zza(ObjectWrapper.wrap(((Object) (mContext))), zzaau, zzaao, s1, zzbtk.zzbrr, ((zzxt) (zzxa1)));
		return;
		zzbtp.zza(ObjectWrapper.wrap(((Object) (mContext))), zzaau, zzaao, s1, zzbtk.zzbrr, ((zzxt) (zzxa1)));
		return;
		arraylist = new ArrayList(((java.util.Collection) (zzyc)));
		if(zzbtl == null)
			break MISSING_BLOCK_LABEL_436;
		iterator = zzbtl.iterator();
_L1:
		if(!iterator.hasNext())
			break MISSING_BLOCK_LABEL_436;
		s2 = (String)iterator.next();
		obj = ":false";
		s = ((String) (obj));
		if(zzbtm == null)
			break MISSING_BLOCK_LABEL_374;
		s = ((String) (obj));
		if(zzbtm.contains(((Object) (s2))))
			s = ":true";
		obj = ((Object) (new StringBuilder(7 + String.valueOf(((Object) (s2))).length() + String.valueOf(((Object) (s))).length())));
		((StringBuilder) (obj)).append("custom:");
		((StringBuilder) (obj)).append(s2);
		((StringBuilder) (obj)).append(s);
		((List) (arraylist)).add(((Object) (((StringBuilder) (obj)).toString())));
		  goto _L1
		zzbtp.zza(ObjectWrapper.wrap(((Object) (mContext))), zzaao, s1, zzbtk.zzbrr, ((zzxt) (zzxa1)), zzyb, ((List) (arraylist)));
		return;
		zzx(5);
	//  216  480:aload_0         
	//  217  481:iconst_5        
	//  218  482:invokevirtual   #259 <Method void zzx(int)>
		return;
	//  219  485:return          
	}

	static void zza(zzxb zzxb1, zzxa zzxa1)
	{
		zzxb1.zza(zzxa1);
	//    0    0:aload_0         
	//    1    1:aload_1         
	//    2    2:invokespecial   #262 <Method void zza(zzxa)>
	//    3    5:return          
	}

	static boolean zza(zzxb zzxb1, int i)
	{
		return zzxb1.zzy(1);
	//    0    0:aload_0         
	//    1    1:iconst_1        
	//    2    2:invokespecial   #267 <Method boolean zzy(int)>
	//    3    5:ireturn         
	}

	static int zzb(zzxb zzxb1)
	{
		return zzxb1.zzbtq;
	//    0    0:aload_0         
	//    1    1:getfield        #55  <Field int zzbtq>
	//    2    4:ireturn         
	}

	private final String zzbk(String s)
	{
		if(s == null || !zzmk()) goto _L2; else goto _L1
	//    0    0:aload_1         
	//    1    1:ifnull          51
	//    2    4:aload_0         
	//    3    5:invokespecial   #274 <Method boolean zzmk()>
	//    4    8:ifeq            51
_L1:
		if(zzy(2))
	//*   5   11:aload_0         
	//*   6   12:iconst_2        
	//*   7   13:invokespecial   #267 <Method boolean zzy(int)>
	//*   8   16:ifeq            21
			return s;
	//    9   19:aload_1         
	//   10   20:areturn         
		Object obj;
		obj = ((Object) (new JSONObject(s)));
	//   11   21:new             #276 <Class JSONObject>
	//   12   24:dup             
	//   13   25:aload_1         
	//   14   26:invokespecial   #279 <Method void JSONObject(String)>
	//   15   29:astore_2        
		((JSONObject) (obj)).remove("cpm_floor_cents");
	//   16   30:aload_2         
	//   17   31:ldc2            #281 <String "cpm_floor_cents">
	//   18   34:invokevirtual   #285 <Method Object JSONObject.remove(String)>
	//   19   37:pop             
		obj = ((Object) (((JSONObject) (obj)).toString()));
	//   20   38:aload_2         
	//   21   39:invokevirtual   #286 <Method String JSONObject.toString()>
	//   22   42:astore_2        
		return ((String) (obj));
	//   23   43:aload_2         
	//   24   44:areturn         
_L4:
		zzakb.zzdk("Could not remove field. Returning the original value");
	//   25   45:ldc2            #288 <String "Could not remove field. Returning the original value">
	//   26   48:invokestatic    #291 <Method void zzakb.zzdk(String)>
_L2:
		return s;
	//   27   51:aload_1         
	//   28   52:areturn         
		JSONException jsonexception;
		jsonexception;
	//   29   53:astore_2        
		if(true) goto _L4; else goto _L3
_L3:
	//*  30   54:goto            45
	}

	private static NativeAdOptions zzbl(String s)
	{
		com.google.android.gms.ads.formats.NativeAdOptions.Builder builder;
		builder = new com.google.android.gms.ads.formats.NativeAdOptions.Builder();
	//    0    0:new             #293 <Class com.google.android.gms.ads.formats.NativeAdOptions$Builder>
	//    1    3:dup             
	//    2    4:invokespecial   #294 <Method void com.google.android.gms.ads.formats.NativeAdOptions$Builder()>
	//    3    7:astore_2        
		if(s == null)
	//*   4    8:aload_0         
	//*   5    9:ifnonnull       17
			return builder.build();
	//    6   12:aload_2         
	//    7   13:invokevirtual   #298 <Method NativeAdOptions com.google.android.gms.ads.formats.NativeAdOptions$Builder.build()>
	//    8   16:areturn         
		s = ((String) (new JSONObject(s)));
	//    9   17:new             #276 <Class JSONObject>
	//   10   20:dup             
	//   11   21:aload_0         
	//   12   22:invokespecial   #279 <Method void JSONObject(String)>
	//   13   25:astore_0        
		byte byte0 = 0;
	//   14   26:iconst_0        
	//   15   27:istore_1        
		builder.setRequestMultipleImages(((JSONObject) (s)).optBoolean("multiple_images", false));
	//   16   28:aload_2         
	//   17   29:aload_0         
	//   18   30:ldc2            #300 <String "multiple_images">
	//   19   33:iconst_0        
	//   20   34:invokevirtual   #304 <Method boolean JSONObject.optBoolean(String, boolean)>
	//   21   37:invokevirtual   #308 <Method com.google.android.gms.ads.formats.NativeAdOptions$Builder com.google.android.gms.ads.formats.NativeAdOptions$Builder.setRequestMultipleImages(boolean)>
	//   22   40:pop             
		builder.setReturnUrlsForImageAssets(((JSONObject) (s)).optBoolean("only_urls", false));
	//   23   41:aload_2         
	//   24   42:aload_0         
	//   25   43:ldc2            #310 <String "only_urls">
	//   26   46:iconst_0        
	//   27   47:invokevirtual   #304 <Method boolean JSONObject.optBoolean(String, boolean)>
	//   28   50:invokevirtual   #313 <Method com.google.android.gms.ads.formats.NativeAdOptions$Builder com.google.android.gms.ads.formats.NativeAdOptions$Builder.setReturnUrlsForImageAssets(boolean)>
	//   29   53:pop             
		s = ((JSONObject) (s)).optString("native_image_orientation", "any");
	//   30   54:aload_0         
	//   31   55:ldc2            #315 <String "native_image_orientation">
	//   32   58:ldc2            #317 <String "any">
	//   33   61:invokevirtual   #321 <Method String JSONObject.optString(String, String)>
	//   34   64:astore_0        
		if("landscape".equals(((Object) (s))))
	//*  35   65:ldc2            #323 <String "landscape">
	//*  36   68:aload_0         
	//*  37   69:invokevirtual   #69  <Method boolean String.equals(Object)>
	//*  38   72:ifeq            80
		{
			byte0 = 2;
	//   39   75:iconst_2        
	//   40   76:istore_1        
			break MISSING_BLOCK_LABEL_108;
	//   41   77:goto            108
		}
		if("portrait".equals(((Object) (s))))
	//*  42   80:ldc2            #325 <String "portrait">
	//*  43   83:aload_0         
	//*  44   84:invokevirtual   #69  <Method boolean String.equals(Object)>
	//*  45   87:ifeq            95
		{
			byte0 = 1;
	//   46   90:iconst_1        
	//   47   91:istore_1        
			break MISSING_BLOCK_LABEL_108;
	//   48   92:goto            108
		}
		if(!"any".equals(((Object) (s))))
	//*  49   95:ldc2            #317 <String "any">
	//*  50   98:aload_0         
	//*  51   99:invokevirtual   #69  <Method boolean String.equals(Object)>
	//*  52  102:ifeq            130
	//*  53  105:goto            108
	//*  54  108:aload_2         
	//*  55  109:iload_1         
	//*  56  110:invokevirtual   #329 <Method com.google.android.gms.ads.formats.NativeAdOptions$Builder com.google.android.gms.ads.formats.NativeAdOptions$Builder.setImageOrientation(int)>
	//*  57  113:pop             
	//*  58  114:goto            125
	//*  59  117:astore_0        
	//*  60  118:ldc2            #331 <String "Exception occurred when creating native ad options">
	//*  61  121:aload_0         
	//*  62  122:invokestatic    #256 <Method void zzakb.zzc(String, Throwable)>
	//*  63  125:aload_2         
	//*  64  126:invokevirtual   #298 <Method NativeAdOptions com.google.android.gms.ads.formats.NativeAdOptions$Builder.build()>
	//*  65  129:areturn         
			byte0 = -1;
	//   66  130:iconst_m1       
	//   67  131:istore_1        
		try
		{
			builder.setImageOrientation(((int) (byte0)));
		}
		// Misplaced declaration of an exception variable
		catch(String s)
		{
			zzakb.zzc("Exception occurred when creating native ad options", ((Throwable) (s)));
		}
		return builder.build();
	//*  68  132:goto            108
	}

	static zzxq zzc(zzxb zzxb1)
	{
		return zzxb1.zzmj();
	//    0    0:aload_0         
	//    1    1:invokespecial   #336 <Method zzxq zzmj()>
	//    2    4:areturn         
	}

	static zzxq zzd(zzxb zzxb1)
	{
		return zzxb1.zzbtp;
	//    0    0:aload_0         
	//    1    1:getfield        #126 <Field zzxq zzbtp>
	//    2    4:areturn         
	}

	static boolean zze(zzxb zzxb1)
	{
		return zzxb1.zzmk();
	//    0    0:aload_0         
	//    1    1:invokespecial   #274 <Method boolean zzmk()>
	//    2    4:ireturn         
	}

	static String zzf(zzxb zzxb1)
	{
		return zzxb1.zzbth;
	//    0    0:aload_0         
	//    1    1:getfield        #75  <Field String zzbth>
	//    2    4:areturn         
	}

	private final String zzmh()
	{
		if(!TextUtils.isEmpty(((CharSequence) (zzbtk.zzbrv))))
	//*   0    0:aload_0         
	//*   1    1:getfield        #61  <Field zzwx zzbtk>
	//*   2    4:getfield        #344 <Field String zzwx.zzbrv>
	//*   3    7:invokestatic    #350 <Method boolean TextUtils.isEmpty(CharSequence)>
	//*   4   10:ifne            45
			if(zzwh.zzbn(zzbtk.zzbrv))
	//*   5   13:aload_0         
	//*   6   14:getfield        #59  <Field zzxn zzwh>
	//*   7   17:aload_0         
	//*   8   18:getfield        #61  <Field zzwx zzbtk>
	//*   9   21:getfield        #344 <Field String zzwx.zzbrv>
	//*  10   24:invokeinterface #356 <Method boolean zzxn.zzbn(String)>
	//*  11   29:ifeq            36
				return "com.google.android.gms.ads.mediation.customevent.CustomEventAdapter";
	//   12   32:ldc2            #358 <String "com.google.android.gms.ads.mediation.customevent.CustomEventAdapter">
	//   13   35:areturn         
			else
				return "com.google.ads.mediation.customevent.CustomEventAdapter";
	//   14   36:ldc1            #63  <String "com.google.ads.mediation.customevent.CustomEventAdapter">
	//   15   38:areturn         
		  goto _L1
_L3:
		zzakb.zzdk("Fail to determine the custom event's version, assuming the old one.");
	//   16   39:ldc2            #360 <String "Fail to determine the custom event's version, assuming the old one.">
	//   17   42:invokestatic    #291 <Method void zzakb.zzdk(String)>
_L1:
		return "com.google.ads.mediation.customevent.CustomEventAdapter";
	//   18   45:ldc1            #63  <String "com.google.ads.mediation.customevent.CustomEventAdapter">
	//   19   47:areturn         
		RemoteException remoteexception;
		remoteexception;
	//   20   48:astore_1        
		if(true) goto _L3; else goto _L2
_L2:
	//*  21   49:goto            39
	}

	private final zzxw zzmi()
	{
		if(zzbtq == 0 && zzmk()) goto _L2; else goto _L1
	//    0    0:aload_0         
	//    1    1:getfield        #55  <Field int zzbtq>
	//    2    4:ifne            69
	//    3    7:aload_0         
	//    4    8:invokespecial   #274 <Method boolean zzmk()>
	//    5   11:ifne            17
	//*   6   14:goto            69
_L2:
		if(!zzy(4) || zzbtr == null || zzbtr.zzmm() == 0) goto _L4; else goto _L3
	//    7   17:aload_0         
	//    8   18:iconst_4        
	//    9   19:invokespecial   #267 <Method boolean zzy(int)>
	//   10   22:ifeq            57
	//   11   25:aload_0         
	//   12   26:getfield        #364 <Field zzxw zzbtr>
	//   13   29:ifnull          57
	//   14   32:aload_0         
	//   15   33:getfield        #364 <Field zzxw zzbtr>
	//   16   36:invokeinterface #369 <Method int zzxw.zzmm()>
	//   17   41:ifeq            57
_L3:
		zzxw zzxw1 = zzbtr;
	//   18   44:aload_0         
	//   19   45:getfield        #364 <Field zzxw zzbtr>
	//   20   48:astore_1        
		return zzxw1;
	//   21   49:aload_1         
	//   22   50:areturn         
_L6:
		zzakb.zzdk("Could not get cpm value from MediationResponseMetadata");
	//   23   51:ldc2            #371 <String "Could not get cpm value from MediationResponseMetadata">
	//   24   54:invokestatic    #291 <Method void zzakb.zzdk(String)>
_L4:
		return ((zzxw) (new zzxd(zzml())));
	//   25   57:new             #373 <Class zzxd>
	//   26   60:dup             
	//   27   61:aload_0         
	//   28   62:invokespecial   #376 <Method int zzml()>
	//   29   65:invokespecial   #377 <Method void zzxd(int)>
	//   30   68:areturn         
_L1:
		return null;
	//   31   69:aconst_null     
	//   32   70:areturn         
		RemoteException remoteexception;
		remoteexception;
	//   33   71:astore_1        
		if(true) goto _L6; else goto _L5
_L5:
	//*  34   72:goto            51
	}

	private final zzxq zzmj()
	{
		Object obj = ((Object) (String.valueOf(((Object) (zzbth)))));
	//    0    0:aload_0         
	//    1    1:getfield        #75  <Field String zzbth>
	//    2    4:invokestatic    #229 <Method String String.valueOf(Object)>
	//    3    7:astore_1        
		if(((String) (obj)).length() != 0)
	//*   4    8:aload_1         
	//*   5    9:invokevirtual   #233 <Method int String.length()>
	//*   6   12:ifeq            26
			obj = ((Object) ("Instantiating mediation adapter: ".concat(((String) (obj)))));
	//    7   15:ldc2            #379 <String "Instantiating mediation adapter: ">
	//    8   18:aload_1         
	//    9   19:invokevirtual   #382 <Method String String.concat(String)>
	//   10   22:astore_1        
		else
	//*  11   23:goto            37
			obj = ((Object) (new String("Instantiating mediation adapter: ")));
	//   12   26:new             #65  <Class String>
	//   13   29:dup             
	//   14   30:ldc2            #379 <String "Instantiating mediation adapter: ">
	//   15   33:invokespecial   #383 <Method void String(String)>
	//   16   36:astore_1        
		zzakb.zzdj(((String) (obj)));
	//   17   37:aload_1         
	//   18   38:invokestatic    #386 <Method void zzakb.zzdj(String)>
		if(!zzael && !zzbtk.zzmg())
	//*  19   41:aload_0         
	//*  20   42:getfield        #99  <Field boolean zzael>
	//*  21   45:ifne            174
	//*  22   48:aload_0         
	//*  23   49:getfield        #61  <Field zzwx zzbtk>
	//*  24   52:invokevirtual   #166 <Method boolean zzwx.zzmg()>
	//*  25   55:ifne            174
		{
			obj = ((Object) (zznk.zzbai));
	//   26   58:getstatic       #392 <Field zzna zznk.zzbai>
	//   27   61:astore_1        
			if(((Boolean)zzkb.zzik().zzd(((zzna) (obj)))).booleanValue() && "com.google.ads.mediation.admob.AdMobAdapter".equals(((Object) (zzbth))))
	//*  28   62:invokestatic    #398 <Method zzni zzkb.zzik()>
	//*  29   65:aload_1         
	//*  30   66:invokevirtual   #403 <Method Object zzni.zzd(zzna)>
	//*  31   69:checkcast       #405 <Class Boolean>
	//*  32   72:invokevirtual   #408 <Method boolean Boolean.booleanValue()>
	//*  33   75:ifeq            102
	//*  34   78:ldc2            #410 <String "com.google.ads.mediation.admob.AdMobAdapter">
	//*  35   81:aload_0         
	//*  36   82:getfield        #75  <Field String zzbth>
	//*  37   85:invokevirtual   #69  <Method boolean String.equals(Object)>
	//*  38   88:ifeq            102
				return zza(((MediationAdapter) (new AdMobAdapter())));
	//   39   91:new             #412 <Class AdMobAdapter>
	//   40   94:dup             
	//   41   95:invokespecial   #413 <Method void AdMobAdapter()>
	//   42   98:invokestatic    #415 <Method zzxq zza(MediationAdapter)>
	//   43  101:areturn         
			obj = ((Object) (zznk.zzbaj));
	//   44  102:getstatic       #418 <Field zzna zznk.zzbaj>
	//   45  105:astore_1        
			if(((Boolean)zzkb.zzik().zzd(((zzna) (obj)))).booleanValue() && "com.google.ads.mediation.AdUrlAdapter".equals(((Object) (zzbth))))
	//*  46  106:invokestatic    #398 <Method zzni zzkb.zzik()>
	//*  47  109:aload_1         
	//*  48  110:invokevirtual   #403 <Method Object zzni.zzd(zzna)>
	//*  49  113:checkcast       #405 <Class Boolean>
	//*  50  116:invokevirtual   #408 <Method boolean Boolean.booleanValue()>
	//*  51  119:ifeq            146
	//*  52  122:ldc2            #420 <String "com.google.ads.mediation.AdUrlAdapter">
	//*  53  125:aload_0         
	//*  54  126:getfield        #75  <Field String zzbth>
	//*  55  129:invokevirtual   #69  <Method boolean String.equals(Object)>
	//*  56  132:ifeq            146
				return zza(((MediationAdapter) (new AdUrlAdapter())));
	//   57  135:new             #422 <Class AdUrlAdapter>
	//   58  138:dup             
	//   59  139:invokespecial   #423 <Method void AdUrlAdapter()>
	//   60  142:invokestatic    #415 <Method zzxq zza(MediationAdapter)>
	//   61  145:areturn         
			if("com.google.ads.mediation.admob.AdMobCustomTabsAdapter".equals(((Object) (zzbth))))
	//*  62  146:ldc2            #425 <String "com.google.ads.mediation.admob.AdMobCustomTabsAdapter">
	//*  63  149:aload_0         
	//*  64  150:getfield        #75  <Field String zzbth>
	//*  65  153:invokevirtual   #69  <Method boolean String.equals(Object)>
	//*  66  156:ifeq            174
				return ((zzxq) (new zzyk(((MediationAdapter) (new zzzv())))));
	//   67  159:new             #119 <Class zzyk>
	//   68  162:dup             
	//   69  163:new             #427 <Class zzzv>
	//   70  166:dup             
	//   71  167:invokespecial   #428 <Method void zzzv()>
	//   72  170:invokespecial   #122 <Method void zzyk(MediationAdapter)>
	//   73  173:areturn         
		}
		try
		{
			obj = ((Object) (zzwh.zzbm(zzbth)));
	//   74  174:aload_0         
	//   75  175:getfield        #59  <Field zzxn zzwh>
	//   76  178:aload_0         
	//   77  179:getfield        #75  <Field String zzbth>
	//   78  182:invokeinterface #432 <Method zzxq zzxn.zzbm(String)>
	//   79  187:astore_1        
		}
	//*  80  188:aload_1         
	//*  81  189:areturn         
		catch(RemoteException remoteexception)
	//*  82  190:astore_2        
		{
			String s = String.valueOf(((Object) (zzbth)));
	//   83  191:aload_0         
	//   84  192:getfield        #75  <Field String zzbth>
	//   85  195:invokestatic    #229 <Method String String.valueOf(Object)>
	//   86  198:astore_1        
			if(s.length() != 0)
	//*  87  199:aload_1         
	//*  88  200:invokevirtual   #233 <Method int String.length()>
	//*  89  203:ifeq            217
				s = "Could not instantiate mediation adapter: ".concat(s);
	//   90  206:ldc2            #434 <String "Could not instantiate mediation adapter: ">
	//   91  209:aload_1         
	//   92  210:invokevirtual   #382 <Method String String.concat(String)>
	//   93  213:astore_1        
			else
	//*  94  214:goto            228
				s = new String("Could not instantiate mediation adapter: ");
	//   95  217:new             #65  <Class String>
	//   96  220:dup             
	//   97  221:ldc2            #434 <String "Could not instantiate mediation adapter: ">
	//   98  224:invokespecial   #383 <Method void String(String)>
	//   99  227:astore_1        
			zzakb.zza(s, ((Throwable) (remoteexception)));
	//  100  228:aload_1         
	//  101  229:aload_2         
	//  102  230:invokestatic    #436 <Method void zzakb.zza(String, Throwable)>
			return null;
	//  103  233:aconst_null     
	//  104  234:areturn         
		}
		return ((zzxq) (obj));
	}

	private final boolean zzmk()
	{
		return zzbtj.zzbsx != -1;
	//    0    0:aload_0         
	//    1    1:getfield        #77  <Field zzwy zzbtj>
	//    2    4:getfield        #439 <Field int zzwy.zzbsx>
	//    3    7:iconst_m1       
	//    4    8:icmpeq          13
	//    5   11:iconst_1        
	//    6   12:ireturn         
	//    7   13:iconst_0        
	//    8   14:ireturn         
	}

	private final int zzml()
	{
		JSONException jsonexception;
		if(zzbtk.zzbsb == null)
	//*   0    0:aload_0         
	//*   1    1:getfield        #61  <Field zzwx zzbtk>
	//*   2    4:getfield        #133 <Field String zzwx.zzbsb>
	//*   3    7:ifnonnull       12
			return 0;
	//    4   10:iconst_0        
	//    5   11:ireturn         
		int i;
		int j;
		JSONObject jsonobject;
		try
		{
			jsonobject = new JSONObject(zzbtk.zzbsb);
	//    6   12:new             #276 <Class JSONObject>
	//    7   15:dup             
	//    8   16:aload_0         
	//    9   17:getfield        #61  <Field zzwx zzbtk>
	//   10   20:getfield        #133 <Field String zzwx.zzbsb>
	//   11   23:invokespecial   #279 <Method void JSONObject(String)>
	//   12   26:astore_3        
		}
	//*  13   27:ldc2            #410 <String "com.google.ads.mediation.admob.AdMobAdapter">
	//*  14   30:aload_0         
	//*  15   31:getfield        #75  <Field String zzbth>
	//*  16   34:invokevirtual   #69  <Method boolean String.equals(Object)>
	//*  17   37:ifeq            49
	//*  18   40:aload_3         
	//*  19   41:ldc2            #441 <String "cpm_cents">
	//*  20   44:iconst_0        
	//*  21   45:invokevirtual   #445 <Method int JSONObject.optInt(String, int)>
	//*  22   48:ireturn         
	//*  23   49:aload_0         
	//*  24   50:iconst_2        
	//*  25   51:invokespecial   #267 <Method boolean zzy(int)>
	//*  26   54:ifeq            69
	//*  27   57:aload_3         
	//*  28   58:ldc2            #281 <String "cpm_floor_cents">
	//*  29   61:iconst_0        
	//*  30   62:invokevirtual   #445 <Method int JSONObject.optInt(String, int)>
	//*  31   65:istore_1        
	//*  32   66:goto            71
	//*  33   69:iconst_0        
	//*  34   70:istore_1        
	//*  35   71:iload_1         
	//*  36   72:istore_2        
	//*  37   73:iload_1         
	//*  38   74:ifne            86
	//*  39   77:aload_3         
	//*  40   78:ldc2            #447 <String "penalized_average_cpm_cents">
	//*  41   81:iconst_0        
	//*  42   82:invokevirtual   #445 <Method int JSONObject.optInt(String, int)>
	//*  43   85:istore_2        
	//*  44   86:iload_2         
	//*  45   87:ireturn         
	//*  46   88:ldc2            #449 <String "Could not convert to json. Returning 0">
	//*  47   91:invokestatic    #291 <Method void zzakb.zzdk(String)>
	//*  48   94:iconst_0        
	//*  49   95:ireturn         
		// Misplaced declaration of an exception variable
		catch(JSONException jsonexception)
		{
			zzakb.zzdk("Could not convert to json. Returning 0");
			return 0;
		}
		if("com.google.ads.mediation.admob.AdMobAdapter".equals(((Object) (zzbth))))
			return jsonobject.optInt("cpm_cents", 0);
		if(zzy(2))
			i = jsonobject.optInt("cpm_floor_cents", 0);
		else
			i = 0;
		j = i;
		if(i == 0)
			j = jsonobject.optInt("penalized_average_cpm_cents", 0);
		return j;
	//*  50   96:astore_3        
	//*  51   97:goto            88
	}

	private final boolean zzy(int i)
	{
		Bundle bundle;
		if(zzael)
	//*   0    0:aload_0         
	//*   1    1:getfield        #99  <Field boolean zzael>
	//*   2    4:ifeq            20
		{
			bundle = zzbtp.zzmr();
	//    3    7:aload_0         
	//    4    8:getfield        #126 <Field zzxq zzbtp>
	//    5   11:invokeinterface #453 <Method Bundle zzxq.zzmr()>
	//    6   16:astore_2        
			break MISSING_BLOCK_LABEL_53;
	//    7   17:goto            53
		}
		if(zzaau.zzarc)
	//*   8   20:aload_0         
	//*   9   21:getfield        #95  <Field zzjn zzaau>
	//*  10   24:getfield        #148 <Field boolean zzjn.zzarc>
	//*  11   27:ifeq            43
		{
			bundle = zzbtp.getInterstitialAdapterInfo();
	//   12   30:aload_0         
	//   13   31:getfield        #126 <Field zzxq zzbtp>
	//   14   34:invokeinterface #456 <Method Bundle zzxq.getInterstitialAdapterInfo()>
	//   15   39:astore_2        
			break MISSING_BLOCK_LABEL_53;
	//   16   40:goto            53
		}
		try
		{
			bundle = zzbtp.zzmq();
	//   17   43:aload_0         
	//   18   44:getfield        #126 <Field zzxq zzbtp>
	//   19   47:invokeinterface #459 <Method Bundle zzxq.zzmq()>
	//   20   52:astore_2        
		}
	//*  21   53:aload_2         
	//*  22   54:ifnull          73
	//*  23   57:aload_2         
	//*  24   58:ldc2            #461 <String "capabilities">
	//*  25   61:iconst_0        
	//*  26   62:invokevirtual   #466 <Method int Bundle.getInt(String, int)>
	//*  27   65:iload_1         
	//*  28   66:iand            
	//*  29   67:iload_1         
	//*  30   68:icmpne          73
	//*  31   71:iconst_1        
	//*  32   72:ireturn         
	//*  33   73:iconst_0        
	//*  34   74:ireturn         
	//*  35   75:ldc2            #468 <String "Could not get adapter info. Returning false">
	//*  36   78:invokestatic    #291 <Method void zzakb.zzdk(String)>
	//*  37   81:iconst_0        
	//*  38   82:ireturn         
		// Misplaced declaration of an exception variable
		catch(RemoteException remoteexception)
		{
			zzakb.zzdk("Could not get adapter info. Returning false");
			return false;
		}
		RemoteException remoteexception;
		return bundle != null && (bundle.getInt("capabilities", 0) & i) == i;
	//*  39   83:astore_2        
	//*  40   84:goto            75
	}

	public final void cancel()
	{
		Object obj = mLock;
	//    0    0:aload_0         
	//    1    1:getfield        #53  <Field Object mLock>
	//    2    4:astore_1        
		obj;
	//    3    5:aload_1         
		JVM INSTR monitorenter ;
	//    4    6:monitorenter    
		Object obj1;
		try
		{
			if(zzbtp != null)
	//*   5    7:aload_0         
	//*   6    8:getfield        #126 <Field zzxq zzbtp>
	//*   7   11:ifnull          38
				zzbtp.destroy();
	//    8   14:aload_0         
	//    9   15:getfield        #126 <Field zzxq zzbtp>
	//   10   18:invokeinterface #472 <Method void zzxq.destroy()>
			break MISSING_BLOCK_LABEL_38;
	//   11   23:goto            38
		}
	//*  12   26:astore_2        
	//*  13   27:goto            53
		// Misplaced declaration of an exception variable
		catch(Object obj1) { }
	//   14   30:astore_2        
		break MISSING_BLOCK_LABEL_31;
		obj1;
		break MISSING_BLOCK_LABEL_53;
		zzakb.zzc("Could not destroy mediation adapter.", ((Throwable) (obj1)));
	//   15   31:ldc2            #474 <String "Could not destroy mediation adapter.">
	//   16   34:aload_2         
	//   17   35:invokestatic    #256 <Method void zzakb.zzc(String, Throwable)>
		zzbtq = -1;
	//   18   38:aload_0         
	//   19   39:iconst_m1       
	//   20   40:putfield        #55  <Field int zzbtq>
		mLock.notify();
	//   21   43:aload_0         
	//   22   44:getfield        #53  <Field Object mLock>
	//   23   47:invokevirtual   #477 <Method void Object.notify()>
		obj;
	//   24   50:aload_1         
		JVM INSTR monitorexit ;
	//   25   51:monitorexit     
		return;
	//   26   52:return          
		obj;
	//   27   53:aload_1         
		JVM INSTR monitorexit ;
	//   28   54:monitorexit     
		throw obj1;
	//   29   55:aload_2         
	//   30   56:athrow          
	}

	public final zzxe zza(long l, long l1)
	{
		Object obj = mLock;
	//    0    0:aload_0         
	//    1    1:getfield        #53  <Field Object mLock>
	//    2    4:astore          13
		obj;
	//    3    6:aload           13
		JVM INSTR monitorenter ;
	//    4    8:monitorenter    
		long l2;
		long l3;
		Object obj1;
		l2 = SystemClock.elapsedRealtime();
	//    5    9:invokestatic    #486 <Method long SystemClock.elapsedRealtime()>
	//    6   12:lstore          5
		obj1 = ((Object) (new zzxa()));
	//    7   14:new             #488 <Class zzxa>
	//    8   17:dup             
	//    9   18:invokespecial   #489 <Method void zzxa()>
	//   10   21:astore          14
		zzakk.zzcrm.post(((Runnable) (new zzxc(this, ((zzxa) (obj1))))));
	//   11   23:getstatic       #495 <Field Handler zzakk.zzcrm>
	//   12   26:new             #497 <Class zzxc>
	//   13   29:dup             
	//   14   30:aload_0         
	//   15   31:aload           14
	//   16   33:invokespecial   #499 <Method void zzxc(zzxb, zzxa)>
	//   17   36:invokevirtual   #505 <Method boolean Handler.post(Runnable)>
	//   18   39:pop             
		l3 = zzbti;
	//   19   40:aload_0         
	//   20   41:getfield        #86  <Field long zzbti>
	//   21   44:lstore          7
_L5:
		if(zzbtq == -2) goto _L2; else goto _L1
	//   22   46:aload_0         
	//   23   47:getfield        #55  <Field int zzbtq>
	//   24   50:bipush          -2
	//   25   52:icmpeq          105
_L1:
		l = zzbv.zzer().elapsedRealtime();
	//   26   55:invokestatic    #511 <Method Clock zzbv.zzer()>
	//   27   58:invokeinterface #514 <Method long Clock.elapsedRealtime()>
	//   28   63:lstore_1        
		obj1 = ((Object) (new zzxe(zzbtk, zzbtp, zzbth, ((zzxa) (obj1)), zzbtq, zzmi(), l - l2)));
	//   29   64:new             #516 <Class zzxe>
	//   30   67:dup             
	//   31   68:aload_0         
	//   32   69:getfield        #61  <Field zzwx zzbtk>
	//   33   72:aload_0         
	//   34   73:getfield        #126 <Field zzxq zzbtp>
	//   35   76:aload_0         
	//   36   77:getfield        #75  <Field String zzbth>
	//   37   80:aload           14
	//   38   82:aload_0         
	//   39   83:getfield        #55  <Field int zzbtq>
	//   40   86:aload_0         
	//   41   87:invokespecial   #518 <Method zzxw zzmi()>
	//   42   90:lload_1         
	//   43   91:lload           5
	//   44   93:lsub            
	//   45   94:invokespecial   #521 <Method void zzxe(zzwx, zzxq, String, zzxa, int, zzxw, long)>
	//   46   97:astore          14
	//*  47   99:aload           13
		return ((zzxe) (obj1));
	//   48  101:monitorexit     
	//   49  102:aload           14
	//   50  104:areturn         
_L2:
		long l5 = SystemClock.elapsedRealtime();
	//   51  105:invokestatic    #486 <Method long SystemClock.elapsedRealtime()>
	//   52  108:lstore          11
		long l4;
		l4 = l3 - (l5 - l2);
	//   53  110:lload           7
	//   54  112:lload           11
	//   55  114:lload           5
	//   56  116:lsub            
	//   57  117:lsub            
	//   58  118:lstore          9
		l5 = l1 - (l5 - l);
	//   59  120:lload_3         
	//   60  121:lload           11
	//   61  123:lload_1         
	//   62  124:lsub            
	//   63  125:lsub            
	//   64  126:lstore          11
		if(l4 > 0L && l5 > 0L) goto _L4; else goto _L3
	//   65  128:lload           9
	//   66  130:lconst_0        
	//   67  131:lcmp            
	//   68  132:ifle            170
	//   69  135:lload           11
	//   70  137:lconst_0        
	//   71  138:lcmp            
	//   72  139:ifgt            145
	//*  73  142:goto            170
_L4:
		mLock.wait(Math.min(l4, l5));
	//   74  145:aload_0         
	//   75  146:getfield        #53  <Field Object mLock>
	//   76  149:lload           9
	//   77  151:lload           11
	//   78  153:invokestatic    #527 <Method long Math.min(long, long)>
	//   79  156:invokevirtual   #531 <Method void Object.wait(long)>
		  goto _L5
	//*  80  159:goto            197
_L6:
		zzbtq = 5;
	//   81  162:aload_0         
	//   82  163:iconst_5        
	//   83  164:putfield        #55  <Field int zzbtq>
		  goto _L5
	//*  84  167:goto            197
_L3:
		zzakb.zzdj("Timed out waiting for adapter.");
	//   85  170:ldc2            #533 <String "Timed out waiting for adapter.">
	//   86  173:invokestatic    #386 <Method void zzakb.zzdj(String)>
		zzbtq = 3;
	//   87  176:aload_0         
	//   88  177:iconst_3        
	//   89  178:putfield        #55  <Field int zzbtq>
		  goto _L5
	//*  90  181:goto            197
		Exception exception;
		exception;
	//   91  184:astore          14
		obj;
	//   92  186:aload           13
		JVM INSTR monitorexit ;
	//   93  188:monitorexit     
		throw exception;
	//   94  189:aload           14
	//   95  191:athrow          
		InterruptedException interruptedexception;
		interruptedexception;
	//   96  192:astore          15
		  goto _L6
	//*  97  194:goto            162
	//*  98  197:goto            46
	}

	public final void zza(int i, zzxw zzxw1)
	{
		synchronized(mLock)
	//*   0    0:aload_0         
	//*   1    1:getfield        #53  <Field Object mLock>
	//*   2    4:astore_3        
	//*   3    5:aload_3         
	//*   4    6:monitorenter    
		{
			zzbtq = 0;
	//    5    7:aload_0         
	//    6    8:iconst_0        
	//    7    9:putfield        #55  <Field int zzbtq>
			zzbtr = zzxw1;
	//    8   12:aload_0         
	//    9   13:aload_2         
	//   10   14:putfield        #364 <Field zzxw zzbtr>
			mLock.notify();
	//   11   17:aload_0         
	//   12   18:getfield        #53  <Field Object mLock>
	//   13   21:invokevirtual   #477 <Method void Object.notify()>
		}
	//   14   24:aload_3         
	//   15   25:monitorexit     
		return;
	//   16   26:return          
		zzxw1;
	//   17   27:astore_2        
		obj;
	//   18   28:aload_3         
		JVM INSTR monitorexit ;
	//   19   29:monitorexit     
		throw zzxw1;
	//   20   30:aload_2         
	//   21   31:athrow          
	}

	public final void zzx(int i)
	{
		synchronized(mLock)
	//*   0    0:aload_0         
	//*   1    1:getfield        #53  <Field Object mLock>
	//*   2    4:astore_2        
	//*   3    5:aload_2         
	//*   4    6:monitorenter    
		{
			zzbtq = i;
	//    5    7:aload_0         
	//    6    8:iload_1         
	//    7    9:putfield        #55  <Field int zzbtq>
			mLock.notify();
	//    8   12:aload_0         
	//    9   13:getfield        #53  <Field Object mLock>
	//   10   16:invokevirtual   #477 <Method void Object.notify()>
		}
	//   11   19:aload_2         
	//   12   20:monitorexit     
		return;
	//   13   21:return          
		exception;
	//   14   22:astore_3        
		obj;
	//   15   23:aload_2         
		JVM INSTR monitorexit ;
	//   16   24:monitorexit     
		throw exception;
	//   17   25:aload_3         
	//   18   26:athrow          
	}

	private final Context mContext;
	private final Object mLock = new Object();
	private zzjj zzaao;
	private final zzjn zzaau;
	private final boolean zzael;
	private final String zzbth;
	private final long zzbti;
	private final zzwy zzbtj;
	private final zzwx zzbtk;
	private final List zzbtl;
	private final List zzbtm;
	private final boolean zzbtn;
	private final boolean zzbto;
	private zzxq zzbtp;
	private int zzbtq;
	private zzxw zzbtr;
	private final zzxn zzwh;
	private final zzpl zzyb;
	private final List zzyc;
	private final zzang zzyf;
}
