// Decompiled by Jad v1.5.8g. Copyright 2001 Pavel Kouznetsov.
// Jad home page: http://www.kpdus.com/jad.html
// Decompiler options: packimports(3) annotate safe 

package com.samsung.aasaservice;


// Referenced classes of package com.samsung.aasaservice:
//			R

public static final class R$styleable
{

	public static final int ActionBar[] = {
		0x7f010000, 0x7f010001, 0x7f01002c, 0x7f010055, 0x7f010056, 0x7f010057, 0x7f010058, 0x7f010059, 0x7f01005a, 0x7f01005b, 
		0x7f01005c, 0x7f01005d, 0x7f01005e, 0x7f01005f, 0x7f010060, 0x7f010061, 0x7f010062, 0x7f010063, 0x7f010064, 0x7f010065, 
		0x7f010066, 0x7f010067, 0x7f010068, 0x7f010069, 0x7f01006a, 0x7f01006b, 0x7f01006c
	};
	public static final int ActionBarLayout[] = {
		0x10100b3
	};
	public static final int ActionBarLayout_android_layout_gravity = 0;
	public static final int ActionBar_background = 11;
	public static final int ActionBar_backgroundSplit = 13;
	public static final int ActionBar_backgroundStacked = 12;
	public static final int ActionBar_contentInsetEnd = 22;
	public static final int ActionBar_contentInsetLeft = 23;
	public static final int ActionBar_contentInsetRight = 24;
	public static final int ActionBar_contentInsetStart = 21;
	public static final int ActionBar_customNavigationLayout = 14;
	public static final int ActionBar_displayOptions = 4;
	public static final int ActionBar_divider = 10;
	public static final int ActionBar_elevation = 25;
	public static final int ActionBar_height = 1;
	public static final int ActionBar_hideOnContentScroll = 20;
	public static final int ActionBar_homeAsUpIndicator = 2;
	public static final int ActionBar_homeLayout = 15;
	public static final int ActionBar_icon = 8;
	public static final int ActionBar_indeterminateProgressStyle = 17;
	public static final int ActionBar_itemPadding = 19;
	public static final int ActionBar_logo = 9;
	public static final int ActionBar_navigationMode = 3;
	public static final int ActionBar_popupTheme = 26;
	public static final int ActionBar_progressBarPadding = 18;
	public static final int ActionBar_progressBarStyle = 16;
	public static final int ActionBar_subtitle = 5;
	public static final int ActionBar_subtitleTextStyle = 7;
	public static final int ActionBar_title = 0;
	public static final int ActionBar_titleTextStyle = 6;
	public static final int ActionMenuItemView[] = {
		0x101013f
	};
	public static final int ActionMenuItemView_android_minWidth = 0;
	public static final int ActionMenuView[] = new int[0];
	public static final int ActionMode[] = {
		0x7f010001, 0x7f010058, 0x7f010059, 0x7f01005d, 0x7f01005f, 0x7f01006d
	};
	public static final int ActionMode_background = 3;
	public static final int ActionMode_backgroundSplit = 4;
	public static final int ActionMode_closeItemLayout = 5;
	public static final int ActionMode_height = 0;
	public static final int ActionMode_subtitleTextStyle = 2;
	public static final int ActionMode_titleTextStyle = 1;
	public static final int ActivityChooserView[] = {
		0x7f010084, 0x7f010085
	};
	public static final int ActivityChooserView_expandActivityOverflowButtonDrawable = 1;
	public static final int ActivityChooserView_initialActivityCount = 0;
	public static final int CompatTextView[] = {
		0x7f010086
	};
	public static final int CompatTextView_textAllCaps = 0;
	public static final int DrawerArrowToggle[] = {
		0x7f010099, 0x7f01009a, 0x7f01009b, 0x7f01009c, 0x7f01009d, 0x7f01009e, 0x7f01009f, 0x7f0100a0
	};
	public static final int DrawerArrowToggle_barSize = 6;
	public static final int DrawerArrowToggle_color = 0;
	public static final int DrawerArrowToggle_drawableSize = 2;
	public static final int DrawerArrowToggle_gapBetweenBars = 3;
	public static final int DrawerArrowToggle_middleBarArrowSize = 5;
	public static final int DrawerArrowToggle_spinBars = 1;
	public static final int DrawerArrowToggle_thickness = 7;
	public static final int DrawerArrowToggle_topBottomBarArrowSize = 4;
	public static final int LinearLayoutCompat[] = {
		0x10100af, 0x10100c4, 0x1010126, 0x1010127, 0x1010128, 0x7f01005c, 0x7f010087, 0x7f010088, 0x7f010089
	};
	public static final int LinearLayoutCompat_Layout[] = {
		0x10100b3, 0x10100f4, 0x10100f5, 0x1010181
	};
	public static final int LinearLayoutCompat_Layout_android_layout_gravity = 0;
	public static final int LinearLayoutCompat_Layout_android_layout_height = 2;
	public static final int LinearLayoutCompat_Layout_android_layout_weight = 3;
	public static final int LinearLayoutCompat_Layout_android_layout_width = 1;
	public static final int LinearLayoutCompat_android_baselineAligned = 2;
	public static final int LinearLayoutCompat_android_baselineAlignedChildIndex = 3;
	public static final int LinearLayoutCompat_android_gravity = 0;
	public static final int LinearLayoutCompat_android_orientation = 1;
	public static final int LinearLayoutCompat_android_weightSum = 4;
	public static final int LinearLayoutCompat_divider = 5;
	public static final int LinearLayoutCompat_dividerPadding = 8;
	public static final int LinearLayoutCompat_measureWithLargestChild = 6;
	public static final int LinearLayoutCompat_showDividers = 7;
	public static final int ListPopupWindow[] = {
		0x10102ac, 0x10102ad
	};
	public static final int ListPopupWindow_android_dropDownHorizontalOffset = 0;
	public static final int ListPopupWindow_android_dropDownVerticalOffset = 1;
	public static final int MenuGroup[] = {
		0x101000e, 0x10100d0, 0x1010194, 0x10101de, 0x10101df, 0x10101e0
	};
	public static final int MenuGroup_android_checkableBehavior = 5;
	public static final int MenuGroup_android_enabled = 0;
	public static final int MenuGroup_android_id = 1;
	public static final int MenuGroup_android_menuCategory = 3;
	public static final int MenuGroup_android_orderInCategory = 4;
	public static final int MenuGroup_android_visible = 2;
	public static final int MenuItem[] = {
		0x1010002, 0x101000e, 0x10100d0, 0x1010106, 0x1010194, 0x10101de, 0x10101df, 0x10101e1, 0x10101e2, 0x10101e3, 
		0x10101e4, 0x10101e5, 0x101026f, 0x7f010071, 0x7f010072, 0x7f010073, 0x7f010074
	};
	public static final int MenuItem_actionLayout = 14;
	public static final int MenuItem_actionProviderClass = 16;
	public static final int MenuItem_actionViewClass = 15;
	public static final int MenuItem_android_alphabeticShortcut = 9;
	public static final int MenuItem_android_checkable = 11;
	public static final int MenuItem_android_checked = 3;
	public static final int MenuItem_android_enabled = 1;
	public static final int MenuItem_android_icon = 0;
	public static final int MenuItem_android_id = 2;
	public static final int MenuItem_android_menuCategory = 5;
	public static final int MenuItem_android_numericShortcut = 10;
	public static final int MenuItem_android_onClick = 12;
	public static final int MenuItem_android_orderInCategory = 6;
	public static final int MenuItem_android_title = 7;
	public static final int MenuItem_android_titleCondensed = 8;
	public static final int MenuItem_android_visible = 4;
	public static final int MenuItem_showAsAction = 13;
	public static final int MenuView[] = {
		0x10100ae, 0x101012c, 0x101012d, 0x101012e, 0x101012f, 0x1010130, 0x1010131, 0x7f010070
	};
	public static final int MenuView_android_headerBackground = 4;
	public static final int MenuView_android_horizontalDivider = 2;
	public static final int MenuView_android_itemBackground = 5;
	public static final int MenuView_android_itemIconDisabledAlpha = 6;
	public static final int MenuView_android_itemTextAppearance = 1;
	public static final int MenuView_android_verticalDivider = 3;
	public static final int MenuView_android_windowAnimationStyle = 0;
	public static final int MenuView_preserveIconSpacing = 7;
	public static final int PopupWindow[] = {
		0x1010176, 0x7f010098
	};
	public static final int PopupWindowBackgroundState[] = {
		0x7f010097
	};
	public static final int PopupWindowBackgroundState_state_above_anchor = 0;
	public static final int PopupWindow_android_popupBackground = 0;
	public static final int PopupWindow_overlapAnchor = 1;
	public static final int SearchView[] = {
		0x10100da, 0x101011f, 0x1010220, 0x1010264, 0x7f010079, 0x7f01007a, 0x7f01007b, 0x7f01007c, 0x7f01007d, 0x7f01007e, 
		0x7f01007f, 0x7f010080, 0x7f010081, 0x7f010082, 0x7f010083
	};
	public static final int SearchView_android_focusable = 0;
	public static final int SearchView_android_imeOptions = 3;
	public static final int SearchView_android_inputType = 2;
	public static final int SearchView_android_maxWidth = 1;
	public static final int SearchView_closeIcon = 7;
	public static final int SearchView_commitIcon = 11;
	public static final int SearchView_goIcon = 8;
	public static final int SearchView_iconifiedByDefault = 5;
	public static final int SearchView_layout = 4;
	public static final int SearchView_queryBackground = 13;
	public static final int SearchView_queryHint = 6;
	public static final int SearchView_searchIcon = 9;
	public static final int SearchView_submitBackground = 14;
	public static final int SearchView_suggestionRowLayout = 12;
	public static final int SearchView_voiceIcon = 10;
	public static final int Spinner[] = {
		0x10100af, 0x10100d4, 0x1010175, 0x1010176, 0x1010262, 0x10102ac, 0x10102ad, 0x7f010075, 0x7f010076, 0x7f010077, 
		0x7f010078
	};
	public static final int Spinner_android_background = 1;
	public static final int Spinner_android_dropDownHorizontalOffset = 5;
	public static final int Spinner_android_dropDownSelector = 2;
	public static final int Spinner_android_dropDownVerticalOffset = 6;
	public static final int Spinner_android_dropDownWidth = 4;
	public static final int Spinner_android_gravity = 0;
	public static final int Spinner_android_popupBackground = 3;
	public static final int Spinner_disableChildrenWhenDisabled = 10;
	public static final int Spinner_popupPromptView = 9;
	public static final int Spinner_prompt = 7;
	public static final int Spinner_spinnerMode = 8;
	public static final int SwitchCompat[] = {
		0x1010124, 0x1010125, 0x1010142, 0x7f0100a2, 0x7f0100a3, 0x7f0100a4, 0x7f0100a5, 0x7f0100a6, 0x7f0100a7, 0x7f0100a8
	};
	public static final int SwitchCompat_android_textOff = 1;
	public static final int SwitchCompat_android_textOn = 0;
	public static final int SwitchCompat_android_thumb = 2;
	public static final int SwitchCompat_showText = 9;
	public static final int SwitchCompat_splitTrack = 8;
	public static final int SwitchCompat_switchMinWidth = 6;
	public static final int SwitchCompat_switchPadding = 7;
	public static final int SwitchCompat_switchTextAppearance = 5;
	public static final int SwitchCompat_thumbTextPadding = 4;
	public static final int SwitchCompat_track = 3;
	public static final int Theme[] = {
		0x1010057, 0x7f010003, 0x7f010004, 0x7f010005, 0x7f010006, 0x7f010007, 0x7f010008, 0x7f010009, 0x7f01000a, 0x7f01000b, 
		0x7f01000c, 0x7f01000d, 0x7f01000e, 0x7f01000f, 0x7f010010, 0x7f010011, 0x7f010012, 0x7f010013, 0x7f010014, 0x7f010015, 
		0x7f010016, 0x7f010017, 0x7f010018, 0x7f010019, 0x7f01001a, 0x7f01001b, 0x7f01001c, 0x7f01001d, 0x7f01001e, 0x7f01001f, 
		0x7f010020, 0x7f010021, 0x7f010022, 0x7f010023, 0x7f010024, 0x7f010025, 0x7f010026, 0x7f010027, 0x7f010028, 0x7f010029, 
		0x7f01002a, 0x7f01002b, 0x7f01002c, 0x7f01002d, 0x7f01002e, 0x7f01002f, 0x7f010030, 0x7f010031, 0x7f010032, 0x7f010033, 
		0x7f010034, 0x7f010035, 0x7f010036, 0x7f010037, 0x7f010038, 0x7f010039, 0x7f01003a, 0x7f01003b, 0x7f01003c, 0x7f01003d, 
		0x7f01003e, 0x7f01003f, 0x7f010040, 0x7f010041, 0x7f010042, 0x7f010043, 0x7f010044, 0x7f010045, 0x7f010046, 0x7f010047, 
		0x7f010048, 0x7f010049, 0x7f01004a, 0x7f01004b, 0x7f01004c, 0x7f01004d, 0x7f01004e, 0x7f01004f, 0x7f010050, 0x7f010051, 
		0x7f010052, 0x7f010053, 0x7f010054
	};
	public static final int Theme_actionBarDivider = 19;
	public static final int Theme_actionBarItemBackground = 20;
	public static final int Theme_actionBarPopupTheme = 13;
	public static final int Theme_actionBarSize = 18;
	public static final int Theme_actionBarSplitStyle = 15;
	public static final int Theme_actionBarStyle = 14;
	public static final int Theme_actionBarTabBarStyle = 9;
	public static final int Theme_actionBarTabStyle = 8;
	public static final int Theme_actionBarTabTextStyle = 10;
	public static final int Theme_actionBarTheme = 16;
	public static final int Theme_actionBarWidgetTheme = 17;
	public static final int Theme_actionButtonStyle = 43;
	public static final int Theme_actionDropDownStyle = 38;
	public static final int Theme_actionMenuTextAppearance = 21;
	public static final int Theme_actionMenuTextColor = 22;
	public static final int Theme_actionModeBackground = 25;
	public static final int Theme_actionModeCloseButtonStyle = 24;
	public static final int Theme_actionModeCloseDrawable = 27;
	public static final int Theme_actionModeCopyDrawable = 29;
	public static final int Theme_actionModeCutDrawable = 28;
	public static final int Theme_actionModeFindDrawable = 33;
	public static final int Theme_actionModePasteDrawable = 30;
	public static final int Theme_actionModePopupWindowStyle = 35;
	public static final int Theme_actionModeSelectAllDrawable = 31;
	public static final int Theme_actionModeShareDrawable = 32;
	public static final int Theme_actionModeSplitBackground = 26;
	public static final int Theme_actionModeStyle = 23;
	public static final int Theme_actionModeWebSearchDrawable = 34;
	public static final int Theme_actionOverflowButtonStyle = 11;
	public static final int Theme_actionOverflowMenuStyle = 12;
	public static final int Theme_activityChooserViewStyle = 50;
	public static final int Theme_android_windowIsFloating = 0;
	public static final int Theme_buttonBarButtonStyle = 45;
	public static final int Theme_buttonBarStyle = 44;
	public static final int Theme_colorAccent = 77;
	public static final int Theme_colorButtonNormal = 81;
	public static final int Theme_colorControlActivated = 79;
	public static final int Theme_colorControlHighlight = 80;
	public static final int Theme_colorControlNormal = 78;
	public static final int Theme_colorPrimary = 75;
	public static final int Theme_colorPrimaryDark = 76;
	public static final int Theme_colorSwitchThumbNormal = 82;
	public static final int Theme_dividerHorizontal = 49;
	public static final int Theme_dividerVertical = 48;
	public static final int Theme_dropDownListViewStyle = 67;
	public static final int Theme_dropdownListPreferredItemHeight = 39;
	public static final int Theme_editTextBackground = 56;
	public static final int Theme_editTextColor = 55;
	public static final int Theme_homeAsUpIndicator = 42;
	public static final int Theme_listChoiceBackgroundIndicator = 74;
	public static final int Theme_listPopupWindowStyle = 68;
	public static final int Theme_listPreferredItemHeight = 62;
	public static final int Theme_listPreferredItemHeightLarge = 64;
	public static final int Theme_listPreferredItemHeightSmall = 63;
	public static final int Theme_listPreferredItemPaddingLeft = 65;
	public static final int Theme_listPreferredItemPaddingRight = 66;
	public static final int Theme_panelBackground = 71;
	public static final int Theme_panelMenuListTheme = 73;
	public static final int Theme_panelMenuListWidth = 72;
	public static final int Theme_popupMenuStyle = 53;
	public static final int Theme_popupWindowStyle = 54;
	public static final int Theme_searchViewStyle = 61;
	public static final int Theme_selectableItemBackground = 46;
	public static final int Theme_selectableItemBackgroundBorderless = 47;
	public static final int Theme_spinnerDropDownItemStyle = 41;
	public static final int Theme_spinnerStyle = 40;
	public static final int Theme_switchStyle = 57;
	public static final int Theme_textAppearanceLargePopupMenu = 36;
	public static final int Theme_textAppearanceListItem = 69;
	public static final int Theme_textAppearanceListItemSmall = 70;
	public static final int Theme_textAppearanceSearchResultSubtitle = 59;
	public static final int Theme_textAppearanceSearchResultTitle = 58;
	public static final int Theme_textAppearanceSmallPopupMenu = 37;
	public static final int Theme_textColorSearchUrl = 60;
	public static final int Theme_toolbarNavigationButtonStyle = 52;
	public static final int Theme_toolbarStyle = 51;
	public static final int Theme_windowActionBar = 1;
	public static final int Theme_windowActionBarOverlay = 2;
	public static final int Theme_windowActionModeOverlay = 3;
	public static final int Theme_windowFixedHeightMajor = 7;
	public static final int Theme_windowFixedHeightMinor = 5;
	public static final int Theme_windowFixedWidthMajor = 4;
	public static final int Theme_windowFixedWidthMinor = 6;
	public static final int Toolbar[] = {
		0x10100af, 0x1010140, 0x7f010000, 0x7f010057, 0x7f010067, 0x7f010068, 0x7f010069, 0x7f01006a, 0x7f01006c, 0x7f01008a, 
		0x7f01008b, 0x7f01008c, 0x7f01008d, 0x7f01008e, 0x7f01008f, 0x7f010090, 0x7f010091, 0x7f010092, 0x7f010093, 0x7f010094, 
		0x7f010095, 0x7f010096
	};
	public static final int Toolbar_android_gravity = 0;
	public static final int Toolbar_android_minHeight = 1;
	public static final int Toolbar_collapseContentDescription = 19;
	public static final int Toolbar_collapseIcon = 18;
	public static final int Toolbar_contentInsetEnd = 5;
	public static final int Toolbar_contentInsetLeft = 6;
	public static final int Toolbar_contentInsetRight = 7;
	public static final int Toolbar_contentInsetStart = 4;
	public static final int Toolbar_maxButtonHeight = 16;
	public static final int Toolbar_navigationContentDescription = 21;
	public static final int Toolbar_navigationIcon = 20;
	public static final int Toolbar_popupTheme = 8;
	public static final int Toolbar_subtitle = 3;
	public static final int Toolbar_subtitleTextAppearance = 10;
	public static final int Toolbar_theme = 17;
	public static final int Toolbar_title = 2;
	public static final int Toolbar_titleMarginBottom = 15;
	public static final int Toolbar_titleMarginEnd = 13;
	public static final int Toolbar_titleMarginStart = 12;
	public static final int Toolbar_titleMarginTop = 14;
	public static final int Toolbar_titleMargins = 11;
	public static final int Toolbar_titleTextAppearance = 9;
	public static final int View[] = {
		0x10100da, 0x7f01006e, 0x7f01006f
	};
	public static final int ViewStubCompat[] = {
		0x10100d0, 0x10100f2, 0x10100f3
	};
	public static final int ViewStubCompat_android_id = 0;
	public static final int ViewStubCompat_android_inflatedId = 2;
	public static final int ViewStubCompat_android_layout = 1;
	public static final int View_android_focusable = 0;
	public static final int View_paddingEnd = 2;
	public static final int View_paddingStart = 1;

	static 
	{
	//    0    0:bipush          27
	//    1    2:newarray        int[]
	//    2    4:dup             
	//    3    5:iconst_0        
	//    4    6:ldc2            #360 <Int 0x7f010000>
	//    5    9:iastore         
	//    6   10:dup             
	//    7   11:iconst_1        
	//    8   12:ldc2            #361 <Int 0x7f010001>
	//    9   15:iastore         
	//   10   16:dup             
	//   11   17:iconst_2        
	//   12   18:ldc2            #362 <Int 0x7f01002c>
	//   13   21:iastore         
	//   14   22:dup             
	//   15   23:iconst_3        
	//   16   24:ldc2            #363 <Int 0x7f010055>
	//   17   27:iastore         
	//   18   28:dup             
	//   19   29:iconst_4        
	//   20   30:ldc2            #364 <Int 0x7f010056>
	//   21   33:iastore         
	//   22   34:dup             
	//   23   35:iconst_5        
	//   24   36:ldc2            #365 <Int 0x7f010057>
	//   25   39:iastore         
	//   26   40:dup             
	//   27   41:bipush          6
	//   28   43:ldc2            #366 <Int 0x7f010058>
	//   29   46:iastore         
	//   30   47:dup             
	//   31   48:bipush          7
	//   32   50:ldc2            #367 <Int 0x7f010059>
	//   33   53:iastore         
	//   34   54:dup             
	//   35   55:bipush          8
	//   36   57:ldc2            #368 <Int 0x7f01005a>
	//   37   60:iastore         
	//   38   61:dup             
	//   39   62:bipush          9
	//   40   64:ldc2            #369 <Int 0x7f01005b>
	//   41   67:iastore         
	//   42   68:dup             
	//   43   69:bipush          10
	//   44   71:ldc2            #370 <Int 0x7f01005c>
	//   45   74:iastore         
	//   46   75:dup             
	//   47   76:bipush          11
	//   48   78:ldc2            #371 <Int 0x7f01005d>
	//   49   81:iastore         
	//   50   82:dup             
	//   51   83:bipush          12
	//   52   85:ldc2            #372 <Int 0x7f01005e>
	//   53   88:iastore         
	//   54   89:dup             
	//   55   90:bipush          13
	//   56   92:ldc2            #373 <Int 0x7f01005f>
	//   57   95:iastore         
	//   58   96:dup             
	//   59   97:bipush          14
	//   60   99:ldc2            #374 <Int 0x7f010060>
	//   61  102:iastore         
	//   62  103:dup             
	//   63  104:bipush          15
	//   64  106:ldc2            #375 <Int 0x7f010061>
	//   65  109:iastore         
	//   66  110:dup             
	//   67  111:bipush          16
	//   68  113:ldc2            #376 <Int 0x7f010062>
	//   69  116:iastore         
	//   70  117:dup             
	//   71  118:bipush          17
	//   72  120:ldc2            #377 <Int 0x7f010063>
	//   73  123:iastore         
	//   74  124:dup             
	//   75  125:bipush          18
	//   76  127:ldc2            #378 <Int 0x7f010064>
	//   77  130:iastore         
	//   78  131:dup             
	//   79  132:bipush          19
	//   80  134:ldc2            #379 <Int 0x7f010065>
	//   81  137:iastore         
	//   82  138:dup             
	//   83  139:bipush          20
	//   84  141:ldc2            #380 <Int 0x7f010066>
	//   85  144:iastore         
	//   86  145:dup             
	//   87  146:bipush          21
	//   88  148:ldc2            #381 <Int 0x7f010067>
	//   89  151:iastore         
	//   90  152:dup             
	//   91  153:bipush          22
	//   92  155:ldc2            #382 <Int 0x7f010068>
	//   93  158:iastore         
	//   94  159:dup             
	//   95  160:bipush          23
	//   96  162:ldc2            #383 <Int 0x7f010069>
	//   97  165:iastore         
	//   98  166:dup             
	//   99  167:bipush          24
	//  100  169:ldc2            #384 <Int 0x7f01006a>
	//  101  172:iastore         
	//  102  173:dup             
	//  103  174:bipush          25
	//  104  176:ldc2            #385 <Int 0x7f01006b>
	//  105  179:iastore         
	//  106  180:dup             
	//  107  181:bipush          26
	//  108  183:ldc2            #386 <Int 0x7f01006c>
	//  109  186:iastore         
	//  110  187:putstatic       #388 <Field int[] ActionBar>
	//  111  190:iconst_1        
	//  112  191:newarray        int[]
	//  113  193:dup             
	//  114  194:iconst_0        
	//  115  195:ldc2            #389 <Int 0x10100b3>
	//  116  198:iastore         
	//  117  199:putstatic       #391 <Field int[] ActionBarLayout>
	//  118  202:iconst_1        
	//  119  203:newarray        int[]
	//  120  205:dup             
	//  121  206:iconst_0        
	//  122  207:ldc2            #392 <Int 0x101013f>
	//  123  210:iastore         
	//  124  211:putstatic       #394 <Field int[] ActionMenuItemView>
	//  125  214:iconst_0        
	//  126  215:newarray        int[]
	//  127  217:putstatic       #396 <Field int[] ActionMenuView>
	//  128  220:bipush          6
	//  129  222:newarray        int[]
	//  130  224:dup             
	//  131  225:iconst_0        
	//  132  226:ldc2            #361 <Int 0x7f010001>
	//  133  229:iastore         
	//  134  230:dup             
	//  135  231:iconst_1        
	//  136  232:ldc2            #366 <Int 0x7f010058>
	//  137  235:iastore         
	//  138  236:dup             
	//  139  237:iconst_2        
	//  140  238:ldc2            #367 <Int 0x7f010059>
	//  141  241:iastore         
	//  142  242:dup             
	//  143  243:iconst_3        
	//  144  244:ldc2            #371 <Int 0x7f01005d>
	//  145  247:iastore         
	//  146  248:dup             
	//  147  249:iconst_4        
	//  148  250:ldc2            #373 <Int 0x7f01005f>
	//  149  253:iastore         
	//  150  254:dup             
	//  151  255:iconst_5        
	//  152  256:ldc2            #397 <Int 0x7f01006d>
	//  153  259:iastore         
	//  154  260:putstatic       #399 <Field int[] ActionMode>
	//  155  263:iconst_2        
	//  156  264:newarray        int[]
	//  157  266:dup             
	//  158  267:iconst_0        
	//  159  268:ldc2            #400 <Int 0x7f010084>
	//  160  271:iastore         
	//  161  272:dup             
	//  162  273:iconst_1        
	//  163  274:ldc2            #401 <Int 0x7f010085>
	//  164  277:iastore         
	//  165  278:putstatic       #403 <Field int[] ActivityChooserView>
	//  166  281:iconst_1        
	//  167  282:newarray        int[]
	//  168  284:dup             
	//  169  285:iconst_0        
	//  170  286:ldc2            #404 <Int 0x7f010086>
	//  171  289:iastore         
	//  172  290:putstatic       #406 <Field int[] CompatTextView>
	//  173  293:bipush          8
	//  174  295:newarray        int[]
	//  175  297:dup             
	//  176  298:iconst_0        
	//  177  299:ldc2            #407 <Int 0x7f010099>
	//  178  302:iastore         
	//  179  303:dup             
	//  180  304:iconst_1        
	//  181  305:ldc2            #408 <Int 0x7f01009a>
	//  182  308:iastore         
	//  183  309:dup             
	//  184  310:iconst_2        
	//  185  311:ldc2            #409 <Int 0x7f01009b>
	//  186  314:iastore         
	//  187  315:dup             
	//  188  316:iconst_3        
	//  189  317:ldc2            #410 <Int 0x7f01009c>
	//  190  320:iastore         
	//  191  321:dup             
	//  192  322:iconst_4        
	//  193  323:ldc2            #411 <Int 0x7f01009d>
	//  194  326:iastore         
	//  195  327:dup             
	//  196  328:iconst_5        
	//  197  329:ldc2            #412 <Int 0x7f01009e>
	//  198  332:iastore         
	//  199  333:dup             
	//  200  334:bipush          6
	//  201  336:ldc2            #413 <Int 0x7f01009f>
	//  202  339:iastore         
	//  203  340:dup             
	//  204  341:bipush          7
	//  205  343:ldc2            #414 <Int 0x7f0100a0>
	//  206  346:iastore         
	//  207  347:putstatic       #416 <Field int[] DrawerArrowToggle>
	//  208  350:bipush          9
	//  209  352:newarray        int[]
	//  210  354:dup             
	//  211  355:iconst_0        
	//  212  356:ldc2            #417 <Int 0x10100af>
	//  213  359:iastore         
	//  214  360:dup             
	//  215  361:iconst_1        
	//  216  362:ldc2            #418 <Int 0x10100c4>
	//  217  365:iastore         
	//  218  366:dup             
	//  219  367:iconst_2        
	//  220  368:ldc2            #419 <Int 0x1010126>
	//  221  371:iastore         
	//  222  372:dup             
	//  223  373:iconst_3        
	//  224  374:ldc2            #420 <Int 0x1010127>
	//  225  377:iastore         
	//  226  378:dup             
	//  227  379:iconst_4        
	//  228  380:ldc2            #421 <Int 0x1010128>
	//  229  383:iastore         
	//  230  384:dup             
	//  231  385:iconst_5        
	//  232  386:ldc2            #370 <Int 0x7f01005c>
	//  233  389:iastore         
	//  234  390:dup             
	//  235  391:bipush          6
	//  236  393:ldc2            #422 <Int 0x7f010087>
	//  237  396:iastore         
	//  238  397:dup             
	//  239  398:bipush          7
	//  240  400:ldc2            #423 <Int 0x7f010088>
	//  241  403:iastore         
	//  242  404:dup             
	//  243  405:bipush          8
	//  244  407:ldc2            #424 <Int 0x7f010089>
	//  245  410:iastore         
	//  246  411:putstatic       #426 <Field int[] LinearLayoutCompat>
	//  247  414:iconst_4        
	//  248  415:newarray        int[]
	//  249  417:dup             
	//  250  418:iconst_0        
	//  251  419:ldc2            #389 <Int 0x10100b3>
	//  252  422:iastore         
	//  253  423:dup             
	//  254  424:iconst_1        
	//  255  425:ldc2            #427 <Int 0x10100f4>
	//  256  428:iastore         
	//  257  429:dup             
	//  258  430:iconst_2        
	//  259  431:ldc2            #428 <Int 0x10100f5>
	//  260  434:iastore         
	//  261  435:dup             
	//  262  436:iconst_3        
	//  263  437:ldc2            #429 <Int 0x1010181>
	//  264  440:iastore         
	//  265  441:putstatic       #431 <Field int[] LinearLayoutCompat_Layout>
	//  266  444:iconst_2        
	//  267  445:newarray        int[]
	//  268  447:dup             
	//  269  448:iconst_0        
	//  270  449:ldc2            #432 <Int 0x10102ac>
	//  271  452:iastore         
	//  272  453:dup             
	//  273  454:iconst_1        
	//  274  455:ldc2            #433 <Int 0x10102ad>
	//  275  458:iastore         
	//  276  459:putstatic       #435 <Field int[] ListPopupWindow>
	//  277  462:bipush          6
	//  278  464:newarray        int[]
	//  279  466:dup             
	//  280  467:iconst_0        
	//  281  468:ldc2            #436 <Int 0x101000e>
	//  282  471:iastore         
	//  283  472:dup             
	//  284  473:iconst_1        
	//  285  474:ldc2            #437 <Int 0x10100d0>
	//  286  477:iastore         
	//  287  478:dup             
	//  288  479:iconst_2        
	//  289  480:ldc2            #438 <Int 0x1010194>
	//  290  483:iastore         
	//  291  484:dup             
	//  292  485:iconst_3        
	//  293  486:ldc2            #439 <Int 0x10101de>
	//  294  489:iastore         
	//  295  490:dup             
	//  296  491:iconst_4        
	//  297  492:ldc2            #440 <Int 0x10101df>
	//  298  495:iastore         
	//  299  496:dup             
	//  300  497:iconst_5        
	//  301  498:ldc2            #441 <Int 0x10101e0>
	//  302  501:iastore         
	//  303  502:putstatic       #443 <Field int[] MenuGroup>
	//  304  505:bipush          17
	//  305  507:newarray        int[]
	//  306  509:dup             
	//  307  510:iconst_0        
	//  308  511:ldc2            #444 <Int 0x1010002>
	//  309  514:iastore         
	//  310  515:dup             
	//  311  516:iconst_1        
	//  312  517:ldc2            #436 <Int 0x101000e>
	//  313  520:iastore         
	//  314  521:dup             
	//  315  522:iconst_2        
	//  316  523:ldc2            #437 <Int 0x10100d0>
	//  317  526:iastore         
	//  318  527:dup             
	//  319  528:iconst_3        
	//  320  529:ldc2            #445 <Int 0x1010106>
	//  321  532:iastore         
	//  322  533:dup             
	//  323  534:iconst_4        
	//  324  535:ldc2            #438 <Int 0x1010194>
	//  325  538:iastore         
	//  326  539:dup             
	//  327  540:iconst_5        
	//  328  541:ldc2            #439 <Int 0x10101de>
	//  329  544:iastore         
	//  330  545:dup             
	//  331  546:bipush          6
	//  332  548:ldc2            #440 <Int 0x10101df>
	//  333  551:iastore         
	//  334  552:dup             
	//  335  553:bipush          7
	//  336  555:ldc2            #446 <Int 0x10101e1>
	//  337  558:iastore         
	//  338  559:dup             
	//  339  560:bipush          8
	//  340  562:ldc2            #447 <Int 0x10101e2>
	//  341  565:iastore         
	//  342  566:dup             
	//  343  567:bipush          9
	//  344  569:ldc2            #448 <Int 0x10101e3>
	//  345  572:iastore         
	//  346  573:dup             
	//  347  574:bipush          10
	//  348  576:ldc2            #449 <Int 0x10101e4>
	//  349  579:iastore         
	//  350  580:dup             
	//  351  581:bipush          11
	//  352  583:ldc2            #450 <Int 0x10101e5>
	//  353  586:iastore         
	//  354  587:dup             
	//  355  588:bipush          12
	//  356  590:ldc2            #451 <Int 0x101026f>
	//  357  593:iastore         
	//  358  594:dup             
	//  359  595:bipush          13
	//  360  597:ldc2            #452 <Int 0x7f010071>
	//  361  600:iastore         
	//  362  601:dup             
	//  363  602:bipush          14
	//  364  604:ldc2            #453 <Int 0x7f010072>
	//  365  607:iastore         
	//  366  608:dup             
	//  367  609:bipush          15
	//  368  611:ldc2            #454 <Int 0x7f010073>
	//  369  614:iastore         
	//  370  615:dup             
	//  371  616:bipush          16
	//  372  618:ldc2            #455 <Int 0x7f010074>
	//  373  621:iastore         
	//  374  622:putstatic       #457 <Field int[] MenuItem>
	//  375  625:bipush          8
	//  376  627:newarray        int[]
	//  377  629:dup             
	//  378  630:iconst_0        
	//  379  631:ldc2            #458 <Int 0x10100ae>
	//  380  634:iastore         
	//  381  635:dup             
	//  382  636:iconst_1        
	//  383  637:ldc2            #459 <Int 0x101012c>
	//  384  640:iastore         
	//  385  641:dup             
	//  386  642:iconst_2        
	//  387  643:ldc2            #460 <Int 0x101012d>
	//  388  646:iastore         
	//  389  647:dup             
	//  390  648:iconst_3        
	//  391  649:ldc2            #461 <Int 0x101012e>
	//  392  652:iastore         
	//  393  653:dup             
	//  394  654:iconst_4        
	//  395  655:ldc2            #462 <Int 0x101012f>
	//  396  658:iastore         
	//  397  659:dup             
	//  398  660:iconst_5        
	//  399  661:ldc2            #463 <Int 0x1010130>
	//  400  664:iastore         
	//  401  665:dup             
	//  402  666:bipush          6
	//  403  668:ldc2            #464 <Int 0x1010131>
	//  404  671:iastore         
	//  405  672:dup             
	//  406  673:bipush          7
	//  407  675:ldc2            #465 <Int 0x7f010070>
	//  408  678:iastore         
	//  409  679:putstatic       #467 <Field int[] MenuView>
	//  410  682:iconst_2        
	//  411  683:newarray        int[]
	//  412  685:dup             
	//  413  686:iconst_0        
	//  414  687:ldc2            #468 <Int 0x1010176>
	//  415  690:iastore         
	//  416  691:dup             
	//  417  692:iconst_1        
	//  418  693:ldc2            #469 <Int 0x7f010098>
	//  419  696:iastore         
	//  420  697:putstatic       #471 <Field int[] PopupWindow>
	//  421  700:iconst_1        
	//  422  701:newarray        int[]
	//  423  703:dup             
	//  424  704:iconst_0        
	//  425  705:ldc2            #472 <Int 0x7f010097>
	//  426  708:iastore         
	//  427  709:putstatic       #474 <Field int[] PopupWindowBackgroundState>
	//  428  712:bipush          15
	//  429  714:newarray        int[]
	//  430  716:dup             
	//  431  717:iconst_0        
	//  432  718:ldc2            #475 <Int 0x10100da>
	//  433  721:iastore         
	//  434  722:dup             
	//  435  723:iconst_1        
	//  436  724:ldc2            #476 <Int 0x101011f>
	//  437  727:iastore         
	//  438  728:dup             
	//  439  729:iconst_2        
	//  440  730:ldc2            #477 <Int 0x1010220>
	//  441  733:iastore         
	//  442  734:dup             
	//  443  735:iconst_3        
	//  444  736:ldc2            #478 <Int 0x1010264>
	//  445  739:iastore         
	//  446  740:dup             
	//  447  741:iconst_4        
	//  448  742:ldc2            #479 <Int 0x7f010079>
	//  449  745:iastore         
	//  450  746:dup             
	//  451  747:iconst_5        
	//  452  748:ldc2            #480 <Int 0x7f01007a>
	//  453  751:iastore         
	//  454  752:dup             
	//  455  753:bipush          6
	//  456  755:ldc2            #481 <Int 0x7f01007b>
	//  457  758:iastore         
	//  458  759:dup             
	//  459  760:bipush          7
	//  460  762:ldc2            #482 <Int 0x7f01007c>
	//  461  765:iastore         
	//  462  766:dup             
	//  463  767:bipush          8
	//  464  769:ldc2            #483 <Int 0x7f01007d>
	//  465  772:iastore         
	//  466  773:dup             
	//  467  774:bipush          9
	//  468  776:ldc2            #484 <Int 0x7f01007e>
	//  469  779:iastore         
	//  470  780:dup             
	//  471  781:bipush          10
	//  472  783:ldc2            #485 <Int 0x7f01007f>
	//  473  786:iastore         
	//  474  787:dup             
	//  475  788:bipush          11
	//  476  790:ldc2            #486 <Int 0x7f010080>
	//  477  793:iastore         
	//  478  794:dup             
	//  479  795:bipush          12
	//  480  797:ldc2            #487 <Int 0x7f010081>
	//  481  800:iastore         
	//  482  801:dup             
	//  483  802:bipush          13
	//  484  804:ldc2            #488 <Int 0x7f010082>
	//  485  807:iastore         
	//  486  808:dup             
	//  487  809:bipush          14
	//  488  811:ldc2            #489 <Int 0x7f010083>
	//  489  814:iastore         
	//  490  815:putstatic       #491 <Field int[] SearchView>
	//  491  818:bipush          11
	//  492  820:newarray        int[]
	//  493  822:dup             
	//  494  823:iconst_0        
	//  495  824:ldc2            #417 <Int 0x10100af>
	//  496  827:iastore         
	//  497  828:dup             
	//  498  829:iconst_1        
	//  499  830:ldc2            #492 <Int 0x10100d4>
	//  500  833:iastore         
	//  501  834:dup             
	//  502  835:iconst_2        
	//  503  836:ldc2            #493 <Int 0x1010175>
	//  504  839:iastore         
	//  505  840:dup             
	//  506  841:iconst_3        
	//  507  842:ldc2            #468 <Int 0x1010176>
	//  508  845:iastore         
	//  509  846:dup             
	//  510  847:iconst_4        
	//  511  848:ldc2            #494 <Int 0x1010262>
	//  512  851:iastore         
	//  513  852:dup             
	//  514  853:iconst_5        
	//  515  854:ldc2            #432 <Int 0x10102ac>
	//  516  857:iastore         
	//  517  858:dup             
	//  518  859:bipush          6
	//  519  861:ldc2            #433 <Int 0x10102ad>
	//  520  864:iastore         
	//  521  865:dup             
	//  522  866:bipush          7
	//  523  868:ldc2            #495 <Int 0x7f010075>
	//  524  871:iastore         
	//  525  872:dup             
	//  526  873:bipush          8
	//  527  875:ldc2            #496 <Int 0x7f010076>
	//  528  878:iastore         
	//  529  879:dup             
	//  530  880:bipush          9
	//  531  882:ldc2            #497 <Int 0x7f010077>
	//  532  885:iastore         
	//  533  886:dup             
	//  534  887:bipush          10
	//  535  889:ldc2            #498 <Int 0x7f010078>
	//  536  892:iastore         
	//  537  893:putstatic       #500 <Field int[] Spinner>
	//  538  896:bipush          10
	//  539  898:newarray        int[]
	//  540  900:dup             
	//  541  901:iconst_0        
	//  542  902:ldc2            #501 <Int 0x1010124>
	//  543  905:iastore         
	//  544  906:dup             
	//  545  907:iconst_1        
	//  546  908:ldc2            #502 <Int 0x1010125>
	//  547  911:iastore         
	//  548  912:dup             
	//  549  913:iconst_2        
	//  550  914:ldc2            #503 <Int 0x1010142>
	//  551  917:iastore         
	//  552  918:dup             
	//  553  919:iconst_3        
	//  554  920:ldc2            #504 <Int 0x7f0100a2>
	//  555  923:iastore         
	//  556  924:dup             
	//  557  925:iconst_4        
	//  558  926:ldc2            #505 <Int 0x7f0100a3>
	//  559  929:iastore         
	//  560  930:dup             
	//  561  931:iconst_5        
	//  562  932:ldc2            #506 <Int 0x7f0100a4>
	//  563  935:iastore         
	//  564  936:dup             
	//  565  937:bipush          6
	//  566  939:ldc2            #507 <Int 0x7f0100a5>
	//  567  942:iastore         
	//  568  943:dup             
	//  569  944:bipush          7
	//  570  946:ldc2            #508 <Int 0x7f0100a6>
	//  571  949:iastore         
	//  572  950:dup             
	//  573  951:bipush          8
	//  574  953:ldc2            #509 <Int 0x7f0100a7>
	//  575  956:iastore         
	//  576  957:dup             
	//  577  958:bipush          9
	//  578  960:ldc2            #510 <Int 0x7f0100a8>
	//  579  963:iastore         
	//  580  964:putstatic       #512 <Field int[] SwitchCompat>
	//  581  967:bipush          83
	//  582  969:newarray        int[]
	//  583  971:dup             
	//  584  972:iconst_0        
	//  585  973:ldc2            #513 <Int 0x1010057>
	//  586  976:iastore         
	//  587  977:dup             
	//  588  978:iconst_1        
	//  589  979:ldc2            #514 <Int 0x7f010003>
	//  590  982:iastore         
	//  591  983:dup             
	//  592  984:iconst_2        
	//  593  985:ldc2            #515 <Int 0x7f010004>
	//  594  988:iastore         
	//  595  989:dup             
	//  596  990:iconst_3        
	//  597  991:ldc2            #516 <Int 0x7f010005>
	//  598  994:iastore         
	//  599  995:dup             
	//  600  996:iconst_4        
	//  601  997:ldc2            #517 <Int 0x7f010006>
	//  602 1000:iastore         
	//  603 1001:dup             
	//  604 1002:iconst_5        
	//  605 1003:ldc2            #518 <Int 0x7f010007>
	//  606 1006:iastore         
	//  607 1007:dup             
	//  608 1008:bipush          6
	//  609 1010:ldc2            #519 <Int 0x7f010008>
	//  610 1013:iastore         
	//  611 1014:dup             
	//  612 1015:bipush          7
	//  613 1017:ldc2            #520 <Int 0x7f010009>
	//  614 1020:iastore         
	//  615 1021:dup             
	//  616 1022:bipush          8
	//  617 1024:ldc2            #521 <Int 0x7f01000a>
	//  618 1027:iastore         
	//  619 1028:dup             
	//  620 1029:bipush          9
	//  621 1031:ldc2            #522 <Int 0x7f01000b>
	//  622 1034:iastore         
	//  623 1035:dup             
	//  624 1036:bipush          10
	//  625 1038:ldc2            #523 <Int 0x7f01000c>
	//  626 1041:iastore         
	//  627 1042:dup             
	//  628 1043:bipush          11
	//  629 1045:ldc2            #524 <Int 0x7f01000d>
	//  630 1048:iastore         
	//  631 1049:dup             
	//  632 1050:bipush          12
	//  633 1052:ldc2            #525 <Int 0x7f01000e>
	//  634 1055:iastore         
	//  635 1056:dup             
	//  636 1057:bipush          13
	//  637 1059:ldc2            #526 <Int 0x7f01000f>
	//  638 1062:iastore         
	//  639 1063:dup             
	//  640 1064:bipush          14
	//  641 1066:ldc2            #527 <Int 0x7f010010>
	//  642 1069:iastore         
	//  643 1070:dup             
	//  644 1071:bipush          15
	//  645 1073:ldc2            #528 <Int 0x7f010011>
	//  646 1076:iastore         
	//  647 1077:dup             
	//  648 1078:bipush          16
	//  649 1080:ldc2            #529 <Int 0x7f010012>
	//  650 1083:iastore         
	//  651 1084:dup             
	//  652 1085:bipush          17
	//  653 1087:ldc2            #530 <Int 0x7f010013>
	//  654 1090:iastore         
	//  655 1091:dup             
	//  656 1092:bipush          18
	//  657 1094:ldc2            #531 <Int 0x7f010014>
	//  658 1097:iastore         
	//  659 1098:dup             
	//  660 1099:bipush          19
	//  661 1101:ldc2            #532 <Int 0x7f010015>
	//  662 1104:iastore         
	//  663 1105:dup             
	//  664 1106:bipush          20
	//  665 1108:ldc2            #533 <Int 0x7f010016>
	//  666 1111:iastore         
	//  667 1112:dup             
	//  668 1113:bipush          21
	//  669 1115:ldc2            #534 <Int 0x7f010017>
	//  670 1118:iastore         
	//  671 1119:dup             
	//  672 1120:bipush          22
	//  673 1122:ldc2            #535 <Int 0x7f010018>
	//  674 1125:iastore         
	//  675 1126:dup             
	//  676 1127:bipush          23
	//  677 1129:ldc2            #536 <Int 0x7f010019>
	//  678 1132:iastore         
	//  679 1133:dup             
	//  680 1134:bipush          24
	//  681 1136:ldc2            #537 <Int 0x7f01001a>
	//  682 1139:iastore         
	//  683 1140:dup             
	//  684 1141:bipush          25
	//  685 1143:ldc2            #538 <Int 0x7f01001b>
	//  686 1146:iastore         
	//  687 1147:dup             
	//  688 1148:bipush          26
	//  689 1150:ldc2            #539 <Int 0x7f01001c>
	//  690 1153:iastore         
	//  691 1154:dup             
	//  692 1155:bipush          27
	//  693 1157:ldc2            #540 <Int 0x7f01001d>
	//  694 1160:iastore         
	//  695 1161:dup             
	//  696 1162:bipush          28
	//  697 1164:ldc2            #541 <Int 0x7f01001e>
	//  698 1167:iastore         
	//  699 1168:dup             
	//  700 1169:bipush          29
	//  701 1171:ldc2            #542 <Int 0x7f01001f>
	//  702 1174:iastore         
	//  703 1175:dup             
	//  704 1176:bipush          30
	//  705 1178:ldc2            #543 <Int 0x7f010020>
	//  706 1181:iastore         
	//  707 1182:dup             
	//  708 1183:bipush          31
	//  709 1185:ldc2            #544 <Int 0x7f010021>
	//  710 1188:iastore         
	//  711 1189:dup             
	//  712 1190:bipush          32
	//  713 1192:ldc2            #545 <Int 0x7f010022>
	//  714 1195:iastore         
	//  715 1196:dup             
	//  716 1197:bipush          33
	//  717 1199:ldc2            #546 <Int 0x7f010023>
	//  718 1202:iastore         
	//  719 1203:dup             
	//  720 1204:bipush          34
	//  721 1206:ldc2            #547 <Int 0x7f010024>
	//  722 1209:iastore         
	//  723 1210:dup             
	//  724 1211:bipush          35
	//  725 1213:ldc2            #548 <Int 0x7f010025>
	//  726 1216:iastore         
	//  727 1217:dup             
	//  728 1218:bipush          36
	//  729 1220:ldc2            #549 <Int 0x7f010026>
	//  730 1223:iastore         
	//  731 1224:dup             
	//  732 1225:bipush          37
	//  733 1227:ldc2            #550 <Int 0x7f010027>
	//  734 1230:iastore         
	//  735 1231:dup             
	//  736 1232:bipush          38
	//  737 1234:ldc2            #551 <Int 0x7f010028>
	//  738 1237:iastore         
	//  739 1238:dup             
	//  740 1239:bipush          39
	//  741 1241:ldc2            #552 <Int 0x7f010029>
	//  742 1244:iastore         
	//  743 1245:dup             
	//  744 1246:bipush          40
	//  745 1248:ldc2            #553 <Int 0x7f01002a>
	//  746 1251:iastore         
	//  747 1252:dup             
	//  748 1253:bipush          41
	//  749 1255:ldc2            #554 <Int 0x7f01002b>
	//  750 1258:iastore         
	//  751 1259:dup             
	//  752 1260:bipush          42
	//  753 1262:ldc2            #362 <Int 0x7f01002c>
	//  754 1265:iastore         
	//  755 1266:dup             
	//  756 1267:bipush          43
	//  757 1269:ldc2            #555 <Int 0x7f01002d>
	//  758 1272:iastore         
	//  759 1273:dup             
	//  760 1274:bipush          44
	//  761 1276:ldc2            #556 <Int 0x7f01002e>
	//  762 1279:iastore         
	//  763 1280:dup             
	//  764 1281:bipush          45
	//  765 1283:ldc2            #557 <Int 0x7f01002f>
	//  766 1286:iastore         
	//  767 1287:dup             
	//  768 1288:bipush          46
	//  769 1290:ldc2            #558 <Int 0x7f010030>
	//  770 1293:iastore         
	//  771 1294:dup             
	//  772 1295:bipush          47
	//  773 1297:ldc2            #559 <Int 0x7f010031>
	//  774 1300:iastore         
	//  775 1301:dup             
	//  776 1302:bipush          48
	//  777 1304:ldc2            #560 <Int 0x7f010032>
	//  778 1307:iastore         
	//  779 1308:dup             
	//  780 1309:bipush          49
	//  781 1311:ldc2            #561 <Int 0x7f010033>
	//  782 1314:iastore         
	//  783 1315:dup             
	//  784 1316:bipush          50
	//  785 1318:ldc2            #562 <Int 0x7f010034>
	//  786 1321:iastore         
	//  787 1322:dup             
	//  788 1323:bipush          51
	//  789 1325:ldc2            #563 <Int 0x7f010035>
	//  790 1328:iastore         
	//  791 1329:dup             
	//  792 1330:bipush          52
	//  793 1332:ldc2            #564 <Int 0x7f010036>
	//  794 1335:iastore         
	//  795 1336:dup             
	//  796 1337:bipush          53
	//  797 1339:ldc2            #565 <Int 0x7f010037>
	//  798 1342:iastore         
	//  799 1343:dup             
	//  800 1344:bipush          54
	//  801 1346:ldc2            #566 <Int 0x7f010038>
	//  802 1349:iastore         
	//  803 1350:dup             
	//  804 1351:bipush          55
	//  805 1353:ldc2            #567 <Int 0x7f010039>
	//  806 1356:iastore         
	//  807 1357:dup             
	//  808 1358:bipush          56
	//  809 1360:ldc2            #568 <Int 0x7f01003a>
	//  810 1363:iastore         
	//  811 1364:dup             
	//  812 1365:bipush          57
	//  813 1367:ldc2            #569 <Int 0x7f01003b>
	//  814 1370:iastore         
	//  815 1371:dup             
	//  816 1372:bipush          58
	//  817 1374:ldc2            #570 <Int 0x7f01003c>
	//  818 1377:iastore         
	//  819 1378:dup             
	//  820 1379:bipush          59
	//  821 1381:ldc2            #571 <Int 0x7f01003d>
	//  822 1384:iastore         
	//  823 1385:dup             
	//  824 1386:bipush          60
	//  825 1388:ldc2            #572 <Int 0x7f01003e>
	//  826 1391:iastore         
	//  827 1392:dup             
	//  828 1393:bipush          61
	//  829 1395:ldc2            #573 <Int 0x7f01003f>
	//  830 1398:iastore         
	//  831 1399:dup             
	//  832 1400:bipush          62
	//  833 1402:ldc2            #574 <Int 0x7f010040>
	//  834 1405:iastore         
	//  835 1406:dup             
	//  836 1407:bipush          63
	//  837 1409:ldc2            #575 <Int 0x7f010041>
	//  838 1412:iastore         
	//  839 1413:dup             
	//  840 1414:bipush          64
	//  841 1416:ldc2            #576 <Int 0x7f010042>
	//  842 1419:iastore         
	//  843 1420:dup             
	//  844 1421:bipush          65
	//  845 1423:ldc2            #577 <Int 0x7f010043>
	//  846 1426:iastore         
	//  847 1427:dup             
	//  848 1428:bipush          66
	//  849 1430:ldc2            #578 <Int 0x7f010044>
	//  850 1433:iastore         
	//  851 1434:dup             
	//  852 1435:bipush          67
	//  853 1437:ldc2            #579 <Int 0x7f010045>
	//  854 1440:iastore         
	//  855 1441:dup             
	//  856 1442:bipush          68
	//  857 1444:ldc2            #580 <Int 0x7f010046>
	//  858 1447:iastore         
	//  859 1448:dup             
	//  860 1449:bipush          69
	//  861 1451:ldc2            #581 <Int 0x7f010047>
	//  862 1454:iastore         
	//  863 1455:dup             
	//  864 1456:bipush          70
	//  865 1458:ldc2            #582 <Int 0x7f010048>
	//  866 1461:iastore         
	//  867 1462:dup             
	//  868 1463:bipush          71
	//  869 1465:ldc2            #583 <Int 0x7f010049>
	//  870 1468:iastore         
	//  871 1469:dup             
	//  872 1470:bipush          72
	//  873 1472:ldc2            #584 <Int 0x7f01004a>
	//  874 1475:iastore         
	//  875 1476:dup             
	//  876 1477:bipush          73
	//  877 1479:ldc2            #585 <Int 0x7f01004b>
	//  878 1482:iastore         
	//  879 1483:dup             
	//  880 1484:bipush          74
	//  881 1486:ldc2            #586 <Int 0x7f01004c>
	//  882 1489:iastore         
	//  883 1490:dup             
	//  884 1491:bipush          75
	//  885 1493:ldc2            #587 <Int 0x7f01004d>
	//  886 1496:iastore         
	//  887 1497:dup             
	//  888 1498:bipush          76
	//  889 1500:ldc2            #588 <Int 0x7f01004e>
	//  890 1503:iastore         
	//  891 1504:dup             
	//  892 1505:bipush          77
	//  893 1507:ldc2            #589 <Int 0x7f01004f>
	//  894 1510:iastore         
	//  895 1511:dup             
	//  896 1512:bipush          78
	//  897 1514:ldc2            #590 <Int 0x7f010050>
	//  898 1517:iastore         
	//  899 1518:dup             
	//  900 1519:bipush          79
	//  901 1521:ldc2            #591 <Int 0x7f010051>
	//  902 1524:iastore         
	//  903 1525:dup             
	//  904 1526:bipush          80
	//  905 1528:ldc2            #592 <Int 0x7f010052>
	//  906 1531:iastore         
	//  907 1532:dup             
	//  908 1533:bipush          81
	//  909 1535:ldc2            #593 <Int 0x7f010053>
	//  910 1538:iastore         
	//  911 1539:dup             
	//  912 1540:bipush          82
	//  913 1542:ldc2            #594 <Int 0x7f010054>
	//  914 1545:iastore         
	//  915 1546:putstatic       #596 <Field int[] Theme>
	//  916 1549:bipush          22
	//  917 1551:newarray        int[]
	//  918 1553:dup             
	//  919 1554:iconst_0        
	//  920 1555:ldc2            #417 <Int 0x10100af>
	//  921 1558:iastore         
	//  922 1559:dup             
	//  923 1560:iconst_1        
	//  924 1561:ldc2            #597 <Int 0x1010140>
	//  925 1564:iastore         
	//  926 1565:dup             
	//  927 1566:iconst_2        
	//  928 1567:ldc2            #360 <Int 0x7f010000>
	//  929 1570:iastore         
	//  930 1571:dup             
	//  931 1572:iconst_3        
	//  932 1573:ldc2            #365 <Int 0x7f010057>
	//  933 1576:iastore         
	//  934 1577:dup             
	//  935 1578:iconst_4        
	//  936 1579:ldc2            #381 <Int 0x7f010067>
	//  937 1582:iastore         
	//  938 1583:dup             
	//  939 1584:iconst_5        
	//  940 1585:ldc2            #382 <Int 0x7f010068>
	//  941 1588:iastore         
	//  942 1589:dup             
	//  943 1590:bipush          6
	//  944 1592:ldc2            #383 <Int 0x7f010069>
	//  945 1595:iastore         
	//  946 1596:dup             
	//  947 1597:bipush          7
	//  948 1599:ldc2            #384 <Int 0x7f01006a>
	//  949 1602:iastore         
	//  950 1603:dup             
	//  951 1604:bipush          8
	//  952 1606:ldc2            #386 <Int 0x7f01006c>
	//  953 1609:iastore         
	//  954 1610:dup             
	//  955 1611:bipush          9
	//  956 1613:ldc2            #598 <Int 0x7f01008a>
	//  957 1616:iastore         
	//  958 1617:dup             
	//  959 1618:bipush          10
	//  960 1620:ldc2            #599 <Int 0x7f01008b>
	//  961 1623:iastore         
	//  962 1624:dup             
	//  963 1625:bipush          11
	//  964 1627:ldc2            #600 <Int 0x7f01008c>
	//  965 1630:iastore         
	//  966 1631:dup             
	//  967 1632:bipush          12
	//  968 1634:ldc2            #601 <Int 0x7f01008d>
	//  969 1637:iastore         
	//  970 1638:dup             
	//  971 1639:bipush          13
	//  972 1641:ldc2            #602 <Int 0x7f01008e>
	//  973 1644:iastore         
	//  974 1645:dup             
	//  975 1646:bipush          14
	//  976 1648:ldc2            #603 <Int 0x7f01008f>
	//  977 1651:iastore         
	//  978 1652:dup             
	//  979 1653:bipush          15
	//  980 1655:ldc2            #604 <Int 0x7f010090>
	//  981 1658:iastore         
	//  982 1659:dup             
	//  983 1660:bipush          16
	//  984 1662:ldc2            #605 <Int 0x7f010091>
	//  985 1665:iastore         
	//  986 1666:dup             
	//  987 1667:bipush          17
	//  988 1669:ldc2            #606 <Int 0x7f010092>
	//  989 1672:iastore         
	//  990 1673:dup             
	//  991 1674:bipush          18
	//  992 1676:ldc2            #607 <Int 0x7f010093>
	//  993 1679:iastore         
	//  994 1680:dup             
	//  995 1681:bipush          19
	//  996 1683:ldc2            #608 <Int 0x7f010094>
	//  997 1686:iastore         
	//  998 1687:dup             
	//  999 1688:bipush          20
	// 1000 1690:ldc2            #609 <Int 0x7f010095>
	// 1001 1693:iastore         
	// 1002 1694:dup             
	// 1003 1695:bipush          21
	// 1004 1697:ldc2            #610 <Int 0x7f010096>
	// 1005 1700:iastore         
	// 1006 1701:putstatic       #612 <Field int[] Toolbar>
	// 1007 1704:iconst_3        
	// 1008 1705:newarray        int[]
	// 1009 1707:dup             
	// 1010 1708:iconst_0        
	// 1011 1709:ldc2            #475 <Int 0x10100da>
	// 1012 1712:iastore         
	// 1013 1713:dup             
	// 1014 1714:iconst_1        
	// 1015 1715:ldc2            #613 <Int 0x7f01006e>
	// 1016 1718:iastore         
	// 1017 1719:dup             
	// 1018 1720:iconst_2        
	// 1019 1721:ldc2            #614 <Int 0x7f01006f>
	// 1020 1724:iastore         
	// 1021 1725:putstatic       #616 <Field int[] View>
	// 1022 1728:iconst_3        
	// 1023 1729:newarray        int[]
	// 1024 1731:dup             
	// 1025 1732:iconst_0        
	// 1026 1733:ldc2            #437 <Int 0x10100d0>
	// 1027 1736:iastore         
	// 1028 1737:dup             
	// 1029 1738:iconst_1        
	// 1030 1739:ldc2            #617 <Int 0x10100f2>
	// 1031 1742:iastore         
	// 1032 1743:dup             
	// 1033 1744:iconst_2        
	// 1034 1745:ldc2            #618 <Int 0x10100f3>
	// 1035 1748:iastore         
	// 1036 1749:putstatic       #620 <Field int[] ViewStubCompat>
	//*1037 1752:return          
	}

	public R$styleable()
	{
	//    0    0:aload_0         
	//    1    1:invokespecial   #624 <Method void Object()>
	//    2    4:return          
	}
}
