// Decompiled by Jad v1.5.8g. Copyright 2001 Pavel Kouznetsov.
// Jad home page: http://www.kpdus.com/jad.html
// Decompiler options: packimports(3) annotate safe 

package com.google.android.gms.internal.ads;


// Referenced classes of package com.google.android.gms.internal.ads:
//			awj, awg, ajg, awn, 
//			awh, awp

public final class alu extends awj
{

	public alu()
	{
	//    0    0:aload_0         
	//    1    1:invokespecial   #33  <Method void awj()>
		a = null;
	//    2    4:aload_0         
	//    3    5:aconst_null     
	//    4    6:putfield        #35  <Field Long a>
		b = null;
	//    5    9:aload_0         
	//    6   10:aconst_null     
	//    7   11:putfield        #37  <Field Long b>
		c = null;
	//    8   14:aload_0         
	//    9   15:aconst_null     
	//   10   16:putfield        #39  <Field Long c>
		d = null;
	//   11   19:aload_0         
	//   12   20:aconst_null     
	//   13   21:putfield        #41  <Field Long d>
		e = null;
	//   14   24:aload_0         
	//   15   25:aconst_null     
	//   16   26:putfield        #43  <Field Long e>
		f = null;
	//   17   29:aload_0         
	//   18   30:aconst_null     
	//   19   31:putfield        #45  <Field Long f>
		h = null;
	//   20   34:aload_0         
	//   21   35:aconst_null     
	//   22   36:putfield        #47  <Field Long h>
		i = null;
	//   23   39:aload_0         
	//   24   40:aconst_null     
	//   25   41:putfield        #49  <Field Long i>
		j = null;
	//   26   44:aload_0         
	//   27   45:aconst_null     
	//   28   46:putfield        #51  <Field Long j>
		l = null;
	//   29   49:aload_0         
	//   30   50:aconst_null     
	//   31   51:putfield        #53  <Field Long l>
		m = null;
	//   32   54:aload_0         
	//   33   55:aconst_null     
	//   34   56:putfield        #55  <Field Long m>
		n = null;
	//   35   59:aload_0         
	//   36   60:aconst_null     
	//   37   61:putfield        #57  <Field Long n>
		o = null;
	//   38   64:aload_0         
	//   39   65:aconst_null     
	//   40   66:putfield        #59  <Field Long o>
		p = null;
	//   41   69:aload_0         
	//   42   70:aconst_null     
	//   43   71:putfield        #61  <Field Long p>
		q = null;
	//   44   74:aload_0         
	//   45   75:aconst_null     
	//   46   76:putfield        #63  <Field Long q>
		r = null;
	//   47   79:aload_0         
	//   48   80:aconst_null     
	//   49   81:putfield        #65  <Field Long r>
		s = null;
	//   50   84:aload_0         
	//   51   85:aconst_null     
	//   52   86:putfield        #67  <Field Long s>
		u = null;
	//   53   89:aload_0         
	//   54   90:aconst_null     
	//   55   91:putfield        #69  <Field Long u>
		v = null;
	//   56   94:aload_0         
	//   57   95:aconst_null     
	//   58   96:putfield        #71  <Field Long v>
		aa = -1;
	//   59   99:aload_0         
	//   60  100:iconst_m1       
	//   61  101:putfield        #75  <Field int aa>
	//   62  104:return          
	}

	private final alu b(awg awg1)
	{
_L25:
		int i1 = awg1.a();
	//    0    0:aload_1         
	//    1    1:invokevirtual   #84  <Method int awg.a()>
	//    2    4:istore_2        
		i1;
	//    3    5:iload_2         
		JVM INSTR lookupswitch 22: default 192
	//	               0: 543
	//	               8: 529
	//	               16: 515
	//	               24: 501
	//	               32: 487
	//	               40: 473
	//	               48: 459
	//	               56: 422
	//	               64: 408
	//	               72: 394
	//	               80: 380
	//	               88: 343
	//	               96: 329
	//	               104: 315
	//	               112: 301
	//	               120: 287
	//	               128: 273
	//	               136: 259
	//	               144: 245
	//	               152: 231
	//	               160: 217
	//	               168: 203;
	//    4    6:lookupswitch    22: default 192
	//	               0: 543
	//	               8: 529
	//	               16: 515
	//	               24: 501
	//	               32: 487
	//	               40: 473
	//	               48: 459
	//	               56: 422
	//	               64: 408
	//	               72: 394
	//	               80: 380
	//	               88: 343
	//	               96: 329
	//	               104: 315
	//	               112: 301
	//	               120: 287
	//	               128: 273
	//	               136: 259
	//	               144: 245
	//	               152: 231
	//	               160: 217
	//	               168: 203
		   goto _L1 _L2 _L3 _L4 _L5 _L6 _L7 _L8 _L9 _L10 _L11 _L12 _L13 _L14 _L15 _L16 _L17 _L18 _L19 _L20 _L21 _L22 _L23
_L1:
		if(super.a(awg1, i1)) goto _L25; else goto _L24
	//    5  192:aload_0         
	//    6  193:aload_1         
	//    7  194:iload_2         
	//    8  195:invokespecial   #87  <Method boolean awj.a(awg, int)>
	//    9  198:ifne            0
_L24:
		return this;
	//   10  201:aload_0         
	//   11  202:areturn         
_L23:
		v = Long.valueOf(awg1.h());
	//   12  203:aload_0         
	//   13  204:aload_1         
	//   14  205:invokevirtual   #90  <Method long awg.h()>
	//   15  208:invokestatic    #96  <Method Long Long.valueOf(long)>
	//   16  211:putfield        #71  <Field Long v>
		  goto _L25
	//*  17  214:goto            0
_L22:
		u = Long.valueOf(awg1.h());
	//   18  217:aload_0         
	//   19  218:aload_1         
	//   20  219:invokevirtual   #90  <Method long awg.h()>
	//   21  222:invokestatic    #96  <Method Long Long.valueOf(long)>
	//   22  225:putfield        #69  <Field Long u>
		  goto _L25
	//*  23  228:goto            0
_L21:
		s = Long.valueOf(awg1.h());
	//   24  231:aload_0         
	//   25  232:aload_1         
	//   26  233:invokevirtual   #90  <Method long awg.h()>
	//   27  236:invokestatic    #96  <Method Long Long.valueOf(long)>
	//   28  239:putfield        #67  <Field Long s>
		  goto _L25
	//*  29  242:goto            0
_L20:
		r = Long.valueOf(awg1.h());
	//   30  245:aload_0         
	//   31  246:aload_1         
	//   32  247:invokevirtual   #90  <Method long awg.h()>
	//   33  250:invokestatic    #96  <Method Long Long.valueOf(long)>
	//   34  253:putfield        #65  <Field Long r>
		  goto _L25
	//*  35  256:goto            0
_L19:
		q = Long.valueOf(awg1.h());
	//   36  259:aload_0         
	//   37  260:aload_1         
	//   38  261:invokevirtual   #90  <Method long awg.h()>
	//   39  264:invokestatic    #96  <Method Long Long.valueOf(long)>
	//   40  267:putfield        #63  <Field Long q>
		  goto _L25
	//*  41  270:goto            0
_L18:
		p = Long.valueOf(awg1.h());
	//   42  273:aload_0         
	//   43  274:aload_1         
	//   44  275:invokevirtual   #90  <Method long awg.h()>
	//   45  278:invokestatic    #96  <Method Long Long.valueOf(long)>
	//   46  281:putfield        #61  <Field Long p>
		  goto _L25
	//*  47  284:goto            0
_L17:
		o = Long.valueOf(awg1.h());
	//   48  287:aload_0         
	//   49  288:aload_1         
	//   50  289:invokevirtual   #90  <Method long awg.h()>
	//   51  292:invokestatic    #96  <Method Long Long.valueOf(long)>
	//   52  295:putfield        #59  <Field Long o>
		  goto _L25
	//*  53  298:goto            0
_L16:
		n = Long.valueOf(awg1.h());
	//   54  301:aload_0         
	//   55  302:aload_1         
	//   56  303:invokevirtual   #90  <Method long awg.h()>
	//   57  306:invokestatic    #96  <Method Long Long.valueOf(long)>
	//   58  309:putfield        #57  <Field Long n>
		  goto _L25
	//*  59  312:goto            0
_L15:
		m = Long.valueOf(awg1.h());
	//   60  315:aload_0         
	//   61  316:aload_1         
	//   62  317:invokevirtual   #90  <Method long awg.h()>
	//   63  320:invokestatic    #96  <Method Long Long.valueOf(long)>
	//   64  323:putfield        #55  <Field Long m>
		  goto _L25
	//*  65  326:goto            0
_L14:
		l = Long.valueOf(awg1.h());
	//   66  329:aload_0         
	//   67  330:aload_1         
	//   68  331:invokevirtual   #90  <Method long awg.h()>
	//   69  334:invokestatic    #96  <Method Long Long.valueOf(long)>
	//   70  337:putfield        #53  <Field Long l>
		  goto _L25
	//*  71  340:goto            0
_L13:
		int j1 = awg1.j();
	//   72  343:aload_1         
	//   73  344:invokevirtual   #98  <Method int awg.j()>
	//   74  347:istore_3        
		try
		{
			k = Integer.valueOf(ajg.a(awg1.g()));
	//   75  348:aload_0         
	//   76  349:aload_1         
	//   77  350:invokevirtual   #100 <Method int awg.g()>
	//   78  353:invokestatic    #105 <Method int ajg.a(int)>
	//   79  356:invokestatic    #110 <Method Integer Integer.valueOf(int)>
	//   80  359:putfield        #112 <Field Integer k>
		}
	//*  81  362:goto            0
	//*  82  365:aload_1         
	//*  83  366:iload_3         
	//*  84  367:invokevirtual   #115 <Method void awg.e(int)>
	//*  85  370:aload_0         
	//*  86  371:aload_1         
	//*  87  372:iload_2         
	//*  88  373:invokevirtual   #87  <Method boolean awj.a(awg, int)>
	//*  89  376:pop             
	//*  90  377:goto            0
	//*  91  380:aload_0         
	//*  92  381:aload_1         
	//*  93  382:invokevirtual   #90  <Method long awg.h()>
	//*  94  385:invokestatic    #96  <Method Long Long.valueOf(long)>
	//*  95  388:putfield        #51  <Field Long j>
	//*  96  391:goto            0
	//*  97  394:aload_0         
	//*  98  395:aload_1         
	//*  99  396:invokevirtual   #90  <Method long awg.h()>
	//* 100  399:invokestatic    #96  <Method Long Long.valueOf(long)>
	//* 101  402:putfield        #49  <Field Long i>
	//* 102  405:goto            0
	//* 103  408:aload_0         
	//* 104  409:aload_1         
	//* 105  410:invokevirtual   #90  <Method long awg.h()>
	//* 106  413:invokestatic    #96  <Method Long Long.valueOf(long)>
	//* 107  416:putfield        #47  <Field Long h>
	//* 108  419:goto            0
	//* 109  422:aload_1         
	//* 110  423:invokevirtual   #98  <Method int awg.j()>
	//* 111  426:istore_3        
	//* 112  427:aload_0         
	//* 113  428:aload_1         
	//* 114  429:invokevirtual   #100 <Method int awg.g()>
	//* 115  432:invokestatic    #105 <Method int ajg.a(int)>
	//* 116  435:invokestatic    #110 <Method Integer Integer.valueOf(int)>
	//* 117  438:putfield        #117 <Field Integer g>
	//* 118  441:goto            0
	//* 119  444:aload_1         
	//* 120  445:iload_3         
	//* 121  446:invokevirtual   #115 <Method void awg.e(int)>
	//* 122  449:aload_0         
	//* 123  450:aload_1         
	//* 124  451:iload_2         
	//* 125  452:invokevirtual   #87  <Method boolean awj.a(awg, int)>
	//* 126  455:pop             
	//* 127  456:goto            0
	//* 128  459:aload_0         
	//* 129  460:aload_1         
	//* 130  461:invokevirtual   #90  <Method long awg.h()>
	//* 131  464:invokestatic    #96  <Method Long Long.valueOf(long)>
	//* 132  467:putfield        #45  <Field Long f>
	//* 133  470:goto            0
	//* 134  473:aload_0         
	//* 135  474:aload_1         
	//* 136  475:invokevirtual   #90  <Method long awg.h()>
	//* 137  478:invokestatic    #96  <Method Long Long.valueOf(long)>
	//* 138  481:putfield        #43  <Field Long e>
	//* 139  484:goto            0
	//* 140  487:aload_0         
	//* 141  488:aload_1         
	//* 142  489:invokevirtual   #90  <Method long awg.h()>
	//* 143  492:invokestatic    #96  <Method Long Long.valueOf(long)>
	//* 144  495:putfield        #41  <Field Long d>
	//* 145  498:goto            0
	//* 146  501:aload_0         
	//* 147  502:aload_1         
	//* 148  503:invokevirtual   #90  <Method long awg.h()>
	//* 149  506:invokestatic    #96  <Method Long Long.valueOf(long)>
	//* 150  509:putfield        #39  <Field Long c>
	//* 151  512:goto            0
	//* 152  515:aload_0         
	//* 153  516:aload_1         
	//* 154  517:invokevirtual   #90  <Method long awg.h()>
	//* 155  520:invokestatic    #96  <Method Long Long.valueOf(long)>
	//* 156  523:putfield        #37  <Field Long b>
	//* 157  526:goto            0
	//* 158  529:aload_0         
	//* 159  530:aload_1         
	//* 160  531:invokevirtual   #90  <Method long awg.h()>
	//* 161  534:invokestatic    #96  <Method Long Long.valueOf(long)>
	//* 162  537:putfield        #35  <Field Long a>
	//* 163  540:goto            0
	//* 164  543:aload_0         
	//* 165  544:areturn         
		// Misplaced declaration of an exception variable
		catch(IllegalArgumentException illegalargumentexception)
		{
			awg1.e(j1);
			((awj)this).a(awg1, i1);
		}
		  goto _L25
_L12:
		j = Long.valueOf(awg1.h());
		  goto _L25
_L11:
		i = Long.valueOf(awg1.h());
		  goto _L25
_L10:
		h = Long.valueOf(awg1.h());
		  goto _L25
_L9:
		int k1 = awg1.j();
		try
		{
			g = Integer.valueOf(ajg.a(awg1.g()));
		}
	//* 166  545:astore          4
	//* 167  547:goto            365
		// Misplaced declaration of an exception variable
		catch(IllegalArgumentException illegalargumentexception)
		{
			awg1.e(k1);
			((awj)this).a(awg1, i1);
		}
		  goto _L25
_L8:
		f = Long.valueOf(awg1.h());
		  goto _L25
_L7:
		e = Long.valueOf(awg1.h());
		  goto _L25
_L6:
		d = Long.valueOf(awg1.h());
		  goto _L25
_L5:
		c = Long.valueOf(awg1.h());
		  goto _L25
_L4:
		b = Long.valueOf(awg1.h());
		  goto _L25
_L3:
		a = Long.valueOf(awg1.h());
		  goto _L25
_L2:
		IllegalArgumentException illegalargumentexception;
		return this;
	//* 168  550:astore          4
	//* 169  552:goto            444
	}

	public static alu[] b()
	{
		if(t == null)
	//*   0    0:getstatic       #120 <Field alu[] t>
	//*   1    3:ifnonnull       35
			synchronized(awn.b)
	//*   2    6:getstatic       #125 <Field Object awn.b>
	//*   3    9:astore_0        
	//*   4   10:aload_0         
	//*   5   11:monitorenter    
			{
				if(t == null)
	//*   6   12:getstatic       #120 <Field alu[] t>
	//*   7   15:ifnonnull       25
					t = new alu[0];
	//    8   18:iconst_0        
	//    9   19:anewarray       alu[]
	//   10   22:putstatic       #120 <Field alu[] t>
			}
	//   11   25:aload_0         
	//   12   26:monitorexit     
		break MISSING_BLOCK_LABEL_35;
	//   13   27:goto            35
		exception;
	//   14   30:astore_1        
		obj;
	//   15   31:aload_0         
		JVM INSTR monitorexit ;
	//   16   32:monitorexit     
		throw exception;
	//   17   33:aload_1         
	//   18   34:athrow          
		return t;
	//   19   35:getstatic       #120 <Field alu[] t>
	//   20   38:areturn         
	}

	protected final int a()
	{
		int j1 = super.a();
	//    0    0:aload_0         
	//    1    1:invokespecial   #126 <Method int awj.a()>
	//    2    4:istore_2        
		Object obj = ((Object) (a));
	//    3    5:aload_0         
	//    4    6:getfield        #35  <Field Long a>
	//    5    9:astore_3        
		int i1 = j1;
	//    6   10:iload_2         
	//    7   11:istore_1        
		if(obj != null)
	//*   8   12:aload_3         
	//*   9   13:ifnull          27
			i1 = j1 + awh.d(1, ((Long) (obj)).longValue());
	//   10   16:iload_2         
	//   11   17:iconst_1        
	//   12   18:aload_3         
	//   13   19:invokevirtual   #129 <Method long Long.longValue()>
	//   14   22:invokestatic    #134 <Method int awh.d(int, long)>
	//   15   25:iadd            
	//   16   26:istore_1        
		obj = ((Object) (b));
	//   17   27:aload_0         
	//   18   28:getfield        #37  <Field Long b>
	//   19   31:astore_3        
		j1 = i1;
	//   20   32:iload_1         
	//   21   33:istore_2        
		if(obj != null)
	//*  22   34:aload_3         
	//*  23   35:ifnull          49
			j1 = i1 + awh.d(2, ((Long) (obj)).longValue());
	//   24   38:iload_1         
	//   25   39:iconst_2        
	//   26   40:aload_3         
	//   27   41:invokevirtual   #129 <Method long Long.longValue()>
	//   28   44:invokestatic    #134 <Method int awh.d(int, long)>
	//   29   47:iadd            
	//   30   48:istore_2        
		obj = ((Object) (c));
	//   31   49:aload_0         
	//   32   50:getfield        #39  <Field Long c>
	//   33   53:astore_3        
		i1 = j1;
	//   34   54:iload_2         
	//   35   55:istore_1        
		if(obj != null)
	//*  36   56:aload_3         
	//*  37   57:ifnull          71
			i1 = j1 + awh.d(3, ((Long) (obj)).longValue());
	//   38   60:iload_2         
	//   39   61:iconst_3        
	//   40   62:aload_3         
	//   41   63:invokevirtual   #129 <Method long Long.longValue()>
	//   42   66:invokestatic    #134 <Method int awh.d(int, long)>
	//   43   69:iadd            
	//   44   70:istore_1        
		obj = ((Object) (d));
	//   45   71:aload_0         
	//   46   72:getfield        #41  <Field Long d>
	//   47   75:astore_3        
		j1 = i1;
	//   48   76:iload_1         
	//   49   77:istore_2        
		if(obj != null)
	//*  50   78:aload_3         
	//*  51   79:ifnull          93
			j1 = i1 + awh.d(4, ((Long) (obj)).longValue());
	//   52   82:iload_1         
	//   53   83:iconst_4        
	//   54   84:aload_3         
	//   55   85:invokevirtual   #129 <Method long Long.longValue()>
	//   56   88:invokestatic    #134 <Method int awh.d(int, long)>
	//   57   91:iadd            
	//   58   92:istore_2        
		obj = ((Object) (e));
	//   59   93:aload_0         
	//   60   94:getfield        #43  <Field Long e>
	//   61   97:astore_3        
		i1 = j1;
	//   62   98:iload_2         
	//   63   99:istore_1        
		if(obj != null)
	//*  64  100:aload_3         
	//*  65  101:ifnull          115
			i1 = j1 + awh.d(5, ((Long) (obj)).longValue());
	//   66  104:iload_2         
	//   67  105:iconst_5        
	//   68  106:aload_3         
	//   69  107:invokevirtual   #129 <Method long Long.longValue()>
	//   70  110:invokestatic    #134 <Method int awh.d(int, long)>
	//   71  113:iadd            
	//   72  114:istore_1        
		obj = ((Object) (f));
	//   73  115:aload_0         
	//   74  116:getfield        #45  <Field Long f>
	//   75  119:astore_3        
		j1 = i1;
	//   76  120:iload_1         
	//   77  121:istore_2        
		if(obj != null)
	//*  78  122:aload_3         
	//*  79  123:ifnull          138
			j1 = i1 + awh.d(6, ((Long) (obj)).longValue());
	//   80  126:iload_1         
	//   81  127:bipush          6
	//   82  129:aload_3         
	//   83  130:invokevirtual   #129 <Method long Long.longValue()>
	//   84  133:invokestatic    #134 <Method int awh.d(int, long)>
	//   85  136:iadd            
	//   86  137:istore_2        
		obj = ((Object) (g));
	//   87  138:aload_0         
	//   88  139:getfield        #117 <Field Integer g>
	//   89  142:astore_3        
		i1 = j1;
	//   90  143:iload_2         
	//   91  144:istore_1        
		if(obj != null)
	//*  92  145:aload_3         
	//*  93  146:ifnull          161
			i1 = j1 + awh.b(7, ((Integer) (obj)).intValue());
	//   94  149:iload_2         
	//   95  150:bipush          7
	//   96  152:aload_3         
	//   97  153:invokevirtual   #137 <Method int Integer.intValue()>
	//   98  156:invokestatic    #140 <Method int awh.b(int, int)>
	//   99  159:iadd            
	//  100  160:istore_1        
		obj = ((Object) (h));
	//  101  161:aload_0         
	//  102  162:getfield        #47  <Field Long h>
	//  103  165:astore_3        
		j1 = i1;
	//  104  166:iload_1         
	//  105  167:istore_2        
		if(obj != null)
	//* 106  168:aload_3         
	//* 107  169:ifnull          184
			j1 = i1 + awh.d(8, ((Long) (obj)).longValue());
	//  108  172:iload_1         
	//  109  173:bipush          8
	//  110  175:aload_3         
	//  111  176:invokevirtual   #129 <Method long Long.longValue()>
	//  112  179:invokestatic    #134 <Method int awh.d(int, long)>
	//  113  182:iadd            
	//  114  183:istore_2        
		obj = ((Object) (i));
	//  115  184:aload_0         
	//  116  185:getfield        #49  <Field Long i>
	//  117  188:astore_3        
		i1 = j1;
	//  118  189:iload_2         
	//  119  190:istore_1        
		if(obj != null)
	//* 120  191:aload_3         
	//* 121  192:ifnull          207
			i1 = j1 + awh.d(9, ((Long) (obj)).longValue());
	//  122  195:iload_2         
	//  123  196:bipush          9
	//  124  198:aload_3         
	//  125  199:invokevirtual   #129 <Method long Long.longValue()>
	//  126  202:invokestatic    #134 <Method int awh.d(int, long)>
	//  127  205:iadd            
	//  128  206:istore_1        
		obj = ((Object) (j));
	//  129  207:aload_0         
	//  130  208:getfield        #51  <Field Long j>
	//  131  211:astore_3        
		j1 = i1;
	//  132  212:iload_1         
	//  133  213:istore_2        
		if(obj != null)
	//* 134  214:aload_3         
	//* 135  215:ifnull          230
			j1 = i1 + awh.d(10, ((Long) (obj)).longValue());
	//  136  218:iload_1         
	//  137  219:bipush          10
	//  138  221:aload_3         
	//  139  222:invokevirtual   #129 <Method long Long.longValue()>
	//  140  225:invokestatic    #134 <Method int awh.d(int, long)>
	//  141  228:iadd            
	//  142  229:istore_2        
		obj = ((Object) (k));
	//  143  230:aload_0         
	//  144  231:getfield        #112 <Field Integer k>
	//  145  234:astore_3        
		i1 = j1;
	//  146  235:iload_2         
	//  147  236:istore_1        
		if(obj != null)
	//* 148  237:aload_3         
	//* 149  238:ifnull          253
			i1 = j1 + awh.b(11, ((Integer) (obj)).intValue());
	//  150  241:iload_2         
	//  151  242:bipush          11
	//  152  244:aload_3         
	//  153  245:invokevirtual   #137 <Method int Integer.intValue()>
	//  154  248:invokestatic    #140 <Method int awh.b(int, int)>
	//  155  251:iadd            
	//  156  252:istore_1        
		obj = ((Object) (l));
	//  157  253:aload_0         
	//  158  254:getfield        #53  <Field Long l>
	//  159  257:astore_3        
		j1 = i1;
	//  160  258:iload_1         
	//  161  259:istore_2        
		if(obj != null)
	//* 162  260:aload_3         
	//* 163  261:ifnull          276
			j1 = i1 + awh.d(12, ((Long) (obj)).longValue());
	//  164  264:iload_1         
	//  165  265:bipush          12
	//  166  267:aload_3         
	//  167  268:invokevirtual   #129 <Method long Long.longValue()>
	//  168  271:invokestatic    #134 <Method int awh.d(int, long)>
	//  169  274:iadd            
	//  170  275:istore_2        
		obj = ((Object) (m));
	//  171  276:aload_0         
	//  172  277:getfield        #55  <Field Long m>
	//  173  280:astore_3        
		i1 = j1;
	//  174  281:iload_2         
	//  175  282:istore_1        
		if(obj != null)
	//* 176  283:aload_3         
	//* 177  284:ifnull          299
			i1 = j1 + awh.d(13, ((Long) (obj)).longValue());
	//  178  287:iload_2         
	//  179  288:bipush          13
	//  180  290:aload_3         
	//  181  291:invokevirtual   #129 <Method long Long.longValue()>
	//  182  294:invokestatic    #134 <Method int awh.d(int, long)>
	//  183  297:iadd            
	//  184  298:istore_1        
		obj = ((Object) (n));
	//  185  299:aload_0         
	//  186  300:getfield        #57  <Field Long n>
	//  187  303:astore_3        
		j1 = i1;
	//  188  304:iload_1         
	//  189  305:istore_2        
		if(obj != null)
	//* 190  306:aload_3         
	//* 191  307:ifnull          322
			j1 = i1 + awh.d(14, ((Long) (obj)).longValue());
	//  192  310:iload_1         
	//  193  311:bipush          14
	//  194  313:aload_3         
	//  195  314:invokevirtual   #129 <Method long Long.longValue()>
	//  196  317:invokestatic    #134 <Method int awh.d(int, long)>
	//  197  320:iadd            
	//  198  321:istore_2        
		obj = ((Object) (o));
	//  199  322:aload_0         
	//  200  323:getfield        #59  <Field Long o>
	//  201  326:astore_3        
		i1 = j1;
	//  202  327:iload_2         
	//  203  328:istore_1        
		if(obj != null)
	//* 204  329:aload_3         
	//* 205  330:ifnull          345
			i1 = j1 + awh.d(15, ((Long) (obj)).longValue());
	//  206  333:iload_2         
	//  207  334:bipush          15
	//  208  336:aload_3         
	//  209  337:invokevirtual   #129 <Method long Long.longValue()>
	//  210  340:invokestatic    #134 <Method int awh.d(int, long)>
	//  211  343:iadd            
	//  212  344:istore_1        
		obj = ((Object) (p));
	//  213  345:aload_0         
	//  214  346:getfield        #61  <Field Long p>
	//  215  349:astore_3        
		j1 = i1;
	//  216  350:iload_1         
	//  217  351:istore_2        
		if(obj != null)
	//* 218  352:aload_3         
	//* 219  353:ifnull          368
			j1 = i1 + awh.d(16, ((Long) (obj)).longValue());
	//  220  356:iload_1         
	//  221  357:bipush          16
	//  222  359:aload_3         
	//  223  360:invokevirtual   #129 <Method long Long.longValue()>
	//  224  363:invokestatic    #134 <Method int awh.d(int, long)>
	//  225  366:iadd            
	//  226  367:istore_2        
		obj = ((Object) (q));
	//  227  368:aload_0         
	//  228  369:getfield        #63  <Field Long q>
	//  229  372:astore_3        
		i1 = j1;
	//  230  373:iload_2         
	//  231  374:istore_1        
		if(obj != null)
	//* 232  375:aload_3         
	//* 233  376:ifnull          391
			i1 = j1 + awh.d(17, ((Long) (obj)).longValue());
	//  234  379:iload_2         
	//  235  380:bipush          17
	//  236  382:aload_3         
	//  237  383:invokevirtual   #129 <Method long Long.longValue()>
	//  238  386:invokestatic    #134 <Method int awh.d(int, long)>
	//  239  389:iadd            
	//  240  390:istore_1        
		obj = ((Object) (r));
	//  241  391:aload_0         
	//  242  392:getfield        #65  <Field Long r>
	//  243  395:astore_3        
		j1 = i1;
	//  244  396:iload_1         
	//  245  397:istore_2        
		if(obj != null)
	//* 246  398:aload_3         
	//* 247  399:ifnull          414
			j1 = i1 + awh.d(18, ((Long) (obj)).longValue());
	//  248  402:iload_1         
	//  249  403:bipush          18
	//  250  405:aload_3         
	//  251  406:invokevirtual   #129 <Method long Long.longValue()>
	//  252  409:invokestatic    #134 <Method int awh.d(int, long)>
	//  253  412:iadd            
	//  254  413:istore_2        
		obj = ((Object) (s));
	//  255  414:aload_0         
	//  256  415:getfield        #67  <Field Long s>
	//  257  418:astore_3        
		i1 = j1;
	//  258  419:iload_2         
	//  259  420:istore_1        
		if(obj != null)
	//* 260  421:aload_3         
	//* 261  422:ifnull          437
			i1 = j1 + awh.d(19, ((Long) (obj)).longValue());
	//  262  425:iload_2         
	//  263  426:bipush          19
	//  264  428:aload_3         
	//  265  429:invokevirtual   #129 <Method long Long.longValue()>
	//  266  432:invokestatic    #134 <Method int awh.d(int, long)>
	//  267  435:iadd            
	//  268  436:istore_1        
		obj = ((Object) (u));
	//  269  437:aload_0         
	//  270  438:getfield        #69  <Field Long u>
	//  271  441:astore_3        
		j1 = i1;
	//  272  442:iload_1         
	//  273  443:istore_2        
		if(obj != null)
	//* 274  444:aload_3         
	//* 275  445:ifnull          460
			j1 = i1 + awh.d(20, ((Long) (obj)).longValue());
	//  276  448:iload_1         
	//  277  449:bipush          20
	//  278  451:aload_3         
	//  279  452:invokevirtual   #129 <Method long Long.longValue()>
	//  280  455:invokestatic    #134 <Method int awh.d(int, long)>
	//  281  458:iadd            
	//  282  459:istore_2        
		obj = ((Object) (v));
	//  283  460:aload_0         
	//  284  461:getfield        #71  <Field Long v>
	//  285  464:astore_3        
		i1 = j1;
	//  286  465:iload_2         
	//  287  466:istore_1        
		if(obj != null)
	//* 288  467:aload_3         
	//* 289  468:ifnull          483
			i1 = j1 + awh.d(21, ((Long) (obj)).longValue());
	//  290  471:iload_2         
	//  291  472:bipush          21
	//  292  474:aload_3         
	//  293  475:invokevirtual   #129 <Method long Long.longValue()>
	//  294  478:invokestatic    #134 <Method int awh.d(int, long)>
	//  295  481:iadd            
	//  296  482:istore_1        
		return i1;
	//  297  483:iload_1         
	//  298  484:ireturn         
	}

	public final awp a(awg awg1)
	{
		return ((awp) (b(awg1)));
	//    0    0:aload_0         
	//    1    1:aload_1         
	//    2    2:invokespecial   #143 <Method alu b(awg)>
	//    3    5:areturn         
	}

	public final void a(awh awh1)
	{
		Object obj = ((Object) (a));
	//    0    0:aload_0         
	//    1    1:getfield        #35  <Field Long a>
	//    2    4:astore_2        
		if(obj != null)
	//*   3    5:aload_2         
	//*   4    6:ifnull          18
			awh1.b(1, ((Long) (obj)).longValue());
	//    5    9:aload_1         
	//    6   10:iconst_1        
	//    7   11:aload_2         
	//    8   12:invokevirtual   #129 <Method long Long.longValue()>
	//    9   15:invokevirtual   #147 <Method void awh.b(int, long)>
		obj = ((Object) (b));
	//   10   18:aload_0         
	//   11   19:getfield        #37  <Field Long b>
	//   12   22:astore_2        
		if(obj != null)
	//*  13   23:aload_2         
	//*  14   24:ifnull          36
			awh1.b(2, ((Long) (obj)).longValue());
	//   15   27:aload_1         
	//   16   28:iconst_2        
	//   17   29:aload_2         
	//   18   30:invokevirtual   #129 <Method long Long.longValue()>
	//   19   33:invokevirtual   #147 <Method void awh.b(int, long)>
		obj = ((Object) (c));
	//   20   36:aload_0         
	//   21   37:getfield        #39  <Field Long c>
	//   22   40:astore_2        
		if(obj != null)
	//*  23   41:aload_2         
	//*  24   42:ifnull          54
			awh1.b(3, ((Long) (obj)).longValue());
	//   25   45:aload_1         
	//   26   46:iconst_3        
	//   27   47:aload_2         
	//   28   48:invokevirtual   #129 <Method long Long.longValue()>
	//   29   51:invokevirtual   #147 <Method void awh.b(int, long)>
		obj = ((Object) (d));
	//   30   54:aload_0         
	//   31   55:getfield        #41  <Field Long d>
	//   32   58:astore_2        
		if(obj != null)
	//*  33   59:aload_2         
	//*  34   60:ifnull          72
			awh1.b(4, ((Long) (obj)).longValue());
	//   35   63:aload_1         
	//   36   64:iconst_4        
	//   37   65:aload_2         
	//   38   66:invokevirtual   #129 <Method long Long.longValue()>
	//   39   69:invokevirtual   #147 <Method void awh.b(int, long)>
		obj = ((Object) (e));
	//   40   72:aload_0         
	//   41   73:getfield        #43  <Field Long e>
	//   42   76:astore_2        
		if(obj != null)
	//*  43   77:aload_2         
	//*  44   78:ifnull          90
			awh1.b(5, ((Long) (obj)).longValue());
	//   45   81:aload_1         
	//   46   82:iconst_5        
	//   47   83:aload_2         
	//   48   84:invokevirtual   #129 <Method long Long.longValue()>
	//   49   87:invokevirtual   #147 <Method void awh.b(int, long)>
		obj = ((Object) (f));
	//   50   90:aload_0         
	//   51   91:getfield        #45  <Field Long f>
	//   52   94:astore_2        
		if(obj != null)
	//*  53   95:aload_2         
	//*  54   96:ifnull          109
			awh1.b(6, ((Long) (obj)).longValue());
	//   55   99:aload_1         
	//   56  100:bipush          6
	//   57  102:aload_2         
	//   58  103:invokevirtual   #129 <Method long Long.longValue()>
	//   59  106:invokevirtual   #147 <Method void awh.b(int, long)>
		obj = ((Object) (g));
	//   60  109:aload_0         
	//   61  110:getfield        #117 <Field Integer g>
	//   62  113:astore_2        
		if(obj != null)
	//*  63  114:aload_2         
	//*  64  115:ifnull          128
			awh1.a(7, ((Integer) (obj)).intValue());
	//   65  118:aload_1         
	//   66  119:bipush          7
	//   67  121:aload_2         
	//   68  122:invokevirtual   #137 <Method int Integer.intValue()>
	//   69  125:invokevirtual   #150 <Method void awh.a(int, int)>
		obj = ((Object) (h));
	//   70  128:aload_0         
	//   71  129:getfield        #47  <Field Long h>
	//   72  132:astore_2        
		if(obj != null)
	//*  73  133:aload_2         
	//*  74  134:ifnull          147
			awh1.b(8, ((Long) (obj)).longValue());
	//   75  137:aload_1         
	//   76  138:bipush          8
	//   77  140:aload_2         
	//   78  141:invokevirtual   #129 <Method long Long.longValue()>
	//   79  144:invokevirtual   #147 <Method void awh.b(int, long)>
		obj = ((Object) (i));
	//   80  147:aload_0         
	//   81  148:getfield        #49  <Field Long i>
	//   82  151:astore_2        
		if(obj != null)
	//*  83  152:aload_2         
	//*  84  153:ifnull          166
			awh1.b(9, ((Long) (obj)).longValue());
	//   85  156:aload_1         
	//   86  157:bipush          9
	//   87  159:aload_2         
	//   88  160:invokevirtual   #129 <Method long Long.longValue()>
	//   89  163:invokevirtual   #147 <Method void awh.b(int, long)>
		obj = ((Object) (j));
	//   90  166:aload_0         
	//   91  167:getfield        #51  <Field Long j>
	//   92  170:astore_2        
		if(obj != null)
	//*  93  171:aload_2         
	//*  94  172:ifnull          185
			awh1.b(10, ((Long) (obj)).longValue());
	//   95  175:aload_1         
	//   96  176:bipush          10
	//   97  178:aload_2         
	//   98  179:invokevirtual   #129 <Method long Long.longValue()>
	//   99  182:invokevirtual   #147 <Method void awh.b(int, long)>
		obj = ((Object) (k));
	//  100  185:aload_0         
	//  101  186:getfield        #112 <Field Integer k>
	//  102  189:astore_2        
		if(obj != null)
	//* 103  190:aload_2         
	//* 104  191:ifnull          204
			awh1.a(11, ((Integer) (obj)).intValue());
	//  105  194:aload_1         
	//  106  195:bipush          11
	//  107  197:aload_2         
	//  108  198:invokevirtual   #137 <Method int Integer.intValue()>
	//  109  201:invokevirtual   #150 <Method void awh.a(int, int)>
		obj = ((Object) (l));
	//  110  204:aload_0         
	//  111  205:getfield        #53  <Field Long l>
	//  112  208:astore_2        
		if(obj != null)
	//* 113  209:aload_2         
	//* 114  210:ifnull          223
			awh1.b(12, ((Long) (obj)).longValue());
	//  115  213:aload_1         
	//  116  214:bipush          12
	//  117  216:aload_2         
	//  118  217:invokevirtual   #129 <Method long Long.longValue()>
	//  119  220:invokevirtual   #147 <Method void awh.b(int, long)>
		obj = ((Object) (m));
	//  120  223:aload_0         
	//  121  224:getfield        #55  <Field Long m>
	//  122  227:astore_2        
		if(obj != null)
	//* 123  228:aload_2         
	//* 124  229:ifnull          242
			awh1.b(13, ((Long) (obj)).longValue());
	//  125  232:aload_1         
	//  126  233:bipush          13
	//  127  235:aload_2         
	//  128  236:invokevirtual   #129 <Method long Long.longValue()>
	//  129  239:invokevirtual   #147 <Method void awh.b(int, long)>
		obj = ((Object) (n));
	//  130  242:aload_0         
	//  131  243:getfield        #57  <Field Long n>
	//  132  246:astore_2        
		if(obj != null)
	//* 133  247:aload_2         
	//* 134  248:ifnull          261
			awh1.b(14, ((Long) (obj)).longValue());
	//  135  251:aload_1         
	//  136  252:bipush          14
	//  137  254:aload_2         
	//  138  255:invokevirtual   #129 <Method long Long.longValue()>
	//  139  258:invokevirtual   #147 <Method void awh.b(int, long)>
		obj = ((Object) (o));
	//  140  261:aload_0         
	//  141  262:getfield        #59  <Field Long o>
	//  142  265:astore_2        
		if(obj != null)
	//* 143  266:aload_2         
	//* 144  267:ifnull          280
			awh1.b(15, ((Long) (obj)).longValue());
	//  145  270:aload_1         
	//  146  271:bipush          15
	//  147  273:aload_2         
	//  148  274:invokevirtual   #129 <Method long Long.longValue()>
	//  149  277:invokevirtual   #147 <Method void awh.b(int, long)>
		obj = ((Object) (p));
	//  150  280:aload_0         
	//  151  281:getfield        #61  <Field Long p>
	//  152  284:astore_2        
		if(obj != null)
	//* 153  285:aload_2         
	//* 154  286:ifnull          299
			awh1.b(16, ((Long) (obj)).longValue());
	//  155  289:aload_1         
	//  156  290:bipush          16
	//  157  292:aload_2         
	//  158  293:invokevirtual   #129 <Method long Long.longValue()>
	//  159  296:invokevirtual   #147 <Method void awh.b(int, long)>
		obj = ((Object) (q));
	//  160  299:aload_0         
	//  161  300:getfield        #63  <Field Long q>
	//  162  303:astore_2        
		if(obj != null)
	//* 163  304:aload_2         
	//* 164  305:ifnull          318
			awh1.b(17, ((Long) (obj)).longValue());
	//  165  308:aload_1         
	//  166  309:bipush          17
	//  167  311:aload_2         
	//  168  312:invokevirtual   #129 <Method long Long.longValue()>
	//  169  315:invokevirtual   #147 <Method void awh.b(int, long)>
		obj = ((Object) (r));
	//  170  318:aload_0         
	//  171  319:getfield        #65  <Field Long r>
	//  172  322:astore_2        
		if(obj != null)
	//* 173  323:aload_2         
	//* 174  324:ifnull          337
			awh1.b(18, ((Long) (obj)).longValue());
	//  175  327:aload_1         
	//  176  328:bipush          18
	//  177  330:aload_2         
	//  178  331:invokevirtual   #129 <Method long Long.longValue()>
	//  179  334:invokevirtual   #147 <Method void awh.b(int, long)>
		obj = ((Object) (s));
	//  180  337:aload_0         
	//  181  338:getfield        #67  <Field Long s>
	//  182  341:astore_2        
		if(obj != null)
	//* 183  342:aload_2         
	//* 184  343:ifnull          356
			awh1.b(19, ((Long) (obj)).longValue());
	//  185  346:aload_1         
	//  186  347:bipush          19
	//  187  349:aload_2         
	//  188  350:invokevirtual   #129 <Method long Long.longValue()>
	//  189  353:invokevirtual   #147 <Method void awh.b(int, long)>
		obj = ((Object) (u));
	//  190  356:aload_0         
	//  191  357:getfield        #69  <Field Long u>
	//  192  360:astore_2        
		if(obj != null)
	//* 193  361:aload_2         
	//* 194  362:ifnull          375
			awh1.b(20, ((Long) (obj)).longValue());
	//  195  365:aload_1         
	//  196  366:bipush          20
	//  197  368:aload_2         
	//  198  369:invokevirtual   #129 <Method long Long.longValue()>
	//  199  372:invokevirtual   #147 <Method void awh.b(int, long)>
		obj = ((Object) (v));
	//  200  375:aload_0         
	//  201  376:getfield        #71  <Field Long v>
	//  202  379:astore_2        
		if(obj != null)
	//* 203  380:aload_2         
	//* 204  381:ifnull          394
			awh1.b(21, ((Long) (obj)).longValue());
	//  205  384:aload_1         
	//  206  385:bipush          21
	//  207  387:aload_2         
	//  208  388:invokevirtual   #129 <Method long Long.longValue()>
	//  209  391:invokevirtual   #147 <Method void awh.b(int, long)>
		super.a(awh1);
	//  210  394:aload_0         
	//  211  395:aload_1         
	//  212  396:invokespecial   #152 <Method void awj.a(awh)>
	//  213  399:return          
	}

	private static volatile alu t[];
	public Long a;
	public Long b;
	public Long c;
	public Long d;
	public Long e;
	public Long f;
	public Integer g;
	public Long h;
	public Long i;
	public Long j;
	public Integer k;
	public Long l;
	public Long m;
	public Long n;
	public Long o;
	public Long p;
	public Long q;
	public Long r;
	public Long s;
	private Long u;
	private Long v;
}
