// Decompiled by Jad v1.5.8g. Copyright 2001 Pavel Kouznetsov.
// Jad home page: http://www.kpdus.com/jad.html
// Decompiler options: packimports(3) annotate safe 

package com.google.android.gms.internal.ads;


// Referenced classes of package com.google.android.gms.internal.ads:
//			awj, bss, bvk, awg, 
//			awt, btg, bte, btm, 
//			bto, bsx, bvf, bsv, 
//			buv, awh, arh, awp

public final class bve extends awj
{

	public bve()
	{
	//    0    0:aload_0         
	//    1    1:invokespecial   #30  <Method void awj()>
		a = null;
	//    2    4:aload_0         
	//    3    5:aconst_null     
	//    4    6:putfield        #32  <Field Integer a>
		c = null;
	//    5    9:aload_0         
	//    6   10:aconst_null     
	//    7   11:putfield        #34  <Field buv c>
		d = null;
	//    8   14:aload_0         
	//    9   15:aconst_null     
	//   10   16:putfield        #36  <Field bsv d>
		b = null;
	//   11   19:aload_0         
	//   12   20:aconst_null     
	//   13   21:putfield        #38  <Field bvf b>
		e = new bss[0];
	//   14   24:aload_0         
	//   15   25:iconst_0        
	//   16   26:anewarray       bss[]
	//   17   29:putfield        #42  <Field bss[] e>
		f = null;
	//   18   32:aload_0         
	//   19   33:aconst_null     
	//   20   34:putfield        #44  <Field bsx f>
		g = null;
	//   21   37:aload_0         
	//   22   38:aconst_null     
	//   23   39:putfield        #46  <Field bto g>
		h = null;
	//   24   42:aload_0         
	//   25   43:aconst_null     
	//   26   44:putfield        #48  <Field btm h>
		i = null;
	//   27   47:aload_0         
	//   28   48:aconst_null     
	//   29   49:putfield        #50  <Field bte i>
		j = null;
	//   30   52:aload_0         
	//   31   53:aconst_null     
	//   32   54:putfield        #52  <Field btg j>
		k = bvk.b();
	//   33   57:aload_0         
	//   34   58:invokestatic    #57  <Method bvk[] bvk.b()>
	//   35   61:putfield        #59  <Field bvk[] k>
		Z = null;
	//   36   64:aload_0         
	//   37   65:aconst_null     
	//   38   66:putfield        #63  <Field awl Z>
		aa = -1;
	//   39   69:aload_0         
	//   40   70:iconst_m1       
	//   41   71:putfield        #67  <Field int aa>
	//   42   74:return          
	}

	private final bve b(awg awg1)
	{
_L15:
		int l = awg1.a();
	//    0    0:aload_1         
	//    1    1:invokevirtual   #76  <Method int awg.a()>
	//    2    4:istore_2        
		l;
	//    3    5:iload_2         
		JVM INSTR lookupswitch 12: default 112
	//	               0: 653
	//	               56: 563
	//	               64: 491
	//	               74: 474
	//	               82: 445
	//	               90: 332
	//	               98: 315
	//	               106: 298
	//	               114: 281
	//	               122: 264
	//	               130: 247
	//	               138: 123;
	//    4    6:lookupswitch    12: default 112
	//	               0: 653
	//	               56: 563
	//	               64: 491
	//	               74: 474
	//	               82: 445
	//	               90: 332
	//	               98: 315
	//	               106: 298
	//	               114: 281
	//	               122: 264
	//	               130: 247
	//	               138: 123
		   goto _L1 _L2 _L3 _L4 _L5 _L6 _L7 _L8 _L9 _L10 _L11 _L12 _L13
_L1:
		if(super.a(awg1, l)) goto _L15; else goto _L14
	//    5  112:aload_0         
	//    6  113:aload_1         
	//    7  114:iload_2         
	//    8  115:invokespecial   #79  <Method boolean awj.a(awg, int)>
	//    9  118:ifne            0
_L14:
		return this;
	//   10  121:aload_0         
	//   11  122:areturn         
_L13:
		int i1 = awt.a(awg1, 138);
	//   12  123:aload_1         
	//   13  124:sipush          138
	//   14  127:invokestatic    #84  <Method int awt.a(awg, int)>
	//   15  130:istore_3        
		bvk abvk[] = k;
	//   16  131:aload_0         
	//   17  132:getfield        #59  <Field bvk[] k>
	//   18  135:astore          5
		if(abvk == null)
	//*  19  137:aload           5
	//*  20  139:ifnonnull       147
			l = 0;
	//   21  142:iconst_0        
	//   22  143:istore_2        
		else
	//*  23  144:goto            151
			l = abvk.length;
	//   24  147:aload           5
	//   25  149:arraylength     
	//   26  150:istore_2        
		abvk = new bvk[i1 + l];
	//   27  151:iload_3         
	//   28  152:iload_2         
	//   29  153:iadd            
	//   30  154:anewarray       bvk[]
	//   31  157:astore          5
		i1 = l;
	//   32  159:iload_2         
	//   33  160:istore_3        
		if(l != 0)
	//*  34  161:iload_2         
	//*  35  162:ifeq            179
		{
			System.arraycopy(((Object) (k)), 0, ((Object) (abvk)), 0, l);
	//   36  165:aload_0         
	//   37  166:getfield        #59  <Field bvk[] k>
	//   38  169:iconst_0        
	//   39  170:aload           5
	//   40  172:iconst_0        
	//   41  173:iload_2         
	//   42  174:invokestatic    #90  <Method void System.arraycopy(Object, int, Object, int, int)>
			i1 = l;
	//   43  177:iload_2         
	//   44  178:istore_3        
		}
		for(; i1 < abvk.length - 1; i1++)
	//*  45  179:iload_3         
	//*  46  180:aload           5
	//*  47  182:arraylength     
	//*  48  183:iconst_1        
	//*  49  184:isub            
	//*  50  185:icmpge          219
		{
			abvk[i1] = new bvk();
	//   51  188:aload           5
	//   52  190:iload_3         
	//   53  191:new             #54  <Class bvk>
	//   54  194:dup             
	//   55  195:invokespecial   #91  <Method void bvk()>
	//   56  198:aastore         
			awg1.a(((awp) (abvk[i1])));
	//   57  199:aload_1         
	//   58  200:aload           5
	//   59  202:iload_3         
	//   60  203:aaload          
	//   61  204:invokevirtual   #94  <Method void awg.a(awp)>
			awg1.a();
	//   62  207:aload_1         
	//   63  208:invokevirtual   #76  <Method int awg.a()>
	//   64  211:pop             
		}

	//   65  212:iload_3         
	//   66  213:iconst_1        
	//   67  214:iadd            
	//   68  215:istore_3        
	//*  69  216:goto            179
		abvk[i1] = new bvk();
	//   70  219:aload           5
	//   71  221:iload_3         
	//   72  222:new             #54  <Class bvk>
	//   73  225:dup             
	//   74  226:invokespecial   #91  <Method void bvk()>
	//   75  229:aastore         
		awg1.a(((awp) (abvk[i1])));
	//   76  230:aload_1         
	//   77  231:aload           5
	//   78  233:iload_3         
	//   79  234:aaload          
	//   80  235:invokevirtual   #94  <Method void awg.a(awp)>
		k = abvk;
	//   81  238:aload_0         
	//   82  239:aload           5
	//   83  241:putfield        #59  <Field bvk[] k>
		  goto _L15
	//*  84  244:goto            0
_L12:
		j = (btg)awg1.a(btg.a());
	//   85  247:aload_0         
	//   86  248:aload_1         
	//   87  249:invokestatic    #99  <Method aug btg.a()>
	//   88  252:invokevirtual   #102 <Method ash awg.a(aug)>
	//   89  255:checkcast       #96  <Class btg>
	//   90  258:putfield        #52  <Field btg j>
		  goto _L15
	//*  91  261:goto            0
_L11:
		i = (bte)awg1.a(bte.a());
	//   92  264:aload_0         
	//   93  265:aload_1         
	//   94  266:invokestatic    #105 <Method aug bte.a()>
	//   95  269:invokevirtual   #102 <Method ash awg.a(aug)>
	//   96  272:checkcast       #104 <Class bte>
	//   97  275:putfield        #50  <Field bte i>
		  goto _L15
	//*  98  278:goto            0
_L10:
		h = (btm)awg1.a(btm.a());
	//   99  281:aload_0         
	//  100  282:aload_1         
	//  101  283:invokestatic    #108 <Method aug btm.a()>
	//  102  286:invokevirtual   #102 <Method ash awg.a(aug)>
	//  103  289:checkcast       #107 <Class btm>
	//  104  292:putfield        #48  <Field btm h>
		  goto _L15
	//* 105  295:goto            0
_L9:
		g = (bto)awg1.a(bto.a());
	//  106  298:aload_0         
	//  107  299:aload_1         
	//  108  300:invokestatic    #111 <Method aug bto.a()>
	//  109  303:invokevirtual   #102 <Method ash awg.a(aug)>
	//  110  306:checkcast       #110 <Class bto>
	//  111  309:putfield        #46  <Field bto g>
		  goto _L15
	//* 112  312:goto            0
_L8:
		f = (bsx)awg1.a(bsx.a());
	//  113  315:aload_0         
	//  114  316:aload_1         
	//  115  317:invokestatic    #114 <Method aug bsx.a()>
	//  116  320:invokevirtual   #102 <Method ash awg.a(aug)>
	//  117  323:checkcast       #113 <Class bsx>
	//  118  326:putfield        #44  <Field bsx f>
		  goto _L15
	//* 119  329:goto            0
_L7:
		int j1 = awt.a(awg1, 90);
	//  120  332:aload_1         
	//  121  333:bipush          90
	//  122  335:invokestatic    #84  <Method int awt.a(awg, int)>
	//  123  338:istore_3        
		bss abss[] = e;
	//  124  339:aload_0         
	//  125  340:getfield        #42  <Field bss[] e>
	//  126  343:astore          5
		if(abss == null)
	//* 127  345:aload           5
	//* 128  347:ifnonnull       355
			l = 0;
	//  129  350:iconst_0        
	//  130  351:istore_2        
		else
	//* 131  352:goto            359
			l = abss.length;
	//  132  355:aload           5
	//  133  357:arraylength     
	//  134  358:istore_2        
		abss = new bss[j1 + l];
	//  135  359:iload_3         
	//  136  360:iload_2         
	//  137  361:iadd            
	//  138  362:anewarray       bss[]
	//  139  365:astore          5
		j1 = l;
	//  140  367:iload_2         
	//  141  368:istore_3        
		if(l != 0)
	//* 142  369:iload_2         
	//* 143  370:ifeq            387
		{
			System.arraycopy(((Object) (e)), 0, ((Object) (abss)), 0, l);
	//  144  373:aload_0         
	//  145  374:getfield        #42  <Field bss[] e>
	//  146  377:iconst_0        
	//  147  378:aload           5
	//  148  380:iconst_0        
	//  149  381:iload_2         
	//  150  382:invokestatic    #90  <Method void System.arraycopy(Object, int, Object, int, int)>
			j1 = l;
	//  151  385:iload_2         
	//  152  386:istore_3        
		}
		for(; j1 < abss.length - 1; j1++)
	//* 153  387:iload_3         
	//* 154  388:aload           5
	//* 155  390:arraylength     
	//* 156  391:iconst_1        
	//* 157  392:isub            
	//* 158  393:icmpge          422
		{
			abss[j1] = (bss)awg1.a(bss.a());
	//  159  396:aload           5
	//  160  398:iload_3         
	//  161  399:aload_1         
	//  162  400:invokestatic    #115 <Method aug bss.a()>
	//  163  403:invokevirtual   #102 <Method ash awg.a(aug)>
	//  164  406:checkcast       #40  <Class bss>
	//  165  409:aastore         
			awg1.a();
	//  166  410:aload_1         
	//  167  411:invokevirtual   #76  <Method int awg.a()>
	//  168  414:pop             
		}

	//  169  415:iload_3         
	//  170  416:iconst_1        
	//  171  417:iadd            
	//  172  418:istore_3        
	//* 173  419:goto            387
		abss[j1] = (bss)awg1.a(bss.a());
	//  174  422:aload           5
	//  175  424:iload_3         
	//  176  425:aload_1         
	//  177  426:invokestatic    #115 <Method aug bss.a()>
	//  178  429:invokevirtual   #102 <Method ash awg.a(aug)>
	//  179  432:checkcast       #40  <Class bss>
	//  180  435:aastore         
		e = abss;
	//  181  436:aload_0         
	//  182  437:aload           5
	//  183  439:putfield        #42  <Field bss[] e>
		  goto _L15
	//* 184  442:goto            0
_L6:
		if(b == null)
	//* 185  445:aload_0         
	//* 186  446:getfield        #38  <Field bvf b>
	//* 187  449:ifnonnull       463
			b = new bvf();
	//  188  452:aload_0         
	//  189  453:new             #117 <Class bvf>
	//  190  456:dup             
	//  191  457:invokespecial   #118 <Method void bvf()>
	//  192  460:putfield        #38  <Field bvf b>
		awg1.a(((awp) (b)));
	//  193  463:aload_1         
	//  194  464:aload_0         
	//  195  465:getfield        #38  <Field bvf b>
	//  196  468:invokevirtual   #94  <Method void awg.a(awp)>
		  goto _L15
	//* 197  471:goto            0
_L5:
		d = (bsv)awg1.a(bsv.a());
	//  198  474:aload_0         
	//  199  475:aload_1         
	//  200  476:invokestatic    #121 <Method aug bsv.a()>
	//  201  479:invokevirtual   #102 <Method ash awg.a(aug)>
	//  202  482:checkcast       #120 <Class bsv>
	//  203  485:putfield        #36  <Field bsv d>
		  goto _L15
	//* 204  488:goto            0
_L4:
		int k1;
		int l1;
		k1 = awg1.j();
	//  205  491:aload_1         
	//  206  492:invokevirtual   #123 <Method int awg.j()>
	//  207  495:istore_3        
		l1 = awg1.g();
	//  208  496:aload_1         
	//  209  497:invokevirtual   #125 <Method int awg.g()>
	//  210  500:istore          4
		if(l1 == 1000) goto _L17; else goto _L16
	//  211  502:iload           4
	//  212  504:sipush          1000
	//  213  507:icmpeq          551
_L16:
		l1;
	//  214  510:iload           4
		JVM INSTR tableswitch 0 1: default 536
	//	               0 551
	//	               1 551;
	//  215  512:tableswitch     0 1: default 536
	//	               0 551
	//	               1 551
		   goto _L18 _L17 _L17
_L18:
		awg1.e(k1);
	//  216  536:aload_1         
	//  217  537:iload_3         
	//  218  538:invokevirtual   #128 <Method void awg.e(int)>
		((awj)this).a(awg1, l);
	//  219  541:aload_0         
	//  220  542:aload_1         
	//  221  543:iload_2         
	//  222  544:invokevirtual   #79  <Method boolean awj.a(awg, int)>
	//  223  547:pop             
		  goto _L19
	//* 224  548:goto            0
_L17:
		c = buv.a(l1);
	//  225  551:aload_0         
	//  226  552:iload           4
	//  227  554:invokestatic    #133 <Method buv buv.a(int)>
	//  228  557:putfield        #34  <Field buv c>
		  goto _L19
	//* 229  560:goto            0
_L3:
		k1 = awg1.j();
	//  230  563:aload_1         
	//  231  564:invokevirtual   #123 <Method int awg.j()>
	//  232  567:istore_3        
		  goto _L20
_L19:
		if(true) goto _L15; else goto _L21
_L21:
_L20:
		l1 = awg1.g();
	//  233  568:aload_1         
	//  234  569:invokevirtual   #125 <Method int awg.g()>
	//  235  572:istore          4
		if(l1 < 0 || l1 > 9) goto _L23; else goto _L22
	//  236  574:iload           4
	//  237  576:iflt            598
	//  238  579:iload           4
	//  239  581:bipush          9
	//  240  583:icmpgt          598
_L22:
		a = Integer.valueOf(l1);
	//  241  586:aload_0         
	//  242  587:iload           4
	//  243  589:invokestatic    #139 <Method Integer Integer.valueOf(int)>
	//  244  592:putfield        #32  <Field Integer a>
		  goto _L15
	//* 245  595:goto            0
_L23:
		try
		{
			StringBuilder stringbuilder = new StringBuilder(43);
	//  246  598:new             #141 <Class StringBuilder>
	//  247  601:dup             
	//  248  602:bipush          43
	//  249  604:invokespecial   #143 <Method void StringBuilder(int)>
	//  250  607:astore          5
			stringbuilder.append(l1);
	//  251  609:aload           5
	//  252  611:iload           4
	//  253  613:invokevirtual   #147 <Method StringBuilder StringBuilder.append(int)>
	//  254  616:pop             
			stringbuilder.append(" is not a valid enum AdInitiater");
	//  255  617:aload           5
	//  256  619:ldc1            #149 <String " is not a valid enum AdInitiater">
	//  257  621:invokevirtual   #152 <Method StringBuilder StringBuilder.append(String)>
	//  258  624:pop             
			throw new IllegalArgumentException(stringbuilder.toString());
	//  259  625:new             #71  <Class IllegalArgumentException>
	//  260  628:dup             
	//  261  629:aload           5
	//  262  631:invokevirtual   #156 <Method String StringBuilder.toString()>
	//  263  634:invokespecial   #159 <Method void IllegalArgumentException(String)>
	//  264  637:athrow          
		}
	//* 265  638:aload_1         
	//* 266  639:iload_3         
	//* 267  640:invokevirtual   #128 <Method void awg.e(int)>
	//* 268  643:aload_0         
	//* 269  644:aload_1         
	//* 270  645:iload_2         
	//* 271  646:invokevirtual   #79  <Method boolean awj.a(awg, int)>
	//* 272  649:pop             
	//* 273  650:goto            0
	//* 274  653:aload_0         
	//* 275  654:areturn         
		// Misplaced declaration of an exception variable
		catch(IllegalArgumentException illegalargumentexception)
		{
			awg1.e(k1);
		}
		((awj)this).a(awg1, l);
		  goto _L15
_L2:
		IllegalArgumentException illegalargumentexception;
		return this;
	//* 276  655:astore          5
	//* 277  657:goto            638
	}

	protected final int a()
	{
		int i1 = super.a();
	//    0    0:aload_0         
	//    1    1:invokespecial   #160 <Method int awj.a()>
	//    2    4:istore_2        
		Object obj = ((Object) (a));
	//    3    5:aload_0         
	//    4    6:getfield        #32  <Field Integer a>
	//    5    9:astore          5
		int l = i1;
	//    6   11:iload_2         
	//    7   12:istore_1        
		if(obj != null)
	//*   8   13:aload           5
	//*   9   15:ifnull          31
			l = i1 + awh.b(7, ((Integer) (obj)).intValue());
	//   10   18:iload_2         
	//   11   19:bipush          7
	//   12   21:aload           5
	//   13   23:invokevirtual   #163 <Method int Integer.intValue()>
	//   14   26:invokestatic    #168 <Method int awh.b(int, int)>
	//   15   29:iadd            
	//   16   30:istore_1        
		obj = ((Object) (c));
	//   17   31:aload_0         
	//   18   32:getfield        #34  <Field buv c>
	//   19   35:astore          5
		i1 = l;
	//   20   37:iload_1         
	//   21   38:istore_2        
		if(obj != null)
	//*  22   39:aload           5
	//*  23   41:ifnull          64
		{
			i1 = l;
	//   24   44:iload_1         
	//   25   45:istore_2        
			if(obj != null)
	//*  26   46:aload           5
	//*  27   48:ifnull          64
				i1 = l + awh.b(8, ((buv) (obj)).a());
	//   28   51:iload_1         
	//   29   52:bipush          8
	//   30   54:aload           5
	//   31   56:invokevirtual   #169 <Method int buv.a()>
	//   32   59:invokestatic    #168 <Method int awh.b(int, int)>
	//   33   62:iadd            
	//   34   63:istore_2        
		}
		obj = ((Object) (d));
	//   35   64:aload_0         
	//   36   65:getfield        #36  <Field bsv d>
	//   37   68:astore          5
		int k1 = i1;
	//   38   70:iload_2         
	//   39   71:istore_3        
		if(obj != null)
	//*  40   72:aload           5
	//*  41   74:ifnull          87
			k1 = i1 + arh.c(9, ((atv) (obj)));
	//   42   77:iload_2         
	//   43   78:bipush          9
	//   44   80:aload           5
	//   45   82:invokestatic    #174 <Method int arh.c(int, atv)>
	//   46   85:iadd            
	//   47   86:istore_3        
		obj = ((Object) (b));
	//   48   87:aload_0         
	//   49   88:getfield        #38  <Field bvf b>
	//   50   91:astore          5
		l = k1;
	//   51   93:iload_3         
	//   52   94:istore_1        
		if(obj != null)
	//*  53   95:aload           5
	//*  54   97:ifnull          110
			l = k1 + awh.b(10, ((awp) (obj)));
	//   55  100:iload_3         
	//   56  101:bipush          10
	//   57  103:aload           5
	//   58  105:invokestatic    #177 <Method int awh.b(int, awp)>
	//   59  108:iadd            
	//   60  109:istore_1        
		Object aobj[] = ((Object []) (e));
	//   61  110:aload_0         
	//   62  111:getfield        #42  <Field bss[] e>
	//   63  114:astore          5
		boolean flag = false;
	//   64  116:iconst_0        
	//   65  117:istore          4
		i1 = l;
	//   66  119:iload_1         
	//   67  120:istore_2        
		if(aobj != null)
	//*  68  121:aload           5
	//*  69  123:ifnull          183
		{
			i1 = l;
	//   70  126:iload_1         
	//   71  127:istore_2        
			if(aobj.length > 0)
	//*  72  128:aload           5
	//*  73  130:arraylength     
	//*  74  131:ifle            183
			{
				i1 = 0;
	//   75  134:iconst_0        
	//   76  135:istore_2        
				do
				{
					aobj = ((Object []) (e));
	//   77  136:aload_0         
	//   78  137:getfield        #42  <Field bss[] e>
	//   79  140:astore          5
					if(i1 >= aobj.length)
						break;
	//   80  142:iload_2         
	//   81  143:aload           5
	//   82  145:arraylength     
	//   83  146:icmpge          181
					aobj = ((Object []) (aobj[i1]));
	//   84  149:aload           5
	//   85  151:iload_2         
	//   86  152:aaload          
	//   87  153:astore          5
					k1 = l;
	//   88  155:iload_1         
	//   89  156:istore_3        
					if(aobj != null)
	//*  90  157:aload           5
	//*  91  159:ifnull          172
						k1 = l + arh.c(11, ((atv) (aobj)));
	//   92  162:iload_1         
	//   93  163:bipush          11
	//   94  165:aload           5
	//   95  167:invokestatic    #174 <Method int arh.c(int, atv)>
	//   96  170:iadd            
	//   97  171:istore_3        
					i1++;
	//   98  172:iload_2         
	//   99  173:iconst_1        
	//  100  174:iadd            
	//  101  175:istore_2        
					l = k1;
	//  102  176:iload_3         
	//  103  177:istore_1        
				} while(true);
	//  104  178:goto            136
				i1 = l;
	//  105  181:iload_1         
	//  106  182:istore_2        
			}
		}
		aobj = ((Object []) (f));
	//  107  183:aload_0         
	//  108  184:getfield        #44  <Field bsx f>
	//  109  187:astore          5
		l = i1;
	//  110  189:iload_2         
	//  111  190:istore_1        
		if(aobj != null)
	//* 112  191:aload           5
	//* 113  193:ifnull          206
			l = i1 + arh.c(12, ((atv) (aobj)));
	//  114  196:iload_2         
	//  115  197:bipush          12
	//  116  199:aload           5
	//  117  201:invokestatic    #174 <Method int arh.c(int, atv)>
	//  118  204:iadd            
	//  119  205:istore_1        
		aobj = ((Object []) (g));
	//  120  206:aload_0         
	//  121  207:getfield        #46  <Field bto g>
	//  122  210:astore          5
		i1 = l;
	//  123  212:iload_1         
	//  124  213:istore_2        
		if(aobj != null)
	//* 125  214:aload           5
	//* 126  216:ifnull          229
			i1 = l + arh.c(13, ((atv) (aobj)));
	//  127  219:iload_1         
	//  128  220:bipush          13
	//  129  222:aload           5
	//  130  224:invokestatic    #174 <Method int arh.c(int, atv)>
	//  131  227:iadd            
	//  132  228:istore_2        
		aobj = ((Object []) (h));
	//  133  229:aload_0         
	//  134  230:getfield        #48  <Field btm h>
	//  135  233:astore          5
		l = i1;
	//  136  235:iload_2         
	//  137  236:istore_1        
		if(aobj != null)
	//* 138  237:aload           5
	//* 139  239:ifnull          252
			l = i1 + arh.c(14, ((atv) (aobj)));
	//  140  242:iload_2         
	//  141  243:bipush          14
	//  142  245:aload           5
	//  143  247:invokestatic    #174 <Method int arh.c(int, atv)>
	//  144  250:iadd            
	//  145  251:istore_1        
		aobj = ((Object []) (i));
	//  146  252:aload_0         
	//  147  253:getfield        #50  <Field bte i>
	//  148  256:astore          5
		i1 = l;
	//  149  258:iload_1         
	//  150  259:istore_2        
		if(aobj != null)
	//* 151  260:aload           5
	//* 152  262:ifnull          275
			i1 = l + arh.c(15, ((atv) (aobj)));
	//  153  265:iload_1         
	//  154  266:bipush          15
	//  155  268:aload           5
	//  156  270:invokestatic    #174 <Method int arh.c(int, atv)>
	//  157  273:iadd            
	//  158  274:istore_2        
		aobj = ((Object []) (j));
	//  159  275:aload_0         
	//  160  276:getfield        #52  <Field btg j>
	//  161  279:astore          5
		l = i1;
	//  162  281:iload_2         
	//  163  282:istore_1        
		if(aobj != null)
	//* 164  283:aload           5
	//* 165  285:ifnull          298
			l = i1 + arh.c(16, ((atv) (aobj)));
	//  166  288:iload_2         
	//  167  289:bipush          16
	//  168  291:aload           5
	//  169  293:invokestatic    #174 <Method int arh.c(int, atv)>
	//  170  296:iadd            
	//  171  297:istore_1        
		aobj = ((Object []) (k));
	//  172  298:aload_0         
	//  173  299:getfield        #59  <Field bvk[] k>
	//  174  302:astore          5
		k1 = l;
	//  175  304:iload_1         
	//  176  305:istore_3        
		if(aobj != null)
	//* 177  306:aload           5
	//* 178  308:ifnull          369
		{
			k1 = l;
	//  179  311:iload_1         
	//  180  312:istore_3        
			if(aobj.length > 0)
	//* 181  313:aload           5
	//* 182  315:arraylength     
	//* 183  316:ifle            369
			{
				int j1 = ((int) (flag));
	//  184  319:iload           4
	//  185  321:istore_2        
				do
				{
					bvk abvk[] = k;
	//  186  322:aload_0         
	//  187  323:getfield        #59  <Field bvk[] k>
	//  188  326:astore          5
					k1 = l;
	//  189  328:iload_1         
	//  190  329:istore_3        
					if(j1 >= abvk.length)
						break;
	//  191  330:iload_2         
	//  192  331:aload           5
	//  193  333:arraylength     
	//  194  334:icmpge          369
					bvk bvk1 = abvk[j1];
	//  195  337:aload           5
	//  196  339:iload_2         
	//  197  340:aaload          
	//  198  341:astore          5
					k1 = l;
	//  199  343:iload_1         
	//  200  344:istore_3        
					if(bvk1 != null)
	//* 201  345:aload           5
	//* 202  347:ifnull          360
						k1 = l + awh.b(17, ((awp) (bvk1)));
	//  203  350:iload_1         
	//  204  351:bipush          17
	//  205  353:aload           5
	//  206  355:invokestatic    #177 <Method int awh.b(int, awp)>
	//  207  358:iadd            
	//  208  359:istore_3        
					j1++;
	//  209  360:iload_2         
	//  210  361:iconst_1        
	//  211  362:iadd            
	//  212  363:istore_2        
					l = k1;
	//  213  364:iload_3         
	//  214  365:istore_1        
				} while(true);
	//  215  366:goto            322
			}
		}
		return k1;
	//  216  369:iload_3         
	//  217  370:ireturn         
	}

	public final awp a(awg awg1)
	{
		return ((awp) (b(awg1)));
	//    0    0:aload_0         
	//    1    1:aload_1         
	//    2    2:invokespecial   #180 <Method bve b(awg)>
	//    3    5:areturn         
	}

	public final void a(awh awh1)
	{
		Object obj = ((Object) (a));
	//    0    0:aload_0         
	//    1    1:getfield        #32  <Field Integer a>
	//    2    4:astore          4
		if(obj != null)
	//*   3    6:aload           4
	//*   4    8:ifnull          22
			awh1.a(7, ((Integer) (obj)).intValue());
	//    5   11:aload_1         
	//    6   12:bipush          7
	//    7   14:aload           4
	//    8   16:invokevirtual   #163 <Method int Integer.intValue()>
	//    9   19:invokevirtual   #184 <Method void awh.a(int, int)>
		obj = ((Object) (c));
	//   10   22:aload_0         
	//   11   23:getfield        #34  <Field buv c>
	//   12   26:astore          4
		if(obj != null && obj != null)
	//*  13   28:aload           4
	//*  14   30:ifnull          49
	//*  15   33:aload           4
	//*  16   35:ifnull          49
			awh1.a(8, ((buv) (obj)).a());
	//   17   38:aload_1         
	//   18   39:bipush          8
	//   19   41:aload           4
	//   20   43:invokevirtual   #169 <Method int buv.a()>
	//   21   46:invokevirtual   #184 <Method void awh.a(int, int)>
		obj = ((Object) (d));
	//   22   49:aload_0         
	//   23   50:getfield        #36  <Field bsv d>
	//   24   53:astore          4
		if(obj != null)
	//*  25   55:aload           4
	//*  26   57:ifnull          68
			awh1.a(9, ((atv) (obj)));
	//   27   60:aload_1         
	//   28   61:bipush          9
	//   29   63:aload           4
	//   30   65:invokevirtual   #187 <Method void awh.a(int, atv)>
		obj = ((Object) (b));
	//   31   68:aload_0         
	//   32   69:getfield        #38  <Field bvf b>
	//   33   72:astore          4
		if(obj != null)
	//*  34   74:aload           4
	//*  35   76:ifnull          87
			awh1.a(10, ((awp) (obj)));
	//   36   79:aload_1         
	//   37   80:bipush          10
	//   38   82:aload           4
	//   39   84:invokevirtual   #190 <Method void awh.a(int, awp)>
		Object aobj[] = ((Object []) (e));
	//   40   87:aload_0         
	//   41   88:getfield        #42  <Field bss[] e>
	//   42   91:astore          4
		boolean flag = false;
	//   43   93:iconst_0        
	//   44   94:istore_3        
		if(aobj != null && aobj.length > 0)
	//*  45   95:aload           4
	//*  46   97:ifnull          147
	//*  47  100:aload           4
	//*  48  102:arraylength     
	//*  49  103:ifle            147
		{
			int l = 0;
	//   50  106:iconst_0        
	//   51  107:istore_2        
			do
			{
				aobj = ((Object []) (e));
	//   52  108:aload_0         
	//   53  109:getfield        #42  <Field bss[] e>
	//   54  112:astore          4
				if(l >= aobj.length)
					break;
	//   55  114:iload_2         
	//   56  115:aload           4
	//   57  117:arraylength     
	//   58  118:icmpge          147
				aobj = ((Object []) (aobj[l]));
	//   59  121:aload           4
	//   60  123:iload_2         
	//   61  124:aaload          
	//   62  125:astore          4
				if(aobj != null)
	//*  63  127:aload           4
	//*  64  129:ifnull          140
					awh1.a(11, ((atv) (aobj)));
	//   65  132:aload_1         
	//   66  133:bipush          11
	//   67  135:aload           4
	//   68  137:invokevirtual   #187 <Method void awh.a(int, atv)>
				l++;
	//   69  140:iload_2         
	//   70  141:iconst_1        
	//   71  142:iadd            
	//   72  143:istore_2        
			} while(true);
	//   73  144:goto            108
		}
		aobj = ((Object []) (f));
	//   74  147:aload_0         
	//   75  148:getfield        #44  <Field bsx f>
	//   76  151:astore          4
		if(aobj != null)
	//*  77  153:aload           4
	//*  78  155:ifnull          166
			awh1.a(12, ((atv) (aobj)));
	//   79  158:aload_1         
	//   80  159:bipush          12
	//   81  161:aload           4
	//   82  163:invokevirtual   #187 <Method void awh.a(int, atv)>
		aobj = ((Object []) (g));
	//   83  166:aload_0         
	//   84  167:getfield        #46  <Field bto g>
	//   85  170:astore          4
		if(aobj != null)
	//*  86  172:aload           4
	//*  87  174:ifnull          185
			awh1.a(13, ((atv) (aobj)));
	//   88  177:aload_1         
	//   89  178:bipush          13
	//   90  180:aload           4
	//   91  182:invokevirtual   #187 <Method void awh.a(int, atv)>
		aobj = ((Object []) (h));
	//   92  185:aload_0         
	//   93  186:getfield        #48  <Field btm h>
	//   94  189:astore          4
		if(aobj != null)
	//*  95  191:aload           4
	//*  96  193:ifnull          204
			awh1.a(14, ((atv) (aobj)));
	//   97  196:aload_1         
	//   98  197:bipush          14
	//   99  199:aload           4
	//  100  201:invokevirtual   #187 <Method void awh.a(int, atv)>
		aobj = ((Object []) (i));
	//  101  204:aload_0         
	//  102  205:getfield        #50  <Field bte i>
	//  103  208:astore          4
		if(aobj != null)
	//* 104  210:aload           4
	//* 105  212:ifnull          223
			awh1.a(15, ((atv) (aobj)));
	//  106  215:aload_1         
	//  107  216:bipush          15
	//  108  218:aload           4
	//  109  220:invokevirtual   #187 <Method void awh.a(int, atv)>
		aobj = ((Object []) (j));
	//  110  223:aload_0         
	//  111  224:getfield        #52  <Field btg j>
	//  112  227:astore          4
		if(aobj != null)
	//* 113  229:aload           4
	//* 114  231:ifnull          242
			awh1.a(16, ((atv) (aobj)));
	//  115  234:aload_1         
	//  116  235:bipush          16
	//  117  237:aload           4
	//  118  239:invokevirtual   #187 <Method void awh.a(int, atv)>
		aobj = ((Object []) (k));
	//  119  242:aload_0         
	//  120  243:getfield        #59  <Field bvk[] k>
	//  121  246:astore          4
		if(aobj != null && aobj.length > 0)
	//* 122  248:aload           4
	//* 123  250:ifnull          300
	//* 124  253:aload           4
	//* 125  255:arraylength     
	//* 126  256:ifle            300
		{
			int i1 = ((int) (flag));
	//  127  259:iload_3         
	//  128  260:istore_2        
			do
			{
				bvk abvk[] = k;
	//  129  261:aload_0         
	//  130  262:getfield        #59  <Field bvk[] k>
	//  131  265:astore          4
				if(i1 >= abvk.length)
					break;
	//  132  267:iload_2         
	//  133  268:aload           4
	//  134  270:arraylength     
	//  135  271:icmpge          300
				bvk bvk1 = abvk[i1];
	//  136  274:aload           4
	//  137  276:iload_2         
	//  138  277:aaload          
	//  139  278:astore          4
				if(bvk1 != null)
	//* 140  280:aload           4
	//* 141  282:ifnull          293
					awh1.a(17, ((awp) (bvk1)));
	//  142  285:aload_1         
	//  143  286:bipush          17
	//  144  288:aload           4
	//  145  290:invokevirtual   #190 <Method void awh.a(int, awp)>
				i1++;
	//  146  293:iload_2         
	//  147  294:iconst_1        
	//  148  295:iadd            
	//  149  296:istore_2        
			} while(true);
	//  150  297:goto            261
		}
		super.a(awh1);
	//  151  300:aload_0         
	//  152  301:aload_1         
	//  153  302:invokespecial   #192 <Method void awj.a(awh)>
	//  154  305:return          
	}

	public Integer a;
	public bvf b;
	private buv c;
	private bsv d;
	private bss e[];
	private bsx f;
	private bto g;
	private btm h;
	private bte i;
	private btg j;
	private bvk k[];
}
