// Decompiled by Jad v1.5.8g. Copyright 2001 Pavel Kouznetsov.
// Jad home page: http://www.kpdus.com/jad.html
// Decompiler options: packimports(3) annotate safe 

package com.google.android.gms.internal.ads;


// Referenced classes of package com.google.android.gms.internal.ads:
//			awj, awn, arh, awh, 
//			awg, btw, bvl, buh, 
//			bua, bun, bul, buj, 
//			buf, awp

public final class bvk extends awj
{

	public bvk()
	{
	//    0    0:aload_0         
	//    1    1:invokespecial   #36  <Method void awj()>
		b = null;
	//    2    4:aload_0         
	//    3    5:aconst_null     
	//    4    6:putfield        #38  <Field buf b>
		c = null;
	//    5    9:aload_0         
	//    6   10:aconst_null     
	//    7   11:putfield        #40  <Field buj c>
		d = null;
	//    8   14:aload_0         
	//    9   15:aconst_null     
	//   10   16:putfield        #42  <Field bul d>
		e = null;
	//   11   19:aload_0         
	//   12   20:aconst_null     
	//   13   21:putfield        #44  <Field bun e>
		f = null;
	//   14   24:aload_0         
	//   15   25:aconst_null     
	//   16   26:putfield        #46  <Field bua f>
		g = null;
	//   17   29:aload_0         
	//   18   30:aconst_null     
	//   19   31:putfield        #48  <Field buh g>
		h = null;
	//   20   34:aload_0         
	//   21   35:aconst_null     
	//   22   36:putfield        #50  <Field bvl h>
		i = null;
	//   23   39:aload_0         
	//   24   40:aconst_null     
	//   25   41:putfield        #52  <Field Integer i>
		j = null;
	//   26   44:aload_0         
	//   27   45:aconst_null     
	//   28   46:putfield        #54  <Field Integer j>
		k = null;
	//   29   49:aload_0         
	//   30   50:aconst_null     
	//   31   51:putfield        #56  <Field btw k>
		l = null;
	//   32   54:aload_0         
	//   33   55:aconst_null     
	//   34   56:putfield        #58  <Field Integer l>
		m = null;
	//   35   59:aload_0         
	//   36   60:aconst_null     
	//   37   61:putfield        #60  <Field Integer m>
		n = null;
	//   38   64:aload_0         
	//   39   65:aconst_null     
	//   40   66:putfield        #62  <Field Integer n>
		o = null;
	//   41   69:aload_0         
	//   42   70:aconst_null     
	//   43   71:putfield        #64  <Field Integer o>
		p = null;
	//   44   74:aload_0         
	//   45   75:aconst_null     
	//   46   76:putfield        #66  <Field Integer p>
		q = null;
	//   47   79:aload_0         
	//   48   80:aconst_null     
	//   49   81:putfield        #68  <Field Long q>
		Z = null;
	//   50   84:aload_0         
	//   51   85:aconst_null     
	//   52   86:putfield        #72  <Field awl Z>
		aa = -1;
	//   53   89:aload_0         
	//   54   90:iconst_m1       
	//   55   91:putfield        #76  <Field int aa>
	//   56   94:return          
	}

	public static bvk[] b()
	{
		if(a == null)
	//*   0    0:getstatic       #80  <Field bvk[] a>
	//*   1    3:ifnonnull       35
			synchronized(awn.b)
	//*   2    6:getstatic       #85  <Field Object awn.b>
	//*   3    9:astore_0        
	//*   4   10:aload_0         
	//*   5   11:monitorenter    
			{
				if(a == null)
	//*   6   12:getstatic       #80  <Field bvk[] a>
	//*   7   15:ifnonnull       25
					a = new bvk[0];
	//    8   18:iconst_0        
	//    9   19:anewarray       bvk[]
	//   10   22:putstatic       #80  <Field bvk[] a>
			}
	//   11   25:aload_0         
	//   12   26:monitorexit     
		break MISSING_BLOCK_LABEL_35;
	//   13   27:goto            35
		exception;
	//   14   30:astore_1        
		obj;
	//   15   31:aload_0         
		JVM INSTR monitorexit ;
	//   16   32:monitorexit     
		throw exception;
	//   17   33:aload_1         
	//   18   34:athrow          
		return a;
	//   19   35:getstatic       #80  <Field bvk[] a>
	//   20   38:areturn         
	}

	protected final int a()
	{
		int j1 = super.a();
	//    0    0:aload_0         
	//    1    1:invokespecial   #88  <Method int awj.a()>
	//    2    4:istore_2        
		Object obj = ((Object) (b));
	//    3    5:aload_0         
	//    4    6:getfield        #38  <Field buf b>
	//    5    9:astore_3        
		int i1 = j1;
	//    6   10:iload_2         
	//    7   11:istore_1        
		if(obj != null)
	//*   8   12:aload_3         
	//*   9   13:ifnull          24
			i1 = j1 + arh.c(5, ((atv) (obj)));
	//   10   16:iload_2         
	//   11   17:iconst_5        
	//   12   18:aload_3         
	//   13   19:invokestatic    #93  <Method int arh.c(int, atv)>
	//   14   22:iadd            
	//   15   23:istore_1        
		obj = ((Object) (c));
	//   16   24:aload_0         
	//   17   25:getfield        #40  <Field buj c>
	//   18   28:astore_3        
		j1 = i1;
	//   19   29:iload_1         
	//   20   30:istore_2        
		if(obj != null)
	//*  21   31:aload_3         
	//*  22   32:ifnull          44
			j1 = i1 + arh.c(6, ((atv) (obj)));
	//   23   35:iload_1         
	//   24   36:bipush          6
	//   25   38:aload_3         
	//   26   39:invokestatic    #93  <Method int arh.c(int, atv)>
	//   27   42:iadd            
	//   28   43:istore_2        
		obj = ((Object) (d));
	//   29   44:aload_0         
	//   30   45:getfield        #42  <Field bul d>
	//   31   48:astore_3        
		i1 = j1;
	//   32   49:iload_2         
	//   33   50:istore_1        
		if(obj != null)
	//*  34   51:aload_3         
	//*  35   52:ifnull          64
			i1 = j1 + arh.c(7, ((atv) (obj)));
	//   36   55:iload_2         
	//   37   56:bipush          7
	//   38   58:aload_3         
	//   39   59:invokestatic    #93  <Method int arh.c(int, atv)>
	//   40   62:iadd            
	//   41   63:istore_1        
		obj = ((Object) (e));
	//   42   64:aload_0         
	//   43   65:getfield        #44  <Field bun e>
	//   44   68:astore_3        
		j1 = i1;
	//   45   69:iload_1         
	//   46   70:istore_2        
		if(obj != null)
	//*  47   71:aload_3         
	//*  48   72:ifnull          84
			j1 = i1 + arh.c(8, ((atv) (obj)));
	//   49   75:iload_1         
	//   50   76:bipush          8
	//   51   78:aload_3         
	//   52   79:invokestatic    #93  <Method int arh.c(int, atv)>
	//   53   82:iadd            
	//   54   83:istore_2        
		obj = ((Object) (f));
	//   55   84:aload_0         
	//   56   85:getfield        #46  <Field bua f>
	//   57   88:astore_3        
		i1 = j1;
	//   58   89:iload_2         
	//   59   90:istore_1        
		if(obj != null)
	//*  60   91:aload_3         
	//*  61   92:ifnull          104
			i1 = j1 + arh.c(9, ((atv) (obj)));
	//   62   95:iload_2         
	//   63   96:bipush          9
	//   64   98:aload_3         
	//   65   99:invokestatic    #93  <Method int arh.c(int, atv)>
	//   66  102:iadd            
	//   67  103:istore_1        
		obj = ((Object) (g));
	//   68  104:aload_0         
	//   69  105:getfield        #48  <Field buh g>
	//   70  108:astore_3        
		j1 = i1;
	//   71  109:iload_1         
	//   72  110:istore_2        
		if(obj != null)
	//*  73  111:aload_3         
	//*  74  112:ifnull          124
			j1 = i1 + arh.c(10, ((atv) (obj)));
	//   75  115:iload_1         
	//   76  116:bipush          10
	//   77  118:aload_3         
	//   78  119:invokestatic    #93  <Method int arh.c(int, atv)>
	//   79  122:iadd            
	//   80  123:istore_2        
		obj = ((Object) (h));
	//   81  124:aload_0         
	//   82  125:getfield        #50  <Field bvl h>
	//   83  128:astore_3        
		i1 = j1;
	//   84  129:iload_2         
	//   85  130:istore_1        
		if(obj != null)
	//*  86  131:aload_3         
	//*  87  132:ifnull          144
			i1 = j1 + awh.b(11, ((awp) (obj)));
	//   88  135:iload_2         
	//   89  136:bipush          11
	//   90  138:aload_3         
	//   91  139:invokestatic    #98  <Method int awh.b(int, awp)>
	//   92  142:iadd            
	//   93  143:istore_1        
		obj = ((Object) (i));
	//   94  144:aload_0         
	//   95  145:getfield        #52  <Field Integer i>
	//   96  148:astore_3        
		j1 = i1;
	//   97  149:iload_1         
	//   98  150:istore_2        
		if(obj != null)
	//*  99  151:aload_3         
	//* 100  152:ifnull          167
			j1 = i1 + awh.b(12, ((Integer) (obj)).intValue());
	//  101  155:iload_1         
	//  102  156:bipush          12
	//  103  158:aload_3         
	//  104  159:invokevirtual   #103 <Method int Integer.intValue()>
	//  105  162:invokestatic    #106 <Method int awh.b(int, int)>
	//  106  165:iadd            
	//  107  166:istore_2        
		obj = ((Object) (j));
	//  108  167:aload_0         
	//  109  168:getfield        #54  <Field Integer j>
	//  110  171:astore_3        
		i1 = j1;
	//  111  172:iload_2         
	//  112  173:istore_1        
		if(obj != null)
	//* 113  174:aload_3         
	//* 114  175:ifnull          190
			i1 = j1 + awh.b(13, ((Integer) (obj)).intValue());
	//  115  178:iload_2         
	//  116  179:bipush          13
	//  117  181:aload_3         
	//  118  182:invokevirtual   #103 <Method int Integer.intValue()>
	//  119  185:invokestatic    #106 <Method int awh.b(int, int)>
	//  120  188:iadd            
	//  121  189:istore_1        
		obj = ((Object) (k));
	//  122  190:aload_0         
	//  123  191:getfield        #56  <Field btw k>
	//  124  194:astore_3        
		j1 = i1;
	//  125  195:iload_1         
	//  126  196:istore_2        
		if(obj != null)
	//* 127  197:aload_3         
	//* 128  198:ifnull          210
			j1 = i1 + arh.c(14, ((atv) (obj)));
	//  129  201:iload_1         
	//  130  202:bipush          14
	//  131  204:aload_3         
	//  132  205:invokestatic    #93  <Method int arh.c(int, atv)>
	//  133  208:iadd            
	//  134  209:istore_2        
		obj = ((Object) (l));
	//  135  210:aload_0         
	//  136  211:getfield        #58  <Field Integer l>
	//  137  214:astore_3        
		i1 = j1;
	//  138  215:iload_2         
	//  139  216:istore_1        
		if(obj != null)
	//* 140  217:aload_3         
	//* 141  218:ifnull          233
			i1 = j1 + awh.b(15, ((Integer) (obj)).intValue());
	//  142  221:iload_2         
	//  143  222:bipush          15
	//  144  224:aload_3         
	//  145  225:invokevirtual   #103 <Method int Integer.intValue()>
	//  146  228:invokestatic    #106 <Method int awh.b(int, int)>
	//  147  231:iadd            
	//  148  232:istore_1        
		obj = ((Object) (m));
	//  149  233:aload_0         
	//  150  234:getfield        #60  <Field Integer m>
	//  151  237:astore_3        
		j1 = i1;
	//  152  238:iload_1         
	//  153  239:istore_2        
		if(obj != null)
	//* 154  240:aload_3         
	//* 155  241:ifnull          256
			j1 = i1 + awh.b(16, ((Integer) (obj)).intValue());
	//  156  244:iload_1         
	//  157  245:bipush          16
	//  158  247:aload_3         
	//  159  248:invokevirtual   #103 <Method int Integer.intValue()>
	//  160  251:invokestatic    #106 <Method int awh.b(int, int)>
	//  161  254:iadd            
	//  162  255:istore_2        
		obj = ((Object) (n));
	//  163  256:aload_0         
	//  164  257:getfield        #62  <Field Integer n>
	//  165  260:astore_3        
		i1 = j1;
	//  166  261:iload_2         
	//  167  262:istore_1        
		if(obj != null)
	//* 168  263:aload_3         
	//* 169  264:ifnull          279
			i1 = j1 + awh.b(17, ((Integer) (obj)).intValue());
	//  170  267:iload_2         
	//  171  268:bipush          17
	//  172  270:aload_3         
	//  173  271:invokevirtual   #103 <Method int Integer.intValue()>
	//  174  274:invokestatic    #106 <Method int awh.b(int, int)>
	//  175  277:iadd            
	//  176  278:istore_1        
		obj = ((Object) (o));
	//  177  279:aload_0         
	//  178  280:getfield        #64  <Field Integer o>
	//  179  283:astore_3        
		j1 = i1;
	//  180  284:iload_1         
	//  181  285:istore_2        
		if(obj != null)
	//* 182  286:aload_3         
	//* 183  287:ifnull          302
			j1 = i1 + awh.b(18, ((Integer) (obj)).intValue());
	//  184  290:iload_1         
	//  185  291:bipush          18
	//  186  293:aload_3         
	//  187  294:invokevirtual   #103 <Method int Integer.intValue()>
	//  188  297:invokestatic    #106 <Method int awh.b(int, int)>
	//  189  300:iadd            
	//  190  301:istore_2        
		obj = ((Object) (p));
	//  191  302:aload_0         
	//  192  303:getfield        #66  <Field Integer p>
	//  193  306:astore_3        
		i1 = j1;
	//  194  307:iload_2         
	//  195  308:istore_1        
		if(obj != null)
	//* 196  309:aload_3         
	//* 197  310:ifnull          325
			i1 = j1 + awh.b(19, ((Integer) (obj)).intValue());
	//  198  313:iload_2         
	//  199  314:bipush          19
	//  200  316:aload_3         
	//  201  317:invokevirtual   #103 <Method int Integer.intValue()>
	//  202  320:invokestatic    #106 <Method int awh.b(int, int)>
	//  203  323:iadd            
	//  204  324:istore_1        
		obj = ((Object) (q));
	//  205  325:aload_0         
	//  206  326:getfield        #68  <Field Long q>
	//  207  329:astore_3        
		j1 = i1;
	//  208  330:iload_1         
	//  209  331:istore_2        
		if(obj != null)
	//* 210  332:aload_3         
	//* 211  333:ifnull          348
			j1 = i1 + awh.c(20, ((Long) (obj)).longValue());
	//  212  336:iload_1         
	//  213  337:bipush          20
	//  214  339:aload_3         
	//  215  340:invokevirtual   #112 <Method long Long.longValue()>
	//  216  343:invokestatic    #115 <Method int awh.c(int, long)>
	//  217  346:iadd            
	//  218  347:istore_2        
		return j1;
	//  219  348:iload_2         
	//  220  349:ireturn         
	}

	public final awp a(awg awg1)
	{
_L20:
		int i1 = awg1.a();
	//    0    0:aload_1         
	//    1    1:invokevirtual   #119 <Method int awg.a()>
	//    2    4:istore_2        
		i1;
	//    3    5:iload_2         
		JVM INSTR lookupswitch 17: default 152
	//	               0: 423
	//	               42: 406
	//	               50: 389
	//	               58: 372
	//	               66: 355
	//	               74: 338
	//	               82: 321
	//	               90: 292
	//	               96: 278
	//	               104: 264
	//	               114: 247
	//	               120: 233
	//	               128: 219
	//	               136: 205
	//	               144: 191
	//	               152: 177
	//	               160: 163;
	//    4    6:lookupswitch    17: default 152
	//	               0: 423
	//	               42: 406
	//	               50: 389
	//	               58: 372
	//	               66: 355
	//	               74: 338
	//	               82: 321
	//	               90: 292
	//	               96: 278
	//	               104: 264
	//	               114: 247
	//	               120: 233
	//	               128: 219
	//	               136: 205
	//	               144: 191
	//	               152: 177
	//	               160: 163
		   goto _L1 _L2 _L3 _L4 _L5 _L6 _L7 _L8 _L9 _L10 _L11 _L12 _L13 _L14 _L15 _L16 _L17 _L18
_L1:
		if(super.a(awg1, i1)) goto _L20; else goto _L19
	//    5  152:aload_0         
	//    6  153:aload_1         
	//    7  154:iload_2         
	//    8  155:invokespecial   #122 <Method boolean awj.a(awg, int)>
	//    9  158:ifne            0
_L19:
		return ((awp) (this));
	//   10  161:aload_0         
	//   11  162:areturn         
_L18:
		q = Long.valueOf(awg1.h());
	//   12  163:aload_0         
	//   13  164:aload_1         
	//   14  165:invokevirtual   #124 <Method long awg.h()>
	//   15  168:invokestatic    #128 <Method Long Long.valueOf(long)>
	//   16  171:putfield        #68  <Field Long q>
		  goto _L20
	//*  17  174:goto            0
_L17:
		p = Integer.valueOf(awg1.g());
	//   18  177:aload_0         
	//   19  178:aload_1         
	//   20  179:invokevirtual   #130 <Method int awg.g()>
	//   21  182:invokestatic    #133 <Method Integer Integer.valueOf(int)>
	//   22  185:putfield        #66  <Field Integer p>
		  goto _L20
	//*  23  188:goto            0
_L16:
		o = Integer.valueOf(awg1.g());
	//   24  191:aload_0         
	//   25  192:aload_1         
	//   26  193:invokevirtual   #130 <Method int awg.g()>
	//   27  196:invokestatic    #133 <Method Integer Integer.valueOf(int)>
	//   28  199:putfield        #64  <Field Integer o>
		  goto _L20
	//*  29  202:goto            0
_L15:
		n = Integer.valueOf(awg1.g());
	//   30  205:aload_0         
	//   31  206:aload_1         
	//   32  207:invokevirtual   #130 <Method int awg.g()>
	//   33  210:invokestatic    #133 <Method Integer Integer.valueOf(int)>
	//   34  213:putfield        #62  <Field Integer n>
		  goto _L20
	//*  35  216:goto            0
_L14:
		m = Integer.valueOf(awg1.g());
	//   36  219:aload_0         
	//   37  220:aload_1         
	//   38  221:invokevirtual   #130 <Method int awg.g()>
	//   39  224:invokestatic    #133 <Method Integer Integer.valueOf(int)>
	//   40  227:putfield        #60  <Field Integer m>
		  goto _L20
	//*  41  230:goto            0
_L13:
		l = Integer.valueOf(awg1.g());
	//   42  233:aload_0         
	//   43  234:aload_1         
	//   44  235:invokevirtual   #130 <Method int awg.g()>
	//   45  238:invokestatic    #133 <Method Integer Integer.valueOf(int)>
	//   46  241:putfield        #58  <Field Integer l>
		  goto _L20
	//*  47  244:goto            0
_L12:
		k = (btw)awg1.a(btw.a());
	//   48  247:aload_0         
	//   49  248:aload_1         
	//   50  249:invokestatic    #138 <Method aug btw.a()>
	//   51  252:invokevirtual   #141 <Method ash awg.a(aug)>
	//   52  255:checkcast       #135 <Class btw>
	//   53  258:putfield        #56  <Field btw k>
		  goto _L20
	//*  54  261:goto            0
_L11:
		j = Integer.valueOf(awg1.g());
	//   55  264:aload_0         
	//   56  265:aload_1         
	//   57  266:invokevirtual   #130 <Method int awg.g()>
	//   58  269:invokestatic    #133 <Method Integer Integer.valueOf(int)>
	//   59  272:putfield        #54  <Field Integer j>
		  goto _L20
	//*  60  275:goto            0
_L10:
		i = Integer.valueOf(awg1.g());
	//   61  278:aload_0         
	//   62  279:aload_1         
	//   63  280:invokevirtual   #130 <Method int awg.g()>
	//   64  283:invokestatic    #133 <Method Integer Integer.valueOf(int)>
	//   65  286:putfield        #52  <Field Integer i>
		  goto _L20
	//*  66  289:goto            0
_L9:
		if(h == null)
	//*  67  292:aload_0         
	//*  68  293:getfield        #50  <Field bvl h>
	//*  69  296:ifnonnull       310
			h = new bvl();
	//   70  299:aload_0         
	//   71  300:new             #143 <Class bvl>
	//   72  303:dup             
	//   73  304:invokespecial   #144 <Method void bvl()>
	//   74  307:putfield        #50  <Field bvl h>
		awg1.a(((awp) (h)));
	//   75  310:aload_1         
	//   76  311:aload_0         
	//   77  312:getfield        #50  <Field bvl h>
	//   78  315:invokevirtual   #147 <Method void awg.a(awp)>
		  goto _L20
	//*  79  318:goto            0
_L8:
		g = (buh)awg1.a(buh.a());
	//   80  321:aload_0         
	//   81  322:aload_1         
	//   82  323:invokestatic    #150 <Method aug buh.a()>
	//   83  326:invokevirtual   #141 <Method ash awg.a(aug)>
	//   84  329:checkcast       #149 <Class buh>
	//   85  332:putfield        #48  <Field buh g>
		  goto _L20
	//*  86  335:goto            0
_L7:
		f = (bua)awg1.a(bua.a());
	//   87  338:aload_0         
	//   88  339:aload_1         
	//   89  340:invokestatic    #153 <Method aug bua.a()>
	//   90  343:invokevirtual   #141 <Method ash awg.a(aug)>
	//   91  346:checkcast       #152 <Class bua>
	//   92  349:putfield        #46  <Field bua f>
		  goto _L20
	//*  93  352:goto            0
_L6:
		e = (bun)awg1.a(bun.a());
	//   94  355:aload_0         
	//   95  356:aload_1         
	//   96  357:invokestatic    #156 <Method aug bun.a()>
	//   97  360:invokevirtual   #141 <Method ash awg.a(aug)>
	//   98  363:checkcast       #155 <Class bun>
	//   99  366:putfield        #44  <Field bun e>
		  goto _L20
	//* 100  369:goto            0
_L5:
		d = (bul)awg1.a(bul.a());
	//  101  372:aload_0         
	//  102  373:aload_1         
	//  103  374:invokestatic    #159 <Method aug bul.a()>
	//  104  377:invokevirtual   #141 <Method ash awg.a(aug)>
	//  105  380:checkcast       #158 <Class bul>
	//  106  383:putfield        #42  <Field bul d>
		  goto _L20
	//* 107  386:goto            0
_L4:
		c = (buj)awg1.a(buj.a());
	//  108  389:aload_0         
	//  109  390:aload_1         
	//  110  391:invokestatic    #162 <Method aug buj.a()>
	//  111  394:invokevirtual   #141 <Method ash awg.a(aug)>
	//  112  397:checkcast       #161 <Class buj>
	//  113  400:putfield        #40  <Field buj c>
		  goto _L20
	//* 114  403:goto            0
_L3:
		b = (buf)awg1.a(buf.a());
	//  115  406:aload_0         
	//  116  407:aload_1         
	//  117  408:invokestatic    #165 <Method aug buf.a()>
	//  118  411:invokevirtual   #141 <Method ash awg.a(aug)>
	//  119  414:checkcast       #164 <Class buf>
	//  120  417:putfield        #38  <Field buf b>
		  goto _L20
	//* 121  420:goto            0
_L2:
		return ((awp) (this));
	//  122  423:aload_0         
	//  123  424:areturn         
	}

	public final void a(awh awh1)
	{
		Object obj = ((Object) (b));
	//    0    0:aload_0         
	//    1    1:getfield        #38  <Field buf b>
	//    2    4:astore_2        
		if(obj != null)
	//*   3    5:aload_2         
	//*   4    6:ifnull          15
			awh1.a(5, ((atv) (obj)));
	//    5    9:aload_1         
	//    6   10:iconst_5        
	//    7   11:aload_2         
	//    8   12:invokevirtual   #169 <Method void awh.a(int, atv)>
		obj = ((Object) (c));
	//    9   15:aload_0         
	//   10   16:getfield        #40  <Field buj c>
	//   11   19:astore_2        
		if(obj != null)
	//*  12   20:aload_2         
	//*  13   21:ifnull          31
			awh1.a(6, ((atv) (obj)));
	//   14   24:aload_1         
	//   15   25:bipush          6
	//   16   27:aload_2         
	//   17   28:invokevirtual   #169 <Method void awh.a(int, atv)>
		obj = ((Object) (d));
	//   18   31:aload_0         
	//   19   32:getfield        #42  <Field bul d>
	//   20   35:astore_2        
		if(obj != null)
	//*  21   36:aload_2         
	//*  22   37:ifnull          47
			awh1.a(7, ((atv) (obj)));
	//   23   40:aload_1         
	//   24   41:bipush          7
	//   25   43:aload_2         
	//   26   44:invokevirtual   #169 <Method void awh.a(int, atv)>
		obj = ((Object) (e));
	//   27   47:aload_0         
	//   28   48:getfield        #44  <Field bun e>
	//   29   51:astore_2        
		if(obj != null)
	//*  30   52:aload_2         
	//*  31   53:ifnull          63
			awh1.a(8, ((atv) (obj)));
	//   32   56:aload_1         
	//   33   57:bipush          8
	//   34   59:aload_2         
	//   35   60:invokevirtual   #169 <Method void awh.a(int, atv)>
		obj = ((Object) (f));
	//   36   63:aload_0         
	//   37   64:getfield        #46  <Field bua f>
	//   38   67:astore_2        
		if(obj != null)
	//*  39   68:aload_2         
	//*  40   69:ifnull          79
			awh1.a(9, ((atv) (obj)));
	//   41   72:aload_1         
	//   42   73:bipush          9
	//   43   75:aload_2         
	//   44   76:invokevirtual   #169 <Method void awh.a(int, atv)>
		obj = ((Object) (g));
	//   45   79:aload_0         
	//   46   80:getfield        #48  <Field buh g>
	//   47   83:astore_2        
		if(obj != null)
	//*  48   84:aload_2         
	//*  49   85:ifnull          95
			awh1.a(10, ((atv) (obj)));
	//   50   88:aload_1         
	//   51   89:bipush          10
	//   52   91:aload_2         
	//   53   92:invokevirtual   #169 <Method void awh.a(int, atv)>
		obj = ((Object) (h));
	//   54   95:aload_0         
	//   55   96:getfield        #50  <Field bvl h>
	//   56   99:astore_2        
		if(obj != null)
	//*  57  100:aload_2         
	//*  58  101:ifnull          111
			awh1.a(11, ((awp) (obj)));
	//   59  104:aload_1         
	//   60  105:bipush          11
	//   61  107:aload_2         
	//   62  108:invokevirtual   #172 <Method void awh.a(int, awp)>
		obj = ((Object) (i));
	//   63  111:aload_0         
	//   64  112:getfield        #52  <Field Integer i>
	//   65  115:astore_2        
		if(obj != null)
	//*  66  116:aload_2         
	//*  67  117:ifnull          130
			awh1.a(12, ((Integer) (obj)).intValue());
	//   68  120:aload_1         
	//   69  121:bipush          12
	//   70  123:aload_2         
	//   71  124:invokevirtual   #103 <Method int Integer.intValue()>
	//   72  127:invokevirtual   #175 <Method void awh.a(int, int)>
		obj = ((Object) (j));
	//   73  130:aload_0         
	//   74  131:getfield        #54  <Field Integer j>
	//   75  134:astore_2        
		if(obj != null)
	//*  76  135:aload_2         
	//*  77  136:ifnull          149
			awh1.a(13, ((Integer) (obj)).intValue());
	//   78  139:aload_1         
	//   79  140:bipush          13
	//   80  142:aload_2         
	//   81  143:invokevirtual   #103 <Method int Integer.intValue()>
	//   82  146:invokevirtual   #175 <Method void awh.a(int, int)>
		obj = ((Object) (k));
	//   83  149:aload_0         
	//   84  150:getfield        #56  <Field btw k>
	//   85  153:astore_2        
		if(obj != null)
	//*  86  154:aload_2         
	//*  87  155:ifnull          165
			awh1.a(14, ((atv) (obj)));
	//   88  158:aload_1         
	//   89  159:bipush          14
	//   90  161:aload_2         
	//   91  162:invokevirtual   #169 <Method void awh.a(int, atv)>
		obj = ((Object) (l));
	//   92  165:aload_0         
	//   93  166:getfield        #58  <Field Integer l>
	//   94  169:astore_2        
		if(obj != null)
	//*  95  170:aload_2         
	//*  96  171:ifnull          184
			awh1.a(15, ((Integer) (obj)).intValue());
	//   97  174:aload_1         
	//   98  175:bipush          15
	//   99  177:aload_2         
	//  100  178:invokevirtual   #103 <Method int Integer.intValue()>
	//  101  181:invokevirtual   #175 <Method void awh.a(int, int)>
		obj = ((Object) (m));
	//  102  184:aload_0         
	//  103  185:getfield        #60  <Field Integer m>
	//  104  188:astore_2        
		if(obj != null)
	//* 105  189:aload_2         
	//* 106  190:ifnull          203
			awh1.a(16, ((Integer) (obj)).intValue());
	//  107  193:aload_1         
	//  108  194:bipush          16
	//  109  196:aload_2         
	//  110  197:invokevirtual   #103 <Method int Integer.intValue()>
	//  111  200:invokevirtual   #175 <Method void awh.a(int, int)>
		obj = ((Object) (n));
	//  112  203:aload_0         
	//  113  204:getfield        #62  <Field Integer n>
	//  114  207:astore_2        
		if(obj != null)
	//* 115  208:aload_2         
	//* 116  209:ifnull          222
			awh1.a(17, ((Integer) (obj)).intValue());
	//  117  212:aload_1         
	//  118  213:bipush          17
	//  119  215:aload_2         
	//  120  216:invokevirtual   #103 <Method int Integer.intValue()>
	//  121  219:invokevirtual   #175 <Method void awh.a(int, int)>
		obj = ((Object) (o));
	//  122  222:aload_0         
	//  123  223:getfield        #64  <Field Integer o>
	//  124  226:astore_2        
		if(obj != null)
	//* 125  227:aload_2         
	//* 126  228:ifnull          241
			awh1.a(18, ((Integer) (obj)).intValue());
	//  127  231:aload_1         
	//  128  232:bipush          18
	//  129  234:aload_2         
	//  130  235:invokevirtual   #103 <Method int Integer.intValue()>
	//  131  238:invokevirtual   #175 <Method void awh.a(int, int)>
		obj = ((Object) (p));
	//  132  241:aload_0         
	//  133  242:getfield        #66  <Field Integer p>
	//  134  245:astore_2        
		if(obj != null)
	//* 135  246:aload_2         
	//* 136  247:ifnull          260
			awh1.a(19, ((Integer) (obj)).intValue());
	//  137  250:aload_1         
	//  138  251:bipush          19
	//  139  253:aload_2         
	//  140  254:invokevirtual   #103 <Method int Integer.intValue()>
	//  141  257:invokevirtual   #175 <Method void awh.a(int, int)>
		obj = ((Object) (q));
	//  142  260:aload_0         
	//  143  261:getfield        #68  <Field Long q>
	//  144  264:astore_2        
		if(obj != null)
	//* 145  265:aload_2         
	//* 146  266:ifnull          279
			awh1.a(20, ((Long) (obj)).longValue());
	//  147  269:aload_1         
	//  148  270:bipush          20
	//  149  272:aload_2         
	//  150  273:invokevirtual   #112 <Method long Long.longValue()>
	//  151  276:invokevirtual   #178 <Method void awh.a(int, long)>
		super.a(awh1);
	//  152  279:aload_0         
	//  153  280:aload_1         
	//  154  281:invokespecial   #180 <Method void awj.a(awh)>
	//  155  284:return          
	}

	private static volatile bvk a[];
	private buf b;
	private buj c;
	private bul d;
	private bun e;
	private bua f;
	private buh g;
	private bvl h;
	private Integer i;
	private Integer j;
	private btw k;
	private Integer l;
	private Integer m;
	private Integer n;
	private Integer o;
	private Integer p;
	private Long q;
}
