// Decompiled by Jad v1.5.8g. Copyright 2001 Pavel Kouznetsov.
// Jad home page: http://www.kpdus.com/jad.html
// Decompiler options: packimports(3) annotate safe 

package com.google.android.gms.internal.ads;

import android.content.Context;
import android.os.Bundle;
import android.os.Handler;
import android.os.RemoteException;
import android.os.SystemClock;
import android.text.TextUtils;
import com.google.ads.mediation.AdUrlAdapter;
import com.google.ads.mediation.admob.AdMobAdapter;
import com.google.android.gms.ads.formats.f;
import com.google.android.gms.ads.internal.aw;
import com.google.android.gms.ads.mediation.b;
import com.google.android.gms.c.d;
import com.google.android.gms.common.util.e;
import java.util.ArrayList;
import java.util.Iterator;
import java.util.List;
import org.json.JSONException;
import org.json.JSONObject;

// Referenced classes of package com.google.android.gms.internal.ads:
//			kd, jv, jw, lk, 
//			wx, zzbbi, zzwf, kp, 
//			zzacp, km, kv, kb, 
//			zzanu, jy, xg, ka, 
//			kc, zzwb

public final class jz
	implements kd
{

	public jz(Context context, String s1, km km1, jw jw1, jv jv1, zzwb zzwb, zzwf zzwf1, 
			zzbbi zzbbi1, boolean flag, boolean flag1, zzacp zzacp1, List list, List list1, List list2, 
			boolean flag2)
	{
	//    0    0:aload_0         
	//    1    1:invokespecial   #51  <Method void Object()>
	//    2    4:aload_0         
	//    3    5:new             #4   <Class Object>
	//    4    8:dup             
	//    5    9:invokespecial   #51  <Method void Object()>
	//    6   12:putfield        #53  <Field Object i>
		s = -2;
	//    7   15:aload_0         
	//    8   16:bipush          -2
	//    9   18:putfield        #55  <Field int s>
		h = context;
	//   10   21:aload_0         
	//   11   22:aload_1         
	//   12   23:putfield        #57  <Field Context h>
		b = km1;
	//   13   26:aload_0         
	//   14   27:aload_3         
	//   15   28:putfield        #59  <Field km b>
		e = jv1;
	//   16   31:aload_0         
	//   17   32:aload           5
	//   18   34:putfield        #61  <Field jv e>
		if("com.google.ads.mediation.customevent.CustomEventAdapter".equals(((Object) (s1))))
	//*  19   37:ldc1            #63  <String "com.google.ads.mediation.customevent.CustomEventAdapter">
	//*  20   39:aload_2         
	//*  21   40:invokevirtual   #69  <Method boolean String.equals(Object)>
	//*  22   43:ifeq            57
			a = b();
	//   23   46:aload_0         
	//   24   47:aload_0         
	//   25   48:invokespecial   #72  <Method String b()>
	//   26   51:putfield        #74  <Field String a>
		else
	//*  27   54:goto            62
			a = s1;
	//   28   57:aload_0         
	//   29   58:aload_2         
	//   30   59:putfield        #74  <Field String a>
		d = jw1;
	//   31   62:aload_0         
	//   32   63:aload           4
	//   33   65:putfield        #76  <Field jw d>
		if(jv1.t != -1L)
	//*  34   68:aload           5
	//*  35   70:getfield        #80  <Field long jv.t>
	//*  36   73:ldc2w           #81  <Long -1L>
	//*  37   76:lcmp            
	//*  38   77:ifeq            92
			c = jv1.t;
	//   39   80:aload_0         
	//   40   81:aload           5
	//   41   83:getfield        #80  <Field long jv.t>
	//   42   86:putfield        #84  <Field long c>
		else
	//*  43   89:goto            123
		if(jw1.b != -1L)
	//*  44   92:aload           4
	//*  45   94:getfield        #88  <Field long com.google.android.gms.internal.ads.jw.b>
	//*  46   97:ldc2w           #81  <Long -1L>
	//*  47  100:lcmp            
	//*  48  101:ifeq            116
			c = jw1.b;
	//   49  104:aload_0         
	//   50  105:aload           4
	//   51  107:getfield        #88  <Field long com.google.android.gms.internal.ads.jw.b>
	//   52  110:putfield        #84  <Field long c>
		else
	//*  53  113:goto            123
			c = 10000L;
	//   54  116:aload_0         
	//   55  117:ldc2w           #89  <Long 10000L>
	//   56  120:putfield        #84  <Field long c>
		f = zzwb;
	//   57  123:aload_0         
	//   58  124:aload           6
	//   59  126:putfield        #92  <Field zzwb f>
		g = zzwf1;
	//   60  129:aload_0         
	//   61  130:aload           7
	//   62  132:putfield        #94  <Field zzwf g>
		j = zzbbi1;
	//   63  135:aload_0         
	//   64  136:aload           8
	//   65  138:putfield        #96  <Field zzbbi j>
		k = flag;
	//   66  141:aload_0         
	//   67  142:iload           9
	//   68  144:putfield        #98  <Field boolean k>
		p = flag1;
	//   69  147:aload_0         
	//   70  148:iload           10
	//   71  150:putfield        #100 <Field boolean p>
		l = zzacp1;
	//   72  153:aload_0         
	//   73  154:aload           11
	//   74  156:putfield        #102 <Field zzacp l>
		m = list;
	//   75  159:aload_0         
	//   76  160:aload           12
	//   77  162:putfield        #104 <Field List m>
		n = list1;
	//   78  165:aload_0         
	//   79  166:aload           13
	//   80  168:putfield        #106 <Field List n>
		o = list2;
	//   81  171:aload_0         
	//   82  172:aload           14
	//   83  174:putfield        #108 <Field List o>
		q = flag2;
	//   84  177:aload_0         
	//   85  178:iload           15
	//   86  180:putfield        #110 <Field boolean q>
	//   87  183:return          
	}

	private static kp a(b b1)
	{
		return ((kp) (new lk(b1)));
	//    0    0:new             #114 <Class lk>
	//    1    3:dup             
	//    2    4:aload_0         
	//    3    5:invokespecial   #117 <Method void lk(b)>
	//    4    8:areturn         
	}

	static kp a(jz jz1, kp kp1)
	{
		jz1.r = kp1;
	//    0    0:aload_0         
	//    1    1:aload_1         
	//    2    2:putfield        #120 <Field kp r>
		return kp1;
	//    3    5:aload_1         
	//    4    6:areturn         
	}

	static Object a(jz jz1)
	{
		return jz1.i;
	//    0    0:aload_0         
	//    1    1:getfield        #53  <Field Object i>
	//    2    4:areturn         
	}

	private final String a(String s1)
	{
		JSONException jsonexception;
		if(s1 != null && e())
	//*   0    0:aload_1         
	//*   1    1:ifnull          51
	//*   2    4:aload_0         
	//*   3    5:invokespecial   #127 <Method boolean e()>
	//*   4    8:ifeq            51
		{
			if(b(2))
	//*   5   11:aload_0         
	//*   6   12:iconst_2        
	//*   7   13:invokespecial   #130 <Method boolean b(int)>
	//*   8   16:ifeq            21
				return s1;
	//    9   19:aload_1         
	//   10   20:areturn         
			Object obj;
			try
			{
				obj = ((Object) (new JSONObject(s1)));
	//   11   21:new             #132 <Class JSONObject>
	//   12   24:dup             
	//   13   25:aload_1         
	//   14   26:invokespecial   #135 <Method void JSONObject(String)>
	//   15   29:astore_2        
				((JSONObject) (obj)).remove("cpm_floor_cents");
	//   16   30:aload_2         
	//   17   31:ldc1            #137 <String "cpm_floor_cents">
	//   18   33:invokevirtual   #141 <Method Object JSONObject.remove(String)>
	//   19   36:pop             
				obj = ((Object) (((JSONObject) (obj)).toString()));
	//   20   37:aload_2         
	//   21   38:invokevirtual   #144 <Method String JSONObject.toString()>
	//   22   41:astore_2        
			}
	//*  23   42:aload_2         
	//*  24   43:areturn         
	//*  25   44:ldc1            #146 <String "Could not remove field. Returning the original value">
	//*  26   46:invokestatic    #150 <Method void com.google.android.gms.internal.ads.wx.e(String)>
	//*  27   49:aload_1         
	//*  28   50:areturn         
	//*  29   51:aload_1         
	//*  30   52:areturn         
			// Misplaced declaration of an exception variable
			catch(JSONException jsonexception)
			{
				com.google.android.gms.internal.ads.wx.e("Could not remove field. Returning the original value");
				return s1;
			}
			return ((String) (obj));
		} else
		{
			return s1;
		}
	//*  31   53:astore_2        
	//*  32   54:goto            44
	}

	private final void a(jy jy1)
	{
		String s2 = a(e.k);
	//    0    0:aload_0         
	//    1    1:aload_0         
	//    2    2:getfield        #61  <Field jv e>
	//    3    5:getfield        #156 <Field String jv.k>
	//    4    8:invokespecial   #158 <Method String a(String)>
	//    5   11:astore          4
		if(j.c >= 0x3e8fa0)
			break MISSING_BLOCK_LABEL_87;
	//    6   13:aload_0         
	//    7   14:getfield        #96  <Field zzbbi j>
	//    8   17:getfield        #162 <Field int zzbbi.c>
	//    9   20:ldc1            #163 <Int 0x3e8fa0>
	//   10   22:icmpge          87
		if(g.d)
	//*  11   25:aload_0         
	//*  12   26:getfield        #94  <Field zzwf g>
	//*  13   29:getfield        #167 <Field boolean com.google.android.gms.internal.ads.zzwf.d>
	//*  14   32:ifeq            59
		{
			r.a(com.google.android.gms.c.d.a(((Object) (h))), f, s2, ((ks) (jy1)));
	//   15   35:aload_0         
	//   16   36:getfield        #120 <Field kp r>
	//   17   39:aload_0         
	//   18   40:getfield        #57  <Field Context h>
	//   19   43:invokestatic    #172 <Method com.google.android.gms.c.a d.a(Object)>
	//   20   46:aload_0         
	//   21   47:getfield        #92  <Field zzwb f>
	//   22   50:aload           4
	//   23   52:aload_1         
	//   24   53:invokeinterface #177 <Method void kp.a(com.google.android.gms.c.a, zzwb, String, ks)>
			return;
	//   25   58:return          
		}
		String s1;
		Object obj;
		ArrayList arraylist;
		Iterator iterator;
		String s3;
		try
		{
			r.a(com.google.android.gms.c.d.a(((Object) (h))), g, f, s2, ((ks) (jy1)));
	//   26   59:aload_0         
	//   27   60:getfield        #120 <Field kp r>
	//   28   63:aload_0         
	//   29   64:getfield        #57  <Field Context h>
	//   30   67:invokestatic    #172 <Method com.google.android.gms.c.a d.a(Object)>
	//   31   70:aload_0         
	//   32   71:getfield        #94  <Field zzwf g>
	//   33   74:aload_0         
	//   34   75:getfield        #92  <Field zzwb f>
	//   35   78:aload           4
	//   36   80:aload_1         
	//   37   81:invokeinterface #180 <Method void kp.a(com.google.android.gms.c.a, zzwf, zzwb, String, ks)>
			return;
	//   38   86:return          
		}
	//*  39   87:aload_0         
	//*  40   88:getfield        #98  <Field boolean k>
	//*  41   91:ifne            290
	//*  42   94:aload_0         
	//*  43   95:getfield        #61  <Field jv e>
	//*  44   98:invokevirtual   #182 <Method boolean com.google.android.gms.internal.ads.jv.b()>
	//*  45  101:ifeq            107
	//*  46  104:goto            290
	//*  47  107:aload_0         
	//*  48  108:getfield        #94  <Field zzwf g>
	//*  49  111:getfield        #167 <Field boolean com.google.android.gms.internal.ads.zzwf.d>
	//*  50  114:ifeq            148
	//*  51  117:aload_0         
	//*  52  118:getfield        #120 <Field kp r>
	//*  53  121:aload_0         
	//*  54  122:getfield        #57  <Field Context h>
	//*  55  125:invokestatic    #172 <Method com.google.android.gms.c.a d.a(Object)>
	//*  56  128:aload_0         
	//*  57  129:getfield        #92  <Field zzwb f>
	//*  58  132:aload           4
	//*  59  134:aload_0         
	//*  60  135:getfield        #61  <Field jv e>
	//*  61  138:getfield        #183 <Field String jv.a>
	//*  62  141:aload_1         
	//*  63  142:invokeinterface #186 <Method void kp.a(com.google.android.gms.c.a, zzwb, String, String, ks)>
	//*  64  147:return          
	//*  65  148:aload_0         
	//*  66  149:getfield        #100 <Field boolean p>
	//*  67  152:ifeq            255
	//*  68  155:aload_0         
	//*  69  156:getfield        #61  <Field jv e>
	//*  70  159:getfield        #188 <Field String jv.o>
	//*  71  162:ifnull          220
	//*  72  165:aload_0         
	//*  73  166:getfield        #120 <Field kp r>
	//*  74  169:aload_0         
	//*  75  170:getfield        #57  <Field Context h>
	//*  76  173:invokestatic    #172 <Method com.google.android.gms.c.a d.a(Object)>
	//*  77  176:aload_0         
	//*  78  177:getfield        #92  <Field zzwb f>
	//*  79  180:aload           4
	//*  80  182:aload_0         
	//*  81  183:getfield        #61  <Field jv e>
	//*  82  186:getfield        #183 <Field String jv.a>
	//*  83  189:aload_1         
	//*  84  190:new             #190 <Class zzacp>
	//*  85  193:dup             
	//*  86  194:aload_0         
	//*  87  195:getfield        #61  <Field jv e>
	//*  88  198:getfield        #192 <Field String jv.s>
	//*  89  201:invokestatic    #195 <Method com.google.android.gms.ads.formats.e b(String)>
	//*  90  204:invokespecial   #198 <Method void zzacp(com.google.android.gms.ads.formats.e)>
	//*  91  207:aload_0         
	//*  92  208:getfield        #61  <Field jv e>
	//*  93  211:getfield        #200 <Field List jv.r>
	//*  94  214:invokeinterface #203 <Method void kp.a(com.google.android.gms.c.a, zzwb, String, String, ks, zzacp, List)>
	//*  95  219:return          
	//*  96  220:aload_0         
	//*  97  221:getfield        #120 <Field kp r>
	//*  98  224:aload_0         
	//*  99  225:getfield        #57  <Field Context h>
	//* 100  228:invokestatic    #172 <Method com.google.android.gms.c.a d.a(Object)>
	//* 101  231:aload_0         
	//* 102  232:getfield        #94  <Field zzwf g>
	//* 103  235:aload_0         
	//* 104  236:getfield        #92  <Field zzwb f>
	//* 105  239:aload           4
	//* 106  241:aload_0         
	//* 107  242:getfield        #61  <Field jv e>
	//* 108  245:getfield        #183 <Field String jv.a>
	//* 109  248:aload_1         
	//* 110  249:invokeinterface #206 <Method void kp.a(com.google.android.gms.c.a, zzwf, zzwb, String, String, ks)>
	//* 111  254:return          
	//* 112  255:aload_0         
	//* 113  256:getfield        #120 <Field kp r>
	//* 114  259:aload_0         
	//* 115  260:getfield        #57  <Field Context h>
	//* 116  263:invokestatic    #172 <Method com.google.android.gms.c.a d.a(Object)>
	//* 117  266:aload_0         
	//* 118  267:getfield        #94  <Field zzwf g>
	//* 119  270:aload_0         
	//* 120  271:getfield        #92  <Field zzwb f>
	//* 121  274:aload           4
	//* 122  276:aload_0         
	//* 123  277:getfield        #61  <Field jv e>
	//* 124  280:getfield        #183 <Field String jv.a>
	//* 125  283:aload_1         
	//* 126  284:invokeinterface #206 <Method void kp.a(com.google.android.gms.c.a, zzwf, zzwb, String, String, ks)>
	//* 127  289:return          
	//* 128  290:new             #208 <Class ArrayList>
	//* 129  293:dup             
	//* 130  294:aload_0         
	//* 131  295:getfield        #104 <Field List m>
	//* 132  298:invokespecial   #211 <Method void ArrayList(java.util.Collection)>
	//* 133  301:astore          5
	//* 134  303:aload_0         
	//* 135  304:getfield        #106 <Field List n>
	//* 136  307:ifnull          436
	//* 137  310:aload_0         
	//* 138  311:getfield        #106 <Field List n>
	//* 139  314:invokeinterface #217 <Method Iterator List.iterator()>
	//* 140  319:astore          6
	//* 141  321:aload           6
	//* 142  323:invokeinterface #222 <Method boolean Iterator.hasNext()>
	//* 143  328:ifeq            436
	//* 144  331:aload           6
	//* 145  333:invokeinterface #226 <Method Object Iterator.next()>
	//* 146  338:checkcast       #65  <Class String>
	//* 147  341:astore          7
	//* 148  343:ldc1            #228 <String ":false">
	//* 149  345:astore_3        
	//* 150  346:aload_3         
	//* 151  347:astore_2        
	//* 152  348:aload_0         
	//* 153  349:getfield        #108 <Field List o>
	//* 154  352:ifnull          374
	//* 155  355:aload_3         
	//* 156  356:astore_2        
	//* 157  357:aload_0         
	//* 158  358:getfield        #108 <Field List o>
	//* 159  361:aload           7
	//* 160  363:invokeinterface #231 <Method boolean List.contains(Object)>
	//* 161  368:ifeq            374
	//* 162  371:ldc1            #233 <String ":true">
	//* 163  373:astore_2        
	//* 164  374:new             #235 <Class StringBuilder>
	//* 165  377:dup             
	//* 166  378:aload           7
	//* 167  380:invokestatic    #239 <Method String String.valueOf(Object)>
	//* 168  383:invokevirtual   #243 <Method int String.length()>
	//* 169  386:bipush          7
	//* 170  388:iadd            
	//* 171  389:aload_2         
	//* 172  390:invokestatic    #239 <Method String String.valueOf(Object)>
	//* 173  393:invokevirtual   #243 <Method int String.length()>
	//* 174  396:iadd            
	//* 175  397:invokespecial   #246 <Method void StringBuilder(int)>
	//* 176  400:astore_3        
	//* 177  401:aload_3         
	//* 178  402:ldc1            #248 <String "custom:">
	//* 179  404:invokevirtual   #252 <Method StringBuilder StringBuilder.append(String)>
	//* 180  407:pop             
	//* 181  408:aload_3         
	//* 182  409:aload           7
	//* 183  411:invokevirtual   #252 <Method StringBuilder StringBuilder.append(String)>
	//* 184  414:pop             
	//* 185  415:aload_3         
	//* 186  416:aload_2         
	//* 187  417:invokevirtual   #252 <Method StringBuilder StringBuilder.append(String)>
	//* 188  420:pop             
	//* 189  421:aload           5
	//* 190  423:aload_3         
	//* 191  424:invokevirtual   #253 <Method String StringBuilder.toString()>
	//* 192  427:invokeinterface #256 <Method boolean List.add(Object)>
	//* 193  432:pop             
	//* 194  433:goto            321
	//* 195  436:aload_0         
	//* 196  437:getfield        #120 <Field kp r>
	//* 197  440:aload_0         
	//* 198  441:getfield        #57  <Field Context h>
	//* 199  444:invokestatic    #172 <Method com.google.android.gms.c.a d.a(Object)>
	//* 200  447:aload_0         
	//* 201  448:getfield        #92  <Field zzwb f>
	//* 202  451:aload           4
	//* 203  453:aload_0         
	//* 204  454:getfield        #61  <Field jv e>
	//* 205  457:getfield        #183 <Field String jv.a>
	//* 206  460:aload_1         
	//* 207  461:aload_0         
	//* 208  462:getfield        #102 <Field zzacp l>
	//* 209  465:aload           5
	//* 210  467:invokeinterface #203 <Method void kp.a(com.google.android.gms.c.a, zzwb, String, String, ks, zzacp, List)>
	//* 211  472:return          
		// Misplaced declaration of an exception variable
		catch(jy jy1)
	//* 212  473:astore_1        
		{
			wx.c("Could not request ad from mediation adapter.", ((Throwable) (jy1)));
	//  213  474:ldc2            #258 <String "Could not request ad from mediation adapter.">
	//  214  477:aload_1         
	//  215  478:invokestatic    #261 <Method void wx.c(String, Throwable)>
		}
		break MISSING_BLOCK_LABEL_481;
		if(k || e.b())
			break MISSING_BLOCK_LABEL_290;
		if(g.d)
		{
			r.a(com.google.android.gms.c.d.a(((Object) (h))), f, s2, e.a, ((ks) (jy1)));
			return;
		}
		if(!p)
			break MISSING_BLOCK_LABEL_255;
		if(e.o != null)
		{
			r.a(com.google.android.gms.c.d.a(((Object) (h))), f, s2, e.a, ((ks) (jy1)), new zzacp(b(e.s)), e.r);
			return;
		}
		r.a(com.google.android.gms.c.d.a(((Object) (h))), g, f, s2, e.a, ((ks) (jy1)));
		return;
		r.a(com.google.android.gms.c.d.a(((Object) (h))), g, f, s2, e.a, ((ks) (jy1)));
		return;
		arraylist = new ArrayList(((java.util.Collection) (m)));
		if(n == null)
			break MISSING_BLOCK_LABEL_436;
		iterator = n.iterator();
_L1:
		if(!iterator.hasNext())
			break MISSING_BLOCK_LABEL_436;
		s3 = (String)iterator.next();
		obj = ":false";
		s1 = ((String) (obj));
		if(o == null)
			break MISSING_BLOCK_LABEL_374;
		s1 = ((String) (obj));
		if(o.contains(((Object) (s3))))
			s1 = ":true";
		obj = ((Object) (new StringBuilder(String.valueOf(((Object) (s3))).length() + 7 + String.valueOf(((Object) (s1))).length())));
		((StringBuilder) (obj)).append("custom:");
		((StringBuilder) (obj)).append(s3);
		((StringBuilder) (obj)).append(s1);
		((List) (arraylist)).add(((Object) (((StringBuilder) (obj)).toString())));
		  goto _L1
		r.a(com.google.android.gms.c.d.a(((Object) (h))), f, s2, e.a, ((ks) (jy1)), l, ((List) (arraylist)));
		return;
		a(5);
	//  216  481:aload_0         
	//  217  482:iconst_5        
	//  218  483:invokevirtual   #263 <Method void a(int)>
		return;
	//  219  486:return          
	}

	static void a(jz jz1, jy jy1)
	{
		jz1.a(jy1);
	//    0    0:aload_0         
	//    1    1:aload_1         
	//    2    2:invokespecial   #266 <Method void a(jy)>
	//    3    5:return          
	}

	static boolean a(jz jz1, int i1)
	{
		return jz1.b(1);
	//    0    0:aload_0         
	//    1    1:iconst_1        
	//    2    2:invokespecial   #130 <Method boolean b(int)>
	//    3    5:ireturn         
	}

	static int b(jz jz1)
	{
		return jz1.s;
	//    0    0:aload_0         
	//    1    1:getfield        #55  <Field int s>
	//    2    4:ireturn         
	}

	private static com.google.android.gms.ads.formats.e b(String s1)
	{
		f f1;
		f1 = new f();
	//    0    0:new             #270 <Class f>
	//    1    3:dup             
	//    2    4:invokespecial   #271 <Method void f()>
	//    3    7:astore_2        
		if(s1 == null)
	//*   4    8:aload_0         
	//*   5    9:ifnonnull       17
			return f1.a();
	//    6   12:aload_2         
	//    7   13:invokevirtual   #274 <Method com.google.android.gms.ads.formats.e f.a()>
	//    8   16:areturn         
		s1 = ((String) (new JSONObject(s1)));
	//    9   17:new             #132 <Class JSONObject>
	//   10   20:dup             
	//   11   21:aload_0         
	//   12   22:invokespecial   #135 <Method void JSONObject(String)>
	//   13   25:astore_0        
		byte byte0 = 0;
	//   14   26:iconst_0        
	//   15   27:istore_1        
		f1.b(((JSONObject) (s1)).optBoolean("multiple_images", false));
	//   16   28:aload_2         
	//   17   29:aload_0         
	//   18   30:ldc2            #276 <String "multiple_images">
	//   19   33:iconst_0        
	//   20   34:invokevirtual   #280 <Method boolean JSONObject.optBoolean(String, boolean)>
	//   21   37:invokevirtual   #283 <Method f f.b(boolean)>
	//   22   40:pop             
		f1.a(((JSONObject) (s1)).optBoolean("only_urls", false));
	//   23   41:aload_2         
	//   24   42:aload_0         
	//   25   43:ldc2            #285 <String "only_urls">
	//   26   46:iconst_0        
	//   27   47:invokevirtual   #280 <Method boolean JSONObject.optBoolean(String, boolean)>
	//   28   50:invokevirtual   #287 <Method f f.a(boolean)>
	//   29   53:pop             
		s1 = ((JSONObject) (s1)).optString("native_image_orientation", "any");
	//   30   54:aload_0         
	//   31   55:ldc2            #289 <String "native_image_orientation">
	//   32   58:ldc2            #291 <String "any">
	//   33   61:invokevirtual   #295 <Method String JSONObject.optString(String, String)>
	//   34   64:astore_0        
		if("landscape".equals(((Object) (s1))))
	//*  35   65:ldc2            #297 <String "landscape">
	//*  36   68:aload_0         
	//*  37   69:invokevirtual   #69  <Method boolean String.equals(Object)>
	//*  38   72:ifeq            80
		{
			byte0 = 2;
	//   39   75:iconst_2        
	//   40   76:istore_1        
			break MISSING_BLOCK_LABEL_108;
	//   41   77:goto            108
		}
		if("portrait".equals(((Object) (s1))))
	//*  42   80:ldc2            #299 <String "portrait">
	//*  43   83:aload_0         
	//*  44   84:invokevirtual   #69  <Method boolean String.equals(Object)>
	//*  45   87:ifeq            95
		{
			byte0 = 1;
	//   46   90:iconst_1        
	//   47   91:istore_1        
			break MISSING_BLOCK_LABEL_108;
	//   48   92:goto            108
		}
		if(!"any".equals(((Object) (s1))))
	//*  49   95:ldc2            #291 <String "any">
	//*  50   98:aload_0         
	//*  51   99:invokevirtual   #69  <Method boolean String.equals(Object)>
	//*  52  102:ifeq            130
	//*  53  105:goto            108
	//*  54  108:aload_2         
	//*  55  109:iload_1         
	//*  56  110:invokevirtual   #302 <Method f f.a(int)>
	//*  57  113:pop             
	//*  58  114:goto            125
	//*  59  117:astore_0        
	//*  60  118:ldc2            #304 <String "Exception occurred when creating native ad options">
	//*  61  121:aload_0         
	//*  62  122:invokestatic    #261 <Method void wx.c(String, Throwable)>
	//*  63  125:aload_2         
	//*  64  126:invokevirtual   #274 <Method com.google.android.gms.ads.formats.e f.a()>
	//*  65  129:areturn         
			byte0 = -1;
	//   66  130:iconst_m1       
	//   67  131:istore_1        
		try
		{
			f1.a(((int) (byte0)));
		}
		// Misplaced declaration of an exception variable
		catch(String s1)
		{
			wx.c("Exception occurred when creating native ad options", ((Throwable) (s1)));
		}
		return f1.a();
	//*  68  132:goto            108
	}

	private final String b()
	{
		if(!TextUtils.isEmpty(((CharSequence) (e.e))))
	//*   0    0:aload_0         
	//*   1    1:getfield        #61  <Field jv e>
	//*   2    4:getfield        #306 <Field String com.google.android.gms.internal.ads.jv.e>
	//*   3    7:invokestatic    #312 <Method boolean TextUtils.isEmpty(CharSequence)>
	//*   4   10:ifne            45
			if(b.b(e.e))
	//*   5   13:aload_0         
	//*   6   14:getfield        #59  <Field km b>
	//*   7   17:aload_0         
	//*   8   18:getfield        #61  <Field jv e>
	//*   9   21:getfield        #306 <Field String com.google.android.gms.internal.ads.jv.e>
	//*  10   24:invokeinterface #317 <Method boolean com.google.android.gms.internal.ads.km.b(String)>
	//*  11   29:ifeq            36
				return "com.google.android.gms.ads.mediation.customevent.CustomEventAdapter";
	//   12   32:ldc2            #319 <String "com.google.android.gms.ads.mediation.customevent.CustomEventAdapter">
	//   13   35:areturn         
			else
				return "com.google.ads.mediation.customevent.CustomEventAdapter";
	//   14   36:ldc1            #63  <String "com.google.ads.mediation.customevent.CustomEventAdapter">
	//   15   38:areturn         
		  goto _L1
_L3:
		com.google.android.gms.internal.ads.wx.e("Fail to determine the custom event's version, assuming the old one.");
	//   16   39:ldc2            #321 <String "Fail to determine the custom event's version, assuming the old one.">
	//   17   42:invokestatic    #150 <Method void com.google.android.gms.internal.ads.wx.e(String)>
_L1:
		return "com.google.ads.mediation.customevent.CustomEventAdapter";
	//   18   45:ldc1            #63  <String "com.google.ads.mediation.customevent.CustomEventAdapter">
	//   19   47:areturn         
		RemoteException remoteexception;
		remoteexception;
	//   20   48:astore_1        
		if(true) goto _L3; else goto _L2
_L2:
	//*  21   49:goto            39
	}

	private final boolean b(int i1)
	{
		Bundle bundle;
		if(k)
	//*   0    0:aload_0         
	//*   1    1:getfield        #98  <Field boolean k>
	//*   2    4:ifeq            20
		{
			bundle = r.l();
	//    3    7:aload_0         
	//    4    8:getfield        #120 <Field kp r>
	//    5   11:invokeinterface #324 <Method Bundle kp.l()>
	//    6   16:astore_2        
			break MISSING_BLOCK_LABEL_53;
	//    7   17:goto            53
		}
		if(g.d)
	//*   8   20:aload_0         
	//*   9   21:getfield        #94  <Field zzwf g>
	//*  10   24:getfield        #167 <Field boolean com.google.android.gms.internal.ads.zzwf.d>
	//*  11   27:ifeq            43
		{
			bundle = r.k();
	//   12   30:aload_0         
	//   13   31:getfield        #120 <Field kp r>
	//   14   34:invokeinterface #326 <Method Bundle kp.k()>
	//   15   39:astore_2        
			break MISSING_BLOCK_LABEL_53;
	//   16   40:goto            53
		}
		try
		{
			bundle = r.j();
	//   17   43:aload_0         
	//   18   44:getfield        #120 <Field kp r>
	//   19   47:invokeinterface #328 <Method Bundle kp.j()>
	//   20   52:astore_2        
		}
	//*  21   53:aload_2         
	//*  22   54:ifnull          75
	//*  23   57:aload_2         
	//*  24   58:ldc2            #330 <String "capabilities">
	//*  25   61:iconst_0        
	//*  26   62:invokevirtual   #336 <Method int Bundle.getInt(String, int)>
	//*  27   65:iload_1         
	//*  28   66:iand            
	//*  29   67:iload_1         
	//*  30   68:icmpne          73
	//*  31   71:iconst_1        
	//*  32   72:ireturn         
	//*  33   73:iconst_0        
	//*  34   74:ireturn         
	//*  35   75:iconst_0        
	//*  36   76:ireturn         
	//*  37   77:ldc2            #338 <String "Could not get adapter info. Returning false">
	//*  38   80:invokestatic    #150 <Method void com.google.android.gms.internal.ads.wx.e(String)>
	//*  39   83:iconst_0        
	//*  40   84:ireturn         
		// Misplaced declaration of an exception variable
		catch(RemoteException remoteexception)
		{
			com.google.android.gms.internal.ads.wx.e("Could not get adapter info. Returning false");
			return false;
		}
		RemoteException remoteexception;
		if(bundle != null)
			return (bundle.getInt("capabilities", 0) & i1) == i1;
		else
			return false;
	//*  41   85:astore_2        
	//*  42   86:goto            77
	}

	static kp c(jz jz1)
	{
		return jz1.d();
	//    0    0:aload_0         
	//    1    1:invokespecial   #342 <Method kp d()>
	//    2    4:areturn         
	}

	private final kv c()
	{
		if(s == 0 && e()) goto _L2; else goto _L1
	//    0    0:aload_0         
	//    1    1:getfield        #55  <Field int s>
	//    2    4:ifne            69
	//    3    7:aload_0         
	//    4    8:invokespecial   #127 <Method boolean e()>
	//    5   11:ifne            17
	//*   6   14:goto            69
_L2:
		if(!b(4) || t == null || t.a() == 0) goto _L4; else goto _L3
	//    7   17:aload_0         
	//    8   18:iconst_4        
	//    9   19:invokespecial   #130 <Method boolean b(int)>
	//   10   22:ifeq            57
	//   11   25:aload_0         
	//   12   26:getfield        #345 <Field kv t>
	//   13   29:ifnull          57
	//   14   32:aload_0         
	//   15   33:getfield        #345 <Field kv t>
	//   16   36:invokeinterface #349 <Method int kv.a()>
	//   17   41:ifeq            57
_L3:
		kv kv1 = t;
	//   18   44:aload_0         
	//   19   45:getfield        #345 <Field kv t>
	//   20   48:astore_1        
		return kv1;
	//   21   49:aload_1         
	//   22   50:areturn         
_L6:
		com.google.android.gms.internal.ads.wx.e("Could not get cpm value from MediationResponseMetadata");
	//   23   51:ldc2            #351 <String "Could not get cpm value from MediationResponseMetadata">
	//   24   54:invokestatic    #150 <Method void com.google.android.gms.internal.ads.wx.e(String)>
_L4:
		return ((kv) (new kb(f())));
	//   25   57:new             #353 <Class kb>
	//   26   60:dup             
	//   27   61:aload_0         
	//   28   62:invokespecial   #355 <Method int f()>
	//   29   65:invokespecial   #356 <Method void kb(int)>
	//   30   68:areturn         
_L1:
		return null;
	//   31   69:aconst_null     
	//   32   70:areturn         
		RemoteException remoteexception;
		remoteexception;
	//   33   71:astore_1        
		if(true) goto _L6; else goto _L5
_L5:
	//*  34   72:goto            51
	}

	private final kp d()
	{
		Object obj = ((Object) (String.valueOf(((Object) (a)))));
	//    0    0:aload_0         
	//    1    1:getfield        #74  <Field String a>
	//    2    4:invokestatic    #239 <Method String String.valueOf(Object)>
	//    3    7:astore_1        
		if(((String) (obj)).length() != 0)
	//*   4    8:aload_1         
	//*   5    9:invokevirtual   #243 <Method int String.length()>
	//*   6   12:ifeq            26
			obj = ((Object) ("Instantiating mediation adapter: ".concat(((String) (obj)))));
	//    7   15:ldc2            #358 <String "Instantiating mediation adapter: ">
	//    8   18:aload_1         
	//    9   19:invokevirtual   #361 <Method String String.concat(String)>
	//   10   22:astore_1        
		else
	//*  11   23:goto            37
			obj = ((Object) (new String("Instantiating mediation adapter: ")));
	//   12   26:new             #65  <Class String>
	//   13   29:dup             
	//   14   30:ldc2            #358 <String "Instantiating mediation adapter: ">
	//   15   33:invokespecial   #362 <Method void String(String)>
	//   16   36:astore_1        
		com.google.android.gms.internal.ads.wx.d(((String) (obj)));
	//   17   37:aload_1         
	//   18   38:invokestatic    #364 <Method void com.google.android.gms.internal.ads.wx.d(String)>
		if(!k && !e.b())
	//*  19   41:aload_0         
	//*  20   42:getfield        #98  <Field boolean k>
	//*  21   45:ifne            134
	//*  22   48:aload_0         
	//*  23   49:getfield        #61  <Field jv e>
	//*  24   52:invokevirtual   #182 <Method boolean com.google.android.gms.internal.ads.jv.b()>
	//*  25   55:ifne            134
		{
			if("com.google.ads.mediation.admob.AdMobAdapter".equals(((Object) (a))))
	//*  26   58:ldc2            #366 <String "com.google.ads.mediation.admob.AdMobAdapter">
	//*  27   61:aload_0         
	//*  28   62:getfield        #74  <Field String a>
	//*  29   65:invokevirtual   #69  <Method boolean String.equals(Object)>
	//*  30   68:ifeq            82
				return a(((b) (new AdMobAdapter())));
	//   31   71:new             #368 <Class AdMobAdapter>
	//   32   74:dup             
	//   33   75:invokespecial   #369 <Method void AdMobAdapter()>
	//   34   78:invokestatic    #371 <Method kp a(b)>
	//   35   81:areturn         
			if("com.google.ads.mediation.AdUrlAdapter".equals(((Object) (a))))
	//*  36   82:ldc2            #373 <String "com.google.ads.mediation.AdUrlAdapter">
	//*  37   85:aload_0         
	//*  38   86:getfield        #74  <Field String a>
	//*  39   89:invokevirtual   #69  <Method boolean String.equals(Object)>
	//*  40   92:ifeq            106
				return a(((b) (new AdUrlAdapter())));
	//   41   95:new             #375 <Class AdUrlAdapter>
	//   42   98:dup             
	//   43   99:invokespecial   #376 <Method void AdUrlAdapter()>
	//   44  102:invokestatic    #371 <Method kp a(b)>
	//   45  105:areturn         
			if("com.google.ads.mediation.admob.AdMobCustomTabsAdapter".equals(((Object) (a))))
	//*  46  106:ldc2            #378 <String "com.google.ads.mediation.admob.AdMobCustomTabsAdapter">
	//*  47  109:aload_0         
	//*  48  110:getfield        #74  <Field String a>
	//*  49  113:invokevirtual   #69  <Method boolean String.equals(Object)>
	//*  50  116:ifeq            134
				return ((kp) (new lk(((b) (new zzanu())))));
	//   51  119:new             #114 <Class lk>
	//   52  122:dup             
	//   53  123:new             #380 <Class zzanu>
	//   54  126:dup             
	//   55  127:invokespecial   #381 <Method void zzanu()>
	//   56  130:invokespecial   #117 <Method void lk(b)>
	//   57  133:areturn         
		}
		try
		{
			obj = ((Object) (b.a(a)));
	//   58  134:aload_0         
	//   59  135:getfield        #59  <Field km b>
	//   60  138:aload_0         
	//   61  139:getfield        #74  <Field String a>
	//   62  142:invokeinterface #384 <Method kp km.a(String)>
	//   63  147:astore_1        
		}
	//*  64  148:aload_1         
	//*  65  149:areturn         
		catch(RemoteException remoteexception)
	//*  66  150:astore_2        
		{
			String s1 = String.valueOf(((Object) (a)));
	//   67  151:aload_0         
	//   68  152:getfield        #74  <Field String a>
	//   69  155:invokestatic    #239 <Method String String.valueOf(Object)>
	//   70  158:astore_1        
			if(s1.length() != 0)
	//*  71  159:aload_1         
	//*  72  160:invokevirtual   #243 <Method int String.length()>
	//*  73  163:ifeq            177
				s1 = "Could not instantiate mediation adapter: ".concat(s1);
	//   74  166:ldc2            #386 <String "Could not instantiate mediation adapter: ">
	//   75  169:aload_1         
	//   76  170:invokevirtual   #361 <Method String String.concat(String)>
	//   77  173:astore_1        
			else
	//*  78  174:goto            188
				s1 = new String("Could not instantiate mediation adapter: ");
	//   79  177:new             #65  <Class String>
	//   80  180:dup             
	//   81  181:ldc2            #386 <String "Could not instantiate mediation adapter: ">
	//   82  184:invokespecial   #362 <Method void String(String)>
	//   83  187:astore_1        
			wx.a(s1, ((Throwable) (remoteexception)));
	//   84  188:aload_1         
	//   85  189:aload_2         
	//   86  190:invokestatic    #388 <Method void wx.a(String, Throwable)>
			return null;
	//   87  193:aconst_null     
	//   88  194:areturn         
		}
		return ((kp) (obj));
	}

	static kp d(jz jz1)
	{
		return jz1.r;
	//    0    0:aload_0         
	//    1    1:getfield        #120 <Field kp r>
	//    2    4:areturn         
	}

	private final boolean e()
	{
		return d.m != -1;
	//    0    0:aload_0         
	//    1    1:getfield        #76  <Field jw d>
	//    2    4:getfield        #390 <Field int jw.m>
	//    3    7:iconst_m1       
	//    4    8:icmpeq          13
	//    5   11:iconst_1        
	//    6   12:ireturn         
	//    7   13:iconst_0        
	//    8   14:ireturn         
	}

	static boolean e(jz jz1)
	{
		return jz1.e();
	//    0    0:aload_0         
	//    1    1:invokespecial   #127 <Method boolean e()>
	//    2    4:ireturn         
	}

	private final int f()
	{
		JSONException jsonexception;
		if(e.k == null)
	//*   0    0:aload_0         
	//*   1    1:getfield        #61  <Field jv e>
	//*   2    4:getfield        #156 <Field String jv.k>
	//*   3    7:ifnonnull       12
			return 0;
	//    4   10:iconst_0        
	//    5   11:ireturn         
		int i1;
		int j1;
		JSONObject jsonobject;
		try
		{
			jsonobject = new JSONObject(e.k);
	//    6   12:new             #132 <Class JSONObject>
	//    7   15:dup             
	//    8   16:aload_0         
	//    9   17:getfield        #61  <Field jv e>
	//   10   20:getfield        #156 <Field String jv.k>
	//   11   23:invokespecial   #135 <Method void JSONObject(String)>
	//   12   26:astore_3        
		}
	//*  13   27:ldc2            #366 <String "com.google.ads.mediation.admob.AdMobAdapter">
	//*  14   30:aload_0         
	//*  15   31:getfield        #74  <Field String a>
	//*  16   34:invokevirtual   #69  <Method boolean String.equals(Object)>
	//*  17   37:ifeq            49
	//*  18   40:aload_3         
	//*  19   41:ldc2            #393 <String "cpm_cents">
	//*  20   44:iconst_0        
	//*  21   45:invokevirtual   #396 <Method int JSONObject.optInt(String, int)>
	//*  22   48:ireturn         
	//*  23   49:aload_0         
	//*  24   50:iconst_2        
	//*  25   51:invokespecial   #130 <Method boolean b(int)>
	//*  26   54:ifeq            68
	//*  27   57:aload_3         
	//*  28   58:ldc1            #137 <String "cpm_floor_cents">
	//*  29   60:iconst_0        
	//*  30   61:invokevirtual   #396 <Method int JSONObject.optInt(String, int)>
	//*  31   64:istore_1        
	//*  32   65:goto            70
	//*  33   68:iconst_0        
	//*  34   69:istore_1        
	//*  35   70:iload_1         
	//*  36   71:istore_2        
	//*  37   72:iload_1         
	//*  38   73:ifne            85
	//*  39   76:aload_3         
	//*  40   77:ldc2            #398 <String "penalized_average_cpm_cents">
	//*  41   80:iconst_0        
	//*  42   81:invokevirtual   #396 <Method int JSONObject.optInt(String, int)>
	//*  43   84:istore_2        
	//*  44   85:iload_2         
	//*  45   86:ireturn         
	//*  46   87:ldc2            #400 <String "Could not convert to json. Returning 0">
	//*  47   90:invokestatic    #150 <Method void com.google.android.gms.internal.ads.wx.e(String)>
	//*  48   93:iconst_0        
	//*  49   94:ireturn         
		// Misplaced declaration of an exception variable
		catch(JSONException jsonexception)
		{
			com.google.android.gms.internal.ads.wx.e("Could not convert to json. Returning 0");
			return 0;
		}
		if("com.google.ads.mediation.admob.AdMobAdapter".equals(((Object) (a))))
			return jsonobject.optInt("cpm_cents", 0);
		if(b(2))
			i1 = jsonobject.optInt("cpm_floor_cents", 0);
		else
			i1 = 0;
		j1 = i1;
		if(i1 == 0)
			j1 = jsonobject.optInt("penalized_average_cpm_cents", 0);
		return j1;
	//*  50   95:astore_3        
	//*  51   96:goto            87
	}

	static String f(jz jz1)
	{
		return jz1.a;
	//    0    0:aload_0         
	//    1    1:getfield        #74  <Field String a>
	//    2    4:areturn         
	}

	public final kc a(long l1, long l2)
	{
		Object obj = i;
	//    0    0:aload_0         
	//    1    1:getfield        #53  <Field Object i>
	//    2    4:astore          13
		obj;
	//    3    6:aload           13
		JVM INSTR monitorenter ;
	//    4    8:monitorenter    
		long l3;
		long l4;
		Object obj1;
		l3 = SystemClock.elapsedRealtime();
	//    5    9:invokestatic    #410 <Method long SystemClock.elapsedRealtime()>
	//    6   12:lstore          5
		obj1 = ((Object) (new jy()));
	//    7   14:new             #412 <Class jy>
	//    8   17:dup             
	//    9   18:invokespecial   #413 <Method void jy()>
	//   10   21:astore          14
		xg.a.post(((Runnable) (new ka(this, ((jy) (obj1))))));
	//   11   23:getstatic       #418 <Field Handler xg.a>
	//   12   26:new             #420 <Class ka>
	//   13   29:dup             
	//   14   30:aload_0         
	//   15   31:aload           14
	//   16   33:invokespecial   #422 <Method void ka(jz, jy)>
	//   17   36:invokevirtual   #428 <Method boolean Handler.post(Runnable)>
	//   18   39:pop             
		l4 = c;
	//   19   40:aload_0         
	//   20   41:getfield        #84  <Field long c>
	//   21   44:lstore          7
_L5:
		if(s == -2) goto _L2; else goto _L1
	//   22   46:aload_0         
	//   23   47:getfield        #55  <Field int s>
	//   24   50:bipush          -2
	//   25   52:icmpeq          105
_L1:
		l1 = aw.l().b();
	//   26   55:invokestatic    #433 <Method e aw.l()>
	//   27   58:invokeinterface #437 <Method long e.b()>
	//   28   63:lstore_1        
		obj1 = ((Object) (new kc(e, r, a, ((jy) (obj1)), s, c(), l1 - l3)));
	//   29   64:new             #439 <Class kc>
	//   30   67:dup             
	//   31   68:aload_0         
	//   32   69:getfield        #61  <Field jv e>
	//   33   72:aload_0         
	//   34   73:getfield        #120 <Field kp r>
	//   35   76:aload_0         
	//   36   77:getfield        #74  <Field String a>
	//   37   80:aload           14
	//   38   82:aload_0         
	//   39   83:getfield        #55  <Field int s>
	//   40   86:aload_0         
	//   41   87:invokespecial   #441 <Method kv c()>
	//   42   90:lload_1         
	//   43   91:lload           5
	//   44   93:lsub            
	//   45   94:invokespecial   #444 <Method void kc(jv, kp, String, jy, int, kv, long)>
	//   46   97:astore          14
	//*  47   99:aload           13
		return ((kc) (obj1));
	//   48  101:monitorexit     
	//   49  102:aload           14
	//   50  104:areturn         
_L2:
		long l6 = SystemClock.elapsedRealtime();
	//   51  105:invokestatic    #410 <Method long SystemClock.elapsedRealtime()>
	//   52  108:lstore          11
		long l5;
		l5 = l4 - (l6 - l3);
	//   53  110:lload           7
	//   54  112:lload           11
	//   55  114:lload           5
	//   56  116:lsub            
	//   57  117:lsub            
	//   58  118:lstore          9
		l6 = l2 - (l6 - l1);
	//   59  120:lload_3         
	//   60  121:lload           11
	//   61  123:lload_1         
	//   62  124:lsub            
	//   63  125:lsub            
	//   64  126:lstore          11
		if(l5 > 0L && l6 > 0L) goto _L4; else goto _L3
	//   65  128:lload           9
	//   66  130:lconst_0        
	//   67  131:lcmp            
	//   68  132:ifle            170
	//   69  135:lload           11
	//   70  137:lconst_0        
	//   71  138:lcmp            
	//   72  139:ifgt            145
	//*  73  142:goto            170
_L4:
		i.wait(Math.min(l5, l6));
	//   74  145:aload_0         
	//   75  146:getfield        #53  <Field Object i>
	//   76  149:lload           9
	//   77  151:lload           11
	//   78  153:invokestatic    #450 <Method long Math.min(long, long)>
	//   79  156:invokevirtual   #454 <Method void Object.wait(long)>
		  goto _L5
	//*  80  159:goto            46
_L6:
		s = 5;
	//   81  162:aload_0         
	//   82  163:iconst_5        
	//   83  164:putfield        #55  <Field int s>
		  goto _L5
	//*  84  167:goto            46
_L3:
		com.google.android.gms.internal.ads.wx.d("Timed out waiting for adapter.");
	//   85  170:ldc2            #456 <String "Timed out waiting for adapter.">
	//   86  173:invokestatic    #364 <Method void com.google.android.gms.internal.ads.wx.d(String)>
		s = 3;
	//   87  176:aload_0         
	//   88  177:iconst_3        
	//   89  178:putfield        #55  <Field int s>
		  goto _L5
	//*  90  181:goto            46
		Exception exception;
		exception;
	//   91  184:astore          14
		obj;
	//   92  186:aload           13
		JVM INSTR monitorexit ;
	//   93  188:monitorexit     
		throw exception;
	//   94  189:aload           14
	//   95  191:athrow          
		InterruptedException interruptedexception;
		interruptedexception;
	//   96  192:astore          15
		  goto _L6
	//*  97  194:goto            162
	}

	public final void a()
	{
		Object obj = i;
	//    0    0:aload_0         
	//    1    1:getfield        #53  <Field Object i>
	//    2    4:astore_1        
		obj;
	//    3    5:aload_1         
		JVM INSTR monitorenter ;
	//    4    6:monitorenter    
		Object obj1;
		try
		{
			if(r != null)
	//*   5    7:aload_0         
	//*   6    8:getfield        #120 <Field kp r>
	//*   7   11:ifnull          38
				r.c();
	//    8   14:aload_0         
	//    9   15:getfield        #120 <Field kp r>
	//   10   18:invokeinterface #458 <Method void kp.c()>
			break MISSING_BLOCK_LABEL_38;
	//   11   23:goto            38
		}
	//*  12   26:astore_2        
	//*  13   27:goto            53
		// Misplaced declaration of an exception variable
		catch(Object obj1) { }
	//   14   30:astore_2        
		break MISSING_BLOCK_LABEL_31;
		obj1;
		break MISSING_BLOCK_LABEL_53;
		wx.c("Could not destroy mediation adapter.", ((Throwable) (obj1)));
	//   15   31:ldc2            #460 <String "Could not destroy mediation adapter.">
	//   16   34:aload_2         
	//   17   35:invokestatic    #261 <Method void wx.c(String, Throwable)>
		s = -1;
	//   18   38:aload_0         
	//   19   39:iconst_m1       
	//   20   40:putfield        #55  <Field int s>
		i.notify();
	//   21   43:aload_0         
	//   22   44:getfield        #53  <Field Object i>
	//   23   47:invokevirtual   #463 <Method void Object.notify()>
		obj;
	//   24   50:aload_1         
		JVM INSTR monitorexit ;
	//   25   51:monitorexit     
		return;
	//   26   52:return          
		obj;
	//   27   53:aload_1         
		JVM INSTR monitorexit ;
	//   28   54:monitorexit     
		throw obj1;
	//   29   55:aload_2         
	//   30   56:athrow          
	}

	public final void a(int i1)
	{
		synchronized(i)
	//*   0    0:aload_0         
	//*   1    1:getfield        #53  <Field Object i>
	//*   2    4:astore_2        
	//*   3    5:aload_2         
	//*   4    6:monitorenter    
		{
			s = i1;
	//    5    7:aload_0         
	//    6    8:iload_1         
	//    7    9:putfield        #55  <Field int s>
			i.notify();
	//    8   12:aload_0         
	//    9   13:getfield        #53  <Field Object i>
	//   10   16:invokevirtual   #463 <Method void Object.notify()>
		}
	//   11   19:aload_2         
	//   12   20:monitorexit     
		return;
	//   13   21:return          
		exception;
	//   14   22:astore_3        
		obj;
	//   15   23:aload_2         
		JVM INSTR monitorexit ;
	//   16   24:monitorexit     
		throw exception;
	//   17   25:aload_3         
	//   18   26:athrow          
	}

	public final void a(int i1, kv kv1)
	{
		synchronized(i)
	//*   0    0:aload_0         
	//*   1    1:getfield        #53  <Field Object i>
	//*   2    4:astore_3        
	//*   3    5:aload_3         
	//*   4    6:monitorenter    
		{
			s = 0;
	//    5    7:aload_0         
	//    6    8:iconst_0        
	//    7    9:putfield        #55  <Field int s>
			t = kv1;
	//    8   12:aload_0         
	//    9   13:aload_2         
	//   10   14:putfield        #345 <Field kv t>
			i.notify();
	//   11   17:aload_0         
	//   12   18:getfield        #53  <Field Object i>
	//   13   21:invokevirtual   #463 <Method void Object.notify()>
		}
	//   14   24:aload_3         
	//   15   25:monitorexit     
		return;
	//   16   26:return          
		kv1;
	//   17   27:astore_2        
		obj;
	//   18   28:aload_3         
		JVM INSTR monitorexit ;
	//   19   29:monitorexit     
		throw kv1;
	//   20   30:aload_2         
	//   21   31:athrow          
	}

	private final String a;
	private final km b;
	private final long c;
	private final jw d;
	private final jv e;
	private zzwb f;
	private final zzwf g;
	private final Context h;
	private final Object i = new Object();
	private final zzbbi j;
	private final boolean k;
	private final zzacp l;
	private final List m;
	private final List n;
	private final List o;
	private final boolean p;
	private final boolean q;
	private kp r;
	private int s;
	private kv t;
}
