// Decompiled by Jad v1.5.8g. Copyright 2001 Pavel Kouznetsov.
// Jad home page: http://www.kpdus.com/jad.html
// Decompiler options: packimports(3) annotate safe 

package com.google.android.gms.internal.ads;

import android.location.Location;
import android.os.Bundle;
import android.os.Parcel;
import com.google.android.gms.common.internal.ak;
import com.google.android.gms.common.internal.safeparcel.AbstractSafeParcelable;
import com.google.android.gms.common.internal.safeparcel.c;
import java.util.List;

// Referenced classes of package com.google.android.gms.internal.ads:
//			bvv, zzzs, zzvv

public final class zzwb extends AbstractSafeParcelable
{

	public zzwb(int i1, long l1, Bundle bundle, int j1, List list, boolean flag, 
			int k1, boolean flag1, String s1, zzzs zzzs, Location location, String s2, Bundle bundle1, 
			Bundle bundle2, List list1, String s3, String s4, boolean flag2, zzvv zzvv, int i2, 
			String s5)
	{
	//    0    0:aload_0         
	//    1    1:invokespecial   #51  <Method void AbstractSafeParcelable()>
		a = i1;
	//    2    4:aload_0         
	//    3    5:iload_1         
	//    4    6:putfield        #53  <Field int a>
		b = l1;
	//    5    9:aload_0         
	//    6   10:lload_2         
	//    7   11:putfield        #55  <Field long b>
		if(bundle == null)
	//*   8   14:aload           4
	//*   9   16:ifnonnull       31
			bundle = new Bundle();
	//   10   19:new             #57  <Class Bundle>
	//   11   22:dup             
	//   12   23:invokespecial   #58  <Method void Bundle()>
	//   13   26:astore          4
	//*  14   28:goto            31
		c = bundle;
	//   15   31:aload_0         
	//   16   32:aload           4
	//   17   34:putfield        #60  <Field Bundle c>
		d = j1;
	//   18   37:aload_0         
	//   19   38:iload           5
	//   20   40:putfield        #62  <Field int d>
		e = list;
	//   21   43:aload_0         
	//   22   44:aload           6
	//   23   46:putfield        #64  <Field List e>
		f = flag;
	//   24   49:aload_0         
	//   25   50:iload           7
	//   26   52:putfield        #66  <Field boolean f>
		g = k1;
	//   27   55:aload_0         
	//   28   56:iload           8
	//   29   58:putfield        #68  <Field int g>
		h = flag1;
	//   30   61:aload_0         
	//   31   62:iload           9
	//   32   64:putfield        #70  <Field boolean h>
		i = s1;
	//   33   67:aload_0         
	//   34   68:aload           10
	//   35   70:putfield        #72  <Field String i>
		j = zzzs;
	//   36   73:aload_0         
	//   37   74:aload           11
	//   38   76:putfield        #74  <Field zzzs j>
		k = location;
	//   39   79:aload_0         
	//   40   80:aload           12
	//   41   82:putfield        #76  <Field Location k>
		l = s2;
	//   42   85:aload_0         
	//   43   86:aload           13
	//   44   88:putfield        #78  <Field String l>
		if(bundle1 == null)
	//*  45   91:aload           14
	//*  46   93:ifnonnull       108
			bundle1 = new Bundle();
	//   47   96:new             #57  <Class Bundle>
	//   48   99:dup             
	//   49  100:invokespecial   #58  <Method void Bundle()>
	//   50  103:astore          14
	//*  51  105:goto            108
		m = bundle1;
	//   52  108:aload_0         
	//   53  109:aload           14
	//   54  111:putfield        #80  <Field Bundle m>
		n = bundle2;
	//   55  114:aload_0         
	//   56  115:aload           15
	//   57  117:putfield        #82  <Field Bundle n>
		o = list1;
	//   58  120:aload_0         
	//   59  121:aload           16
	//   60  123:putfield        #84  <Field List o>
		p = s3;
	//   61  126:aload_0         
	//   62  127:aload           17
	//   63  129:putfield        #86  <Field String p>
		q = s4;
	//   64  132:aload_0         
	//   65  133:aload           18
	//   66  135:putfield        #88  <Field String q>
		r = flag2;
	//   67  138:aload_0         
	//   68  139:iload           19
	//   69  141:putfield        #90  <Field boolean r>
		s = zzvv;
	//   70  144:aload_0         
	//   71  145:aload           20
	//   72  147:putfield        #92  <Field zzvv s>
		t = i2;
	//   73  150:aload_0         
	//   74  151:iload           21
	//   75  153:putfield        #94  <Field int t>
		u = s5;
	//   76  156:aload_0         
	//   77  157:aload           22
	//   78  159:putfield        #96  <Field String u>
	//   79  162:return          
	}

	public final zzwb a()
	{
		Bundle bundle = m.getBundle("com.google.ads.mediation.admob.AdMobAdapter");
	//    0    0:aload_0         
	//    1    1:getfield        #80  <Field Bundle m>
	//    2    4:ldc1            #100 <String "com.google.ads.mediation.admob.AdMobAdapter">
	//    3    6:invokevirtual   #104 <Method Bundle Bundle.getBundle(String)>
	//    4    9:astore_1        
		if(bundle == null)
	//*   5   10:aload_1         
	//*   6   11:ifnonnull       32
		{
			bundle = c;
	//    7   14:aload_0         
	//    8   15:getfield        #60  <Field Bundle c>
	//    9   18:astore_1        
			m.putBundle("com.google.ads.mediation.admob.AdMobAdapter", bundle);
	//   10   19:aload_0         
	//   11   20:getfield        #80  <Field Bundle m>
	//   12   23:ldc1            #100 <String "com.google.ads.mediation.admob.AdMobAdapter">
	//   13   25:aload_1         
	//   14   26:invokevirtual   #108 <Method void Bundle.putBundle(String, Bundle)>
		}
	//*  15   29:goto            32
		return new zzwb(a, b, bundle, d, e, f, g, h, i, j, k, l, m, n, o, p, q, r, s, t, u);
	//   16   32:new             #2   <Class zzwb>
	//   17   35:dup             
	//   18   36:aload_0         
	//   19   37:getfield        #53  <Field int a>
	//   20   40:aload_0         
	//   21   41:getfield        #55  <Field long b>
	//   22   44:aload_1         
	//   23   45:aload_0         
	//   24   46:getfield        #62  <Field int d>
	//   25   49:aload_0         
	//   26   50:getfield        #64  <Field List e>
	//   27   53:aload_0         
	//   28   54:getfield        #66  <Field boolean f>
	//   29   57:aload_0         
	//   30   58:getfield        #68  <Field int g>
	//   31   61:aload_0         
	//   32   62:getfield        #70  <Field boolean h>
	//   33   65:aload_0         
	//   34   66:getfield        #72  <Field String i>
	//   35   69:aload_0         
	//   36   70:getfield        #74  <Field zzzs j>
	//   37   73:aload_0         
	//   38   74:getfield        #76  <Field Location k>
	//   39   77:aload_0         
	//   40   78:getfield        #78  <Field String l>
	//   41   81:aload_0         
	//   42   82:getfield        #80  <Field Bundle m>
	//   43   85:aload_0         
	//   44   86:getfield        #82  <Field Bundle n>
	//   45   89:aload_0         
	//   46   90:getfield        #84  <Field List o>
	//   47   93:aload_0         
	//   48   94:getfield        #86  <Field String p>
	//   49   97:aload_0         
	//   50   98:getfield        #88  <Field String q>
	//   51  101:aload_0         
	//   52  102:getfield        #90  <Field boolean r>
	//   53  105:aload_0         
	//   54  106:getfield        #92  <Field zzvv s>
	//   55  109:aload_0         
	//   56  110:getfield        #94  <Field int t>
	//   57  113:aload_0         
	//   58  114:getfield        #96  <Field String u>
	//   59  117:invokespecial   #110 <Method void zzwb(int, long, Bundle, int, List, boolean, int, boolean, String, zzzs, Location, String, Bundle, Bundle, List, String, String, boolean, zzvv, int, String)>
	//   60  120:areturn         
	}

	public final boolean equals(Object obj)
	{
		if(!(obj instanceof zzwb))
	//*   0    0:aload_1         
	//*   1    1:instanceof      #2   <Class zzwb>
	//*   2    4:ifne            9
			return false;
	//    3    7:iconst_0        
	//    4    8:ireturn         
		obj = ((Object) ((zzwb)obj));
	//    5    9:aload_1         
	//    6   10:checkcast       #2   <Class zzwb>
	//    7   13:astore_1        
		return a == ((zzwb) (obj)).a && b == ((zzwb) (obj)).b && ak.a(((Object) (c)), ((Object) (((zzwb) (obj)).c))) && d == ((zzwb) (obj)).d && ak.a(((Object) (e)), ((Object) (((zzwb) (obj)).e))) && f == ((zzwb) (obj)).f && g == ((zzwb) (obj)).g && h == ((zzwb) (obj)).h && ak.a(((Object) (i)), ((Object) (((zzwb) (obj)).i))) && ak.a(((Object) (j)), ((Object) (((zzwb) (obj)).j))) && ak.a(((Object) (k)), ((Object) (((zzwb) (obj)).k))) && ak.a(((Object) (l)), ((Object) (((zzwb) (obj)).l))) && ak.a(((Object) (m)), ((Object) (((zzwb) (obj)).m))) && ak.a(((Object) (n)), ((Object) (((zzwb) (obj)).n))) && ak.a(((Object) (o)), ((Object) (((zzwb) (obj)).o))) && ak.a(((Object) (p)), ((Object) (((zzwb) (obj)).p))) && ak.a(((Object) (q)), ((Object) (((zzwb) (obj)).q))) && r == ((zzwb) (obj)).r && t == ((zzwb) (obj)).t && ak.a(((Object) (u)), ((Object) (((zzwb) (obj)).u)));
	//    8   14:aload_0         
	//    9   15:getfield        #53  <Field int a>
	//   10   18:aload_1         
	//   11   19:getfield        #53  <Field int a>
	//   12   22:icmpne          273
	//   13   25:aload_0         
	//   14   26:getfield        #55  <Field long b>
	//   15   29:aload_1         
	//   16   30:getfield        #55  <Field long b>
	//   17   33:lcmp            
	//   18   34:ifne            273
	//   19   37:aload_0         
	//   20   38:getfield        #60  <Field Bundle c>
	//   21   41:aload_1         
	//   22   42:getfield        #60  <Field Bundle c>
	//   23   45:invokestatic    #117 <Method boolean ak.a(Object, Object)>
	//   24   48:ifeq            273
	//   25   51:aload_0         
	//   26   52:getfield        #62  <Field int d>
	//   27   55:aload_1         
	//   28   56:getfield        #62  <Field int d>
	//   29   59:icmpne          273
	//   30   62:aload_0         
	//   31   63:getfield        #64  <Field List e>
	//   32   66:aload_1         
	//   33   67:getfield        #64  <Field List e>
	//   34   70:invokestatic    #117 <Method boolean ak.a(Object, Object)>
	//   35   73:ifeq            273
	//   36   76:aload_0         
	//   37   77:getfield        #66  <Field boolean f>
	//   38   80:aload_1         
	//   39   81:getfield        #66  <Field boolean f>
	//   40   84:icmpne          273
	//   41   87:aload_0         
	//   42   88:getfield        #68  <Field int g>
	//   43   91:aload_1         
	//   44   92:getfield        #68  <Field int g>
	//   45   95:icmpne          273
	//   46   98:aload_0         
	//   47   99:getfield        #70  <Field boolean h>
	//   48  102:aload_1         
	//   49  103:getfield        #70  <Field boolean h>
	//   50  106:icmpne          273
	//   51  109:aload_0         
	//   52  110:getfield        #72  <Field String i>
	//   53  113:aload_1         
	//   54  114:getfield        #72  <Field String i>
	//   55  117:invokestatic    #117 <Method boolean ak.a(Object, Object)>
	//   56  120:ifeq            273
	//   57  123:aload_0         
	//   58  124:getfield        #74  <Field zzzs j>
	//   59  127:aload_1         
	//   60  128:getfield        #74  <Field zzzs j>
	//   61  131:invokestatic    #117 <Method boolean ak.a(Object, Object)>
	//   62  134:ifeq            273
	//   63  137:aload_0         
	//   64  138:getfield        #76  <Field Location k>
	//   65  141:aload_1         
	//   66  142:getfield        #76  <Field Location k>
	//   67  145:invokestatic    #117 <Method boolean ak.a(Object, Object)>
	//   68  148:ifeq            273
	//   69  151:aload_0         
	//   70  152:getfield        #78  <Field String l>
	//   71  155:aload_1         
	//   72  156:getfield        #78  <Field String l>
	//   73  159:invokestatic    #117 <Method boolean ak.a(Object, Object)>
	//   74  162:ifeq            273
	//   75  165:aload_0         
	//   76  166:getfield        #80  <Field Bundle m>
	//   77  169:aload_1         
	//   78  170:getfield        #80  <Field Bundle m>
	//   79  173:invokestatic    #117 <Method boolean ak.a(Object, Object)>
	//   80  176:ifeq            273
	//   81  179:aload_0         
	//   82  180:getfield        #82  <Field Bundle n>
	//   83  183:aload_1         
	//   84  184:getfield        #82  <Field Bundle n>
	//   85  187:invokestatic    #117 <Method boolean ak.a(Object, Object)>
	//   86  190:ifeq            273
	//   87  193:aload_0         
	//   88  194:getfield        #84  <Field List o>
	//   89  197:aload_1         
	//   90  198:getfield        #84  <Field List o>
	//   91  201:invokestatic    #117 <Method boolean ak.a(Object, Object)>
	//   92  204:ifeq            273
	//   93  207:aload_0         
	//   94  208:getfield        #86  <Field String p>
	//   95  211:aload_1         
	//   96  212:getfield        #86  <Field String p>
	//   97  215:invokestatic    #117 <Method boolean ak.a(Object, Object)>
	//   98  218:ifeq            273
	//   99  221:aload_0         
	//  100  222:getfield        #88  <Field String q>
	//  101  225:aload_1         
	//  102  226:getfield        #88  <Field String q>
	//  103  229:invokestatic    #117 <Method boolean ak.a(Object, Object)>
	//  104  232:ifeq            273
	//  105  235:aload_0         
	//  106  236:getfield        #90  <Field boolean r>
	//  107  239:aload_1         
	//  108  240:getfield        #90  <Field boolean r>
	//  109  243:icmpne          273
	//  110  246:aload_0         
	//  111  247:getfield        #94  <Field int t>
	//  112  250:aload_1         
	//  113  251:getfield        #94  <Field int t>
	//  114  254:icmpne          273
	//  115  257:aload_0         
	//  116  258:getfield        #96  <Field String u>
	//  117  261:aload_1         
	//  118  262:getfield        #96  <Field String u>
	//  119  265:invokestatic    #117 <Method boolean ak.a(Object, Object)>
	//  120  268:ifeq            273
	//  121  271:iconst_1        
	//  122  272:ireturn         
	//  123  273:iconst_0        
	//  124  274:ireturn         
	}

	public final int hashCode()
	{
		return ak.a(new Object[] {
			Integer.valueOf(a), Long.valueOf(b), c, Integer.valueOf(d), e, Boolean.valueOf(f), Integer.valueOf(g), Boolean.valueOf(h), i, j, 
			k, l, m, n, o, p, q, Boolean.valueOf(r), Integer.valueOf(t), u
		});
	//    0    0:bipush          20
	//    1    2:anewarray       Object[]
	//    2    5:dup             
	//    3    6:iconst_0        
	//    4    7:aload_0         
	//    5    8:getfield        #53  <Field int a>
	//    6   11:invokestatic    #127 <Method Integer Integer.valueOf(int)>
	//    7   14:aastore         
	//    8   15:dup             
	//    9   16:iconst_1        
	//   10   17:aload_0         
	//   11   18:getfield        #55  <Field long b>
	//   12   21:invokestatic    #132 <Method Long Long.valueOf(long)>
	//   13   24:aastore         
	//   14   25:dup             
	//   15   26:iconst_2        
	//   16   27:aload_0         
	//   17   28:getfield        #60  <Field Bundle c>
	//   18   31:aastore         
	//   19   32:dup             
	//   20   33:iconst_3        
	//   21   34:aload_0         
	//   22   35:getfield        #62  <Field int d>
	//   23   38:invokestatic    #127 <Method Integer Integer.valueOf(int)>
	//   24   41:aastore         
	//   25   42:dup             
	//   26   43:iconst_4        
	//   27   44:aload_0         
	//   28   45:getfield        #64  <Field List e>
	//   29   48:aastore         
	//   30   49:dup             
	//   31   50:iconst_5        
	//   32   51:aload_0         
	//   33   52:getfield        #66  <Field boolean f>
	//   34   55:invokestatic    #137 <Method Boolean Boolean.valueOf(boolean)>
	//   35   58:aastore         
	//   36   59:dup             
	//   37   60:bipush          6
	//   38   62:aload_0         
	//   39   63:getfield        #68  <Field int g>
	//   40   66:invokestatic    #127 <Method Integer Integer.valueOf(int)>
	//   41   69:aastore         
	//   42   70:dup             
	//   43   71:bipush          7
	//   44   73:aload_0         
	//   45   74:getfield        #70  <Field boolean h>
	//   46   77:invokestatic    #137 <Method Boolean Boolean.valueOf(boolean)>
	//   47   80:aastore         
	//   48   81:dup             
	//   49   82:bipush          8
	//   50   84:aload_0         
	//   51   85:getfield        #72  <Field String i>
	//   52   88:aastore         
	//   53   89:dup             
	//   54   90:bipush          9
	//   55   92:aload_0         
	//   56   93:getfield        #74  <Field zzzs j>
	//   57   96:aastore         
	//   58   97:dup             
	//   59   98:bipush          10
	//   60  100:aload_0         
	//   61  101:getfield        #76  <Field Location k>
	//   62  104:aastore         
	//   63  105:dup             
	//   64  106:bipush          11
	//   65  108:aload_0         
	//   66  109:getfield        #78  <Field String l>
	//   67  112:aastore         
	//   68  113:dup             
	//   69  114:bipush          12
	//   70  116:aload_0         
	//   71  117:getfield        #80  <Field Bundle m>
	//   72  120:aastore         
	//   73  121:dup             
	//   74  122:bipush          13
	//   75  124:aload_0         
	//   76  125:getfield        #82  <Field Bundle n>
	//   77  128:aastore         
	//   78  129:dup             
	//   79  130:bipush          14
	//   80  132:aload_0         
	//   81  133:getfield        #84  <Field List o>
	//   82  136:aastore         
	//   83  137:dup             
	//   84  138:bipush          15
	//   85  140:aload_0         
	//   86  141:getfield        #86  <Field String p>
	//   87  144:aastore         
	//   88  145:dup             
	//   89  146:bipush          16
	//   90  148:aload_0         
	//   91  149:getfield        #88  <Field String q>
	//   92  152:aastore         
	//   93  153:dup             
	//   94  154:bipush          17
	//   95  156:aload_0         
	//   96  157:getfield        #90  <Field boolean r>
	//   97  160:invokestatic    #137 <Method Boolean Boolean.valueOf(boolean)>
	//   98  163:aastore         
	//   99  164:dup             
	//  100  165:bipush          18
	//  101  167:aload_0         
	//  102  168:getfield        #94  <Field int t>
	//  103  171:invokestatic    #127 <Method Integer Integer.valueOf(int)>
	//  104  174:aastore         
	//  105  175:dup             
	//  106  176:bipush          19
	//  107  178:aload_0         
	//  108  179:getfield        #96  <Field String u>
	//  109  182:aastore         
	//  110  183:invokestatic    #140 <Method int ak.a(Object[])>
	//  111  186:ireturn         
	}

	public final void writeToParcel(Parcel parcel, int i1)
	{
		int j1 = com.google.android.gms.common.internal.safeparcel.c.a(parcel);
	//    0    0:aload_1         
	//    1    1:invokestatic    #147 <Method int c.a(Parcel)>
	//    2    4:istore_3        
		com.google.android.gms.common.internal.safeparcel.c.a(parcel, 1, a);
	//    3    5:aload_1         
	//    4    6:iconst_1        
	//    5    7:aload_0         
	//    6    8:getfield        #53  <Field int a>
	//    7   11:invokestatic    #150 <Method void c.a(Parcel, int, int)>
		com.google.android.gms.common.internal.safeparcel.c.a(parcel, 2, b);
	//    8   14:aload_1         
	//    9   15:iconst_2        
	//   10   16:aload_0         
	//   11   17:getfield        #55  <Field long b>
	//   12   20:invokestatic    #153 <Method void c.a(Parcel, int, long)>
		com.google.android.gms.common.internal.safeparcel.c.a(parcel, 3, c, false);
	//   13   23:aload_1         
	//   14   24:iconst_3        
	//   15   25:aload_0         
	//   16   26:getfield        #60  <Field Bundle c>
	//   17   29:iconst_0        
	//   18   30:invokestatic    #156 <Method void c.a(Parcel, int, Bundle, boolean)>
		com.google.android.gms.common.internal.safeparcel.c.a(parcel, 4, d);
	//   19   33:aload_1         
	//   20   34:iconst_4        
	//   21   35:aload_0         
	//   22   36:getfield        #62  <Field int d>
	//   23   39:invokestatic    #150 <Method void c.a(Parcel, int, int)>
		com.google.android.gms.common.internal.safeparcel.c.b(parcel, 5, e, false);
	//   24   42:aload_1         
	//   25   43:iconst_5        
	//   26   44:aload_0         
	//   27   45:getfield        #64  <Field List e>
	//   28   48:iconst_0        
	//   29   49:invokestatic    #159 <Method void c.b(Parcel, int, List, boolean)>
		com.google.android.gms.common.internal.safeparcel.c.a(parcel, 6, f);
	//   30   52:aload_1         
	//   31   53:bipush          6
	//   32   55:aload_0         
	//   33   56:getfield        #66  <Field boolean f>
	//   34   59:invokestatic    #162 <Method void c.a(Parcel, int, boolean)>
		com.google.android.gms.common.internal.safeparcel.c.a(parcel, 7, g);
	//   35   62:aload_1         
	//   36   63:bipush          7
	//   37   65:aload_0         
	//   38   66:getfield        #68  <Field int g>
	//   39   69:invokestatic    #150 <Method void c.a(Parcel, int, int)>
		com.google.android.gms.common.internal.safeparcel.c.a(parcel, 8, h);
	//   40   72:aload_1         
	//   41   73:bipush          8
	//   42   75:aload_0         
	//   43   76:getfield        #70  <Field boolean h>
	//   44   79:invokestatic    #162 <Method void c.a(Parcel, int, boolean)>
		com.google.android.gms.common.internal.safeparcel.c.a(parcel, 9, i, false);
	//   45   82:aload_1         
	//   46   83:bipush          9
	//   47   85:aload_0         
	//   48   86:getfield        #72  <Field String i>
	//   49   89:iconst_0        
	//   50   90:invokestatic    #165 <Method void c.a(Parcel, int, String, boolean)>
		com.google.android.gms.common.internal.safeparcel.c.a(parcel, 10, ((android.os.Parcelable) (j)), i1, false);
	//   51   93:aload_1         
	//   52   94:bipush          10
	//   53   96:aload_0         
	//   54   97:getfield        #74  <Field zzzs j>
	//   55  100:iload_2         
	//   56  101:iconst_0        
	//   57  102:invokestatic    #168 <Method void c.a(Parcel, int, android.os.Parcelable, int, boolean)>
		com.google.android.gms.common.internal.safeparcel.c.a(parcel, 11, ((android.os.Parcelable) (k)), i1, false);
	//   58  105:aload_1         
	//   59  106:bipush          11
	//   60  108:aload_0         
	//   61  109:getfield        #76  <Field Location k>
	//   62  112:iload_2         
	//   63  113:iconst_0        
	//   64  114:invokestatic    #168 <Method void c.a(Parcel, int, android.os.Parcelable, int, boolean)>
		com.google.android.gms.common.internal.safeparcel.c.a(parcel, 12, l, false);
	//   65  117:aload_1         
	//   66  118:bipush          12
	//   67  120:aload_0         
	//   68  121:getfield        #78  <Field String l>
	//   69  124:iconst_0        
	//   70  125:invokestatic    #165 <Method void c.a(Parcel, int, String, boolean)>
		com.google.android.gms.common.internal.safeparcel.c.a(parcel, 13, m, false);
	//   71  128:aload_1         
	//   72  129:bipush          13
	//   73  131:aload_0         
	//   74  132:getfield        #80  <Field Bundle m>
	//   75  135:iconst_0        
	//   76  136:invokestatic    #156 <Method void c.a(Parcel, int, Bundle, boolean)>
		com.google.android.gms.common.internal.safeparcel.c.a(parcel, 14, n, false);
	//   77  139:aload_1         
	//   78  140:bipush          14
	//   79  142:aload_0         
	//   80  143:getfield        #82  <Field Bundle n>
	//   81  146:iconst_0        
	//   82  147:invokestatic    #156 <Method void c.a(Parcel, int, Bundle, boolean)>
		com.google.android.gms.common.internal.safeparcel.c.b(parcel, 15, o, false);
	//   83  150:aload_1         
	//   84  151:bipush          15
	//   85  153:aload_0         
	//   86  154:getfield        #84  <Field List o>
	//   87  157:iconst_0        
	//   88  158:invokestatic    #159 <Method void c.b(Parcel, int, List, boolean)>
		com.google.android.gms.common.internal.safeparcel.c.a(parcel, 16, p, false);
	//   89  161:aload_1         
	//   90  162:bipush          16
	//   91  164:aload_0         
	//   92  165:getfield        #86  <Field String p>
	//   93  168:iconst_0        
	//   94  169:invokestatic    #165 <Method void c.a(Parcel, int, String, boolean)>
		com.google.android.gms.common.internal.safeparcel.c.a(parcel, 17, q, false);
	//   95  172:aload_1         
	//   96  173:bipush          17
	//   97  175:aload_0         
	//   98  176:getfield        #88  <Field String q>
	//   99  179:iconst_0        
	//  100  180:invokestatic    #165 <Method void c.a(Parcel, int, String, boolean)>
		com.google.android.gms.common.internal.safeparcel.c.a(parcel, 18, r);
	//  101  183:aload_1         
	//  102  184:bipush          18
	//  103  186:aload_0         
	//  104  187:getfield        #90  <Field boolean r>
	//  105  190:invokestatic    #162 <Method void c.a(Parcel, int, boolean)>
		com.google.android.gms.common.internal.safeparcel.c.a(parcel, 19, ((android.os.Parcelable) (s)), i1, false);
	//  106  193:aload_1         
	//  107  194:bipush          19
	//  108  196:aload_0         
	//  109  197:getfield        #92  <Field zzvv s>
	//  110  200:iload_2         
	//  111  201:iconst_0        
	//  112  202:invokestatic    #168 <Method void c.a(Parcel, int, android.os.Parcelable, int, boolean)>
		com.google.android.gms.common.internal.safeparcel.c.a(parcel, 20, t);
	//  113  205:aload_1         
	//  114  206:bipush          20
	//  115  208:aload_0         
	//  116  209:getfield        #94  <Field int t>
	//  117  212:invokestatic    #150 <Method void c.a(Parcel, int, int)>
		com.google.android.gms.common.internal.safeparcel.c.a(parcel, 21, u, false);
	//  118  215:aload_1         
	//  119  216:bipush          21
	//  120  218:aload_0         
	//  121  219:getfield        #96  <Field String u>
	//  122  222:iconst_0        
	//  123  223:invokestatic    #165 <Method void c.a(Parcel, int, String, boolean)>
		com.google.android.gms.common.internal.safeparcel.c.a(parcel, j1);
	//  124  226:aload_1         
	//  125  227:iload_3         
	//  126  228:invokestatic    #170 <Method void c.a(Parcel, int)>
	//  127  231:return          
	}

	public static final android.os.Parcelable.Creator CREATOR = new bvv();
	public final int a;
	public final long b;
	public final Bundle c;
	public final int d;
	public final List e;
	public final boolean f;
	public final int g;
	public final boolean h;
	public final String i;
	public final zzzs j;
	public final Location k;
	public final String l;
	public final Bundle m;
	public final Bundle n;
	public final List o;
	public final String p;
	public final String q;
	public final boolean r;
	public final zzvv s;
	public final int t;
	public final String u;

	static 
	{
	//    0    0:new             #43  <Class bvv>
	//    1    3:dup             
	//    2    4:invokespecial   #46  <Method void bvv()>
	//    3    7:putstatic       #48  <Field android.os.Parcelable$Creator CREATOR>
	//*   4   10:return          
	}
}
