// Decompiled by Jad v1.5.8g. Copyright 2001 Pavel Kouznetsov.
// Jad home page: http://www.kpdus.com/jad.html
// Decompiler options: packimports(3) annotate safe 

package com.google.android.gms.internal;

import android.os.SystemClock;
import java.io.*;
import java.util.*;

// Referenced classes of package com.google.android.gms.internal:
//			zzb, zzs

public class zzv
	implements com.google.android.gms.internal.zzb
{
	static class zza
	{

		public static zza zzf(InputStream inputstream)
			throws IOException
		{
			zza zza1 = new zza();
		//    0    0:new             #2   <Class zzv$zza>
		//    1    3:dup             
		//    2    4:invokespecial   #56  <Method void zzv$zza()>
		//    3    7:astore_1        
			if(zzv.zzb(inputstream) != 0x20150306)
		//*   4    8:aload_0         
		//*   5    9:invokestatic    #59  <Method int zzv.zzb(InputStream)>
		//*   6   12:ldc1            #60  <Int 0x20150306>
		//*   7   14:icmpeq          25
				throw new IOException();
		//    8   17:new             #55  <Class IOException>
		//    9   20:dup             
		//   10   21:invokespecial   #61  <Method void IOException()>
		//   11   24:athrow          
			zza1.zzaA = zzv.zzd(inputstream);
		//   12   25:aload_1         
		//   13   26:aload_0         
		//   14   27:invokestatic    #64  <Method String zzv.zzd(InputStream)>
		//   15   30:putfield        #26  <Field String zzaA>
			zza1.zza = zzv.zzd(inputstream);
		//   16   33:aload_1         
		//   17   34:aload_0         
		//   18   35:invokestatic    #64  <Method String zzv.zzd(InputStream)>
		//   19   38:putfield        #37  <Field String zza>
			if(zza1.zza.equals(""))
		//*  20   41:aload_1         
		//*  21   42:getfield        #37  <Field String zza>
		//*  22   45:ldc1            #66  <String "">
		//*  23   47:invokevirtual   #72  <Method boolean String.equals(Object)>
		//*  24   50:ifeq            58
				zza1.zza = null;
		//   25   53:aload_1         
		//   26   54:aconst_null     
		//   27   55:putfield        #37  <Field String zza>
			zza1.zzb = zzv.zzc(inputstream);
		//   28   58:aload_1         
		//   29   59:aload_0         
		//   30   60:invokestatic    #75  <Method long zzv.zzc(InputStream)>
		//   31   63:putfield        #40  <Field long zzb>
			zza1.zzc = zzv.zzc(inputstream);
		//   32   66:aload_1         
		//   33   67:aload_0         
		//   34   68:invokestatic    #75  <Method long zzv.zzc(InputStream)>
		//   35   71:putfield        #43  <Field long zzc>
			zza1.zzd = zzv.zzc(inputstream);
		//   36   74:aload_1         
		//   37   75:aload_0         
		//   38   76:invokestatic    #75  <Method long zzv.zzc(InputStream)>
		//   39   79:putfield        #46  <Field long zzd>
			zza1.zze = zzv.zzc(inputstream);
		//   40   82:aload_1         
		//   41   83:aload_0         
		//   42   84:invokestatic    #75  <Method long zzv.zzc(InputStream)>
		//   43   87:putfield        #49  <Field long zze>
			zza1.zzf = zzv.zze(inputstream);
		//   44   90:aload_1         
		//   45   91:aload_0         
		//   46   92:invokestatic    #78  <Method Map zzv.zze(InputStream)>
		//   47   95:putfield        #52  <Field Map zzf>
			return zza1;
		//   48   98:aload_1         
		//   49   99:areturn         
		}

		public boolean zza(OutputStream outputstream)
		{
			zzv.zza(outputstream, 0x20150306);
		//    0    0:aload_1         
		//    1    1:ldc1            #60  <Int 0x20150306>
		//    2    3:invokestatic    #83  <Method void zzv.zza(OutputStream, int)>
			zzv.zza(outputstream, zzaA);
		//    3    6:aload_1         
		//    4    7:aload_0         
		//    5    8:getfield        #26  <Field String zzaA>
		//    6   11:invokestatic    #86  <Method void zzv.zza(OutputStream, String)>
			if(zza != null)
				break MISSING_BLOCK_LABEL_75;
		//    7   14:aload_0         
		//    8   15:getfield        #37  <Field String zza>
		//    9   18:ifnonnull       75
			String s = "";
		//   10   21:ldc1            #66  <String "">
		//   11   23:astore_2        
_L1:
			try
			{
				zzv.zza(outputstream, s);
		//   12   24:aload_1         
		//   13   25:aload_2         
		//   14   26:invokestatic    #86  <Method void zzv.zza(OutputStream, String)>
				zzv.zza(outputstream, zzb);
		//   15   29:aload_1         
		//   16   30:aload_0         
		//   17   31:getfield        #40  <Field long zzb>
		//   18   34:invokestatic    #89  <Method void zzv.zza(OutputStream, long)>
				zzv.zza(outputstream, zzc);
		//   19   37:aload_1         
		//   20   38:aload_0         
		//   21   39:getfield        #43  <Field long zzc>
		//   22   42:invokestatic    #89  <Method void zzv.zza(OutputStream, long)>
				zzv.zza(outputstream, zzd);
		//   23   45:aload_1         
		//   24   46:aload_0         
		//   25   47:getfield        #46  <Field long zzd>
		//   26   50:invokestatic    #89  <Method void zzv.zza(OutputStream, long)>
				zzv.zza(outputstream, zze);
		//   27   53:aload_1         
		//   28   54:aload_0         
		//   29   55:getfield        #49  <Field long zze>
		//   30   58:invokestatic    #89  <Method void zzv.zza(OutputStream, long)>
				zzv.zza(zzf, outputstream);
		//   31   61:aload_0         
		//   32   62:getfield        #52  <Field Map zzf>
		//   33   65:aload_1         
		//   34   66:invokestatic    #92  <Method void zzv.zza(Map, OutputStream)>
				outputstream.flush();
		//   35   69:aload_1         
		//   36   70:invokevirtual   #97  <Method void OutputStream.flush()>
			}
		//*  37   73:iconst_1        
		//*  38   74:ireturn         
		//*  39   75:aload_0         
		//*  40   76:getfield        #37  <Field String zza>
		//*  41   79:astore_2        
		//*  42   80:goto            24
			// Misplaced declaration of an exception variable
			catch(OutputStream outputstream)
		//*  43   83:astore_1        
			{
				zzs.zzb("%s", new Object[] {
					((IOException) (outputstream)).toString()
				});
		//   44   84:ldc1            #99  <String "%s">
		//   45   86:iconst_1        
		//   46   87:anewarray       Object[]
		//   47   90:dup             
		//   48   91:iconst_0        
		//   49   92:aload_1         
		//   50   93:invokevirtual   #103 <Method String IOException.toString()>
		//   51   96:aastore         
		//   52   97:invokestatic    #108 <Method void zzs.zzb(String, Object[])>
				return false;
		//   53  100:iconst_0        
		//   54  101:ireturn         
			}
			return true;
			s = zza;
			  goto _L1
		}

		public zzb.zza zzb(byte abyte0[])
		{
			zzb.zza zza1 = new zzb.zza();
		//    0    0:new             #28  <Class zzb$zza>
		//    1    3:dup             
		//    2    4:invokespecial   #110 <Method void zzb$zza()>
		//    3    7:astore_2        
			zza1.data = abyte0;
		//    4    8:aload_2         
		//    5    9:aload_1         
		//    6   10:putfield        #32  <Field byte[] zzb$zza.data>
			zza1.zza = zza;
		//    7   13:aload_2         
		//    8   14:aload_0         
		//    9   15:getfield        #37  <Field String zza>
		//   10   18:putfield        #36  <Field String zzb$zza.zza>
			zza1.zzb = zzb;
		//   11   21:aload_2         
		//   12   22:aload_0         
		//   13   23:getfield        #40  <Field long zzb>
		//   14   26:putfield        #39  <Field long zzb$zza.zzb>
			zza1.zzc = zzc;
		//   15   29:aload_2         
		//   16   30:aload_0         
		//   17   31:getfield        #43  <Field long zzc>
		//   18   34:putfield        #42  <Field long zzb$zza.zzc>
			zza1.zzd = zzd;
		//   19   37:aload_2         
		//   20   38:aload_0         
		//   21   39:getfield        #46  <Field long zzd>
		//   22   42:putfield        #45  <Field long zzb$zza.zzd>
			zza1.zze = zze;
		//   23   45:aload_2         
		//   24   46:aload_0         
		//   25   47:getfield        #49  <Field long zze>
		//   26   50:putfield        #48  <Field long zzb$zza.zze>
			zza1.zzf = zzf;
		//   27   53:aload_2         
		//   28   54:aload_0         
		//   29   55:getfield        #52  <Field Map zzf>
		//   30   58:putfield        #51  <Field Map zzb$zza.zzf>
			return zza1;
		//   31   61:aload_2         
		//   32   62:areturn         
		}

		public String zza;
		public String zzaA;
		public long zzaz;
		public long zzb;
		public long zzc;
		public long zzd;
		public long zze;
		public Map zzf;

		private zza()
		{
		//    0    0:aload_0         
		//    1    1:invokespecial   #22  <Method void Object()>
		//    2    4:return          
		}

		public zza(String s, zzb.zza zza1)
		{
		//    0    0:aload_0         
		//    1    1:invokespecial   #22  <Method void Object()>
			zzaA = s;
		//    2    4:aload_0         
		//    3    5:aload_1         
		//    4    6:putfield        #26  <Field String zzaA>
			zzaz = zza1.data.length;
		//    5    9:aload_0         
		//    6   10:aload_2         
		//    7   11:getfield        #32  <Field byte[] zzb$zza.data>
		//    8   14:arraylength     
		//    9   15:i2l             
		//   10   16:putfield        #34  <Field long zzaz>
			zza = zza1.zza;
		//   11   19:aload_0         
		//   12   20:aload_2         
		//   13   21:getfield        #36  <Field String zzb$zza.zza>
		//   14   24:putfield        #37  <Field String zza>
			zzb = zza1.zzb;
		//   15   27:aload_0         
		//   16   28:aload_2         
		//   17   29:getfield        #39  <Field long zzb$zza.zzb>
		//   18   32:putfield        #40  <Field long zzb>
			zzc = zza1.zzc;
		//   19   35:aload_0         
		//   20   36:aload_2         
		//   21   37:getfield        #42  <Field long zzb$zza.zzc>
		//   22   40:putfield        #43  <Field long zzc>
			zzd = zza1.zzd;
		//   23   43:aload_0         
		//   24   44:aload_2         
		//   25   45:getfield        #45  <Field long zzb$zza.zzd>
		//   26   48:putfield        #46  <Field long zzd>
			zze = zza1.zze;
		//   27   51:aload_0         
		//   28   52:aload_2         
		//   29   53:getfield        #48  <Field long zzb$zza.zze>
		//   30   56:putfield        #49  <Field long zze>
			zzf = zza1.zzf;
		//   31   59:aload_0         
		//   32   60:aload_2         
		//   33   61:getfield        #51  <Field Map zzb$zza.zzf>
		//   34   64:putfield        #52  <Field Map zzf>
		//   35   67:return          
		}
	}

	private static class zzb extends FilterInputStream
	{

		static int zza(zzb zzb1)
		{
			return zzb1.zzaB;
		//    0    0:aload_0         
		//    1    1:getfield        #15  <Field int zzaB>
		//    2    4:ireturn         
		}

		public int read()
			throws IOException
		{
			int i = super.read();
		//    0    0:aload_0         
		//    1    1:invokespecial   #26  <Method int FilterInputStream.read()>
		//    2    4:istore_1        
			if(i != -1)
		//*   3    5:iload_1         
		//*   4    6:iconst_m1       
		//*   5    7:icmpeq          20
				zzaB = zzaB + 1;
		//    6   10:aload_0         
		//    7   11:aload_0         
		//    8   12:getfield        #15  <Field int zzaB>
		//    9   15:iconst_1        
		//   10   16:iadd            
		//   11   17:putfield        #15  <Field int zzaB>
			return i;
		//   12   20:iload_1         
		//   13   21:ireturn         
		}

		public int read(byte abyte0[], int i, int j)
			throws IOException
		{
			i = super.read(abyte0, i, j);
		//    0    0:aload_0         
		//    1    1:aload_1         
		//    2    2:iload_2         
		//    3    3:iload_3         
		//    4    4:invokespecial   #30  <Method int FilterInputStream.read(byte[], int, int)>
		//    5    7:istore_2        
			if(i != -1)
		//*   6    8:iload_2         
		//*   7    9:iconst_m1       
		//*   8   10:icmpeq          23
				zzaB = zzaB + i;
		//    9   13:aload_0         
		//   10   14:aload_0         
		//   11   15:getfield        #15  <Field int zzaB>
		//   12   18:iload_2         
		//   13   19:iadd            
		//   14   20:putfield        #15  <Field int zzaB>
			return i;
		//   15   23:iload_2         
		//   16   24:ireturn         
		}

		private int zzaB;

		private zzb(InputStream inputstream)
		{
			super(inputstream);
		//    0    0:aload_0         
		//    1    1:aload_1         
		//    2    2:invokespecial   #13  <Method void FilterInputStream(InputStream)>
			zzaB = 0;
		//    3    5:aload_0         
		//    4    6:iconst_0        
		//    5    7:putfield        #15  <Field int zzaB>
		//    6   10:return          
		}

	}


	public zzv(File file)
	{
		this(file, 0x500000);
	//    0    0:aload_0         
	//    1    1:aload_1         
	//    2    2:ldc1            #26  <Int 0x500000>
	//    3    4:invokespecial   #29  <Method void zzv(File, int)>
	//    4    7:return          
	}

	public zzv(File file, int i)
	{
	//    0    0:aload_0         
	//    1    1:invokespecial   #33  <Method void Object()>
		zzav = ((Map) (new LinkedHashMap(16, 0.75F, true)));
	//    2    4:aload_0         
	//    3    5:new             #35  <Class LinkedHashMap>
	//    4    8:dup             
	//    5    9:bipush          16
	//    6   11:ldc1            #36  <Float 0.75F>
	//    7   13:iconst_1        
	//    8   14:invokespecial   #39  <Method void LinkedHashMap(int, float, boolean)>
	//    9   17:putfield        #41  <Field Map zzav>
		zzaw = 0L;
	//   10   20:aload_0         
	//   11   21:lconst_0        
	//   12   22:putfield        #43  <Field long zzaw>
		zzax = file;
	//   13   25:aload_0         
	//   14   26:aload_1         
	//   15   27:putfield        #45  <Field File zzax>
		zzay = i;
	//   16   30:aload_0         
	//   17   31:iload_2         
	//   18   32:putfield        #47  <Field int zzay>
	//   19   35:return          
	}

	private void removeEntry(String s)
	{
		zza zza1 = (zza)zzav.get(((Object) (s)));
	//    0    0:aload_0         
	//    1    1:getfield        #41  <Field Map zzav>
	//    2    4:aload_1         
	//    3    5:invokeinterface #55  <Method Object Map.get(Object)>
	//    4   10:checkcast       #10  <Class zzv$zza>
	//    5   13:astore_2        
		if(zza1 != null)
	//*   6   14:aload_2         
	//*   7   15:ifnull          42
		{
			zzaw = zzaw - zza1.zzaz;
	//    8   18:aload_0         
	//    9   19:aload_0         
	//   10   20:getfield        #43  <Field long zzaw>
	//   11   23:aload_2         
	//   12   24:getfield        #58  <Field long zzv$zza.zzaz>
	//   13   27:lsub            
	//   14   28:putfield        #43  <Field long zzaw>
			zzav.remove(((Object) (s)));
	//   15   31:aload_0         
	//   16   32:getfield        #41  <Field Map zzav>
	//   17   35:aload_1         
	//   18   36:invokeinterface #61  <Method Object Map.remove(Object)>
	//   19   41:pop             
		}
	//   20   42:return          
	}

	private static int zza(InputStream inputstream)
		throws IOException
	{
		int i = inputstream.read();
	//    0    0:aload_0         
	//    1    1:invokevirtual   #70  <Method int InputStream.read()>
	//    2    4:istore_1        
		if(i == -1)
	//*   3    5:iload_1         
	//*   4    6:iconst_m1       
	//*   5    7:icmpne          18
			throw new EOFException();
	//    6   10:new             #72  <Class EOFException>
	//    7   13:dup             
	//    8   14:invokespecial   #73  <Method void EOFException()>
	//    9   17:athrow          
		else
			return i;
	//   10   18:iload_1         
	//   11   19:ireturn         
	}

	static void zza(OutputStream outputstream, int i)
		throws IOException
	{
		outputstream.write(i >> 0 & 0xff);
	//    0    0:aload_0         
	//    1    1:iload_1         
	//    2    2:iconst_0        
	//    3    3:ishr            
	//    4    4:sipush          255
	//    5    7:iand            
	//    6    8:invokevirtual   #81  <Method void OutputStream.write(int)>
		outputstream.write(i >> 8 & 0xff);
	//    7   11:aload_0         
	//    8   12:iload_1         
	//    9   13:bipush          8
	//   10   15:ishr            
	//   11   16:sipush          255
	//   12   19:iand            
	//   13   20:invokevirtual   #81  <Method void OutputStream.write(int)>
		outputstream.write(i >> 16 & 0xff);
	//   14   23:aload_0         
	//   15   24:iload_1         
	//   16   25:bipush          16
	//   17   27:ishr            
	//   18   28:sipush          255
	//   19   31:iand            
	//   20   32:invokevirtual   #81  <Method void OutputStream.write(int)>
		outputstream.write(i >> 24 & 0xff);
	//   21   35:aload_0         
	//   22   36:iload_1         
	//   23   37:bipush          24
	//   24   39:ishr            
	//   25   40:sipush          255
	//   26   43:iand            
	//   27   44:invokevirtual   #81  <Method void OutputStream.write(int)>
	//   28   47:return          
	}

	static void zza(OutputStream outputstream, long l)
		throws IOException
	{
		outputstream.write(((int) ((byte)(int)(l >>> 0))));
	//    0    0:aload_0         
	//    1    1:lload_1         
	//    2    2:iconst_0        
	//    3    3:lushr           
	//    4    4:l2i             
	//    5    5:int2byte        
	//    6    6:invokevirtual   #81  <Method void OutputStream.write(int)>
		outputstream.write(((int) ((byte)(int)(l >>> 8))));
	//    7    9:aload_0         
	//    8   10:lload_1         
	//    9   11:bipush          8
	//   10   13:lushr           
	//   11   14:l2i             
	//   12   15:int2byte        
	//   13   16:invokevirtual   #81  <Method void OutputStream.write(int)>
		outputstream.write(((int) ((byte)(int)(l >>> 16))));
	//   14   19:aload_0         
	//   15   20:lload_1         
	//   16   21:bipush          16
	//   17   23:lushr           
	//   18   24:l2i             
	//   19   25:int2byte        
	//   20   26:invokevirtual   #81  <Method void OutputStream.write(int)>
		outputstream.write(((int) ((byte)(int)(l >>> 24))));
	//   21   29:aload_0         
	//   22   30:lload_1         
	//   23   31:bipush          24
	//   24   33:lushr           
	//   25   34:l2i             
	//   26   35:int2byte        
	//   27   36:invokevirtual   #81  <Method void OutputStream.write(int)>
		outputstream.write(((int) ((byte)(int)(l >>> 32))));
	//   28   39:aload_0         
	//   29   40:lload_1         
	//   30   41:bipush          32
	//   31   43:lushr           
	//   32   44:l2i             
	//   33   45:int2byte        
	//   34   46:invokevirtual   #81  <Method void OutputStream.write(int)>
		outputstream.write(((int) ((byte)(int)(l >>> 40))));
	//   35   49:aload_0         
	//   36   50:lload_1         
	//   37   51:bipush          40
	//   38   53:lushr           
	//   39   54:l2i             
	//   40   55:int2byte        
	//   41   56:invokevirtual   #81  <Method void OutputStream.write(int)>
		outputstream.write(((int) ((byte)(int)(l >>> 48))));
	//   42   59:aload_0         
	//   43   60:lload_1         
	//   44   61:bipush          48
	//   45   63:lushr           
	//   46   64:l2i             
	//   47   65:int2byte        
	//   48   66:invokevirtual   #81  <Method void OutputStream.write(int)>
		outputstream.write(((int) ((byte)(int)(l >>> 56))));
	//   49   69:aload_0         
	//   50   70:lload_1         
	//   51   71:bipush          56
	//   52   73:lushr           
	//   53   74:l2i             
	//   54   75:int2byte        
	//   55   76:invokevirtual   #81  <Method void OutputStream.write(int)>
	//   56   79:return          
	}

	static void zza(OutputStream outputstream, String s)
		throws IOException
	{
		s = ((String) (s.getBytes("UTF-8")));
	//    0    0:aload_1         
	//    1    1:ldc1            #85  <String "UTF-8">
	//    2    3:invokevirtual   #91  <Method byte[] String.getBytes(String)>
	//    3    6:astore_1        
		zza(outputstream, s.length);
	//    4    7:aload_0         
	//    5    8:aload_1         
	//    6    9:arraylength     
	//    7   10:i2l             
	//    8   11:invokestatic    #93  <Method void zza(OutputStream, long)>
		outputstream.write(((byte []) (s)), 0, s.length);
	//    9   14:aload_0         
	//   10   15:aload_1         
	//   11   16:iconst_0        
	//   12   17:aload_1         
	//   13   18:arraylength     
	//   14   19:invokevirtual   #96  <Method void OutputStream.write(byte[], int, int)>
	//   15   22:return          
	}

	private void zza(String s, zza zza1)
	{
		if(!zzav.containsKey(((Object) (s))))
	//*   0    0:aload_0         
	//*   1    1:getfield        #41  <Field Map zzav>
	//*   2    4:aload_1         
	//*   3    5:invokeinterface #101 <Method boolean Map.containsKey(Object)>
	//*   4   10:ifne            39
		{
			zzaw = zzaw + zza1.zzaz;
	//    5   13:aload_0         
	//    6   14:aload_0         
	//    7   15:getfield        #43  <Field long zzaw>
	//    8   18:aload_2         
	//    9   19:getfield        #58  <Field long zzv$zza.zzaz>
	//   10   22:ladd            
	//   11   23:putfield        #43  <Field long zzaw>
		} else
	//*  12   26:aload_0         
	//*  13   27:getfield        #41  <Field Map zzav>
	//*  14   30:aload_1         
	//*  15   31:aload_2         
	//*  16   32:invokeinterface #105 <Method Object Map.put(Object, Object)>
	//*  17   37:pop             
	//*  18   38:return          
		{
			zza zza2 = (zza)zzav.get(((Object) (s)));
	//   19   39:aload_0         
	//   20   40:getfield        #41  <Field Map zzav>
	//   21   43:aload_1         
	//   22   44:invokeinterface #55  <Method Object Map.get(Object)>
	//   23   49:checkcast       #10  <Class zzv$zza>
	//   24   52:astore          5
			long l = zzaw;
	//   25   54:aload_0         
	//   26   55:getfield        #43  <Field long zzaw>
	//   27   58:lstore_3        
			zzaw = (zza1.zzaz - zza2.zzaz) + l;
	//   28   59:aload_0         
	//   29   60:aload_2         
	//   30   61:getfield        #58  <Field long zzv$zza.zzaz>
	//   31   64:aload           5
	//   32   66:getfield        #58  <Field long zzv$zza.zzaz>
	//   33   69:lsub            
	//   34   70:lload_3         
	//   35   71:ladd            
	//   36   72:putfield        #43  <Field long zzaw>
		}
		zzav.put(((Object) (s)), ((Object) (zza1)));
	//*  37   75:goto            26
	}

	static void zza(Map map, OutputStream outputstream)
		throws IOException
	{
		if(map != null)
	//*   0    0:aload_0         
	//*   1    1:ifnull          74
		{
			zza(outputstream, map.size());
	//    2    4:aload_1         
	//    3    5:aload_0         
	//    4    6:invokeinterface #109 <Method int Map.size()>
	//    5   11:invokestatic    #111 <Method void zza(OutputStream, int)>
			java.util.Map.Entry entry;
			for(map = ((Map) (map.entrySet().iterator())); ((Iterator) (map)).hasNext(); zza(outputstream, (String)entry.getValue()))
	//*   6   14:aload_0         
	//*   7   15:invokeinterface #115 <Method Set Map.entrySet()>
	//*   8   20:invokeinterface #121 <Method Iterator Set.iterator()>
	//*   9   25:astore_0        
	//*  10   26:aload_0         
	//*  11   27:invokeinterface #127 <Method boolean Iterator.hasNext()>
	//*  12   32:ifeq            79
			{
				entry = (java.util.Map.Entry)((Iterator) (map)).next();
	//   13   35:aload_0         
	//   14   36:invokeinterface #131 <Method Object Iterator.next()>
	//   15   41:checkcast       #133 <Class java.util.Map$Entry>
	//   16   44:astore_2        
				zza(outputstream, (String)entry.getKey());
	//   17   45:aload_1         
	//   18   46:aload_2         
	//   19   47:invokeinterface #136 <Method Object java.util.Map$Entry.getKey()>
	//   20   52:checkcast       #87  <Class String>
	//   21   55:invokestatic    #138 <Method void zza(OutputStream, String)>
			}

	//   22   58:aload_1         
	//   23   59:aload_2         
	//   24   60:invokeinterface #141 <Method Object java.util.Map$Entry.getValue()>
	//   25   65:checkcast       #87  <Class String>
	//   26   68:invokestatic    #138 <Method void zza(OutputStream, String)>
		} else
	//*  27   71:goto            26
		{
			zza(outputstream, 0);
	//   28   74:aload_1         
	//   29   75:iconst_0        
	//   30   76:invokestatic    #111 <Method void zza(OutputStream, int)>
		}
	//   31   79:return          
	}

	private static byte[] zza(InputStream inputstream, int i)
		throws IOException
	{
		byte abyte0[] = new byte[i];
	//    0    0:iload_1         
	//    1    1:newarray        byte[]
	//    2    3:astore          4
		int j = 0;
	//    3    5:iconst_0        
	//    4    6:istore_2        
		do
		{
			if(j >= i)
				break;
	//    5    7:iload_2         
	//    6    8:iload_1         
	//    7    9:icmpge          35
			int k = inputstream.read(abyte0, j, i - j);
	//    8   12:aload_0         
	//    9   13:aload           4
	//   10   15:iload_2         
	//   11   16:iload_1         
	//   12   17:iload_2         
	//   13   18:isub            
	//   14   19:invokevirtual   #147 <Method int InputStream.read(byte[], int, int)>
	//   15   22:istore_3        
			if(k == -1)
				break;
	//   16   23:iload_3         
	//   17   24:iconst_m1       
	//   18   25:icmpeq          35
			j += k;
	//   19   28:iload_2         
	//   20   29:iload_3         
	//   21   30:iadd            
	//   22   31:istore_2        
		} while(true);
	//   23   32:goto            7
		if(j != i)
	//*  24   35:iload_2         
	//*  25   36:iload_1         
	//*  26   37:icmpeq          83
			throw new IOException((new StringBuilder(50)).append("Expected ").append(i).append(" bytes, read ").append(j).append(" bytes").toString());
	//   27   40:new             #64  <Class IOException>
	//   28   43:dup             
	//   29   44:new             #149 <Class StringBuilder>
	//   30   47:dup             
	//   31   48:bipush          50
	//   32   50:invokespecial   #151 <Method void StringBuilder(int)>
	//   33   53:ldc1            #153 <String "Expected ">
	//   34   55:invokevirtual   #157 <Method StringBuilder StringBuilder.append(String)>
	//   35   58:iload_1         
	//   36   59:invokevirtual   #160 <Method StringBuilder StringBuilder.append(int)>
	//   37   62:ldc1            #162 <String " bytes, read ">
	//   38   64:invokevirtual   #157 <Method StringBuilder StringBuilder.append(String)>
	//   39   67:iload_2         
	//   40   68:invokevirtual   #160 <Method StringBuilder StringBuilder.append(int)>
	//   41   71:ldc1            #164 <String " bytes">
	//   42   73:invokevirtual   #157 <Method StringBuilder StringBuilder.append(String)>
	//   43   76:invokevirtual   #168 <Method String StringBuilder.toString()>
	//   44   79:invokespecial   #170 <Method void IOException(String)>
	//   45   82:athrow          
		else
			return abyte0;
	//   46   83:aload           4
	//   47   85:areturn         
	}

	static int zzb(InputStream inputstream)
		throws IOException
	{
		return zza(inputstream) << 0 | 0 | zza(inputstream) << 8 | zza(inputstream) << 16 | zza(inputstream) << 24;
	//    0    0:aload_0         
	//    1    1:invokestatic    #172 <Method int zza(InputStream)>
	//    2    4:iconst_0        
	//    3    5:ishl            
	//    4    6:iconst_0        
	//    5    7:ior             
	//    6    8:aload_0         
	//    7    9:invokestatic    #172 <Method int zza(InputStream)>
	//    8   12:bipush          8
	//    9   14:ishl            
	//   10   15:ior             
	//   11   16:aload_0         
	//   12   17:invokestatic    #172 <Method int zza(InputStream)>
	//   13   20:bipush          16
	//   14   22:ishl            
	//   15   23:ior             
	//   16   24:aload_0         
	//   17   25:invokestatic    #172 <Method int zza(InputStream)>
	//   18   28:bipush          24
	//   19   30:ishl            
	//   20   31:ior             
	//   21   32:ireturn         
	}

	static long zzc(InputStream inputstream)
		throws IOException
	{
		return 0L | ((long)zza(inputstream) & 255L) << 0 | ((long)zza(inputstream) & 255L) << 8 | ((long)zza(inputstream) & 255L) << 16 | ((long)zza(inputstream) & 255L) << 24 | ((long)zza(inputstream) & 255L) << 32 | ((long)zza(inputstream) & 255L) << 40 | ((long)zza(inputstream) & 255L) << 48 | ((long)zza(inputstream) & 255L) << 56;
	//    0    0:lconst_0        
	//    1    1:aload_0         
	//    2    2:invokestatic    #172 <Method int zza(InputStream)>
	//    3    5:i2l             
	//    4    6:ldc2w           #175 <Long 255L>
	//    5    9:land            
	//    6   10:iconst_0        
	//    7   11:lshl            
	//    8   12:lor             
	//    9   13:aload_0         
	//   10   14:invokestatic    #172 <Method int zza(InputStream)>
	//   11   17:i2l             
	//   12   18:ldc2w           #175 <Long 255L>
	//   13   21:land            
	//   14   22:bipush          8
	//   15   24:lshl            
	//   16   25:lor             
	//   17   26:aload_0         
	//   18   27:invokestatic    #172 <Method int zza(InputStream)>
	//   19   30:i2l             
	//   20   31:ldc2w           #175 <Long 255L>
	//   21   34:land            
	//   22   35:bipush          16
	//   23   37:lshl            
	//   24   38:lor             
	//   25   39:aload_0         
	//   26   40:invokestatic    #172 <Method int zza(InputStream)>
	//   27   43:i2l             
	//   28   44:ldc2w           #175 <Long 255L>
	//   29   47:land            
	//   30   48:bipush          24
	//   31   50:lshl            
	//   32   51:lor             
	//   33   52:aload_0         
	//   34   53:invokestatic    #172 <Method int zza(InputStream)>
	//   35   56:i2l             
	//   36   57:ldc2w           #175 <Long 255L>
	//   37   60:land            
	//   38   61:bipush          32
	//   39   63:lshl            
	//   40   64:lor             
	//   41   65:aload_0         
	//   42   66:invokestatic    #172 <Method int zza(InputStream)>
	//   43   69:i2l             
	//   44   70:ldc2w           #175 <Long 255L>
	//   45   73:land            
	//   46   74:bipush          40
	//   47   76:lshl            
	//   48   77:lor             
	//   49   78:aload_0         
	//   50   79:invokestatic    #172 <Method int zza(InputStream)>
	//   51   82:i2l             
	//   52   83:ldc2w           #175 <Long 255L>
	//   53   86:land            
	//   54   87:bipush          48
	//   55   89:lshl            
	//   56   90:lor             
	//   57   91:aload_0         
	//   58   92:invokestatic    #172 <Method int zza(InputStream)>
	//   59   95:i2l             
	//   60   96:ldc2w           #175 <Long 255L>
	//   61   99:land            
	//   62  100:bipush          56
	//   63  102:lshl            
	//   64  103:lor             
	//   65  104:lreturn         
	}

	private void zzc(int i)
	{
		if(zzaw + (long)i >= (long)zzay)
	//*   0    0:aload_0         
	//*   1    1:getfield        #43  <Field long zzaw>
	//*   2    4:iload_1         
	//*   3    5:i2l             
	//*   4    6:ladd            
	//*   5    7:aload_0         
	//*   6    8:getfield        #47  <Field int zzay>
	//*   7   11:i2l             
	//*   8   12:lcmp            
	//*   9   13:ifge            17
	//*  10   16:return          
		{
			if(zzs.DEBUG)
	//*  11   17:getstatic       #182 <Field boolean zzs.DEBUG>
	//*  12   20:ifeq            32
				zzs.zza("Pruning old cache entries.", new Object[0]);
	//   13   23:ldc1            #184 <String "Pruning old cache entries.">
	//   14   25:iconst_0        
	//   15   26:anewarray       Object[]
	//   16   29:invokestatic    #187 <Method void zzs.zza(String, Object[])>
			long l = zzaw;
	//   17   32:aload_0         
	//   18   33:getfield        #43  <Field long zzaw>
	//   19   36:lstore_3        
			long l1 = SystemClock.elapsedRealtime();
	//   20   37:invokestatic    #193 <Method long SystemClock.elapsedRealtime()>
	//   21   40:lstore          5
			Iterator iterator = zzav.entrySet().iterator();
	//   22   42:aload_0         
	//   23   43:getfield        #41  <Field Map zzav>
	//   24   46:invokeinterface #115 <Method Set Map.entrySet()>
	//   25   51:invokeinterface #121 <Method Iterator Set.iterator()>
	//   26   56:astore          7
			int j = 0;
	//   27   58:iconst_0        
	//   28   59:istore_2        
			do
			{
				if(!iterator.hasNext())
					break;
	//   29   60:aload           7
	//   30   62:invokeinterface #127 <Method boolean Iterator.hasNext()>
	//   31   67:ifeq            232
				zza zza1 = (zza)((java.util.Map.Entry)iterator.next()).getValue();
	//   32   70:aload           7
	//   33   72:invokeinterface #131 <Method Object Iterator.next()>
	//   34   77:checkcast       #133 <Class java.util.Map$Entry>
	//   35   80:invokeinterface #141 <Method Object java.util.Map$Entry.getValue()>
	//   36   85:checkcast       #10  <Class zzv$zza>
	//   37   88:astore          8
				if(zzf(zza1.zzaA).delete())
	//*  38   90:aload_0         
	//*  39   91:aload           8
	//*  40   93:getfield        #197 <Field String zzv$zza.zzaA>
	//*  41   96:invokevirtual   #201 <Method File zzf(String)>
	//*  42   99:invokevirtual   #206 <Method boolean File.delete()>
	//*  43  102:ifeq            197
					zzaw = zzaw - zza1.zzaz;
	//   44  105:aload_0         
	//   45  106:aload_0         
	//   46  107:getfield        #43  <Field long zzaw>
	//   47  110:aload           8
	//   48  112:getfield        #58  <Field long zzv$zza.zzaz>
	//   49  115:lsub            
	//   50  116:putfield        #43  <Field long zzaw>
				else
	//*  51  119:aload           7
	//*  52  121:invokeinterface #208 <Method void Iterator.remove()>
	//*  53  126:iload_2         
	//*  54  127:iconst_1        
	//*  55  128:iadd            
	//*  56  129:istore_2        
	//*  57  130:aload_0         
	//*  58  131:getfield        #43  <Field long zzaw>
	//*  59  134:iload_1         
	//*  60  135:i2l             
	//*  61  136:ladd            
	//*  62  137:l2f             
	//*  63  138:aload_0         
	//*  64  139:getfield        #47  <Field int zzay>
	//*  65  142:i2f             
	//*  66  143:ldc1            #209 <Float 0.9F>
	//*  67  145:fmul            
	//*  68  146:fcmpg           
	//*  69  147:ifge            229
	//*  70  150:getstatic       #182 <Field boolean zzs.DEBUG>
	//*  71  153:ifeq            16
	//*  72  156:ldc1            #211 <String "pruned %d files, %d bytes, %d ms">
	//*  73  158:iconst_3        
	//*  74  159:anewarray       Object[]
	//*  75  162:dup             
	//*  76  163:iconst_0        
	//*  77  164:iload_2         
	//*  78  165:invokestatic    #217 <Method Integer Integer.valueOf(int)>
	//*  79  168:aastore         
	//*  80  169:dup             
	//*  81  170:iconst_1        
	//*  82  171:aload_0         
	//*  83  172:getfield        #43  <Field long zzaw>
	//*  84  175:lload_3         
	//*  85  176:lsub            
	//*  86  177:invokestatic    #222 <Method Long Long.valueOf(long)>
	//*  87  180:aastore         
	//*  88  181:dup             
	//*  89  182:iconst_2        
	//*  90  183:invokestatic    #193 <Method long SystemClock.elapsedRealtime()>
	//*  91  186:lload           5
	//*  92  188:lsub            
	//*  93  189:invokestatic    #222 <Method Long Long.valueOf(long)>
	//*  94  192:aastore         
	//*  95  193:invokestatic    #187 <Method void zzs.zza(String, Object[])>
	//*  96  196:return          
					zzs.zzb("Could not delete cache entry for key=%s, filename=%s", new Object[] {
						zza1.zzaA, zze(zza1.zzaA)
					});
	//   97  197:ldc1            #224 <String "Could not delete cache entry for key=%s, filename=%s">
	//   98  199:iconst_2        
	//   99  200:anewarray       Object[]
	//  100  203:dup             
	//  101  204:iconst_0        
	//  102  205:aload           8
	//  103  207:getfield        #197 <Field String zzv$zza.zzaA>
	//  104  210:aastore         
	//  105  211:dup             
	//  106  212:iconst_1        
	//  107  213:aload_0         
	//  108  214:aload           8
	//  109  216:getfield        #197 <Field String zzv$zza.zzaA>
	//  110  219:invokespecial   #228 <Method String zze(String)>
	//  111  222:aastore         
	//  112  223:invokestatic    #230 <Method void zzs.zzb(String, Object[])>
				iterator.remove();
				j++;
			} while((float)(zzaw + (long)i) >= (float)zzay * 0.9F);
			if(zzs.DEBUG)
			{
				zzs.zza("pruned %d files, %d bytes, %d ms", new Object[] {
					Integer.valueOf(j), Long.valueOf(zzaw - l), Long.valueOf(SystemClock.elapsedRealtime() - l1)
				});
				return;
			}
		}
	//* 113  226:goto            119
	//* 114  229:goto            60
	//* 115  232:goto            150
	}

	static String zzd(InputStream inputstream)
		throws IOException
	{
		return new String(zza(inputstream, (int)zzc(inputstream)), "UTF-8");
	//    0    0:new             #87  <Class String>
	//    1    3:dup             
	//    2    4:aload_0         
	//    3    5:aload_0         
	//    4    6:invokestatic    #234 <Method long zzc(InputStream)>
	//    5    9:l2i             
	//    6   10:invokestatic    #236 <Method byte[] zza(InputStream, int)>
	//    7   13:ldc1            #85  <String "UTF-8">
	//    8   15:invokespecial   #239 <Method void String(byte[], String)>
	//    9   18:areturn         
	}

	private String zze(String s)
	{
		int i = s.length() / 2;
	//    0    0:aload_1         
	//    1    1:invokevirtual   #242 <Method int String.length()>
	//    2    4:iconst_2        
	//    3    5:idiv            
	//    4    6:istore_2        
		String s1 = String.valueOf(((Object) (String.valueOf(s.substring(0, i).hashCode()))));
	//    5    7:aload_1         
	//    6    8:iconst_0        
	//    7    9:iload_2         
	//    8   10:invokevirtual   #246 <Method String String.substring(int, int)>
	//    9   13:invokevirtual   #249 <Method int String.hashCode()>
	//   10   16:invokestatic    #252 <Method String String.valueOf(int)>
	//   11   19:invokestatic    #255 <Method String String.valueOf(Object)>
	//   12   22:astore_3        
		s = String.valueOf(((Object) (String.valueOf(s.substring(i).hashCode()))));
	//   13   23:aload_1         
	//   14   24:iload_2         
	//   15   25:invokevirtual   #257 <Method String String.substring(int)>
	//   16   28:invokevirtual   #249 <Method int String.hashCode()>
	//   17   31:invokestatic    #252 <Method String String.valueOf(int)>
	//   18   34:invokestatic    #255 <Method String String.valueOf(Object)>
	//   19   37:astore_1        
		if(s.length() != 0)
	//*  20   38:aload_1         
	//*  21   39:invokevirtual   #242 <Method int String.length()>
	//*  22   42:ifeq            51
			return s1.concat(s);
	//   23   45:aload_3         
	//   24   46:aload_1         
	//   25   47:invokevirtual   #260 <Method String String.concat(String)>
	//   26   50:areturn         
		else
			return new String(s1);
	//   27   51:new             #87  <Class String>
	//   28   54:dup             
	//   29   55:aload_3         
	//   30   56:invokespecial   #261 <Method void String(String)>
	//   31   59:areturn         
	}

	static Map zze(InputStream inputstream)
		throws IOException
	{
		int j = zzb(inputstream);
	//    0    0:aload_0         
	//    1    1:invokestatic    #264 <Method int zzb(InputStream)>
	//    2    4:istore_2        
		int i;
		Object obj;
		if(j == 0)
	//*   3    5:iload_2         
	//*   4    6:ifne            48
			obj = ((Object) (Collections.emptyMap()));
	//    5    9:invokestatic    #270 <Method Map Collections.emptyMap()>
	//    6   12:astore_3        
		else
	//*   7   13:iconst_0        
	//*   8   14:istore_1        
	//*   9   15:iload_1         
	//*  10   16:iload_2         
	//*  11   17:icmpge          60
	//*  12   20:aload_3         
	//*  13   21:aload_0         
	//*  14   22:invokestatic    #272 <Method String zzd(InputStream)>
	//*  15   25:invokevirtual   #275 <Method String String.intern()>
	//*  16   28:aload_0         
	//*  17   29:invokestatic    #272 <Method String zzd(InputStream)>
	//*  18   32:invokevirtual   #275 <Method String String.intern()>
	//*  19   35:invokeinterface #105 <Method Object Map.put(Object, Object)>
	//*  20   40:pop             
	//*  21   41:iload_1         
	//*  22   42:iconst_1        
	//*  23   43:iadd            
	//*  24   44:istore_1        
	//*  25   45:goto            15
			obj = ((Object) (new HashMap(j)));
	//   26   48:new             #277 <Class HashMap>
	//   27   51:dup             
	//   28   52:iload_2         
	//   29   53:invokespecial   #278 <Method void HashMap(int)>
	//   30   56:astore_3        
		for(i = 0; i < j; i++)
			((Map) (obj)).put(((Object) (zzd(inputstream).intern())), ((Object) (zzd(inputstream).intern())));

	//*  31   57:goto            13
		return ((Map) (obj));
	//   32   60:aload_3         
	//   33   61:areturn         
	}

	public void initialize()
	{
		this;
	//    0    0:aload_0         
		JVM INSTR monitorenter ;
	//    1    1:monitorenter    
		if(zzax.exists()) goto _L2; else goto _L1
	//    2    2:aload_0         
	//    3    3:getfield        #45  <Field File zzax>
	//    4    6:invokevirtual   #283 <Method boolean File.exists()>
	//    5    9:ifne            45
_L1:
		if(!zzax.mkdirs())
	//*   6   12:aload_0         
	//*   7   13:getfield        #45  <Field File zzax>
	//*   8   16:invokevirtual   #286 <Method boolean File.mkdirs()>
	//*   9   19:ifne            42
			zzs.zzc("Unable to create cache dir %s", new Object[] {
				zzax.getAbsolutePath()
			});
	//   10   22:ldc2            #288 <String "Unable to create cache dir %s">
	//   11   25:iconst_1        
	//   12   26:anewarray       Object[]
	//   13   29:dup             
	//   14   30:iconst_0        
	//   15   31:aload_0         
	//   16   32:getfield        #45  <Field File zzax>
	//   17   35:invokevirtual   #291 <Method String File.getAbsolutePath()>
	//   18   38:aastore         
	//   19   39:invokestatic    #293 <Method void zzs.zzc(String, Object[])>
_L6:
		this;
	//   20   42:aload_0         
		JVM INSTR monitorexit ;
	//   21   43:monitorexit     
		return;
	//   22   44:return          
_L2:
		File afile[] = zzax.listFiles();
	//   23   45:aload_0         
	//   24   46:getfield        #45  <Field File zzax>
	//   25   49:invokevirtual   #297 <Method File[] File.listFiles()>
	//   26   52:astore          5
		if(afile == null)
			continue; /* Loop/switch isn't completed */
	//   27   54:aload           5
	//   28   56:ifnull          42
		int j = afile.length;
	//   29   59:aload           5
	//   30   61:arraylength     
	//   31   62:istore_2        
		int i = 0;
	//   32   63:iconst_0        
	//   33   64:istore_1        
_L4:
		Object obj;
		File file;
		if(i >= j)
			break; /* Loop/switch isn't completed */
	//   34   65:iload_1         
	//   35   66:iload_2         
	//   36   67:icmpge          42
		file = afile[i];
	//   37   70:aload           5
	//   38   72:iload_1         
	//   39   73:aaload          
	//   40   74:astore          6
		obj = null;
	//   41   76:aconst_null     
	//   42   77:astore_3        
		Object obj1 = ((Object) (new BufferedInputStream(((InputStream) (new FileInputStream(file))))));
	//   43   78:new             #299 <Class BufferedInputStream>
	//   44   81:dup             
	//   45   82:new             #301 <Class FileInputStream>
	//   46   85:dup             
	//   47   86:aload           6
	//   48   88:invokespecial   #303 <Method void FileInputStream(File)>
	//   49   91:invokespecial   #306 <Method void BufferedInputStream(InputStream)>
	//   50   94:astore          4
		obj = obj1;
	//   51   96:aload           4
	//   52   98:astore_3        
		zza zza1 = zza.zzf(((InputStream) (obj1)));
	//   53   99:aload           4
	//   54  101:invokestatic    #309 <Method zzv$zza zzv$zza.zzf(InputStream)>
	//   55  104:astore          7
		obj = obj1;
	//   56  106:aload           4
	//   57  108:astore_3        
		zza1.zzaz = file.length();
	//   58  109:aload           7
	//   59  111:aload           6
	//   60  113:invokevirtual   #311 <Method long File.length()>
	//   61  116:putfield        #58  <Field long zzv$zza.zzaz>
		obj = obj1;
	//   62  119:aload           4
	//   63  121:astore_3        
		zza(zza1.zzaA, zza1);
	//   64  122:aload_0         
	//   65  123:aload           7
	//   66  125:getfield        #197 <Field String zzv$zza.zzaA>
	//   67  128:aload           7
	//   68  130:invokespecial   #313 <Method void zza(String, zzv$zza)>
		Exception exception;
		try
		{
			((BufferedInputStream) (obj1)).close();
	//   69  133:aload           4
	//   70  135:invokevirtual   #316 <Method void BufferedInputStream.close()>
		}
	//*  71  138:iload_1         
	//*  72  139:iconst_1        
	//*  73  140:iadd            
	//*  74  141:istore_1        
	//*  75  142:goto            65
	//*  76  145:astore_3        
	//*  77  146:aconst_null     
	//*  78  147:astore          4
	//*  79  149:aload           6
	//*  80  151:ifnull          163
	//*  81  154:aload           4
	//*  82  156:astore_3        
	//*  83  157:aload           6
	//*  84  159:invokevirtual   #206 <Method boolean File.delete()>
	//*  85  162:pop             
	//*  86  163:aload           4
	//*  87  165:ifnull          138
	//*  88  168:aload           4
	//*  89  170:invokevirtual   #316 <Method void BufferedInputStream.close()>
	//*  90  173:goto            138
	//*  91  176:astore_3        
	//*  92  177:goto            138
	//*  93  180:astore          5
	//*  94  182:aload_3         
	//*  95  183:astore          4
	//*  96  185:aload           5
	//*  97  187:astore_3        
	//*  98  188:aload           4
	//*  99  190:ifnull          198
	//* 100  193:aload           4
	//* 101  195:invokevirtual   #316 <Method void BufferedInputStream.close()>
	//* 102  198:aload_3         
	//* 103  199:athrow          
	//* 104  200:astore_3        
	//* 105  201:aload_0         
	//* 106  202:monitorexit     
	//* 107  203:aload_3         
	//* 108  204:athrow          
		// Misplaced declaration of an exception variable
		catch(Object obj) { }
	//  109  205:astore_3        
		i++;
		if(true) goto _L4; else goto _L3
_L3:
		if(true) goto _L6; else goto _L5
_L5:
		obj;
		obj1 = null;
_L10:
		if(file == null)
			break MISSING_BLOCK_LABEL_163;
		obj = obj1;
		file.delete();
		if(obj1 == null)
			break MISSING_BLOCK_LABEL_138;
		try
		{
			((BufferedInputStream) (obj1)).close();
		}
		// Misplaced declaration of an exception variable
		catch(Object obj) { }
		break MISSING_BLOCK_LABEL_138;
		exception;
		obj1 = obj;
		obj = ((Object) (exception));
_L8:
		if(obj1 == null)
			break MISSING_BLOCK_LABEL_198;
		try
		{
			((BufferedInputStream) (obj1)).close();
		}
	//* 110  206:goto            138
		// Misplaced declaration of an exception variable
		catch(Object obj1) { }
	//  111  209:astore          4
		throw obj;
		obj;
		this;
		JVM INSTR monitorexit ;
		throw obj;
	//* 112  211:goto            198
		exception;
	//  113  214:astore          5
		obj1 = obj;
	//  114  216:aload_3         
	//  115  217:astore          4
		obj = ((Object) (exception));
	//  116  219:aload           5
	//  117  221:astore_3        
		if(true) goto _L8; else goto _L7
	//  118  222:goto            188
_L7:
		IOException ioexception;
		ioexception;
	//  119  225:astore_3        
		if(true) goto _L10; else goto _L9
_L9:
	//* 120  226:goto            149
	}

	public void remove(String s)
	{
		this;
	//    0    0:aload_0         
		JVM INSTR monitorenter ;
	//    1    1:monitorenter    
		boolean flag;
		flag = zzf(s).delete();
	//    2    2:aload_0         
	//    3    3:aload_1         
	//    4    4:invokevirtual   #201 <Method File zzf(String)>
	//    5    7:invokevirtual   #206 <Method boolean File.delete()>
	//    6   10:istore_2        
		removeEntry(s);
	//    7   11:aload_0         
	//    8   12:aload_1         
	//    9   13:invokespecial   #318 <Method void removeEntry(String)>
		if(flag)
			break MISSING_BLOCK_LABEL_41;
	//   10   16:iload_2         
	//   11   17:ifne            41
		zzs.zzb("Could not delete cache entry for key=%s, filename=%s", new Object[] {
			s, zze(s)
		});
	//   12   20:ldc1            #224 <String "Could not delete cache entry for key=%s, filename=%s">
	//   13   22:iconst_2        
	//   14   23:anewarray       Object[]
	//   15   26:dup             
	//   16   27:iconst_0        
	//   17   28:aload_1         
	//   18   29:aastore         
	//   19   30:dup             
	//   20   31:iconst_1        
	//   21   32:aload_0         
	//   22   33:aload_1         
	//   23   34:invokespecial   #228 <Method String zze(String)>
	//   24   37:aastore         
	//   25   38:invokestatic    #230 <Method void zzs.zzb(String, Object[])>
		this;
	//   26   41:aload_0         
		JVM INSTR monitorexit ;
	//   27   42:monitorexit     
		return;
	//   28   43:return          
		s;
	//   29   44:astore_1        
	//*  30   45:aload_0         
		throw s;
	//   31   46:monitorexit     
	//   32   47:aload_1         
	//   33   48:athrow          
	}

	public zzb.zza zza(String s)
	{
		this;
	//    0    0:aload_0         
		JVM INSTR monitorenter ;
	//    1    1:monitorenter    
		Object obj = ((Object) ((zza)zzav.get(((Object) (s)))));
	//    2    2:aload_0         
	//    3    3:getfield        #41  <Field Map zzav>
	//    4    6:aload_1         
	//    5    7:invokeinterface #55  <Method Object Map.get(Object)>
	//    6   12:checkcast       #10  <Class zzv$zza>
	//    7   15:astore          4
		if(obj != null) goto _L2; else goto _L1
	//    8   17:aload           4
	//    9   19:ifnonnull       28
_L1:
		s = null;
	//   10   22:aconst_null     
	//   11   23:astore_1        
_L3:
		this;
	//   12   24:aload_0         
		JVM INSTR monitorexit ;
	//   13   25:monitorexit     
		return ((zzb.zza) (s));
	//   14   26:aload_1         
	//   15   27:areturn         
_L2:
		File file = zzf(s);
	//   16   28:aload_0         
	//   17   29:aload_1         
	//   18   30:invokevirtual   #201 <Method File zzf(String)>
	//   19   33:astore          5
		zzb zzb2 = new zzb(((InputStream) (new FileInputStream(file))));
	//   20   35:new             #13  <Class zzv$zzb>
	//   21   38:dup             
	//   22   39:new             #301 <Class FileInputStream>
	//   23   42:dup             
	//   24   43:aload           5
	//   25   45:invokespecial   #303 <Method void FileInputStream(File)>
	//   26   48:aconst_null     
	//   27   49:invokespecial   #322 <Method void zzv$zzb(InputStream, zzv$1)>
	//   28   52:astore_3        
		zzb zzb1 = zzb2;
	//   29   53:aload_3         
	//   30   54:astore_2        
		zza.zzf(((InputStream) (zzb2)));
	//   31   55:aload_3         
	//   32   56:invokestatic    #309 <Method zzv$zza zzv$zza.zzf(InputStream)>
	//   33   59:pop             
		zzb1 = zzb2;
	//   34   60:aload_3         
	//   35   61:astore_2        
		obj = ((Object) (((zza) (obj)).zzb(zza(((InputStream) (zzb2)), (int)(file.length() - (long)zzb.zza(zzb2))))));
	//   36   62:aload           4
	//   37   64:aload_3         
	//   38   65:aload           5
	//   39   67:invokevirtual   #311 <Method long File.length()>
	//   40   70:aload_3         
	//   41   71:invokestatic    #325 <Method int zzv$zzb.zza(zzv$zzb)>
	//   42   74:i2l             
	//   43   75:lsub            
	//   44   76:l2i             
	//   45   77:invokestatic    #236 <Method byte[] zza(InputStream, int)>
	//   46   80:invokevirtual   #328 <Method zzb$zza zzv$zza.zzb(byte[])>
	//   47   83:astore          4
		s = ((String) (obj));
	//   48   85:aload           4
	//   49   87:astore_1        
		try
		{
			zzb2.close();
	//   50   88:aload_3         
	//   51   89:invokevirtual   #329 <Method void zzv$zzb.close()>
		}
	//*  52   92:goto            24
		// Misplaced declaration of an exception variable
		catch(String s)
	//*  53   95:astore_1        
		{
			s = null;
	//   54   96:aconst_null     
	//   55   97:astore_1        
		}
		  goto _L3
	//*  56   98:goto            24
		IOException ioexception;
		ioexception;
	//   57  101:astore          4
		zzb2 = null;
	//   58  103:aconst_null     
	//   59  104:astore_3        
_L5:
		zzb1 = zzb2;
	//   60  105:aload_3         
	//   61  106:astore_2        
		zzs.zzb("%s: %s", new Object[] {
			file.getAbsolutePath(), ioexception.toString()
		});
	//   62  107:ldc2            #331 <String "%s: %s">
	//   63  110:iconst_2        
	//   64  111:anewarray       Object[]
	//   65  114:dup             
	//   66  115:iconst_0        
	//   67  116:aload           5
	//   68  118:invokevirtual   #291 <Method String File.getAbsolutePath()>
	//   69  121:aastore         
	//   70  122:dup             
	//   71  123:iconst_1        
	//   72  124:aload           4
	//   73  126:invokevirtual   #332 <Method String IOException.toString()>
	//   74  129:aastore         
	//   75  130:invokestatic    #230 <Method void zzs.zzb(String, Object[])>
		zzb1 = zzb2;
	//   76  133:aload_3         
	//   77  134:astore_2        
		remove(s);
	//   78  135:aload_0         
	//   79  136:aload_1         
	//   80  137:invokevirtual   #334 <Method void remove(String)>
		if(zzb2 == null)
			break MISSING_BLOCK_LABEL_148;
	//   81  140:aload_3         
	//   82  141:ifnull          148
		zzb2.close();
	//   83  144:aload_3         
	//   84  145:invokevirtual   #329 <Method void zzv$zzb.close()>
		s = null;
	//   85  148:aconst_null     
	//   86  149:astore_1        
		  goto _L3
	//*  87  150:goto            24
		s;
	//   88  153:astore_1        
		s = null;
	//   89  154:aconst_null     
	//   90  155:astore_1        
		  goto _L3
	//*  91  156:goto            24
		s;
	//   92  159:astore_1        
		zzb1 = null;
	//   93  160:aconst_null     
	//   94  161:astore_2        
_L4:
		if(zzb1 == null)
			break MISSING_BLOCK_LABEL_170;
	//   95  162:aload_2         
	//   96  163:ifnull          170
		zzb1.close();
	//   97  166:aload_2         
	//   98  167:invokevirtual   #329 <Method void zzv$zzb.close()>
		throw s;
	//   99  170:aload_1         
	//  100  171:athrow          
		s;
	//  101  172:astore_1        
		this;
	//  102  173:aload_0         
		JVM INSTR monitorexit ;
	//  103  174:monitorexit     
		throw s;
	//  104  175:aload_1         
	//  105  176:athrow          
		s;
	//  106  177:astore_1        
		s = null;
	//  107  178:aconst_null     
	//  108  179:astore_1        
		  goto _L3
	//* 109  180:goto            24
		s;
	//  110  183:astore_1        
		  goto _L4
	//* 111  184:goto            162
		ioexception;
	//  112  187:astore          4
		  goto _L5
	//* 113  189:goto            105
	}

	public void zza(String s, zzb.zza zza1)
	{
		this;
	//    0    0:aload_0         
		JVM INSTR monitorenter ;
	//    1    1:monitorenter    
		File file;
		FileOutputStream fileoutputstream;
		zza zza2;
		zzc(zza1.data.length);
	//    2    2:aload_0         
	//    3    3:aload_2         
	//    4    4:getfield        #341 <Field byte[] zzb$zza.data>
	//    5    7:arraylength     
	//    6    8:invokespecial   #343 <Method void zzc(int)>
		file = zzf(s);
	//    7   11:aload_0         
	//    8   12:aload_1         
	//    9   13:invokevirtual   #201 <Method File zzf(String)>
	//   10   16:astore_3        
		try
		{
			fileoutputstream = new FileOutputStream(file);
	//   11   17:new             #345 <Class FileOutputStream>
	//   12   20:dup             
	//   13   21:aload_3         
	//   14   22:invokespecial   #346 <Method void FileOutputStream(File)>
	//   15   25:astore          4
			zza2 = new zza(s, zza1);
	//   16   27:new             #10  <Class zzv$zza>
	//   17   30:dup             
	//   18   31:aload_1         
	//   19   32:aload_2         
	//   20   33:invokespecial   #348 <Method void zzv$zza(String, zzb$zza)>
	//   21   36:astore          5
			if(!zza2.zza(((OutputStream) (fileoutputstream))))
	//*  22   38:aload           5
	//*  23   40:aload           4
	//*  24   42:invokevirtual   #351 <Method boolean zzv$zza.zza(OutputStream)>
	//*  25   45:ifne            106
			{
				fileoutputstream.close();
	//   26   48:aload           4
	//   27   50:invokevirtual   #352 <Method void FileOutputStream.close()>
				zzs.zzb("Failed to write header for %s", new Object[] {
					file.getAbsolutePath()
				});
	//   28   53:ldc2            #354 <String "Failed to write header for %s">
	//   29   56:iconst_1        
	//   30   57:anewarray       Object[]
	//   31   60:dup             
	//   32   61:iconst_0        
	//   33   62:aload_3         
	//   34   63:invokevirtual   #291 <Method String File.getAbsolutePath()>
	//   35   66:aastore         
	//   36   67:invokestatic    #230 <Method void zzs.zzb(String, Object[])>
				throw new IOException();
	//   37   70:new             #64  <Class IOException>
	//   38   73:dup             
	//   39   74:invokespecial   #355 <Method void IOException()>
	//   40   77:athrow          
			}
			break MISSING_BLOCK_LABEL_106;
		}
		// Misplaced declaration of an exception variable
		catch(String s) { }
	//   41   78:astore_1        
		if(!file.delete())
	//*  42   79:aload_3         
	//*  43   80:invokevirtual   #206 <Method boolean File.delete()>
	//*  44   83:ifne            103
			zzs.zzb("Could not clean up file %s", new Object[] {
				file.getAbsolutePath()
			});
	//   45   86:ldc2            #357 <String "Could not clean up file %s">
	//   46   89:iconst_1        
	//   47   90:anewarray       Object[]
	//   48   93:dup             
	//   49   94:iconst_0        
	//   50   95:aload_3         
	//   51   96:invokevirtual   #291 <Method String File.getAbsolutePath()>
	//   52   99:aastore         
	//   53  100:invokestatic    #230 <Method void zzs.zzb(String, Object[])>
_L1:
		this;
	//   54  103:aload_0         
		JVM INSTR monitorexit ;
	//   55  104:monitorexit     
		return;
	//   56  105:return          
		fileoutputstream.write(zza1.data);
	//   57  106:aload           4
	//   58  108:aload_2         
	//   59  109:getfield        #341 <Field byte[] zzb$zza.data>
	//   60  112:invokevirtual   #360 <Method void FileOutputStream.write(byte[])>
		fileoutputstream.close();
	//   61  115:aload           4
	//   62  117:invokevirtual   #352 <Method void FileOutputStream.close()>
		zza(s, zza2);
	//   63  120:aload_0         
	//   64  121:aload_1         
	//   65  122:aload           5
	//   66  124:invokespecial   #313 <Method void zza(String, zzv$zza)>
		  goto _L1
	//*  67  127:goto            103
		s;
	//   68  130:astore_1        
	//*  69  131:aload_0         
		throw s;
	//   70  132:monitorexit     
	//   71  133:aload_1         
	//   72  134:athrow          
	}

	public File zzf(String s)
	{
		return new File(zzax, zze(s));
	//    0    0:new             #203 <Class File>
	//    1    3:dup             
	//    2    4:aload_0         
	//    3    5:getfield        #45  <Field File zzax>
	//    4    8:aload_0         
	//    5    9:aload_1         
	//    6   10:invokespecial   #228 <Method String zze(String)>
	//    7   13:invokespecial   #363 <Method void File(File, String)>
	//    8   16:areturn         
	}

	private final Map zzav;
	private long zzaw;
	private final File zzax;
	private final int zzay;
}
