// Decompiled by Jad v1.5.8g. Copyright 2001 Pavel Kouznetsov.
// Jad home page: http://www.kpdus.com/jad.html
// Decompiler options: packimports(3) annotate safe 

package com.google.android.gms.internal.clearcut;


// Referenced classes of package com.google.android.gms.internal.clearcut:
//			zzcg, zzdq, zzge, zzgf, 
//			zzdz, zzcj, zzgo, zzck, 
//			zzgp

public static final class zzge$zzs extends zzcg
	implements zzdq
{
	public static final class zza extends zzcg.zza
		implements zzdq
	{

		private zza()
		{
			super(((zzcg) (zzge.zzs.zzfl())));
		//    0    0:aload_0         
		//    1    1:invokestatic    #19  <Method zzge$zzs zzge$zzs.zzfl()>
		//    2    4:invokespecial   #22  <Method void zzcg$zza(zzcg)>
		//    3    7:return          
		}

		zza(zzgf zzgf1)
		{
			this();
		//    0    0:aload_0         
		//    1    1:invokespecial   #26  <Method void zzge$zzs$zza()>
		//    2    4:return          
		}
	}

	public static final class zzb extends Enum
		implements zzcj
	{

		public static zzb[] values()
		{
			return (zzb[])((zzb []) (zzbfy)).clone();
		//    0    0:getstatic       #134 <Field zzge$zzs$zzb[] zzbfy>
		//    1    3:invokevirtual   #155 <Method Object _5B_Lcom.google.android.gms.internal.clearcut.zzge$zzs$zzb_3B_.clone()>
		//    2    6:checkcast       #151 <Class zzge$zzs$zzb[]>
		//    3    9:areturn         
		}

		public static zzb zzaz(int i)
		{
			if(i != 100)
		//*   0    0:iload_0         
		//*   1    1:bipush          100
		//*   2    3:icmpeq          182
				switch(i)
		//*   3    6:iload_0         
				{
		//*   4    7:tableswitch     0 19: default 100
		//		               0 178
		//		               1 174
		//		               2 170
		//		               3 166
		//		               4 162
		//		               5 158
		//		               6 154
		//		               7 150
		//		               8 146
		//		               9 142
		//		               10 138
		//		               11 134
		//		               12 130
		//		               13 126
		//		               14 122
		//		               15 118
		//		               16 114
		//		               17 110
		//		               18 106
		//		               19 102
				default:
					return null;
		//    5  100:aconst_null     
		//    6  101:areturn         

				case 19: // '\023'
					return zzbfw;
		//    7  102:getstatic       #128 <Field zzge$zzs$zzb zzbfw>
		//    8  105:areturn         

				case 18: // '\022'
					return zzbfv;
		//    9  106:getstatic       #124 <Field zzge$zzs$zzb zzbfv>
		//   10  109:areturn         

				case 17: // '\021'
					return zzbfu;
		//   11  110:getstatic       #120 <Field zzge$zzs$zzb zzbfu>
		//   12  113:areturn         

				case 16: // '\020'
					return zzbft;
		//   13  114:getstatic       #116 <Field zzge$zzs$zzb zzbft>
		//   14  117:areturn         

				case 15: // '\017'
					return zzbfs;
		//   15  118:getstatic       #112 <Field zzge$zzs$zzb zzbfs>
		//   16  121:areturn         

				case 14: // '\016'
					return zzbfr;
		//   17  122:getstatic       #108 <Field zzge$zzs$zzb zzbfr>
		//   18  125:areturn         

				case 13: // '\r'
					return zzbfq;
		//   19  126:getstatic       #104 <Field zzge$zzs$zzb zzbfq>
		//   20  129:areturn         

				case 12: // '\f'
					return zzbfp;
		//   21  130:getstatic       #100 <Field zzge$zzs$zzb zzbfp>
		//   22  133:areturn         

				case 11: // '\013'
					return zzbfo;
		//   23  134:getstatic       #96  <Field zzge$zzs$zzb zzbfo>
		//   24  137:areturn         

				case 10: // '\n'
					return zzbfn;
		//   25  138:getstatic       #92  <Field zzge$zzs$zzb zzbfn>
		//   26  141:areturn         

				case 9: // '\t'
					return zzbfm;
		//   27  142:getstatic       #88  <Field zzge$zzs$zzb zzbfm>
		//   28  145:areturn         

				case 8: // '\b'
					return zzbfl;
		//   29  146:getstatic       #84  <Field zzge$zzs$zzb zzbfl>
		//   30  149:areturn         

				case 7: // '\007'
					return zzbfk;
		//   31  150:getstatic       #80  <Field zzge$zzs$zzb zzbfk>
		//   32  153:areturn         

				case 6: // '\006'
					return zzbfj;
		//   33  154:getstatic       #76  <Field zzge$zzs$zzb zzbfj>
		//   34  157:areturn         

				case 5: // '\005'
					return zzbfi;
		//   35  158:getstatic       #72  <Field zzge$zzs$zzb zzbfi>
		//   36  161:areturn         

				case 4: // '\004'
					return zzbfh;
		//   37  162:getstatic       #68  <Field zzge$zzs$zzb zzbfh>
		//   38  165:areturn         

				case 3: // '\003'
					return zzbfg;
		//   39  166:getstatic       #64  <Field zzge$zzs$zzb zzbfg>
		//   40  169:areturn         

				case 2: // '\002'
					return zzbff;
		//   41  170:getstatic       #60  <Field zzge$zzs$zzb zzbff>
		//   42  173:areturn         

				case 1: // '\001'
					return zzbfe;
		//   43  174:getstatic       #56  <Field zzge$zzs$zzb zzbfe>
		//   44  177:areturn         

				case 0: // '\0'
					return zzbfd;
		//   45  178:getstatic       #52  <Field zzge$zzs$zzb zzbfd>
		//   46  181:areturn         
				}
			else
				return zzbfx;
		//   47  182:getstatic       #132 <Field zzge$zzs$zzb zzbfx>
		//   48  185:areturn         
		}

		public static zzck zzd()
		{
			return zzbq;
		//    0    0:getstatic       #140 <Field zzck zzbq>
		//    1    3:areturn         
		}

		public final int zzc()
		{
			return value;
		//    0    0:aload_0         
		//    1    1:getfield        #146 <Field int value>
		//    2    4:ireturn         
		}

		private static final zzb zzbfd;
		private static final zzb zzbfe;
		private static final zzb zzbff;
		private static final zzb zzbfg;
		private static final zzb zzbfh;
		private static final zzb zzbfi;
		private static final zzb zzbfj;
		private static final zzb zzbfk;
		private static final zzb zzbfl;
		private static final zzb zzbfm;
		private static final zzb zzbfn;
		private static final zzb zzbfo;
		private static final zzb zzbfp;
		private static final zzb zzbfq;
		private static final zzb zzbfr;
		private static final zzb zzbfs;
		private static final zzb zzbft;
		private static final zzb zzbfu;
		private static final zzb zzbfv;
		private static final zzb zzbfw;
		private static final zzb zzbfx;
		private static final zzb zzbfy[];
		private static final zzck zzbq = new zzgo();
		private final int value;

		static 
		{
			zzbfd = new zzb("UNKNOWN_MOBILE_SUBTYPE", 0, 0);
		//    0    0:new             #2   <Class zzge$zzs$zzb>
		//    1    3:dup             
		//    2    4:ldc1            #46  <String "UNKNOWN_MOBILE_SUBTYPE">
		//    3    6:iconst_0        
		//    4    7:iconst_0        
		//    5    8:invokespecial   #50  <Method void zzge$zzs$zzb(String, int, int)>
		//    6   11:putstatic       #52  <Field zzge$zzs$zzb zzbfd>
			zzbfe = new zzb("GPRS", 1, 1);
		//    7   14:new             #2   <Class zzge$zzs$zzb>
		//    8   17:dup             
		//    9   18:ldc1            #54  <String "GPRS">
		//   10   20:iconst_1        
		//   11   21:iconst_1        
		//   12   22:invokespecial   #50  <Method void zzge$zzs$zzb(String, int, int)>
		//   13   25:putstatic       #56  <Field zzge$zzs$zzb zzbfe>
			zzbff = new zzb("EDGE", 2, 2);
		//   14   28:new             #2   <Class zzge$zzs$zzb>
		//   15   31:dup             
		//   16   32:ldc1            #58  <String "EDGE">
		//   17   34:iconst_2        
		//   18   35:iconst_2        
		//   19   36:invokespecial   #50  <Method void zzge$zzs$zzb(String, int, int)>
		//   20   39:putstatic       #60  <Field zzge$zzs$zzb zzbff>
			zzbfg = new zzb("UMTS", 3, 3);
		//   21   42:new             #2   <Class zzge$zzs$zzb>
		//   22   45:dup             
		//   23   46:ldc1            #62  <String "UMTS">
		//   24   48:iconst_3        
		//   25   49:iconst_3        
		//   26   50:invokespecial   #50  <Method void zzge$zzs$zzb(String, int, int)>
		//   27   53:putstatic       #64  <Field zzge$zzs$zzb zzbfg>
			zzbfh = new zzb("CDMA", 4, 4);
		//   28   56:new             #2   <Class zzge$zzs$zzb>
		//   29   59:dup             
		//   30   60:ldc1            #66  <String "CDMA">
		//   31   62:iconst_4        
		//   32   63:iconst_4        
		//   33   64:invokespecial   #50  <Method void zzge$zzs$zzb(String, int, int)>
		//   34   67:putstatic       #68  <Field zzge$zzs$zzb zzbfh>
			zzbfi = new zzb("EVDO_0", 5, 5);
		//   35   70:new             #2   <Class zzge$zzs$zzb>
		//   36   73:dup             
		//   37   74:ldc1            #70  <String "EVDO_0">
		//   38   76:iconst_5        
		//   39   77:iconst_5        
		//   40   78:invokespecial   #50  <Method void zzge$zzs$zzb(String, int, int)>
		//   41   81:putstatic       #72  <Field zzge$zzs$zzb zzbfi>
			zzbfj = new zzb("EVDO_A", 6, 6);
		//   42   84:new             #2   <Class zzge$zzs$zzb>
		//   43   87:dup             
		//   44   88:ldc1            #74  <String "EVDO_A">
		//   45   90:bipush          6
		//   46   92:bipush          6
		//   47   94:invokespecial   #50  <Method void zzge$zzs$zzb(String, int, int)>
		//   48   97:putstatic       #76  <Field zzge$zzs$zzb zzbfj>
			zzbfk = new zzb("RTT", 7, 7);
		//   49  100:new             #2   <Class zzge$zzs$zzb>
		//   50  103:dup             
		//   51  104:ldc1            #78  <String "RTT">
		//   52  106:bipush          7
		//   53  108:bipush          7
		//   54  110:invokespecial   #50  <Method void zzge$zzs$zzb(String, int, int)>
		//   55  113:putstatic       #80  <Field zzge$zzs$zzb zzbfk>
			zzbfl = new zzb("HSDPA", 8, 8);
		//   56  116:new             #2   <Class zzge$zzs$zzb>
		//   57  119:dup             
		//   58  120:ldc1            #82  <String "HSDPA">
		//   59  122:bipush          8
		//   60  124:bipush          8
		//   61  126:invokespecial   #50  <Method void zzge$zzs$zzb(String, int, int)>
		//   62  129:putstatic       #84  <Field zzge$zzs$zzb zzbfl>
			zzbfm = new zzb("HSUPA", 9, 9);
		//   63  132:new             #2   <Class zzge$zzs$zzb>
		//   64  135:dup             
		//   65  136:ldc1            #86  <String "HSUPA">
		//   66  138:bipush          9
		//   67  140:bipush          9
		//   68  142:invokespecial   #50  <Method void zzge$zzs$zzb(String, int, int)>
		//   69  145:putstatic       #88  <Field zzge$zzs$zzb zzbfm>
			zzbfn = new zzb("HSPA", 10, 10);
		//   70  148:new             #2   <Class zzge$zzs$zzb>
		//   71  151:dup             
		//   72  152:ldc1            #90  <String "HSPA">
		//   73  154:bipush          10
		//   74  156:bipush          10
		//   75  158:invokespecial   #50  <Method void zzge$zzs$zzb(String, int, int)>
		//   76  161:putstatic       #92  <Field zzge$zzs$zzb zzbfn>
			zzbfo = new zzb("IDEN", 11, 11);
		//   77  164:new             #2   <Class zzge$zzs$zzb>
		//   78  167:dup             
		//   79  168:ldc1            #94  <String "IDEN">
		//   80  170:bipush          11
		//   81  172:bipush          11
		//   82  174:invokespecial   #50  <Method void zzge$zzs$zzb(String, int, int)>
		//   83  177:putstatic       #96  <Field zzge$zzs$zzb zzbfo>
			zzbfp = new zzb("EVDO_B", 12, 12);
		//   84  180:new             #2   <Class zzge$zzs$zzb>
		//   85  183:dup             
		//   86  184:ldc1            #98  <String "EVDO_B">
		//   87  186:bipush          12
		//   88  188:bipush          12
		//   89  190:invokespecial   #50  <Method void zzge$zzs$zzb(String, int, int)>
		//   90  193:putstatic       #100 <Field zzge$zzs$zzb zzbfp>
			zzbfq = new zzb("LTE", 13, 13);
		//   91  196:new             #2   <Class zzge$zzs$zzb>
		//   92  199:dup             
		//   93  200:ldc1            #102 <String "LTE">
		//   94  202:bipush          13
		//   95  204:bipush          13
		//   96  206:invokespecial   #50  <Method void zzge$zzs$zzb(String, int, int)>
		//   97  209:putstatic       #104 <Field zzge$zzs$zzb zzbfq>
			zzbfr = new zzb("EHRPD", 14, 14);
		//   98  212:new             #2   <Class zzge$zzs$zzb>
		//   99  215:dup             
		//  100  216:ldc1            #106 <String "EHRPD">
		//  101  218:bipush          14
		//  102  220:bipush          14
		//  103  222:invokespecial   #50  <Method void zzge$zzs$zzb(String, int, int)>
		//  104  225:putstatic       #108 <Field zzge$zzs$zzb zzbfr>
			zzbfs = new zzb("HSPAP", 15, 15);
		//  105  228:new             #2   <Class zzge$zzs$zzb>
		//  106  231:dup             
		//  107  232:ldc1            #110 <String "HSPAP">
		//  108  234:bipush          15
		//  109  236:bipush          15
		//  110  238:invokespecial   #50  <Method void zzge$zzs$zzb(String, int, int)>
		//  111  241:putstatic       #112 <Field zzge$zzs$zzb zzbfs>
			zzbft = new zzb("GSM", 16, 16);
		//  112  244:new             #2   <Class zzge$zzs$zzb>
		//  113  247:dup             
		//  114  248:ldc1            #114 <String "GSM">
		//  115  250:bipush          16
		//  116  252:bipush          16
		//  117  254:invokespecial   #50  <Method void zzge$zzs$zzb(String, int, int)>
		//  118  257:putstatic       #116 <Field zzge$zzs$zzb zzbft>
			zzbfu = new zzb("TD_SCDMA", 17, 17);
		//  119  260:new             #2   <Class zzge$zzs$zzb>
		//  120  263:dup             
		//  121  264:ldc1            #118 <String "TD_SCDMA">
		//  122  266:bipush          17
		//  123  268:bipush          17
		//  124  270:invokespecial   #50  <Method void zzge$zzs$zzb(String, int, int)>
		//  125  273:putstatic       #120 <Field zzge$zzs$zzb zzbfu>
			zzbfv = new zzb("IWLAN", 18, 18);
		//  126  276:new             #2   <Class zzge$zzs$zzb>
		//  127  279:dup             
		//  128  280:ldc1            #122 <String "IWLAN">
		//  129  282:bipush          18
		//  130  284:bipush          18
		//  131  286:invokespecial   #50  <Method void zzge$zzs$zzb(String, int, int)>
		//  132  289:putstatic       #124 <Field zzge$zzs$zzb zzbfv>
			zzbfw = new zzb("LTE_CA", 19, 19);
		//  133  292:new             #2   <Class zzge$zzs$zzb>
		//  134  295:dup             
		//  135  296:ldc1            #126 <String "LTE_CA">
		//  136  298:bipush          19
		//  137  300:bipush          19
		//  138  302:invokespecial   #50  <Method void zzge$zzs$zzb(String, int, int)>
		//  139  305:putstatic       #128 <Field zzge$zzs$zzb zzbfw>
			zzbfx = new zzb("COMBINED", 20, 100);
		//  140  308:new             #2   <Class zzge$zzs$zzb>
		//  141  311:dup             
		//  142  312:ldc1            #130 <String "COMBINED">
		//  143  314:bipush          20
		//  144  316:bipush          100
		//  145  318:invokespecial   #50  <Method void zzge$zzs$zzb(String, int, int)>
		//  146  321:putstatic       #132 <Field zzge$zzs$zzb zzbfx>
			zzbfy = (new zzb[] {
				zzbfd, zzbfe, zzbff, zzbfg, zzbfh, zzbfi, zzbfj, zzbfk, zzbfl, zzbfm, 
				zzbfn, zzbfo, zzbfp, zzbfq, zzbfr, zzbfs, zzbft, zzbfu, zzbfv, zzbfw, 
				zzbfx
			});
		//  147  324:bipush          21
		//  148  326:anewarray       zzb[]
		//  149  329:dup             
		//  150  330:iconst_0        
		//  151  331:getstatic       #52  <Field zzge$zzs$zzb zzbfd>
		//  152  334:aastore         
		//  153  335:dup             
		//  154  336:iconst_1        
		//  155  337:getstatic       #56  <Field zzge$zzs$zzb zzbfe>
		//  156  340:aastore         
		//  157  341:dup             
		//  158  342:iconst_2        
		//  159  343:getstatic       #60  <Field zzge$zzs$zzb zzbff>
		//  160  346:aastore         
		//  161  347:dup             
		//  162  348:iconst_3        
		//  163  349:getstatic       #64  <Field zzge$zzs$zzb zzbfg>
		//  164  352:aastore         
		//  165  353:dup             
		//  166  354:iconst_4        
		//  167  355:getstatic       #68  <Field zzge$zzs$zzb zzbfh>
		//  168  358:aastore         
		//  169  359:dup             
		//  170  360:iconst_5        
		//  171  361:getstatic       #72  <Field zzge$zzs$zzb zzbfi>
		//  172  364:aastore         
		//  173  365:dup             
		//  174  366:bipush          6
		//  175  368:getstatic       #76  <Field zzge$zzs$zzb zzbfj>
		//  176  371:aastore         
		//  177  372:dup             
		//  178  373:bipush          7
		//  179  375:getstatic       #80  <Field zzge$zzs$zzb zzbfk>
		//  180  378:aastore         
		//  181  379:dup             
		//  182  380:bipush          8
		//  183  382:getstatic       #84  <Field zzge$zzs$zzb zzbfl>
		//  184  385:aastore         
		//  185  386:dup             
		//  186  387:bipush          9
		//  187  389:getstatic       #88  <Field zzge$zzs$zzb zzbfm>
		//  188  392:aastore         
		//  189  393:dup             
		//  190  394:bipush          10
		//  191  396:getstatic       #92  <Field zzge$zzs$zzb zzbfn>
		//  192  399:aastore         
		//  193  400:dup             
		//  194  401:bipush          11
		//  195  403:getstatic       #96  <Field zzge$zzs$zzb zzbfo>
		//  196  406:aastore         
		//  197  407:dup             
		//  198  408:bipush          12
		//  199  410:getstatic       #100 <Field zzge$zzs$zzb zzbfp>
		//  200  413:aastore         
		//  201  414:dup             
		//  202  415:bipush          13
		//  203  417:getstatic       #104 <Field zzge$zzs$zzb zzbfq>
		//  204  420:aastore         
		//  205  421:dup             
		//  206  422:bipush          14
		//  207  424:getstatic       #108 <Field zzge$zzs$zzb zzbfr>
		//  208  427:aastore         
		//  209  428:dup             
		//  210  429:bipush          15
		//  211  431:getstatic       #112 <Field zzge$zzs$zzb zzbfs>
		//  212  434:aastore         
		//  213  435:dup             
		//  214  436:bipush          16
		//  215  438:getstatic       #116 <Field zzge$zzs$zzb zzbft>
		//  216  441:aastore         
		//  217  442:dup             
		//  218  443:bipush          17
		//  219  445:getstatic       #120 <Field zzge$zzs$zzb zzbfu>
		//  220  448:aastore         
		//  221  449:dup             
		//  222  450:bipush          18
		//  223  452:getstatic       #124 <Field zzge$zzs$zzb zzbfv>
		//  224  455:aastore         
		//  225  456:dup             
		//  226  457:bipush          19
		//  227  459:getstatic       #128 <Field zzge$zzs$zzb zzbfw>
		//  228  462:aastore         
		//  229  463:dup             
		//  230  464:bipush          20
		//  231  466:getstatic       #132 <Field zzge$zzs$zzb zzbfx>
		//  232  469:aastore         
		//  233  470:putstatic       #134 <Field zzge$zzs$zzb[] zzbfy>
		//  234  473:new             #136 <Class zzgo>
		//  235  476:dup             
		//  236  477:invokespecial   #138 <Method void zzgo()>
		//  237  480:putstatic       #140 <Field zzck zzbq>
		//* 238  483:return          
		}

		private zzb(String s, int i, int j)
		{
			super(s, i);
		//    0    0:aload_0         
		//    1    1:aload_1         
		//    2    2:iload_2         
		//    3    3:invokespecial   #144 <Method void Enum(String, int)>
			value = j;
		//    4    6:aload_0         
		//    5    7:iload_3         
		//    6    8:putfield        #146 <Field int value>
		//    7   11:return          
		}
	}

	public static final class zzc extends Enum
		implements zzcj
	{

		public static zzc[] values()
		{
			return (zzc[])((zzc []) (zzbgs)).clone();
		//    0    0:getstatic       #124 <Field zzge$zzs$zzc[] zzbgs>
		//    1    3:invokevirtual   #145 <Method Object _5B_Lcom.google.android.gms.internal.clearcut.zzge$zzs$zzc_3B_.clone()>
		//    2    6:checkcast       #141 <Class zzge$zzs$zzc[]>
		//    3    9:areturn         
		}

		public static zzc zzba(int i)
		{
			switch(i)
		//*   0    0:iload_0         
			{
		//*   1    1:tableswitch     -1 17: default 92
		//		               -1 166
		//		               0 162
		//		               1 158
		//		               2 154
		//		               3 150
		//		               4 146
		//		               5 142
		//		               6 138
		//		               7 134
		//		               8 130
		//		               9 126
		//		               10 122
		//		               11 118
		//		               12 114
		//		               13 110
		//		               14 106
		//		               15 102
		//		               16 98
		//		               17 94
			default:
				return null;
		//    2   92:aconst_null     
		//    3   93:areturn         

			case 17: // '\021'
				return zzbgr;
		//    4   94:getstatic       #122 <Field zzge$zzs$zzc zzbgr>
		//    5   97:areturn         

			case 16: // '\020'
				return zzbgq;
		//    6   98:getstatic       #118 <Field zzge$zzs$zzc zzbgq>
		//    7  101:areturn         

			case 15: // '\017'
				return zzbgp;
		//    8  102:getstatic       #114 <Field zzge$zzs$zzc zzbgp>
		//    9  105:areturn         

			case 14: // '\016'
				return zzbgo;
		//   10  106:getstatic       #110 <Field zzge$zzs$zzc zzbgo>
		//   11  109:areturn         

			case 13: // '\r'
				return zzbgn;
		//   12  110:getstatic       #106 <Field zzge$zzs$zzc zzbgn>
		//   13  113:areturn         

			case 12: // '\f'
				return zzbgm;
		//   14  114:getstatic       #102 <Field zzge$zzs$zzc zzbgm>
		//   15  117:areturn         

			case 11: // '\013'
				return zzbgl;
		//   16  118:getstatic       #98  <Field zzge$zzs$zzc zzbgl>
		//   17  121:areturn         

			case 10: // '\n'
				return zzbgk;
		//   18  122:getstatic       #94  <Field zzge$zzs$zzc zzbgk>
		//   19  125:areturn         

			case 9: // '\t'
				return zzbgj;
		//   20  126:getstatic       #90  <Field zzge$zzs$zzc zzbgj>
		//   21  129:areturn         

			case 8: // '\b'
				return zzbgi;
		//   22  130:getstatic       #86  <Field zzge$zzs$zzc zzbgi>
		//   23  133:areturn         

			case 7: // '\007'
				return zzbgh;
		//   24  134:getstatic       #82  <Field zzge$zzs$zzc zzbgh>
		//   25  137:areturn         

			case 6: // '\006'
				return zzbgg;
		//   26  138:getstatic       #78  <Field zzge$zzs$zzc zzbgg>
		//   27  141:areturn         

			case 5: // '\005'
				return zzbgf;
		//   28  142:getstatic       #74  <Field zzge$zzs$zzc zzbgf>
		//   29  145:areturn         

			case 4: // '\004'
				return zzbge;
		//   30  146:getstatic       #70  <Field zzge$zzs$zzc zzbge>
		//   31  149:areturn         

			case 3: // '\003'
				return zzbgd;
		//   32  150:getstatic       #66  <Field zzge$zzs$zzc zzbgd>
		//   33  153:areturn         

			case 2: // '\002'
				return zzbgc;
		//   34  154:getstatic       #62  <Field zzge$zzs$zzc zzbgc>
		//   35  157:areturn         

			case 1: // '\001'
				return zzbgb;
		//   36  158:getstatic       #58  <Field zzge$zzs$zzc zzbgb>
		//   37  161:areturn         

			case 0: // '\0'
				return zzbga;
		//   38  162:getstatic       #54  <Field zzge$zzs$zzc zzbga>
		//   39  165:areturn         

			case -1: 
				return zzbfz;
		//   40  166:getstatic       #50  <Field zzge$zzs$zzc zzbfz>
		//   41  169:areturn         
			}
		}

		public static zzck zzd()
		{
			return zzbq;
		//    0    0:getstatic       #130 <Field zzck zzbq>
		//    1    3:areturn         
		}

		public final int zzc()
		{
			return value;
		//    0    0:aload_0         
		//    1    1:getfield        #136 <Field int value>
		//    2    4:ireturn         
		}

		private static final zzc zzbfz;
		private static final zzc zzbga;
		private static final zzc zzbgb;
		private static final zzc zzbgc;
		private static final zzc zzbgd;
		private static final zzc zzbge;
		private static final zzc zzbgf;
		private static final zzc zzbgg;
		private static final zzc zzbgh;
		private static final zzc zzbgi;
		private static final zzc zzbgj;
		private static final zzc zzbgk;
		private static final zzc zzbgl;
		private static final zzc zzbgm;
		private static final zzc zzbgn;
		private static final zzc zzbgo;
		private static final zzc zzbgp;
		private static final zzc zzbgq;
		private static final zzc zzbgr;
		private static final zzc zzbgs[];
		private static final zzck zzbq = new zzgp();
		private final int value;

		static 
		{
			zzbfz = new zzc("NONE", 0, -1);
		//    0    0:new             #2   <Class zzge$zzs$zzc>
		//    1    3:dup             
		//    2    4:ldc1            #44  <String "NONE">
		//    3    6:iconst_0        
		//    4    7:iconst_m1       
		//    5    8:invokespecial   #48  <Method void zzge$zzs$zzc(String, int, int)>
		//    6   11:putstatic       #50  <Field zzge$zzs$zzc zzbfz>
			zzbga = new zzc("MOBILE", 1, 0);
		//    7   14:new             #2   <Class zzge$zzs$zzc>
		//    8   17:dup             
		//    9   18:ldc1            #52  <String "MOBILE">
		//   10   20:iconst_1        
		//   11   21:iconst_0        
		//   12   22:invokespecial   #48  <Method void zzge$zzs$zzc(String, int, int)>
		//   13   25:putstatic       #54  <Field zzge$zzs$zzc zzbga>
			zzbgb = new zzc("WIFI", 2, 1);
		//   14   28:new             #2   <Class zzge$zzs$zzc>
		//   15   31:dup             
		//   16   32:ldc1            #56  <String "WIFI">
		//   17   34:iconst_2        
		//   18   35:iconst_1        
		//   19   36:invokespecial   #48  <Method void zzge$zzs$zzc(String, int, int)>
		//   20   39:putstatic       #58  <Field zzge$zzs$zzc zzbgb>
			zzbgc = new zzc("MOBILE_MMS", 3, 2);
		//   21   42:new             #2   <Class zzge$zzs$zzc>
		//   22   45:dup             
		//   23   46:ldc1            #60  <String "MOBILE_MMS">
		//   24   48:iconst_3        
		//   25   49:iconst_2        
		//   26   50:invokespecial   #48  <Method void zzge$zzs$zzc(String, int, int)>
		//   27   53:putstatic       #62  <Field zzge$zzs$zzc zzbgc>
			zzbgd = new zzc("MOBILE_SUPL", 4, 3);
		//   28   56:new             #2   <Class zzge$zzs$zzc>
		//   29   59:dup             
		//   30   60:ldc1            #64  <String "MOBILE_SUPL">
		//   31   62:iconst_4        
		//   32   63:iconst_3        
		//   33   64:invokespecial   #48  <Method void zzge$zzs$zzc(String, int, int)>
		//   34   67:putstatic       #66  <Field zzge$zzs$zzc zzbgd>
			zzbge = new zzc("MOBILE_DUN", 5, 4);
		//   35   70:new             #2   <Class zzge$zzs$zzc>
		//   36   73:dup             
		//   37   74:ldc1            #68  <String "MOBILE_DUN">
		//   38   76:iconst_5        
		//   39   77:iconst_4        
		//   40   78:invokespecial   #48  <Method void zzge$zzs$zzc(String, int, int)>
		//   41   81:putstatic       #70  <Field zzge$zzs$zzc zzbge>
			zzbgf = new zzc("MOBILE_HIPRI", 6, 5);
		//   42   84:new             #2   <Class zzge$zzs$zzc>
		//   43   87:dup             
		//   44   88:ldc1            #72  <String "MOBILE_HIPRI">
		//   45   90:bipush          6
		//   46   92:iconst_5        
		//   47   93:invokespecial   #48  <Method void zzge$zzs$zzc(String, int, int)>
		//   48   96:putstatic       #74  <Field zzge$zzs$zzc zzbgf>
			zzbgg = new zzc("WIMAX", 7, 6);
		//   49   99:new             #2   <Class zzge$zzs$zzc>
		//   50  102:dup             
		//   51  103:ldc1            #76  <String "WIMAX">
		//   52  105:bipush          7
		//   53  107:bipush          6
		//   54  109:invokespecial   #48  <Method void zzge$zzs$zzc(String, int, int)>
		//   55  112:putstatic       #78  <Field zzge$zzs$zzc zzbgg>
			zzbgh = new zzc("BLUETOOTH", 8, 7);
		//   56  115:new             #2   <Class zzge$zzs$zzc>
		//   57  118:dup             
		//   58  119:ldc1            #80  <String "BLUETOOTH">
		//   59  121:bipush          8
		//   60  123:bipush          7
		//   61  125:invokespecial   #48  <Method void zzge$zzs$zzc(String, int, int)>
		//   62  128:putstatic       #82  <Field zzge$zzs$zzc zzbgh>
			zzbgi = new zzc("DUMMY", 9, 8);
		//   63  131:new             #2   <Class zzge$zzs$zzc>
		//   64  134:dup             
		//   65  135:ldc1            #84  <String "DUMMY">
		//   66  137:bipush          9
		//   67  139:bipush          8
		//   68  141:invokespecial   #48  <Method void zzge$zzs$zzc(String, int, int)>
		//   69  144:putstatic       #86  <Field zzge$zzs$zzc zzbgi>
			zzbgj = new zzc("ETHERNET", 10, 9);
		//   70  147:new             #2   <Class zzge$zzs$zzc>
		//   71  150:dup             
		//   72  151:ldc1            #88  <String "ETHERNET">
		//   73  153:bipush          10
		//   74  155:bipush          9
		//   75  157:invokespecial   #48  <Method void zzge$zzs$zzc(String, int, int)>
		//   76  160:putstatic       #90  <Field zzge$zzs$zzc zzbgj>
			zzbgk = new zzc("MOBILE_FOTA", 11, 10);
		//   77  163:new             #2   <Class zzge$zzs$zzc>
		//   78  166:dup             
		//   79  167:ldc1            #92  <String "MOBILE_FOTA">
		//   80  169:bipush          11
		//   81  171:bipush          10
		//   82  173:invokespecial   #48  <Method void zzge$zzs$zzc(String, int, int)>
		//   83  176:putstatic       #94  <Field zzge$zzs$zzc zzbgk>
			zzbgl = new zzc("MOBILE_IMS", 12, 11);
		//   84  179:new             #2   <Class zzge$zzs$zzc>
		//   85  182:dup             
		//   86  183:ldc1            #96  <String "MOBILE_IMS">
		//   87  185:bipush          12
		//   88  187:bipush          11
		//   89  189:invokespecial   #48  <Method void zzge$zzs$zzc(String, int, int)>
		//   90  192:putstatic       #98  <Field zzge$zzs$zzc zzbgl>
			zzbgm = new zzc("MOBILE_CBS", 13, 12);
		//   91  195:new             #2   <Class zzge$zzs$zzc>
		//   92  198:dup             
		//   93  199:ldc1            #100 <String "MOBILE_CBS">
		//   94  201:bipush          13
		//   95  203:bipush          12
		//   96  205:invokespecial   #48  <Method void zzge$zzs$zzc(String, int, int)>
		//   97  208:putstatic       #102 <Field zzge$zzs$zzc zzbgm>
			zzbgn = new zzc("WIFI_P2P", 14, 13);
		//   98  211:new             #2   <Class zzge$zzs$zzc>
		//   99  214:dup             
		//  100  215:ldc1            #104 <String "WIFI_P2P">
		//  101  217:bipush          14
		//  102  219:bipush          13
		//  103  221:invokespecial   #48  <Method void zzge$zzs$zzc(String, int, int)>
		//  104  224:putstatic       #106 <Field zzge$zzs$zzc zzbgn>
			zzbgo = new zzc("MOBILE_IA", 15, 14);
		//  105  227:new             #2   <Class zzge$zzs$zzc>
		//  106  230:dup             
		//  107  231:ldc1            #108 <String "MOBILE_IA">
		//  108  233:bipush          15
		//  109  235:bipush          14
		//  110  237:invokespecial   #48  <Method void zzge$zzs$zzc(String, int, int)>
		//  111  240:putstatic       #110 <Field zzge$zzs$zzc zzbgo>
			zzbgp = new zzc("MOBILE_EMERGENCY", 16, 15);
		//  112  243:new             #2   <Class zzge$zzs$zzc>
		//  113  246:dup             
		//  114  247:ldc1            #112 <String "MOBILE_EMERGENCY">
		//  115  249:bipush          16
		//  116  251:bipush          15
		//  117  253:invokespecial   #48  <Method void zzge$zzs$zzc(String, int, int)>
		//  118  256:putstatic       #114 <Field zzge$zzs$zzc zzbgp>
			zzbgq = new zzc("PROXY", 17, 16);
		//  119  259:new             #2   <Class zzge$zzs$zzc>
		//  120  262:dup             
		//  121  263:ldc1            #116 <String "PROXY">
		//  122  265:bipush          17
		//  123  267:bipush          16
		//  124  269:invokespecial   #48  <Method void zzge$zzs$zzc(String, int, int)>
		//  125  272:putstatic       #118 <Field zzge$zzs$zzc zzbgq>
			zzbgr = new zzc("VPN", 18, 17);
		//  126  275:new             #2   <Class zzge$zzs$zzc>
		//  127  278:dup             
		//  128  279:ldc1            #120 <String "VPN">
		//  129  281:bipush          18
		//  130  283:bipush          17
		//  131  285:invokespecial   #48  <Method void zzge$zzs$zzc(String, int, int)>
		//  132  288:putstatic       #122 <Field zzge$zzs$zzc zzbgr>
			zzbgs = (new zzc[] {
				zzbfz, zzbga, zzbgb, zzbgc, zzbgd, zzbge, zzbgf, zzbgg, zzbgh, zzbgi, 
				zzbgj, zzbgk, zzbgl, zzbgm, zzbgn, zzbgo, zzbgp, zzbgq, zzbgr
			});
		//  133  291:bipush          19
		//  134  293:anewarray       zzc[]
		//  135  296:dup             
		//  136  297:iconst_0        
		//  137  298:getstatic       #50  <Field zzge$zzs$zzc zzbfz>
		//  138  301:aastore         
		//  139  302:dup             
		//  140  303:iconst_1        
		//  141  304:getstatic       #54  <Field zzge$zzs$zzc zzbga>
		//  142  307:aastore         
		//  143  308:dup             
		//  144  309:iconst_2        
		//  145  310:getstatic       #58  <Field zzge$zzs$zzc zzbgb>
		//  146  313:aastore         
		//  147  314:dup             
		//  148  315:iconst_3        
		//  149  316:getstatic       #62  <Field zzge$zzs$zzc zzbgc>
		//  150  319:aastore         
		//  151  320:dup             
		//  152  321:iconst_4        
		//  153  322:getstatic       #66  <Field zzge$zzs$zzc zzbgd>
		//  154  325:aastore         
		//  155  326:dup             
		//  156  327:iconst_5        
		//  157  328:getstatic       #70  <Field zzge$zzs$zzc zzbge>
		//  158  331:aastore         
		//  159  332:dup             
		//  160  333:bipush          6
		//  161  335:getstatic       #74  <Field zzge$zzs$zzc zzbgf>
		//  162  338:aastore         
		//  163  339:dup             
		//  164  340:bipush          7
		//  165  342:getstatic       #78  <Field zzge$zzs$zzc zzbgg>
		//  166  345:aastore         
		//  167  346:dup             
		//  168  347:bipush          8
		//  169  349:getstatic       #82  <Field zzge$zzs$zzc zzbgh>
		//  170  352:aastore         
		//  171  353:dup             
		//  172  354:bipush          9
		//  173  356:getstatic       #86  <Field zzge$zzs$zzc zzbgi>
		//  174  359:aastore         
		//  175  360:dup             
		//  176  361:bipush          10
		//  177  363:getstatic       #90  <Field zzge$zzs$zzc zzbgj>
		//  178  366:aastore         
		//  179  367:dup             
		//  180  368:bipush          11
		//  181  370:getstatic       #94  <Field zzge$zzs$zzc zzbgk>
		//  182  373:aastore         
		//  183  374:dup             
		//  184  375:bipush          12
		//  185  377:getstatic       #98  <Field zzge$zzs$zzc zzbgl>
		//  186  380:aastore         
		//  187  381:dup             
		//  188  382:bipush          13
		//  189  384:getstatic       #102 <Field zzge$zzs$zzc zzbgm>
		//  190  387:aastore         
		//  191  388:dup             
		//  192  389:bipush          14
		//  193  391:getstatic       #106 <Field zzge$zzs$zzc zzbgn>
		//  194  394:aastore         
		//  195  395:dup             
		//  196  396:bipush          15
		//  197  398:getstatic       #110 <Field zzge$zzs$zzc zzbgo>
		//  198  401:aastore         
		//  199  402:dup             
		//  200  403:bipush          16
		//  201  405:getstatic       #114 <Field zzge$zzs$zzc zzbgp>
		//  202  408:aastore         
		//  203  409:dup             
		//  204  410:bipush          17
		//  205  412:getstatic       #118 <Field zzge$zzs$zzc zzbgq>
		//  206  415:aastore         
		//  207  416:dup             
		//  208  417:bipush          18
		//  209  419:getstatic       #122 <Field zzge$zzs$zzc zzbgr>
		//  210  422:aastore         
		//  211  423:putstatic       #124 <Field zzge$zzs$zzc[] zzbgs>
		//  212  426:new             #126 <Class zzgp>
		//  213  429:dup             
		//  214  430:invokespecial   #128 <Method void zzgp()>
		//  215  433:putstatic       #130 <Field zzck zzbq>
		//* 216  436:return          
		}

		private zzc(String s, int i, int j)
		{
			super(s, i);
		//    0    0:aload_0         
		//    1    1:aload_1         
		//    2    2:iload_2         
		//    3    3:invokespecial   #134 <Method void Enum(String, int)>
			value = j;
		//    4    6:aload_0         
		//    5    7:iload_3         
		//    6    8:putfield        #136 <Field int value>
		//    7   11:return          
		}
	}


	static zzge$zzs zzfl()
	{
		return zzbfc;
	//    0    0:getstatic       #35  <Field zzge$zzs zzbfc>
	//    1    3:areturn         
	}

	protected final Object zza(int i, Object obj, Object obj1)
	{
		zzgf.zzba[i - 1];
	//    0    0:getstatic       #51  <Field int[] zzgf.zzba>
	//    1    3:iload_1         
	//    2    4:iconst_1        
	//    3    5:isub            
	//    4    6:iaload          
		JVM INSTR tableswitch 1 7: default 48
	//	               1 169
	//	               2 160
	//	               3 116
	//	               4 112
	//	               5 63
	//	               6 58
	//	               7 56;
	//    5    7:tableswitch     1 7: default 48
	//	               1 169
	//	               2 160
	//	               3 116
	//	               4 112
	//	               5 63
	//	               6 58
	//	               7 56
		   goto _L1 _L2 _L3 _L4 _L5 _L6 _L7 _L8
_L1:
		throw new UnsupportedOperationException();
	//    6   48:new             #53  <Class UnsupportedOperationException>
	//    7   51:dup             
	//    8   52:invokespecial   #54  <Method void UnsupportedOperationException()>
	//    9   55:athrow          
_L8:
		return ((Object) (null));
	//   10   56:aconst_null     
	//   11   57:areturn         
_L7:
		return ((Object) (Byte.valueOf((byte)1)));
	//   12   58:iconst_1        
	//   13   59:invokestatic    #60  <Method Byte Byte.valueOf(byte)>
	//   14   62:areturn         
_L6:
		obj = ((Object) (zzbg));
	//   15   63:getstatic       #62  <Field zzdz zzbg>
	//   16   66:astore_2        
		if(obj != null) goto _L10; else goto _L9
	//   17   67:aload_2         
	//   18   68:ifnonnull       110
_L9:
		com/google/android/gms/internal/clearcut/zzge$zzs;
	//   19   71:ldc1            #2   <Class zzge$zzs>
		JVM INSTR monitorenter ;
	//   20   73:monitorenter    
		obj1 = ((Object) (zzbg));
	//   21   74:getstatic       #62  <Field zzdz zzbg>
	//   22   77:astore_3        
		obj = obj1;
	//   23   78:aload_3         
	//   24   79:astore_2        
		if(obj1 != null) goto _L12; else goto _L11
	//   25   80:aload_3         
	//   26   81:ifnonnull       99
_L11:
		obj = ((Object) (new zzcg$zzb(((zzcg) (zzbfc)))));
	//   27   84:new             #64  <Class zzcg$zzb>
	//   28   87:dup             
	//   29   88:getstatic       #35  <Field zzge$zzs zzbfc>
	//   30   91:invokespecial   #67  <Method void zzcg$zzb(zzcg)>
	//   31   94:astore_2        
		zzbg = ((zzdz) (obj));
	//   32   95:aload_2         
	//   33   96:putstatic       #62  <Field zzdz zzbg>
_L12:
		com/google/android/gms/internal/clearcut/zzge$zzs;
	//   34   99:ldc1            #2   <Class zzge$zzs>
		JVM INSTR monitorexit ;
	//   35  101:monitorexit     
		return obj;
	//   36  102:aload_2         
	//   37  103:areturn         
		obj;
	//   38  104:astore_2        
		com/google/android/gms/internal/clearcut/zzge$zzs;
	//   39  105:ldc1            #2   <Class zzge$zzs>
		JVM INSTR monitorexit ;
	//   40  107:monitorexit     
		throw obj;
	//   41  108:aload_2         
	//   42  109:athrow          
_L10:
		return obj;
	//   43  110:aload_2         
	//   44  111:areturn         
_L5:
		return ((Object) (zzbfc));
	//   45  112:getstatic       #35  <Field zzge$zzs zzbfc>
	//   46  115:areturn         
_L4:
		obj = ((Object) (zzc.zzd()));
	//   47  116:invokestatic    #71  <Method zzck zzge$zzs$zzc.zzd()>
	//   48  119:astore_2        
		obj1 = ((Object) (zzb.zzd()));
	//   49  120:invokestatic    #72  <Method zzck zzge$zzs$zzb.zzd()>
	//   50  123:astore_3        
		return zza(((zzdo) (zzbfc)), "\001\002\000\001\001\002\002\003\000\000\000\001\f\000\002\f\001", new Object[] {
			"zzbb", "zzbfa", obj, "zzbfb", obj1
		});
	//   51  124:getstatic       #35  <Field zzge$zzs zzbfc>
	//   52  127:ldc1            #74  <String "\001\002\000\001\001\002\002\003\000\000\000\001\f\000\002\f\001">
	//   53  129:iconst_5        
	//   54  130:anewarray       Object[]
	//   55  133:dup             
	//   56  134:iconst_0        
	//   57  135:ldc1            #77  <String "zzbb">
	//   58  137:aastore         
	//   59  138:dup             
	//   60  139:iconst_1        
	//   61  140:ldc1            #78  <String "zzbfa">
	//   62  142:aastore         
	//   63  143:dup             
	//   64  144:iconst_2        
	//   65  145:aload_2         
	//   66  146:aastore         
	//   67  147:dup             
	//   68  148:iconst_3        
	//   69  149:ldc1            #79  <String "zzbfb">
	//   70  151:aastore         
	//   71  152:dup             
	//   72  153:iconst_4        
	//   73  154:aload_3         
	//   74  155:aastore         
	//   75  156:invokestatic    #82  <Method Object zza(zzdo, String, Object[])>
	//   76  159:areturn         
_L3:
		return ((Object) (new zza(((zzgf) (null)))));
	//   77  160:new             #12  <Class zzge$zzs$zza>
	//   78  163:dup             
	//   79  164:aconst_null     
	//   80  165:invokespecial   #85  <Method void zzge$zzs$zza(zzgf)>
	//   81  168:areturn         
_L2:
		return ((Object) (new zzge$zzs()));
	//   82  169:new             #2   <Class zzge$zzs>
	//   83  172:dup             
	//   84  173:invokespecial   #33  <Method void zzge$zzs()>
	//   85  176:areturn         
	}

	private static final zzge$zzs zzbfc;
	private static volatile zzdz zzbg;
	private int zzbb;
	private int zzbfa;
	private int zzbfb;

	static 
	{
		zzbfc = new zzge$zzs();
	//    0    0:new             #2   <Class zzge$zzs>
	//    1    3:dup             
	//    2    4:invokespecial   #33  <Method void zzge$zzs()>
	//    3    7:putstatic       #35  <Field zzge$zzs zzbfc>
		zzcg.zza(com/google/android/gms/internal/clearcut/zzge$zzs, ((zzcg) (zzbfc)));
	//    4   10:ldc1            #2   <Class zzge$zzs>
	//    5   12:getstatic       #35  <Field zzge$zzs zzbfc>
	//    6   15:invokestatic    #38  <Method void zzcg.zza(Class, zzcg)>
	//*   7   18:return          
	}

	private zzge$zzs()
	{
	//    0    0:aload_0         
	//    1    1:invokespecial   #40  <Method void zzcg()>
		zzbfa = -1;
	//    2    4:aload_0         
	//    3    5:iconst_m1       
	//    4    6:putfield        #42  <Field int zzbfa>
	//    5    9:return          
	}
}
