// Decompiled by Jad v1.5.8g. Copyright 2001 Pavel Kouznetsov.
// Jad home page: http://www.kpdus.com/jad.html
// Decompiler options: packimports(3) annotate safe 

package com.google.android.gms.internal.clearcut;


// Referenced classes of package com.google.android.gms.internal.clearcut:
//			zzcj, zzge, zzgo, zzck

public static final class zzge$zzs$zzb extends Enum
	implements zzcj
{

	public static zzge$zzs$zzb[] values()
	{
		return (zzge$zzs$zzb[])((zzge$zzs$zzb []) (zzbfy)).clone();
	//    0    0:getstatic       #134 <Field zzge$zzs$zzb[] zzbfy>
	//    1    3:invokevirtual   #155 <Method Object _5B_Lcom.google.android.gms.internal.clearcut.zzge$zzs$zzb_3B_.clone()>
	//    2    6:checkcast       #151 <Class zzge$zzs$zzb[]>
	//    3    9:areturn         
	}

	public static zzge$zzs$zzb zzaz(int i)
	{
		if(i != 100)
	//*   0    0:iload_0         
	//*   1    1:bipush          100
	//*   2    3:icmpeq          182
			switch(i)
	//*   3    6:iload_0         
			{
	//*   4    7:tableswitch     0 19: default 100
	//	               0 178
	//	               1 174
	//	               2 170
	//	               3 166
	//	               4 162
	//	               5 158
	//	               6 154
	//	               7 150
	//	               8 146
	//	               9 142
	//	               10 138
	//	               11 134
	//	               12 130
	//	               13 126
	//	               14 122
	//	               15 118
	//	               16 114
	//	               17 110
	//	               18 106
	//	               19 102
			default:
				return null;
	//    5  100:aconst_null     
	//    6  101:areturn         

			case 19: // '\023'
				return zzbfw;
	//    7  102:getstatic       #128 <Field zzge$zzs$zzb zzbfw>
	//    8  105:areturn         

			case 18: // '\022'
				return zzbfv;
	//    9  106:getstatic       #124 <Field zzge$zzs$zzb zzbfv>
	//   10  109:areturn         

			case 17: // '\021'
				return zzbfu;
	//   11  110:getstatic       #120 <Field zzge$zzs$zzb zzbfu>
	//   12  113:areturn         

			case 16: // '\020'
				return zzbft;
	//   13  114:getstatic       #116 <Field zzge$zzs$zzb zzbft>
	//   14  117:areturn         

			case 15: // '\017'
				return zzbfs;
	//   15  118:getstatic       #112 <Field zzge$zzs$zzb zzbfs>
	//   16  121:areturn         

			case 14: // '\016'
				return zzbfr;
	//   17  122:getstatic       #108 <Field zzge$zzs$zzb zzbfr>
	//   18  125:areturn         

			case 13: // '\r'
				return zzbfq;
	//   19  126:getstatic       #104 <Field zzge$zzs$zzb zzbfq>
	//   20  129:areturn         

			case 12: // '\f'
				return zzbfp;
	//   21  130:getstatic       #100 <Field zzge$zzs$zzb zzbfp>
	//   22  133:areturn         

			case 11: // '\013'
				return zzbfo;
	//   23  134:getstatic       #96  <Field zzge$zzs$zzb zzbfo>
	//   24  137:areturn         

			case 10: // '\n'
				return zzbfn;
	//   25  138:getstatic       #92  <Field zzge$zzs$zzb zzbfn>
	//   26  141:areturn         

			case 9: // '\t'
				return zzbfm;
	//   27  142:getstatic       #88  <Field zzge$zzs$zzb zzbfm>
	//   28  145:areturn         

			case 8: // '\b'
				return zzbfl;
	//   29  146:getstatic       #84  <Field zzge$zzs$zzb zzbfl>
	//   30  149:areturn         

			case 7: // '\007'
				return zzbfk;
	//   31  150:getstatic       #80  <Field zzge$zzs$zzb zzbfk>
	//   32  153:areturn         

			case 6: // '\006'
				return zzbfj;
	//   33  154:getstatic       #76  <Field zzge$zzs$zzb zzbfj>
	//   34  157:areturn         

			case 5: // '\005'
				return zzbfi;
	//   35  158:getstatic       #72  <Field zzge$zzs$zzb zzbfi>
	//   36  161:areturn         

			case 4: // '\004'
				return zzbfh;
	//   37  162:getstatic       #68  <Field zzge$zzs$zzb zzbfh>
	//   38  165:areturn         

			case 3: // '\003'
				return zzbfg;
	//   39  166:getstatic       #64  <Field zzge$zzs$zzb zzbfg>
	//   40  169:areturn         

			case 2: // '\002'
				return zzbff;
	//   41  170:getstatic       #60  <Field zzge$zzs$zzb zzbff>
	//   42  173:areturn         

			case 1: // '\001'
				return zzbfe;
	//   43  174:getstatic       #56  <Field zzge$zzs$zzb zzbfe>
	//   44  177:areturn         

			case 0: // '\0'
				return zzbfd;
	//   45  178:getstatic       #52  <Field zzge$zzs$zzb zzbfd>
	//   46  181:areturn         
			}
		else
			return zzbfx;
	//   47  182:getstatic       #132 <Field zzge$zzs$zzb zzbfx>
	//   48  185:areturn         
	}

	public static zzck zzd()
	{
		return zzbq;
	//    0    0:getstatic       #140 <Field zzck zzbq>
	//    1    3:areturn         
	}

	public final int zzc()
	{
		return value;
	//    0    0:aload_0         
	//    1    1:getfield        #146 <Field int value>
	//    2    4:ireturn         
	}

	private static final zzge$zzs$zzb zzbfd;
	private static final zzge$zzs$zzb zzbfe;
	private static final zzge$zzs$zzb zzbff;
	private static final zzge$zzs$zzb zzbfg;
	private static final zzge$zzs$zzb zzbfh;
	private static final zzge$zzs$zzb zzbfi;
	private static final zzge$zzs$zzb zzbfj;
	private static final zzge$zzs$zzb zzbfk;
	private static final zzge$zzs$zzb zzbfl;
	private static final zzge$zzs$zzb zzbfm;
	private static final zzge$zzs$zzb zzbfn;
	private static final zzge$zzs$zzb zzbfo;
	private static final zzge$zzs$zzb zzbfp;
	private static final zzge$zzs$zzb zzbfq;
	private static final zzge$zzs$zzb zzbfr;
	private static final zzge$zzs$zzb zzbfs;
	private static final zzge$zzs$zzb zzbft;
	private static final zzge$zzs$zzb zzbfu;
	private static final zzge$zzs$zzb zzbfv;
	private static final zzge$zzs$zzb zzbfw;
	private static final zzge$zzs$zzb zzbfx;
	private static final zzge$zzs$zzb zzbfy[];
	private static final zzck zzbq = new zzgo();
	private final int value;

	static 
	{
		zzbfd = new zzge$zzs$zzb("UNKNOWN_MOBILE_SUBTYPE", 0, 0);
	//    0    0:new             #2   <Class zzge$zzs$zzb>
	//    1    3:dup             
	//    2    4:ldc1            #46  <String "UNKNOWN_MOBILE_SUBTYPE">
	//    3    6:iconst_0        
	//    4    7:iconst_0        
	//    5    8:invokespecial   #50  <Method void zzge$zzs$zzb(String, int, int)>
	//    6   11:putstatic       #52  <Field zzge$zzs$zzb zzbfd>
		zzbfe = new zzge$zzs$zzb("GPRS", 1, 1);
	//    7   14:new             #2   <Class zzge$zzs$zzb>
	//    8   17:dup             
	//    9   18:ldc1            #54  <String "GPRS">
	//   10   20:iconst_1        
	//   11   21:iconst_1        
	//   12   22:invokespecial   #50  <Method void zzge$zzs$zzb(String, int, int)>
	//   13   25:putstatic       #56  <Field zzge$zzs$zzb zzbfe>
		zzbff = new zzge$zzs$zzb("EDGE", 2, 2);
	//   14   28:new             #2   <Class zzge$zzs$zzb>
	//   15   31:dup             
	//   16   32:ldc1            #58  <String "EDGE">
	//   17   34:iconst_2        
	//   18   35:iconst_2        
	//   19   36:invokespecial   #50  <Method void zzge$zzs$zzb(String, int, int)>
	//   20   39:putstatic       #60  <Field zzge$zzs$zzb zzbff>
		zzbfg = new zzge$zzs$zzb("UMTS", 3, 3);
	//   21   42:new             #2   <Class zzge$zzs$zzb>
	//   22   45:dup             
	//   23   46:ldc1            #62  <String "UMTS">
	//   24   48:iconst_3        
	//   25   49:iconst_3        
	//   26   50:invokespecial   #50  <Method void zzge$zzs$zzb(String, int, int)>
	//   27   53:putstatic       #64  <Field zzge$zzs$zzb zzbfg>
		zzbfh = new zzge$zzs$zzb("CDMA", 4, 4);
	//   28   56:new             #2   <Class zzge$zzs$zzb>
	//   29   59:dup             
	//   30   60:ldc1            #66  <String "CDMA">
	//   31   62:iconst_4        
	//   32   63:iconst_4        
	//   33   64:invokespecial   #50  <Method void zzge$zzs$zzb(String, int, int)>
	//   34   67:putstatic       #68  <Field zzge$zzs$zzb zzbfh>
		zzbfi = new zzge$zzs$zzb("EVDO_0", 5, 5);
	//   35   70:new             #2   <Class zzge$zzs$zzb>
	//   36   73:dup             
	//   37   74:ldc1            #70  <String "EVDO_0">
	//   38   76:iconst_5        
	//   39   77:iconst_5        
	//   40   78:invokespecial   #50  <Method void zzge$zzs$zzb(String, int, int)>
	//   41   81:putstatic       #72  <Field zzge$zzs$zzb zzbfi>
		zzbfj = new zzge$zzs$zzb("EVDO_A", 6, 6);
	//   42   84:new             #2   <Class zzge$zzs$zzb>
	//   43   87:dup             
	//   44   88:ldc1            #74  <String "EVDO_A">
	//   45   90:bipush          6
	//   46   92:bipush          6
	//   47   94:invokespecial   #50  <Method void zzge$zzs$zzb(String, int, int)>
	//   48   97:putstatic       #76  <Field zzge$zzs$zzb zzbfj>
		zzbfk = new zzge$zzs$zzb("RTT", 7, 7);
	//   49  100:new             #2   <Class zzge$zzs$zzb>
	//   50  103:dup             
	//   51  104:ldc1            #78  <String "RTT">
	//   52  106:bipush          7
	//   53  108:bipush          7
	//   54  110:invokespecial   #50  <Method void zzge$zzs$zzb(String, int, int)>
	//   55  113:putstatic       #80  <Field zzge$zzs$zzb zzbfk>
		zzbfl = new zzge$zzs$zzb("HSDPA", 8, 8);
	//   56  116:new             #2   <Class zzge$zzs$zzb>
	//   57  119:dup             
	//   58  120:ldc1            #82  <String "HSDPA">
	//   59  122:bipush          8
	//   60  124:bipush          8
	//   61  126:invokespecial   #50  <Method void zzge$zzs$zzb(String, int, int)>
	//   62  129:putstatic       #84  <Field zzge$zzs$zzb zzbfl>
		zzbfm = new zzge$zzs$zzb("HSUPA", 9, 9);
	//   63  132:new             #2   <Class zzge$zzs$zzb>
	//   64  135:dup             
	//   65  136:ldc1            #86  <String "HSUPA">
	//   66  138:bipush          9
	//   67  140:bipush          9
	//   68  142:invokespecial   #50  <Method void zzge$zzs$zzb(String, int, int)>
	//   69  145:putstatic       #88  <Field zzge$zzs$zzb zzbfm>
		zzbfn = new zzge$zzs$zzb("HSPA", 10, 10);
	//   70  148:new             #2   <Class zzge$zzs$zzb>
	//   71  151:dup             
	//   72  152:ldc1            #90  <String "HSPA">
	//   73  154:bipush          10
	//   74  156:bipush          10
	//   75  158:invokespecial   #50  <Method void zzge$zzs$zzb(String, int, int)>
	//   76  161:putstatic       #92  <Field zzge$zzs$zzb zzbfn>
		zzbfo = new zzge$zzs$zzb("IDEN", 11, 11);
	//   77  164:new             #2   <Class zzge$zzs$zzb>
	//   78  167:dup             
	//   79  168:ldc1            #94  <String "IDEN">
	//   80  170:bipush          11
	//   81  172:bipush          11
	//   82  174:invokespecial   #50  <Method void zzge$zzs$zzb(String, int, int)>
	//   83  177:putstatic       #96  <Field zzge$zzs$zzb zzbfo>
		zzbfp = new zzge$zzs$zzb("EVDO_B", 12, 12);
	//   84  180:new             #2   <Class zzge$zzs$zzb>
	//   85  183:dup             
	//   86  184:ldc1            #98  <String "EVDO_B">
	//   87  186:bipush          12
	//   88  188:bipush          12
	//   89  190:invokespecial   #50  <Method void zzge$zzs$zzb(String, int, int)>
	//   90  193:putstatic       #100 <Field zzge$zzs$zzb zzbfp>
		zzbfq = new zzge$zzs$zzb("LTE", 13, 13);
	//   91  196:new             #2   <Class zzge$zzs$zzb>
	//   92  199:dup             
	//   93  200:ldc1            #102 <String "LTE">
	//   94  202:bipush          13
	//   95  204:bipush          13
	//   96  206:invokespecial   #50  <Method void zzge$zzs$zzb(String, int, int)>
	//   97  209:putstatic       #104 <Field zzge$zzs$zzb zzbfq>
		zzbfr = new zzge$zzs$zzb("EHRPD", 14, 14);
	//   98  212:new             #2   <Class zzge$zzs$zzb>
	//   99  215:dup             
	//  100  216:ldc1            #106 <String "EHRPD">
	//  101  218:bipush          14
	//  102  220:bipush          14
	//  103  222:invokespecial   #50  <Method void zzge$zzs$zzb(String, int, int)>
	//  104  225:putstatic       #108 <Field zzge$zzs$zzb zzbfr>
		zzbfs = new zzge$zzs$zzb("HSPAP", 15, 15);
	//  105  228:new             #2   <Class zzge$zzs$zzb>
	//  106  231:dup             
	//  107  232:ldc1            #110 <String "HSPAP">
	//  108  234:bipush          15
	//  109  236:bipush          15
	//  110  238:invokespecial   #50  <Method void zzge$zzs$zzb(String, int, int)>
	//  111  241:putstatic       #112 <Field zzge$zzs$zzb zzbfs>
		zzbft = new zzge$zzs$zzb("GSM", 16, 16);
	//  112  244:new             #2   <Class zzge$zzs$zzb>
	//  113  247:dup             
	//  114  248:ldc1            #114 <String "GSM">
	//  115  250:bipush          16
	//  116  252:bipush          16
	//  117  254:invokespecial   #50  <Method void zzge$zzs$zzb(String, int, int)>
	//  118  257:putstatic       #116 <Field zzge$zzs$zzb zzbft>
		zzbfu = new zzge$zzs$zzb("TD_SCDMA", 17, 17);
	//  119  260:new             #2   <Class zzge$zzs$zzb>
	//  120  263:dup             
	//  121  264:ldc1            #118 <String "TD_SCDMA">
	//  122  266:bipush          17
	//  123  268:bipush          17
	//  124  270:invokespecial   #50  <Method void zzge$zzs$zzb(String, int, int)>
	//  125  273:putstatic       #120 <Field zzge$zzs$zzb zzbfu>
		zzbfv = new zzge$zzs$zzb("IWLAN", 18, 18);
	//  126  276:new             #2   <Class zzge$zzs$zzb>
	//  127  279:dup             
	//  128  280:ldc1            #122 <String "IWLAN">
	//  129  282:bipush          18
	//  130  284:bipush          18
	//  131  286:invokespecial   #50  <Method void zzge$zzs$zzb(String, int, int)>
	//  132  289:putstatic       #124 <Field zzge$zzs$zzb zzbfv>
		zzbfw = new zzge$zzs$zzb("LTE_CA", 19, 19);
	//  133  292:new             #2   <Class zzge$zzs$zzb>
	//  134  295:dup             
	//  135  296:ldc1            #126 <String "LTE_CA">
	//  136  298:bipush          19
	//  137  300:bipush          19
	//  138  302:invokespecial   #50  <Method void zzge$zzs$zzb(String, int, int)>
	//  139  305:putstatic       #128 <Field zzge$zzs$zzb zzbfw>
		zzbfx = new zzge$zzs$zzb("COMBINED", 20, 100);
	//  140  308:new             #2   <Class zzge$zzs$zzb>
	//  141  311:dup             
	//  142  312:ldc1            #130 <String "COMBINED">
	//  143  314:bipush          20
	//  144  316:bipush          100
	//  145  318:invokespecial   #50  <Method void zzge$zzs$zzb(String, int, int)>
	//  146  321:putstatic       #132 <Field zzge$zzs$zzb zzbfx>
		zzbfy = (new zzge$zzs$zzb[] {
			zzbfd, zzbfe, zzbff, zzbfg, zzbfh, zzbfi, zzbfj, zzbfk, zzbfl, zzbfm, 
			zzbfn, zzbfo, zzbfp, zzbfq, zzbfr, zzbfs, zzbft, zzbfu, zzbfv, zzbfw, 
			zzbfx
		});
	//  147  324:bipush          21
	//  148  326:anewarray       zzge$zzs$zzb[]
	//  149  329:dup             
	//  150  330:iconst_0        
	//  151  331:getstatic       #52  <Field zzge$zzs$zzb zzbfd>
	//  152  334:aastore         
	//  153  335:dup             
	//  154  336:iconst_1        
	//  155  337:getstatic       #56  <Field zzge$zzs$zzb zzbfe>
	//  156  340:aastore         
	//  157  341:dup             
	//  158  342:iconst_2        
	//  159  343:getstatic       #60  <Field zzge$zzs$zzb zzbff>
	//  160  346:aastore         
	//  161  347:dup             
	//  162  348:iconst_3        
	//  163  349:getstatic       #64  <Field zzge$zzs$zzb zzbfg>
	//  164  352:aastore         
	//  165  353:dup             
	//  166  354:iconst_4        
	//  167  355:getstatic       #68  <Field zzge$zzs$zzb zzbfh>
	//  168  358:aastore         
	//  169  359:dup             
	//  170  360:iconst_5        
	//  171  361:getstatic       #72  <Field zzge$zzs$zzb zzbfi>
	//  172  364:aastore         
	//  173  365:dup             
	//  174  366:bipush          6
	//  175  368:getstatic       #76  <Field zzge$zzs$zzb zzbfj>
	//  176  371:aastore         
	//  177  372:dup             
	//  178  373:bipush          7
	//  179  375:getstatic       #80  <Field zzge$zzs$zzb zzbfk>
	//  180  378:aastore         
	//  181  379:dup             
	//  182  380:bipush          8
	//  183  382:getstatic       #84  <Field zzge$zzs$zzb zzbfl>
	//  184  385:aastore         
	//  185  386:dup             
	//  186  387:bipush          9
	//  187  389:getstatic       #88  <Field zzge$zzs$zzb zzbfm>
	//  188  392:aastore         
	//  189  393:dup             
	//  190  394:bipush          10
	//  191  396:getstatic       #92  <Field zzge$zzs$zzb zzbfn>
	//  192  399:aastore         
	//  193  400:dup             
	//  194  401:bipush          11
	//  195  403:getstatic       #96  <Field zzge$zzs$zzb zzbfo>
	//  196  406:aastore         
	//  197  407:dup             
	//  198  408:bipush          12
	//  199  410:getstatic       #100 <Field zzge$zzs$zzb zzbfp>
	//  200  413:aastore         
	//  201  414:dup             
	//  202  415:bipush          13
	//  203  417:getstatic       #104 <Field zzge$zzs$zzb zzbfq>
	//  204  420:aastore         
	//  205  421:dup             
	//  206  422:bipush          14
	//  207  424:getstatic       #108 <Field zzge$zzs$zzb zzbfr>
	//  208  427:aastore         
	//  209  428:dup             
	//  210  429:bipush          15
	//  211  431:getstatic       #112 <Field zzge$zzs$zzb zzbfs>
	//  212  434:aastore         
	//  213  435:dup             
	//  214  436:bipush          16
	//  215  438:getstatic       #116 <Field zzge$zzs$zzb zzbft>
	//  216  441:aastore         
	//  217  442:dup             
	//  218  443:bipush          17
	//  219  445:getstatic       #120 <Field zzge$zzs$zzb zzbfu>
	//  220  448:aastore         
	//  221  449:dup             
	//  222  450:bipush          18
	//  223  452:getstatic       #124 <Field zzge$zzs$zzb zzbfv>
	//  224  455:aastore         
	//  225  456:dup             
	//  226  457:bipush          19
	//  227  459:getstatic       #128 <Field zzge$zzs$zzb zzbfw>
	//  228  462:aastore         
	//  229  463:dup             
	//  230  464:bipush          20
	//  231  466:getstatic       #132 <Field zzge$zzs$zzb zzbfx>
	//  232  469:aastore         
	//  233  470:putstatic       #134 <Field zzge$zzs$zzb[] zzbfy>
	//  234  473:new             #136 <Class zzgo>
	//  235  476:dup             
	//  236  477:invokespecial   #138 <Method void zzgo()>
	//  237  480:putstatic       #140 <Field zzck zzbq>
	//* 238  483:return          
	}

	private zzge$zzs$zzb(String s, int i, int j)
	{
		super(s, i);
	//    0    0:aload_0         
	//    1    1:aload_1         
	//    2    2:iload_2         
	//    3    3:invokespecial   #144 <Method void Enum(String, int)>
		value = j;
	//    4    6:aload_0         
	//    5    7:iload_3         
	//    6    8:putfield        #146 <Field int value>
	//    7   11:return          
	}
}
