// Decompiled by Jad v1.5.8g. Copyright 2001 Pavel Kouznetsov.
// Jad home page: http://www.kpdus.com/jad.html
// Decompiler options: packimports(3) annotate safe 

package com.google.android.gms.internal.clearcut;


// Referenced classes of package com.google.android.gms.internal.clearcut:
//			zzcg, zzdq, zzge, zzgc, 
//			zzfl, zzgf, zzdz, zzcj, 
//			zzgh, zzck

public static final class zzge$zzg extends zzcg
	implements zzdq
{
	public static final class zza extends zzcg.zza
		implements zzdq
	{

		private zza()
		{
			super(((zzcg) (zzge.zzg.zzez())));
		//    0    0:aload_0         
		//    1    1:invokestatic    #19  <Method zzge$zzg zzge$zzg.zzez()>
		//    2    4:invokespecial   #22  <Method void zzcg$zza(zzcg)>
		//    3    7:return          
		}

		zza(zzgf zzgf1)
		{
			this();
		//    0    0:aload_0         
		//    1    1:invokespecial   #26  <Method void zzge$zzg$zza()>
		//    2    4:return          
		}
	}

	public static final class zzb extends Enum
		implements zzcj
	{

		public static zzb[] values()
		{
			return (zzb[])((zzb []) (zzvt)).clone();
		//    0    0:getstatic       #114 <Field zzge$zzg$zzb[] zzvt>
		//    1    3:invokevirtual   #135 <Method Object _5B_Lcom.google.android.gms.internal.clearcut.zzge$zzg$zzb_3B_.clone()>
		//    2    6:checkcast       #131 <Class zzge$zzg$zzb[]>
		//    3    9:areturn         
		}

		public static zzb zzas(int i)
		{
			switch(i)
		//*   0    0:iload_0         
			{
		//*   1    1:tableswitch     0 16: default 84
		//		               0 150
		//		               1 146
		//		               2 142
		//		               3 138
		//		               4 134
		//		               5 130
		//		               6 126
		//		               7 122
		//		               8 118
		//		               9 114
		//		               10 110
		//		               11 106
		//		               12 102
		//		               13 98
		//		               14 94
		//		               15 90
		//		               16 86
			default:
				return null;
		//    2   84:aconst_null     
		//    3   85:areturn         

			case 16: // '\020'
				return zzvs;
		//    4   86:getstatic       #112 <Field zzge$zzg$zzb zzvs>
		//    5   89:areturn         

			case 15: // '\017'
				return zzvr;
		//    6   90:getstatic       #108 <Field zzge$zzg$zzb zzvr>
		//    7   93:areturn         

			case 14: // '\016'
				return zzvq;
		//    8   94:getstatic       #104 <Field zzge$zzg$zzb zzvq>
		//    9   97:areturn         

			case 13: // '\r'
				return zzvp;
		//   10   98:getstatic       #100 <Field zzge$zzg$zzb zzvp>
		//   11  101:areturn         

			case 12: // '\f'
				return zzvo;
		//   12  102:getstatic       #96  <Field zzge$zzg$zzb zzvo>
		//   13  105:areturn         

			case 11: // '\013'
				return zzvn;
		//   14  106:getstatic       #92  <Field zzge$zzg$zzb zzvn>
		//   15  109:areturn         

			case 10: // '\n'
				return zzvg;
		//   16  110:getstatic       #64  <Field zzge$zzg$zzb zzvg>
		//   17  113:areturn         

			case 9: // '\t'
				return zzvm;
		//   18  114:getstatic       #88  <Field zzge$zzg$zzb zzvm>
		//   19  117:areturn         

			case 8: // '\b'
				return zzvl;
		//   20  118:getstatic       #84  <Field zzge$zzg$zzb zzvl>
		//   21  121:areturn         

			case 7: // '\007'
				return zzvk;
		//   22  122:getstatic       #80  <Field zzge$zzg$zzb zzvk>
		//   23  125:areturn         

			case 6: // '\006'
				return zzvj;
		//   24  126:getstatic       #76  <Field zzge$zzg$zzb zzvj>
		//   25  129:areturn         

			case 5: // '\005'
				return zzvi;
		//   26  130:getstatic       #72  <Field zzge$zzg$zzb zzvi>
		//   27  133:areturn         

			case 4: // '\004'
				return zzvh;
		//   28  134:getstatic       #68  <Field zzge$zzg$zzb zzvh>
		//   29  137:areturn         

			case 3: // '\003'
				return zzvf;
		//   30  138:getstatic       #60  <Field zzge$zzg$zzb zzvf>
		//   31  141:areturn         

			case 2: // '\002'
				return zzve;
		//   32  142:getstatic       #56  <Field zzge$zzg$zzb zzve>
		//   33  145:areturn         

			case 1: // '\001'
				return zzvd;
		//   34  146:getstatic       #52  <Field zzge$zzg$zzb zzvd>
		//   35  149:areturn         

			case 0: // '\0'
				return zzvc;
		//   36  150:getstatic       #48  <Field zzge$zzg$zzb zzvc>
		//   37  153:areturn         
			}
		}

		public static zzck zzd()
		{
			return zzbq;
		//    0    0:getstatic       #120 <Field zzck zzbq>
		//    1    3:areturn         
		}

		public final int zzc()
		{
			return value;
		//    0    0:aload_0         
		//    1    1:getfield        #126 <Field int value>
		//    2    4:ireturn         
		}

		private static final zzck zzbq = new zzgh();
		private static final zzb zzvc;
		private static final zzb zzvd;
		private static final zzb zzve;
		private static final zzb zzvf;
		private static final zzb zzvg;
		private static final zzb zzvh;
		private static final zzb zzvi;
		private static final zzb zzvj;
		private static final zzb zzvk;
		private static final zzb zzvl;
		private static final zzb zzvm;
		private static final zzb zzvn;
		private static final zzb zzvo;
		private static final zzb zzvp;
		private static final zzb zzvq;
		private static final zzb zzvr;
		private static final zzb zzvs;
		private static final zzb zzvt[];
		private final int value;

		static 
		{
			zzvc = new zzb("UNKNOWN", 0, 0);
		//    0    0:new             #2   <Class zzge$zzg$zzb>
		//    1    3:dup             
		//    2    4:ldc1            #42  <String "UNKNOWN">
		//    3    6:iconst_0        
		//    4    7:iconst_0        
		//    5    8:invokespecial   #46  <Method void zzge$zzg$zzb(String, int, int)>
		//    6   11:putstatic       #48  <Field zzge$zzg$zzb zzvc>
			zzvd = new zzb("JS", 1, 1);
		//    7   14:new             #2   <Class zzge$zzg$zzb>
		//    8   17:dup             
		//    9   18:ldc1            #50  <String "JS">
		//   10   20:iconst_1        
		//   11   21:iconst_1        
		//   12   22:invokespecial   #46  <Method void zzge$zzg$zzb(String, int, int)>
		//   13   25:putstatic       #52  <Field zzge$zzg$zzb zzvd>
			zzve = new zzb("DESKTOP", 2, 2);
		//   14   28:new             #2   <Class zzge$zzg$zzb>
		//   15   31:dup             
		//   16   32:ldc1            #54  <String "DESKTOP">
		//   17   34:iconst_2        
		//   18   35:iconst_2        
		//   19   36:invokespecial   #46  <Method void zzge$zzg$zzb(String, int, int)>
		//   20   39:putstatic       #56  <Field zzge$zzg$zzb zzve>
			zzvf = new zzb("IOS", 3, 3);
		//   21   42:new             #2   <Class zzge$zzg$zzb>
		//   22   45:dup             
		//   23   46:ldc1            #58  <String "IOS">
		//   24   48:iconst_3        
		//   25   49:iconst_3        
		//   26   50:invokespecial   #46  <Method void zzge$zzg$zzb(String, int, int)>
		//   27   53:putstatic       #60  <Field zzge$zzg$zzb zzvf>
			zzvg = new zzb("IOS_V2", 4, 10);
		//   28   56:new             #2   <Class zzge$zzg$zzb>
		//   29   59:dup             
		//   30   60:ldc1            #62  <String "IOS_V2">
		//   31   62:iconst_4        
		//   32   63:bipush          10
		//   33   65:invokespecial   #46  <Method void zzge$zzg$zzb(String, int, int)>
		//   34   68:putstatic       #64  <Field zzge$zzg$zzb zzvg>
			zzvh = new zzb("ANDROID", 5, 4);
		//   35   71:new             #2   <Class zzge$zzg$zzb>
		//   36   74:dup             
		//   37   75:ldc1            #66  <String "ANDROID">
		//   38   77:iconst_5        
		//   39   78:iconst_4        
		//   40   79:invokespecial   #46  <Method void zzge$zzg$zzb(String, int, int)>
		//   41   82:putstatic       #68  <Field zzge$zzg$zzb zzvh>
			zzvi = new zzb("PLAY_CE", 6, 5);
		//   42   85:new             #2   <Class zzge$zzg$zzb>
		//   43   88:dup             
		//   44   89:ldc1            #70  <String "PLAY_CE">
		//   45   91:bipush          6
		//   46   93:iconst_5        
		//   47   94:invokespecial   #46  <Method void zzge$zzg$zzb(String, int, int)>
		//   48   97:putstatic       #72  <Field zzge$zzg$zzb zzvi>
			zzvj = new zzb("PYTHON", 7, 6);
		//   49  100:new             #2   <Class zzge$zzg$zzb>
		//   50  103:dup             
		//   51  104:ldc1            #74  <String "PYTHON">
		//   52  106:bipush          7
		//   53  108:bipush          6
		//   54  110:invokespecial   #46  <Method void zzge$zzg$zzb(String, int, int)>
		//   55  113:putstatic       #76  <Field zzge$zzg$zzb zzvj>
			zzvk = new zzb("VR", 8, 7);
		//   56  116:new             #2   <Class zzge$zzg$zzb>
		//   57  119:dup             
		//   58  120:ldc1            #78  <String "VR">
		//   59  122:bipush          8
		//   60  124:bipush          7
		//   61  126:invokespecial   #46  <Method void zzge$zzg$zzb(String, int, int)>
		//   62  129:putstatic       #80  <Field zzge$zzg$zzb zzvk>
			zzvl = new zzb("PANCETTA", 9, 8);
		//   63  132:new             #2   <Class zzge$zzg$zzb>
		//   64  135:dup             
		//   65  136:ldc1            #82  <String "PANCETTA">
		//   66  138:bipush          9
		//   67  140:bipush          8
		//   68  142:invokespecial   #46  <Method void zzge$zzg$zzb(String, int, int)>
		//   69  145:putstatic       #84  <Field zzge$zzg$zzb zzvl>
			zzvm = new zzb("DRIVE_FS", 10, 9);
		//   70  148:new             #2   <Class zzge$zzg$zzb>
		//   71  151:dup             
		//   72  152:ldc1            #86  <String "DRIVE_FS">
		//   73  154:bipush          10
		//   74  156:bipush          9
		//   75  158:invokespecial   #46  <Method void zzge$zzg$zzb(String, int, int)>
		//   76  161:putstatic       #88  <Field zzge$zzg$zzb zzvm>
			zzvn = new zzb("YETI", 11, 11);
		//   77  164:new             #2   <Class zzge$zzg$zzb>
		//   78  167:dup             
		//   79  168:ldc1            #90  <String "YETI">
		//   80  170:bipush          11
		//   81  172:bipush          11
		//   82  174:invokespecial   #46  <Method void zzge$zzg$zzb(String, int, int)>
		//   83  177:putstatic       #92  <Field zzge$zzg$zzb zzvn>
			zzvo = new zzb("MAC", 12, 12);
		//   84  180:new             #2   <Class zzge$zzg$zzb>
		//   85  183:dup             
		//   86  184:ldc1            #94  <String "MAC">
		//   87  186:bipush          12
		//   88  188:bipush          12
		//   89  190:invokespecial   #46  <Method void zzge$zzg$zzb(String, int, int)>
		//   90  193:putstatic       #96  <Field zzge$zzg$zzb zzvo>
			zzvp = new zzb("PLAY_GOOGLE_HOME", 13, 13);
		//   91  196:new             #2   <Class zzge$zzg$zzb>
		//   92  199:dup             
		//   93  200:ldc1            #98  <String "PLAY_GOOGLE_HOME">
		//   94  202:bipush          13
		//   95  204:bipush          13
		//   96  206:invokespecial   #46  <Method void zzge$zzg$zzb(String, int, int)>
		//   97  209:putstatic       #100 <Field zzge$zzg$zzb zzvp>
			zzvq = new zzb("BIRDSONG", 14, 14);
		//   98  212:new             #2   <Class zzge$zzg$zzb>
		//   99  215:dup             
		//  100  216:ldc1            #102 <String "BIRDSONG">
		//  101  218:bipush          14
		//  102  220:bipush          14
		//  103  222:invokespecial   #46  <Method void zzge$zzg$zzb(String, int, int)>
		//  104  225:putstatic       #104 <Field zzge$zzg$zzb zzvq>
			zzvr = new zzb("IOS_FIREBASE", 15, 15);
		//  105  228:new             #2   <Class zzge$zzg$zzb>
		//  106  231:dup             
		//  107  232:ldc1            #106 <String "IOS_FIREBASE">
		//  108  234:bipush          15
		//  109  236:bipush          15
		//  110  238:invokespecial   #46  <Method void zzge$zzg$zzb(String, int, int)>
		//  111  241:putstatic       #108 <Field zzge$zzg$zzb zzvr>
			zzvs = new zzb("GO", 16, 16);
		//  112  244:new             #2   <Class zzge$zzg$zzb>
		//  113  247:dup             
		//  114  248:ldc1            #110 <String "GO">
		//  115  250:bipush          16
		//  116  252:bipush          16
		//  117  254:invokespecial   #46  <Method void zzge$zzg$zzb(String, int, int)>
		//  118  257:putstatic       #112 <Field zzge$zzg$zzb zzvs>
			zzvt = (new zzb[] {
				zzvc, zzvd, zzve, zzvf, zzvg, zzvh, zzvi, zzvj, zzvk, zzvl, 
				zzvm, zzvn, zzvo, zzvp, zzvq, zzvr, zzvs
			});
		//  119  260:bipush          17
		//  120  262:anewarray       zzb[]
		//  121  265:dup             
		//  122  266:iconst_0        
		//  123  267:getstatic       #48  <Field zzge$zzg$zzb zzvc>
		//  124  270:aastore         
		//  125  271:dup             
		//  126  272:iconst_1        
		//  127  273:getstatic       #52  <Field zzge$zzg$zzb zzvd>
		//  128  276:aastore         
		//  129  277:dup             
		//  130  278:iconst_2        
		//  131  279:getstatic       #56  <Field zzge$zzg$zzb zzve>
		//  132  282:aastore         
		//  133  283:dup             
		//  134  284:iconst_3        
		//  135  285:getstatic       #60  <Field zzge$zzg$zzb zzvf>
		//  136  288:aastore         
		//  137  289:dup             
		//  138  290:iconst_4        
		//  139  291:getstatic       #64  <Field zzge$zzg$zzb zzvg>
		//  140  294:aastore         
		//  141  295:dup             
		//  142  296:iconst_5        
		//  143  297:getstatic       #68  <Field zzge$zzg$zzb zzvh>
		//  144  300:aastore         
		//  145  301:dup             
		//  146  302:bipush          6
		//  147  304:getstatic       #72  <Field zzge$zzg$zzb zzvi>
		//  148  307:aastore         
		//  149  308:dup             
		//  150  309:bipush          7
		//  151  311:getstatic       #76  <Field zzge$zzg$zzb zzvj>
		//  152  314:aastore         
		//  153  315:dup             
		//  154  316:bipush          8
		//  155  318:getstatic       #80  <Field zzge$zzg$zzb zzvk>
		//  156  321:aastore         
		//  157  322:dup             
		//  158  323:bipush          9
		//  159  325:getstatic       #84  <Field zzge$zzg$zzb zzvl>
		//  160  328:aastore         
		//  161  329:dup             
		//  162  330:bipush          10
		//  163  332:getstatic       #88  <Field zzge$zzg$zzb zzvm>
		//  164  335:aastore         
		//  165  336:dup             
		//  166  337:bipush          11
		//  167  339:getstatic       #92  <Field zzge$zzg$zzb zzvn>
		//  168  342:aastore         
		//  169  343:dup             
		//  170  344:bipush          12
		//  171  346:getstatic       #96  <Field zzge$zzg$zzb zzvo>
		//  172  349:aastore         
		//  173  350:dup             
		//  174  351:bipush          13
		//  175  353:getstatic       #100 <Field zzge$zzg$zzb zzvp>
		//  176  356:aastore         
		//  177  357:dup             
		//  178  358:bipush          14
		//  179  360:getstatic       #104 <Field zzge$zzg$zzb zzvq>
		//  180  363:aastore         
		//  181  364:dup             
		//  182  365:bipush          15
		//  183  367:getstatic       #108 <Field zzge$zzg$zzb zzvr>
		//  184  370:aastore         
		//  185  371:dup             
		//  186  372:bipush          16
		//  187  374:getstatic       #112 <Field zzge$zzg$zzb zzvs>
		//  188  377:aastore         
		//  189  378:putstatic       #114 <Field zzge$zzg$zzb[] zzvt>
		//  190  381:new             #116 <Class zzgh>
		//  191  384:dup             
		//  192  385:invokespecial   #118 <Method void zzgh()>
		//  193  388:putstatic       #120 <Field zzck zzbq>
		//* 194  391:return          
		}

		private zzb(String s, int i, int j)
		{
			super(s, i);
		//    0    0:aload_0         
		//    1    1:aload_1         
		//    2    2:iload_2         
		//    3    3:invokespecial   #124 <Method void Enum(String, int)>
			value = j;
		//    4    6:aload_0         
		//    5    7:iload_3         
		//    6    8:putfield        #126 <Field int value>
		//    7   11:return          
		}
	}


	static zzge$zzg zzez()
	{
		return zzva;
	//    0    0:getstatic       #63  <Field zzge$zzg zzva>
	//    1    3:areturn         
	}

	protected final Object zza(int i, Object obj, Object obj1)
	{
		int j;
		j = zzgf.zzba[i - 1];
	//    0    0:getstatic       #103 <Field int[] zzgf.zzba>
	//    1    3:iload_1         
	//    2    4:iconst_1        
	//    3    5:isub            
	//    4    6:iaload          
	//    5    7:istore          4
		i = 0;
	//    6    9:iconst_0        
	//    7   10:istore_1        
		j;
	//    8   11:iload           4
		JVM INSTR tableswitch 1 7: default 56
	//	               1 264
	//	               2 255
	//	               3 142
	//	               4 138
	//	               5 89
	//	               6 81
	//	               7 64;
	//    9   13:tableswitch     1 7: default 56
	//	               1 264
	//	               2 255
	//	               3 142
	//	               4 138
	//	               5 89
	//	               6 81
	//	               7 64
		   goto _L1 _L2 _L3 _L4 _L5 _L6 _L7 _L8
_L1:
		throw new UnsupportedOperationException();
	//   10   56:new             #105 <Class UnsupportedOperationException>
	//   11   59:dup             
	//   12   60:invokespecial   #106 <Method void UnsupportedOperationException()>
	//   13   63:athrow          
_L8:
		if(obj != null)
	//*  14   64:aload_2         
	//*  15   65:ifnonnull       71
	//*  16   68:goto            73
			i = 1;
	//   17   71:iconst_1        
	//   18   72:istore_1        
		zzsf = (byte)i;
	//   19   73:aload_0         
	//   20   74:iload_1         
	//   21   75:int2byte        
	//   22   76:putfield        #88  <Field byte zzsf>
		return ((Object) (null));
	//   23   79:aconst_null     
	//   24   80:areturn         
_L7:
		return ((Object) (Byte.valueOf(zzsf)));
	//   25   81:aload_0         
	//   26   82:getfield        #88  <Field byte zzsf>
	//   27   85:invokestatic    #112 <Method Byte Byte.valueOf(byte)>
	//   28   88:areturn         
_L6:
		obj = ((Object) (zzbg));
	//   29   89:getstatic       #114 <Field zzdz zzbg>
	//   30   92:astore_2        
		if(obj != null) goto _L10; else goto _L9
	//   31   93:aload_2         
	//   32   94:ifnonnull       136
_L9:
		com/google/android/gms/internal/clearcut/zzge$zzg;
	//   33   97:ldc1            #2   <Class zzge$zzg>
		JVM INSTR monitorenter ;
	//   34   99:monitorenter    
		obj1 = ((Object) (zzbg));
	//   35  100:getstatic       #114 <Field zzdz zzbg>
	//   36  103:astore_3        
		obj = obj1;
	//   37  104:aload_3         
	//   38  105:astore_2        
		if(obj1 != null) goto _L12; else goto _L11
	//   39  106:aload_3         
	//   40  107:ifnonnull       125
_L11:
		obj = ((Object) (new zzcg$zzb(((zzcg) (zzva)))));
	//   41  110:new             #116 <Class zzcg$zzb>
	//   42  113:dup             
	//   43  114:getstatic       #63  <Field zzge$zzg zzva>
	//   44  117:invokespecial   #119 <Method void zzcg$zzb(zzcg)>
	//   45  120:astore_2        
		zzbg = ((zzdz) (obj));
	//   46  121:aload_2         
	//   47  122:putstatic       #114 <Field zzdz zzbg>
_L12:
		com/google/android/gms/internal/clearcut/zzge$zzg;
	//   48  125:ldc1            #2   <Class zzge$zzg>
		JVM INSTR monitorexit ;
	//   49  127:monitorexit     
		return obj;
	//   50  128:aload_2         
	//   51  129:areturn         
		obj;
	//   52  130:astore_2        
		com/google/android/gms/internal/clearcut/zzge$zzg;
	//   53  131:ldc1            #2   <Class zzge$zzg>
		JVM INSTR monitorexit ;
	//   54  133:monitorexit     
		throw obj;
	//   55  134:aload_2         
	//   56  135:athrow          
_L10:
		return obj;
	//   57  136:aload_2         
	//   58  137:areturn         
_L5:
		return ((Object) (zzva));
	//   59  138:getstatic       #63  <Field zzge$zzg zzva>
	//   60  141:areturn         
_L4:
		obj = ((Object) (zzb.zzd()));
	//   61  142:invokestatic    #123 <Method zzck zzge$zzg$zzb.zzd()>
	//   62  145:astore_2        
		return zza(((zzdo) (zzva)), "\001\017\000\001\001\017\017\020\000\000\001\001\f\000\002\u0409\003\003\t\004\004\t\005\005\t\006\006\b\001\007\b\002\b\t\007\t\t\013\n\t\b\013\t\f\f\002\016\r\t\t\016\t\r\017\t\n", new Object[] {
			"zzbb", "zzty", obj, "zzuo", "zzup", "zzuq", "zzur", "zzum", "zzun", "zzus", 
			"zzuw", "zzut", "zzux", "zzuz", "zzuu", "zzuy", "zzuv"
		});
	//   63  146:getstatic       #63  <Field zzge$zzg zzva>
	//   64  149:ldc1            #125 <String "\001\017\000\001\001\017\017\020\000\000\001\001\f\000\002\u0409\003\003\t\004\004\t\005\005\t\006\006\b\001\007\b\002\b\t\007\t\t\013\n\t\b\013\t\f\f\002\016\r\t\t\016\t\r\017\t\n">
	//   65  151:bipush          17
	//   66  153:anewarray       Object[]
	//   67  156:dup             
	//   68  157:iconst_0        
	//   69  158:ldc1            #128 <String "zzbb">
	//   70  160:aastore         
	//   71  161:dup             
	//   72  162:iconst_1        
	//   73  163:ldc1            #129 <String "zzty">
	//   74  165:aastore         
	//   75  166:dup             
	//   76  167:iconst_2        
	//   77  168:aload_2         
	//   78  169:aastore         
	//   79  170:dup             
	//   80  171:iconst_3        
	//   81  172:ldc1            #130 <String "zzuo">
	//   82  174:aastore         
	//   83  175:dup             
	//   84  176:iconst_4        
	//   85  177:ldc1            #131 <String "zzup">
	//   86  179:aastore         
	//   87  180:dup             
	//   88  181:iconst_5        
	//   89  182:ldc1            #132 <String "zzuq">
	//   90  184:aastore         
	//   91  185:dup             
	//   92  186:bipush          6
	//   93  188:ldc1            #133 <String "zzur">
	//   94  190:aastore         
	//   95  191:dup             
	//   96  192:bipush          7
	//   97  194:ldc1            #134 <String "zzum">
	//   98  196:aastore         
	//   99  197:dup             
	//  100  198:bipush          8
	//  101  200:ldc1            #135 <String "zzun">
	//  102  202:aastore         
	//  103  203:dup             
	//  104  204:bipush          9
	//  105  206:ldc1            #136 <String "zzus">
	//  106  208:aastore         
	//  107  209:dup             
	//  108  210:bipush          10
	//  109  212:ldc1            #137 <String "zzuw">
	//  110  214:aastore         
	//  111  215:dup             
	//  112  216:bipush          11
	//  113  218:ldc1            #138 <String "zzut">
	//  114  220:aastore         
	//  115  221:dup             
	//  116  222:bipush          12
	//  117  224:ldc1            #139 <String "zzux">
	//  118  226:aastore         
	//  119  227:dup             
	//  120  228:bipush          13
	//  121  230:ldc1            #140 <String "zzuz">
	//  122  232:aastore         
	//  123  233:dup             
	//  124  234:bipush          14
	//  125  236:ldc1            #141 <String "zzuu">
	//  126  238:aastore         
	//  127  239:dup             
	//  128  240:bipush          15
	//  129  242:ldc1            #142 <String "zzuy">
	//  130  244:aastore         
	//  131  245:dup             
	//  132  246:bipush          16
	//  133  248:ldc1            #143 <String "zzuv">
	//  134  250:aastore         
	//  135  251:invokestatic    #146 <Method Object zza(zzdo, String, Object[])>
	//  136  254:areturn         
_L3:
		return ((Object) (new zza(((zzgf) (null)))));
	//  137  255:new             #12  <Class zzge$zzg$zza>
	//  138  258:dup             
	//  139  259:aconst_null     
	//  140  260:invokespecial   #149 <Method void zzge$zzg$zza(zzgf)>
	//  141  263:areturn         
_L2:
		return ((Object) (new zzge$zzg()));
	//  142  264:new             #2   <Class zzge$zzg>
	//  143  267:dup             
	//  144  268:invokespecial   #61  <Method void zzge$zzg()>
	//  145  271:areturn         
	}

	private static volatile zzdz zzbg;
	private static final zzge$zzg zzva;
	private static final zzcg$zzf zzvb;
	private int zzbb;
	private byte zzsf;
	private int zzty;
	private String zzum;
	private String zzun;
	private zzge$zzb zzuo;
	private zzge$zzi zzup;
	private zzge$zzm zzuq;
	private zzge$zzu zzur;
	private zzge$zzw zzus;
	private zzge$zzt zzut;
	private zzge$zzr zzuu;
	private zzge$zzx zzuv;
	private zzge$zzf zzuw;
	private zzge$zzn zzux;
	private zzge$zze zzuy;
	private long zzuz;

	static 
	{
		zzva = new zzge$zzg();
	//    0    0:new             #2   <Class zzge$zzg>
	//    1    3:dup             
	//    2    4:invokespecial   #61  <Method void zzge$zzg()>
	//    3    7:putstatic       #63  <Field zzge$zzg zzva>
		zzcg.zza(com/google/android/gms/internal/clearcut/zzge$zzg, ((zzcg) (zzva)));
	//    4   10:ldc1            #2   <Class zzge$zzg>
	//    5   12:getstatic       #63  <Field zzge$zzg zzva>
	//    6   15:invokestatic    #66  <Method void zzcg.zza(Class, zzcg)>
		zzgc zzgc1 = zzgc.zzer();
	//    7   18:invokestatic    #72  <Method zzgc zzgc.zzer()>
	//    8   21:astore_0        
		zzge$zzg zzge$zzg1 = zzva;
	//    9   22:getstatic       #63  <Field zzge$zzg zzva>
	//   10   25:astore_1        
		zzvb = zzcg.zza(((zzdo) (zzgc1)), ((Object) (zzge$zzg1)), ((zzdo) (zzge$zzg1)), ((zzck) (null)), 0x3f3fd17, zzfl.zzqm, com/google/android/gms/internal/clearcut/zzge$zzg);
	//   11   26:aload_0         
	//   12   27:aload_1         
	//   13   28:aload_1         
	//   14   29:aconst_null     
	//   15   30:ldc1            #73  <Int 0x3f3fd17>
	//   16   32:getstatic       #79  <Field zzfl zzfl.zzqm>
	//   17   35:ldc1            #2   <Class zzge$zzg>
	//   18   37:invokestatic    #82  <Method zzcg$zzf zzcg.zza(zzdo, Object, zzdo, zzck, int, zzfl, Class)>
	//   19   40:putstatic       #84  <Field zzcg$zzf zzvb>
	//*  20   43:return          
	}

	private zzge$zzg()
	{
	//    0    0:aload_0         
	//    1    1:invokespecial   #86  <Method void zzcg()>
		zzsf = 2;
	//    2    4:aload_0         
	//    3    5:iconst_2        
	//    4    6:putfield        #88  <Field byte zzsf>
		zzum = "";
	//    5    9:aload_0         
	//    6   10:ldc1            #90  <String "">
	//    7   12:putfield        #92  <Field String zzum>
		zzun = "";
	//    8   15:aload_0         
	//    9   16:ldc1            #90  <String "">
	//   10   18:putfield        #94  <Field String zzun>
	//   11   21:return          
	}
}
